Workbook

Sheet REGENERANTS
C1: 2 | D1: 3 | E1: 4 | F1: 5 | G1: 6 | H1: 7 | I1: 8 | J1: 9 | K1: 10 | L1: 11 | M1: 12 | N1: 13 | O1: 14 | P1: 15 | Q1: 16 | R1: 17 | S1: 16 | T1: 17 | Y1: 16 | Z1: 17 | AA1: 18 | AB1: 19 | AC1: 20 | AD1: 21 | AE1: 22 | AF1: 23 | AG1: 24 | AH1: 25 | AI1: 26 | AJ1: 27 | AK1: 28 | AL1: 29 | AM1: 30 | AN1: 31 | AO1: 32 | AP1: 33 | AQ1: 34 | AR1: 35 | AS1: 36 | AT1: 37 | AU1: 38 | AV1: 39 | AW1: 40 | AX1: 41 | AY1: 42 | AZ1: 43 | BA1: 44 | BB1: 45 | BC1: 46 | BD1: 47 | BE1: 48 | BF1: 49 | BG1: 50 | BH1: 51 | BI1: 52 | BJ1: 53 | BK1: 54 | BL1: 55 | BM1: 56 | BN1: 57 | BO1: 58 | BP1: 59 | BQ1: 60 | BR1: 61 | BS1: 62 | BT1: 63 | BU1: 64 | BV1: 65 | BW1: 66 | BX1: 67 | BY1: 68 | BZ1: 69 | CA1: 70 | CB1: 71 | CC1: 72 | CD1: 73 | CE1: 74 | CF1: 75 | CG1: 76 | CH1: 77 | CI1: 78 | CK1: =SUM(CK11:CK370) | DQ1: =SUM(DQ11:DQ317) | DU1: =SUM(DU11:DU370)
H2: =(SUMIF($F$22:$F$62,"<>*PLV*",$H$22:$H$62)*$CF$20)+(SUMIF($F$22:$F$62,"PLV (PDC ou autre)",$H$22:$H$62)*$CJ$20)+(SUMIF($F$22:$F$62,"PLV (vitrine)",$H$22:$H$62)*$CJ$18)+(SUMIF($F$77:$F$98,"<>*PLV*",$H$77:$H$98)*$CF$75)+(SUMIF($F$77:$F$98,"PLV (PDC ou autre)",$H$77:$H$98)*$CJ$75)+(SUMIF($F$77:$F$98,"PLV (vitrine)",$H$77:$H$98)*$CJ$73)+(SUMIF($F$114:$F$153,"<>*PLV*",$H$114:$H$153)*$CF$112)+(SUMIF($F$114:$F$153,"PLV (PDC ou autre)",$H$114:$H$153)*$CJ$112)+(SUMIF($F$114:$F$153,"PLV (vitrine)",$H$114:$H$153)*$CJ$110)+(SUMIF($F$168:$F$207,"<>*PLV*",$H$168:$H$207)*$CF$166)+(SUMIF($F$168:$F$207,"PLV (PDC ou autre)",$H$168:$H$207)*$CJ$166)+(SUMIF($F$168:$F$207,"PLV (vitrine)",$H$168:$H$207)*$CJ$164)+(SUMIF($F$223:$F$262,"<>*PLV*",$H$223:$H$262)*$CF$221)+(SUMIF($F$223:$F$262,"PLV (PDC ou autre)",$H$223:$H$262)*$CJ$221)+(SUMIF($F$223:$F$262,"PLV (vitrine)",$H$223:$H$262)*$CJ$219)+(SUMIF($F$277:$F$316,"<>*PLV*",$H$277:$H$316)*$CF$275)+(SUMIF($F$277:$F$316,"PLV (PDC ou autre)",$H$277:$H$316)*$CJ$275)+(SUMIF($F$277:$F$316,"PLV (vitrine)",$H$277:$H$316)*$CJ$273)+(SUMIF($F$331:$F$370,"<>*PLV*",$H$331:$H$370)*$CF$329)+(SUMIF($F$331:$F$370,"PLV (PDC ou autre)",$H$331:$H$370)*$CJ$329)+(SUMIF($F$331:$F$370,"PLV (vitrine)",$H$331:$H$370)*$CJ$327) | K2: =K20*CF20+K75*CF75+K112*CF112+K166*CF166+K221*CF221+K275*CF275+K329*CF329 | CK2: =IFERROR(H2=CK1,"FAUX") | DU2: =SUMIFS(DU22:DU371,F22:F371,"*PLV*")
K3: =(SUMIFS($K$22:$K$62,$F$22:$F$62,"*PLV*")*$CF$20)+(SUMIFS($K$77:$K$98,$F$77:$F$98,"*PLV*")*$CF$75)+(SUMIFS($K$114:$K$153,$F$114:$F$153,"*PLV*")*$CF$112)+(SUMIFS($K$168:$K$207,$F$168:$F$207,"*PLV*")*$CF$166)+(SUMIFS($K$223:$K$262,$F$223:$F$262,"*PLV*")*$CF$221)+(SUMIFS($K$277:$K$316,$F$277:$F$316,"*PLV*")*$CF$275)+(SUMIFS($K$331:$K$370,$F$331:$F$370,"*PLV*")*$CF$329) | CG3: =SUM(CG8:CG370) | DS3: =SUM(DS8:DS371,DT8:DT371) | DU3: =SUMIFS(DU22:DU371,F22:F371,"Produit Vente")
K4: =(SUMIFS($K$22:$K$62,$F$22:$F$62,"Produit Vente")*$CF$20)+(SUMIFS($K$77:$K$98,$F$77:$F$98,"Produit Vente")*$CF$75)+(SUMIFS($K$114:$K$153,$F$114:$F$153,"Produit Vente")*$CF$112)+(SUMIFS($K$168:$K$207,$F$168:$F$207,"Produit Vente")*$CF$166)+(SUMIFS($K$223:$K$262,$F$223:$F$262,"Produit Vente")*$CF$221)+(SUMIFS($K$277:$K$316,$F$277:$F$316,"Produit Vente")*$CF$275)+(SUMIFS($K$331:$K$370,$F$331:$F$370,"Produit Vente")*$CF$329) | DU4: =SUMIFS(DU22:DU371,F22:F371,"UG")
C5: =MID(CELL("filename",C5),FIND("]",CELL("filename",C5))+1,255) | K5: =(SUMIFS($K$22:$K$62,$F$22:$F$62,"UG")*$CF$20)+(SUMIFS($K$77:$K$98,$F$77:$F$98,"UG")*$CF$75)+(SUMIFS($K$114:$K$153,$F$114:$F$153,"UG")*$CF$112)+(SUMIFS($K$168:$K$207,$F$168:$F$207,"UG")*$CF$166)+(SUMIFS($K$223:$K$262,$F$223:$F$262,"UG")*$CF$221)+(SUMIFS($K$277:$K$316,$F$277:$F$316,"UG")*$CF$275)+(SUMIFS($K$331:$K$370,$F$331:$F$370,"UG")*$CF$329) | DU5: =SUMIFS(DU22:DU371,F22:F371,"Testeur")
C6: ="<<" | K6: =(SUMIFS($K$22:$K$62,$F$22:$F$62,"Testeur")*$CF$20)+(SUMIFS($K$77:$K$98,$F$77:$F$98,"Testeur")*$CF$75)+(SUMIFS($K$114:$K$153,$F$114:$F$153,"Testeur")*$CF$112)+(SUMIFS($K$168:$K$207,$F$168:$F$207,"Testeur")*$CF$166)+(SUMIFS($K$223:$K$262,$F$223:$F$262,"Testeur")*$CF$221)+(SUMIFS($K$277:$K$316,$F$277:$F$316,"Testeur")*$CF$275)+(SUMIFS($K$331:$K$370,$F$331:$F$370,"Testeur")*$CF$329)
CN8: Nbrs Offres planifiées | CO8: CA | CP8: Marges
C9: 670 offres budgétées en 2025 / 457 offres réalisées --> 730 offres en 2026 (+10%) | AB9: 65 | CM9: Retail | CN9: =SUMIFS($AB20:$AT20,$AB17:$AT17,CN8)+SUMIFS($BZ20:$CC20,$BZ17:$CC17,CN8)+SUMIFS($AB75:$AT75,$AB72:$AT72,CN8)+SUMIFS($BZ75:$CC75,$BZ72:$CC72,CN8)+SUMIFS($AB112:$AT112,$AB109:$AT109,CN8)+SUMIFS($BZ112:$CC112,$BZ109:$CC109,CN8)+SUMIFS($AB166:$AT166,$AB163:$AT163,CN8)+SUMIFS($BZ166:$CC166,$BZ163:$CC163,CN8)+SUMIFS($AB221:$AT221,$AB218:$AT218,CN8)+SUMIFS($BZ221:$CC221,$BZ218:$CC218,CN8)+SUMIFS($AB275:$AT275,$AB272:$AT272,CN8)+SUMIFS($BZ275:$CC275,$BZ272:$CC272,CN8)+SUMIFS($AB329:$AT329,$AB326:$AT326,CN8)+SUMIFS($BZ329:$CC329,$BZ326:$CC326,CN8) | CO9: =SUMIFS($AB20:$AT20,$AB17:$AT17,CO8)+SUMIFS($BZ20:$CC20,$BZ17:$CC17,CO8)+SUMIFS($AB75:$AT75,$AB72:$AT72,CO8)+SUMIFS($BZ75:$CC75,$BZ72:$CC72,CO8)+SUMIFS($AB112:$AT112,$AB109:$AT109,CO8)+SUMIFS($BZ112:$CC112,$BZ109:$CC109,CO8)+SUMIFS($AB166:$AT166,$AB163:$AT163,CO8)+SUMIFS($BZ166:$CC166,$BZ163:$CC163,CO8)+SUMIFS($AB221:$AT221,$AB218:$AT218,CO8)+SUMIFS($BZ221:$CC221,$BZ218:$CC218,CO8)+SUMIFS($AB275:$AT275,$AB272:$AT272,CO8)+SUMIFS($BZ275:$CC275,$BZ272:$CC272,CO8)+SUMIFS($AB329:$AT329,$AB326:$AT326,CO8)+SUMIFS($BZ329:$CC329,$BZ326:$CC326,CO8) | CP9: =IFERROR(SUM(CH38,CH93,CH130,CH184,CH239,CH293,CH347)/CO9,0)
C10: REGENERANTS 1 - Premium | F10: Panachage 50 unités // Remise 15% pour BRI conso 10€ sur 4 produits : Sérum J/N, CDJR, CDJRI, sérum nuit RI (-10€ = prix plancher, à imprimer sur 1 SR sur le présentoir) | CM10: Institut | CN10: =SUMIFS($AV20:$BX20,$AV17:$BX17,CN8)+SUMIFS($AV75:$BX75,$AV72:$BX72,CN8)+SUMIFS($AV112:$BX112,$AV109:$BX109,CN8)+SUMIFS($AV166:$BX166,$AV163:$BX163,CN8)+SUMIFS($AV221:$BX221,$AV218:$BX218,CN8)+SUMIFS($AV275:$BX275,$AV272:$BX272,CN8)+SUMIFS($AV329:$BX329,$AV326:$BX326,CN8) | CO10: =SUMIFS($AV20:$BX20,$AV17:$BX17,CO8)+SUMIFS($AV75:$BX75,$AV72:$BX72,CO8)+SUMIFS($AV112:$BX112,$AV109:$BX109,CO8)+SUMIFS($AV166:$BX166,$AV163:$BX163,CO8)+SUMIFS($AV221:$BX221,$AV218:$BX218,CO8)+SUMIFS($AV275:$BX275,$AV272:$BX272,CO8)+SUMIFS($AV329:$BX329,$AV326:$BX326,CO8) | CP10: =IFERROR(SUM(CH44,CH99,CH136,CH190,CH245,CH299,CH353)/CO10,0)
AB12: 0.5 | AG12: 0.2 | AV12: 0.19 | BA12: 0.1
AB13: Tarif Retail | AV13: Tarif Institut | BZ13: Autres | CF13: Tous réseaux
P15: Additionnelle | AB15: Ambassadeur | AG15: Compagnon | AL15: Challenger | AQ15: Partenaire | AV15: Rose | BA15: Prunelier | BF15: Anthylide | BK15: Calendula | BP15: Bourrache | BU15: Herbacée | BZ15: Autres | CF15: Total
H17: Pdt dans offre | J17: PA x Unit. | K17: Coûts Achats | M17: Tarif Rev. x Unit. | N17: Tarif Rev. | P17: Remise Offres x Prod. | R17: Tarif Rev. Remisé | T17: PPC Unitaire Indicatif | V17: PPC Unitaire Remisé | X17: Montant BRI | Z17: PPC global Indicatif | AB17: Nbrs Offres planifiées | AC17: Remise Statut | AD17: CA | AE17: Marges | AG17: Nbrs Offres planifiées | AH17: Remise Statut | AI17: CA | AJ17: Marges | AL17: Nbrs Offres planifiées | AM17: Remise Statut | AN17: CA | AO17: Marges | AQ17: Nbrs Offres planifiées | AR17: Remise Statut | AS17: CA | AT17: Marges | AV17: Nbrs Offres planifiées | AW17: Remise Statut | AX17: CA | AY17: Marges | BA17: Nbrs Offres planifiées | BB17: Remise Statut | BC17: CA | BD17: Marges | BF17: Nbrs Offres planifiées | BG17: Remise Statut | BH17: CA | BI17: Marges | BK17: Nbrs Offres planifiées | BL17: Remise Statut | BM17: CA | BN17: Marges | BP17: Nbrs Offres planifiées | BQ17: Remise Statut | BR17: CA | BS17: Marges | BU17: Nbrs Offres planifiées | BV17: Remise Statut | BW17: CA | BX17: Marges | BZ17: Nbrs Offres planifiées | CA17: Remise Statut | CB17: CA | CC17: Marges | CF17: Nbrs Offres planifiées | CG17: CA | CH17: Marges | CN17: Marketing | CT17: Commerce | CW17: Diététiques | CX17: Instituts | CY17: Pharmacies | DB17: Grands Magasins | DE17: Pures Players | DP17: Autres | DQ17: Total | DR17: Dont total GC | DS17: Proj CA eshop | DT17: Proj CA GC | DU17: Total coûts | DX17: BESOIN TOTAL POUR COMMANDE ALLEMAGNE | EA17: MAJ le
C18: Code article | D18: Libellé article | E18: Code à barres (EAN) | F18: Typ. Prod | H18: '# | J18: '€ | K18: '€ | M18: '€ | N18: '€ | P18: '€ | R18: '€ | T18: '€ | V18: '€ | X18: '€ | Z18: '€ | AB18: '# | AC18: '€ | AD18: '€ | AE18: '€ | AG18: '# | AH18: '€ | AI18: '€ | AJ18: '€ | AL18: '# | AM18: '€ | AN18: '€ | AO18: '€ | AQ18: '# | AR18: '€ | AS18: '€ | AT18: '€ | AV18: '# | AW18: '€ | AX18: '€ | AY18: '€ | BA18: '# | BB18: '€ | BC18: '€ | BD18: '€ | BF18: '# | BG18: '€ | BH18: '€ | BI18: '€ | BK18: '# | BL18: '€ | BM18: '€ | BN18: '€ | BP18: '# | BQ18: '€ | BR18: '€ | BS18: '€ | BU18: '# | BV18: '€ | BW18: '€ | BX18: '€ | BZ18: '# | CA18: '€ | CB18: '€ | CC18: '€ | CF18: '# | CG18: '€ | CH18: '€ | CJ18: =ROUNDUP(CF20*40%,-1)
R19: <
B20: =C10 | C20: Synthèse | H20: =IFERROR(SUMIFS(H22:H62,F22:F62,"Produit Vente"),"Non trouvé") | J20: =IFERROR($K20/$H20,"Non Trouvé") | K20: =IFERROR(SUM(K22:K62),"Non Trouvé") | M20: =IFERROR($N20/$H20,"Non Trouvé") | N20: =IFERROR(SUM(N22:N62),"Non Trouvé") | P20: =IFERROR(-(R20-N20)/N20,"Non Trouvé") | R20: =IFERROR(SUM(R22:R62),"Non Trouvé") | T20: =IFERROR(SUM(T22:T62),"Non Trouvé") | V20: =IFERROR(SUM(V22:V62),"Non Trouvé") | X20: =IFERROR(SUM(X22:X62),"Non Trouvé") | Z20: =IFERROR(SUM(Z22:Z62),"Non Trouvé") | AB20: =ROUND($AB$9*AB12,0) | AC20: =IFERROR(VLOOKUP(AB15,'[1]Paramètres Généraux'!$O:$P,2,FALSE),"Non Trouvé") | AD20: =IFERROR(SUM(AD22:AD62),"Non Trouvé") | AE20: =IFERROR((AD20-$K20*AB20)/AD20,"Non Trouvé") | AG20: =ROUND($AB$9*AG12,0) | AH20: =IFERROR(VLOOKUP(AG15,'[1]Paramètres Généraux'!$O:$P,2,FALSE),"Non Trouvé") | AI20: =IFERROR(SUM(AI22:AI62),"Non Trouvé") | AJ20: =IFERROR((AI20-$K20*AG20)/AI20,"Non Trouvé") | AL20: =ROUND($AB$9*AL12,0) | AM20: =IFERROR(VLOOKUP(AL15,'[1]Paramètres Généraux'!$O:$P,2,FALSE),"Non Trouvé") | AN20: =IFERROR(SUM(AN22:AN62),"Non Trouvé") | AO20: =IFERROR((AN20-$K20*AL20)/AN20,"Non Trouvé") | AQ20: =ROUND($AB$9*AQ12,0) | AR20: =IFERROR(VLOOKUP(AQ15,'[1]Paramètres Généraux'!$O:$P,2,FALSE),"Non Trouvé") | AS20: =IFERROR(SUM(AS22:AS62),"Non Trouvé") | AT20: =IFERROR((AS20-$K20*AQ20)/AS20,"Non Trouvé") | AV20: =ROUND($AB$9*AV12,0) | AW20: =IFERROR(VLOOKUP(AV15,'[1]Paramètres Généraux'!$O:$P,2,FALSE),"Non Trouvé") | AX20: =IFERROR(SUM(AX22:AX62),"Non Trouvé") | AY20: =IFERROR((AX20-$K20*AV20)/AX20,"Non Trouvé") | BA20: =ROUND($AB$9*BA12,0) | BB20: =IFERROR(VLOOKUP(BA15,'[1]Paramètres Généraux'!$O:$P,2,FALSE),"Non Trouvé") | BC20: =IFERROR(SUM(BC22:BC62),"Non Trouvé") | BD20: =IFERROR((BC20-$K20*BA20)/BC20,"Non Trouvé") | BF20: =ROUND($AB$9*BF12,0) | BG20: =IFERROR(VLOOKUP(BF15,'[1]Paramètres Généraux'!$O:$P,2,FALSE),"Non Trouvé") | BH20: =IFERROR(SUM(BH22:BH62),"Non Trouvé") | BI20: =IFERROR((BH20-$K20*BF20)/BH20,"Non Trouvé") | BK20: =ROUND($AB$9*BK12,0) | BL20: =IFERROR(VLOOKUP(BK15,'[1]Paramètres Généraux'!$O:$P,2,FALSE),"Non Trouvé") | BM20: =IFERROR(SUM(BM22:BM62),"Non Trouvé") | BN20: =IFERROR((BM20-$K20*BK20)/BM20,"Non Trouvé") | BP20: =ROUND($AB$9*BP12,0) | BQ20: =IFERROR(VLOOKUP(BP15,'[1]Paramètres Généraux'!$O:$P,2,FALSE),"Non Trouvé") | BR20: =IFERROR(SUM(BR22:BR62),"Non Trouvé") | BS20: =IFERROR((BR20-$K20*BP20)/BR20,"Non Trouvé") | BU20: =ROUND($AB$9*BU12,0) | BV20: =IFERROR(VLOOKUP(BU15,'[1]Paramètres Généraux'!$O:$P,2,FALSE),"Non Trouvé") | BW20: =IFERROR(SUM(BW22:BW62),"Non Trouvé") | BX20: =IFERROR((BW20-$K20*BU20)/BW20,"Non Trouvé") | BZ20: =ROUND($AB$9*BZ12,0) | CA20: =IFERROR(VLOOKUP(BZ15,'[1]Paramètres Généraux'!$O:$P,2,FALSE),"Non Trouvé") | CB20: =IFERROR(SUM(CB22:CB62),"Non Trouvé") | CC20: =IFERROR((CB20-$K20*BZ20)/CB20,"Non Trouvé") | CF20: =SUMIFS($AB20:$CC20,$AB17:$CC17,CF17) | CG20: =SUMIFS($AB20:$CC20,$AB17:$CC17,CG17) | CH20: =IFERROR((CG20-$K20*CF20)/CG20,"Non Trouvé") | CJ20: =ROUNDUP(CF20*70%,-1) | CN20: Réassort | CO20: Eshop | CP20: Opé Marketing / Communication | CQ20: Devis | CR20: Formation | CS20: Maison DRH | CT20: Dotation Commerciaux | CU20: Animation | CV20: Cadeau Acheteur GC | CW20: Biocoop | CX20: Mlle Bio | CY20: Pharm'O Naturel | CZ20: Anton & Willem | DA20: Elsie Santé | DB20: Printemps & Soprintours | DC20: Samaritaine | DD20: Galeries Lafayette | DE20: Place des Tendances | DF20: Nocibé | DG20: Monoprix | DH20: Nuoo | DI20: Jolimoi | DJ20: La Belle Vie | DK20: Easypara | DL20: New Pharma | DM20: My Origins | DN20: Le Monde du Bio | DO20: Onatera | DP20: Boutique Nature | DX20: CODE ARTICLE | DY20: LIBELLE ARTICLE | DZ20: BESOIN | EA20: COMMANDE VALIDÉE
B22: 1 | C22: 1020202 | D22: =IFERROR(IF($C22="","",VLOOKUP($C22,'[1]Paramètres Articles'!$B:$G,2,FALSE)),"Non Trouvé") | E22: =IFERROR(IF($C22="","",_xlfn.XLOOKUP(REGENERANTS!$C22,'[1]New Base PA'!$F:$F,'[1]New Base PA'!$D:$D,"Not Found",0)),"Non Trouvé") | F22: Produit Vente | H22: 7 | J22: =IFERROR(IF($C22="","",VLOOKUP($C22,'[1]New Base PA'!$F:$J,5,FALSE)),"Non Trouvé") | K22: =IFERROR(IF($C22="","",$J22*$H22),"Non Trouvé") | M22: =IFERROR(IF(AND($F22="Produit Vente",H22>0),VLOOKUP($C22,'[1]Paramètres Articles'!$B:$G,6,FALSE),0),"Non Trouvé") | N22: =IFERROR(IF($C22="","",$M22*$H22),"Non Trouvé") | P22: 0.15 | R22: =IFERROR(IF($C22="","",$N22*(1-$P22)),"Non Trouvé") | T22: =IFERROR(IF($C22="","",VLOOKUP($C22,'[1]Paramètres Articles'!$B:$H,7,FALSE)),"Non Trouvé") | V22: =IFERROR(IF($C22="","",IF($P22="","",$T22*(1-$P22))),"Non Trouvé") | X22: =IFERROR(T22-V22,"") | Z22: =IFERROR(IF(OR(T22=0,T22=""),0,T22*H22),"Non Trouvé") | AB22: =AB20 | AC22: =AC20 | AD22: =IFERROR(IF($C22="","",IF($P$15="Cascade",$R22*(1-AC22)*AB22,IF($P$15="Additionnelle",($N22-($N22*($P22+AC22)))*AB22))),"Non Trouvé") | AG22: =AG20 | AH22: =AH20 | AI22: =IFERROR(IF($C22="","",IF($P$15="Cascade",$R22*(1-AH22)*AG22,IF($P$15="Additionnelle",($N22-($N22*($P22+AH22)))*AG22))),"Non Trouvé") | AL22: =AL20 | AM22: =AM20 | AN22: =IFERROR(IF($C22="","",IF($P$15="Cascade",$R22*(1-AM22)*AL22,IF($P$15="Additionnelle",($N22-($N22*($P22+AM22)))*AL22))),"Non Trouvé") | AQ22: =AQ20 | AR22: =AR20 | AS22: =IFERROR(IF($C22="","",IF($P$15="Cascade",$R22*(1-AR22)*AQ22,IF($P$15="Additionnelle",($N22-($N22*($P22+AR22)))*AQ22))),"Non Trouvé") | AV22: =AV20 | AW22: =AW20 | AX22: =IFERROR(IF($C22="","",IF($P$15="Cascade",$R22*(1-AW22)*AV22,IF($P$15="Additionnelle",($N22-($N22*($P22+AW22)))*AV22))),"Non Trouvé") | BA22: =BA20 | BB22: =BB20 | BC22: =IFERROR(IF($C22="","",IF($P$15="Cascade",$R22*(1-BB22)*BA22,IF($P$15="Additionnelle",($N22-($N22*($P22+BB22)))*BA22))),"Non Trouvé") | BF22: =BF20 | BG22: =BG20 | BH22: =IFERROR(IF($C22="","",IF($P$15="Cascade",$R22*(1-BG22)*BF22,IF($P$15="Additionnelle",($N22-($N22*($P22+BG22)))*BF22))),"Non Trouvé") | BK22: =BK20 | BL22: =BL20 | BM22: =IFERROR(IF($C22="","",IF($P$15="Cascade",$R22*(1-BL22)*BK22,IF($P$15="Additionnelle",($N22-($N22*($P22+BL22)))*BK22))),"Non Trouvé") | BP22: =BP20 | BQ22: =BQ20 | BR22: =IFERROR(IF($C22="","",IF($P$15="Cascade",$R22*(1-BQ22)*BP22,IF($P$15="Additionnelle",($N22-($N22*($P22+BQ22)))*BP22))),"Non Trouvé") | BU22: =BU20 | BV22: =BV20 | BW22: =IFERROR(IF($C22="","",IF($P$15="Cascade",$R22*(1-BV22)*BU22,IF($P$15="Additionnelle",($N22-($N22*($P22+BV22)))*BU22))),"Non Trouvé") | BZ22: =BZ20 | CA22: =CA20 | CB22: =IFERROR(IF($C22="","",IF($P$15="Cascade",$R22*(1-CA22)*BZ22,IF($P$15="Additionnelle",($N22-($N22*($P22+CA22)))*BZ22))),"Non Trouvé") | CK22: =IFERROR(IF(F22='[1]Paramètres Généraux'!$K$12,ROUNDUP((REGENERANTS!H22*REGENERANTS!$CF$20)*'[1]Paramètres Généraux'!$M$12,-1),IF(F22='[1]Paramètres Généraux'!$K$15,ROUNDUP((REGENERANTS!H22*REGENERANTS!$CF$20)*'[1]Paramètres Généraux'!$M$15,-1),REGENERANTS!H22*REGENERANTS!$CF$20)),"nd") | DQ22: =SUM(CN22:DP22) | DR22: =SUM(CV22:DP22) | DS22: =IFERROR((IF(AND($F22="Produit Vente",CO22>0),VLOOKUP($C22,'[1]Paramètres Articles'!$B:$H,7,FALSE)*$CO22)*(1-20%)),0) | DT22: =IFERROR((IF(AND($F22="Produit Vente",DR22>0),VLOOKUP($C22,'[1]Paramètres Articles'!$B:$H,6,FALSE)*$DR22)*(1-15%)),0) | DU22: =IFERROR(DQ22*J22,0) | DY22: =VLOOKUP(DX22,C:D,2,FALSE) | DZ22: =SUMIFS('[1]Moteur Produits'!$C:$C,'[1]Moteur Produits'!$B:$B,$DX22)
B23: =IF(C23="",0,COUNTIFS($B$22:B22,">"&0)+1) | C23: 1020310 | D23: =IFERROR(IF($C23="","",VLOOKUP($C23,'[1]Paramètres Articles'!$B:$G,2,FALSE)),"Non Trouvé") | E23: =IFERROR(IF($C23="","",_xlfn.XLOOKUP(REGENERANTS!$C23,'[1]New Base PA'!$F:$F,'[1]New Base PA'!$D:$D,"Not Found",0)),"Non Trouvé") | F23: Produit Vente | H23: 4 | J23: =IFERROR(IF($C23="","",VLOOKUP($C23,'[1]New Base PA'!$F:$J,5,FALSE)),"Non Trouvé") | K23: =IFERROR(IF($C23="","",$J23*$H23),"Non Trouvé") | M23: =IFERROR(IF(AND($F23="Produit Vente",H23>0),VLOOKUP($C23,'[1]Paramètres Articles'!$B:$G,6,FALSE),0),"Non Trouvé") | N23: =IFERROR(IF($C23="","",$M23*$H23),"Non Trouvé") | P23: 0.15 | R23: =IFERROR(IF($C23="","",$N23*(1-$P23)),"Non Trouvé") | T23: =IFERROR(IF($C23="","",VLOOKUP($C23,'[1]Paramètres Articles'!$B:$H,7,FALSE)),"Non Trouvé") | V23: =IFERROR(IF($C23="","",IF($P23="","",$T23*(1-$P23))),"Non Trouvé") | X23: =IFERROR(T23-V23,"") | Z23: =IFERROR(IF(OR(T23=0,T23=""),0,T23*H23),"Non Trouvé") | AB23: =AB22 | AC23: =AC22 | AD23: =IFERROR(IF($C23="","",IF($P$15="Cascade",$R23*(1-AC23)*AB23,IF($P$15="Additionnelle",($N23-($N23*($P23+AC23)))*AB23))),"Non Trouvé") | AG23: =AG22 | AH23: =AH22 | AI23: =IFERROR(IF($C23="","",IF($P$15="Cascade",$R23*(1-AH23)*AG23,IF($P$15="Additionnelle",($N23-($N23*($P23+AH23)))*AG23))),"Non Trouvé") | AL23: =AL22 | AM23: =AM22 | AN23: =IFERROR(IF($C23="","",IF($P$15="Cascade",$R23*(1-AM23)*AL23,IF($P$15="Additionnelle",($N23-($N23*($P23+AM23)))*AL23))),"Non Trouvé") | AQ23: =AQ22 | AR23: =AR22 | AS23: =IFERROR(IF($C23="","",IF($P$15="Cascade",$R23*(1-AR23)*AQ23,IF($P$15="Additionnelle",($N23-($N23*($P23+AR23)))*AQ23))),"Non Trouvé") | AV23: =AV22 | AW23: =AW22 | AX23: =IFERROR(IF($C23="","",IF($P$15="Cascade",$R23*(1-AW23)*AV23,IF($P$15="Additionnelle",($N23-($N23*($P23+AW23)))*AV23))),"Non Trouvé") | BA23: =BA22 | BB23: =BB22 | BC23: =IFERROR(IF($C23="","",IF($P$15="Cascade",$R23*(1-BB23)*BA23,IF($P$15="Additionnelle",($N23-($N23*($P23+BB23)))*BA23))),"Non Trouvé") | BF23: =BF22 | BG23: =BG22 | BH23: =IFERROR(IF($C23="","",IF($P$15="Cascade",$R23*(1-BG23)*BF23,IF($P$15="Additionnelle",($N23-($N23*($P23+BG23)))*BF23))),"Non Trouvé") | BK23: =BK22 | BL23: =BL22 | BM23: =IFERROR(IF($C23="","",IF($P$15="Cascade",$R23*(1-BL23)*BK23,IF($P$15="Additionnelle",($N23-($N23*($P23+BL23)))*BK23))),"Non Trouvé") | BP23: =BP22 | BQ23: =BQ22 | BR23: =IFERROR(IF($C23="","",IF($P$15="Cascade",$R23*(1-BQ23)*BP23,IF($P$15="Additionnelle",($N23-($N23*($P23+BQ23)))*BP23))),"Non Trouvé") | BU23: =BU22 | BV23: =BV22 | BW23: =IFERROR(IF($C23="","",IF($P$15="Cascade",$R23*(1-BV23)*BU23,IF($P$15="Additionnelle",($N23-($N23*($P23+BV23)))*BU23))),"Non Trouvé") | BZ23: =BZ22 | CA23: =CA22 | CB23: =IFERROR(IF($C23="","",IF($P$15="Cascade",$R23*(1-CA23)*BZ23,IF($P$15="Additionnelle",($N23-($N23*($P23+CA23)))*BZ23))),"Non Trouvé") | CG23: Prix Offre Moy. Remisé : | CH23: =CG20/CF20 | CK23: =IFERROR(IF(F23='[1]Paramètres Généraux'!$K$12,ROUNDUP((REGENERANTS!H23*REGENERANTS!$CF$20)*'[1]Paramètres Généraux'!$M$12,-1),IF(F23='[1]Paramètres Généraux'!$K$15,ROUNDUP((REGENERANTS!H23*REGENERANTS!$CF$20)*'[1]Paramètres Généraux'!$M$15,-1),REGENERANTS!H23*REGENERANTS!$CF$20)),"nd") | DQ23: =SUM(CN23:DP23) | DR23: =SUM(CV23:DP23) | DS23: =IFERROR((IF(AND($F23="Produit Vente",CO23>0),VLOOKUP($C23,'[1]Paramètres Articles'!$B:$H,7,FALSE)*$CO23)*(1-20%)),0) | DT23: =IFERROR((IF(AND($F23="Produit Vente",DR23>0),VLOOKUP($C23,'[1]Paramètres Articles'!$B:$H,6,FALSE)*$DR23)*(1-15%)),0) | DU23: =IFERROR(DQ23*J23,0) | DY23: =VLOOKUP(DX23,C:D,2,FALSE) | DZ23: =SUMIFS('[1]Moteur Produits'!$C:$C,'[1]Moteur Produits'!$B:$B,$DX23)
B24: =IF(C24="",0,COUNTIFS($B$22:B23,">"&0)+1) | C24: 1020401 | D24: =IFERROR(IF($C24="","",VLOOKUP($C24,'[1]Paramètres Articles'!$B:$G,2,FALSE)),"Non Trouvé") | E24: =IFERROR(IF($C24="","",_xlfn.XLOOKUP(REGENERANTS!$C24,'[1]New Base PA'!$F:$F,'[1]New Base PA'!$D:$D,"Not Found",0)),"Non Trouvé") | F24: Produit Vente | H24: 5 | J24: =IFERROR(IF($C24="","",VLOOKUP($C24,'[1]New Base PA'!$F:$J,5,FALSE)),"Non Trouvé") | K24: =IFERROR(IF($C24="","",$J24*$H24),"Non Trouvé") | M24: =IFERROR(IF(AND($F24="Produit Vente",H24>0),VLOOKUP($C24,'[1]Paramètres Articles'!$B:$G,6,FALSE),0),"Non Trouvé") | N24: =IFERROR(IF($C24="","",$M24*$H24),"Non Trouvé") | P24: 0.15 | R24: =IFERROR(IF($C24="","",$N24*(1-$P24)),"Non Trouvé") | T24: =IFERROR(IF($C24="","",VLOOKUP($C24,'[1]Paramètres Articles'!$B:$H,7,FALSE)),"Non Trouvé") | V24: =IFERROR(IF($C24="","",IF($P24="","",$T24*(1-$P24))),"Non Trouvé") | X24: =IFERROR(T24-V24,"") | Z24: =IFERROR(IF(OR(T24=0,T24=""),0,T24*H24),"Non Trouvé") | AB24: =AB23 | AC24: =AC23 | AD24: =IFERROR(IF($C24="","",IF($P$15="Cascade",$R24*(1-AC24)*AB24,IF($P$15="Additionnelle",($N24-($N24*($P24+AC24)))*AB24))),"Non Trouvé") | AG24: =AG23 | AH24: =AH23 | AI24: =IFERROR(IF($C24="","",IF($P$15="Cascade",$R24*(1-AH24)*AG24,IF($P$15="Additionnelle",($N24-($N24*($P24+AH24)))*AG24))),"Non Trouvé") | AL24: =AL23 | AM24: =AM23 | AN24: =IFERROR(IF($C24="","",IF($P$15="Cascade",$R24*(1-AM24)*AL24,IF($P$15="Additionnelle",($N24-($N24*($P24+AM24)))*AL24))),"Non Trouvé") | AQ24: =AQ23 | AR24: =AR23 | AS24: =IFERROR(IF($C24="","",IF($P$15="Cascade",$R24*(1-AR24)*AQ24,IF($P$15="Additionnelle",($N24-($N24*($P24+AR24)))*AQ24))),"Non Trouvé") | AV24: =AV23 | AW24: =AW23 | AX24: =IFERROR(IF($C24="","",IF($P$15="Cascade",$R24*(1-AW24)*AV24,IF($P$15="Additionnelle",($N24-($N24*($P24+AW24)))*AV24))),"Non Trouvé") | BA24: =BA23 | BB24: =BB23 | BC24: =IFERROR(IF($C24="","",IF($P$15="Cascade",$R24*(1-BB24)*BA24,IF($P$15="Additionnelle",($N24-($N24*($P24+BB24)))*BA24))),"Non Trouvé") | BF24: =BF23 | BG24: =BG23 | BH24: =IFERROR(IF($C24="","",IF($P$15="Cascade",$R24*(1-BG24)*BF24,IF($P$15="Additionnelle",($N24-($N24*($P24+BG24)))*BF24))),"Non Trouvé") | BK24: =BK23 | BL24: =BL23 | BM24: =IFERROR(IF($C24="","",IF($P$15="Cascade",$R24*(1-BL24)*BK24,IF($P$15="Additionnelle",($N24-($N24*($P24+BL24)))*BK24))),"Non Trouvé") | BP24: =BP23 | BQ24: =BQ23 | BR24: =IFERROR(IF($C24="","",IF($P$15="Cascade",$R24*(1-BQ24)*BP24,IF($P$15="Additionnelle",($N24-($N24*($P24+BQ24)))*BP24))),"Non Trouvé") | BU24: =BU23 | BV24: =BV23 | BW24: =IFERROR(IF($C24="","",IF($P$15="Cascade",$R24*(1-BV24)*BU24,IF($P$15="Additionnelle",($N24-($N24*($P24+BV24)))*BU24))),"Non Trouvé") | BZ24: =BZ23 | CA24: =CA23 | CB24: =IFERROR(IF($C24="","",IF($P$15="Cascade",$R24*(1-CA24)*BZ24,IF($P$15="Additionnelle",($N24-($N24*($P24+CA24)))*BZ24))),"Non Trouvé") | CG24: Poids Gratuités achats : | CH24: =SUM(CH26:CH29) | CK24: =IFERROR(IF(F24='[1]Paramètres Généraux'!$K$12,ROUNDUP((REGENERANTS!H24*REGENERANTS!$CF$20)*'[1]Paramètres Généraux'!$M$12,-1),IF(F24='[1]Paramètres Généraux'!$K$15,ROUNDUP((REGENERANTS!H24*REGENERANTS!$CF$20)*'[1]Paramètres Généraux'!$M$15,-1),REGENERANTS!H24*REGENERANTS!$CF$20)),"nd") | DQ24: =SUM(CN24:DP24) | DR24: =SUM(CV24:DP24) | DS24: =IFERROR((IF(AND($F24="Produit Vente",CO24>0),VLOOKUP($C24,'[1]Paramètres Articles'!$B:$H,7,FALSE)*$CO24)*(1-20%)),0) | DT24: =IFERROR((IF(AND($F24="Produit Vente",DR24>0),VLOOKUP($C24,'[1]Paramètres Articles'!$B:$H,6,FALSE)*$DR24)*(1-15%)),0) | DU24: =IFERROR(DQ24*J24,0) | DY24: =VLOOKUP(DX24,C:D,2,FALSE) | DZ24: =SUMIFS('[1]Moteur Produits'!$C:$C,'[1]Moteur Produits'!$B:$B,$DX24)
B25: =IF(C25="",0,COUNTIFS($B$22:B24,">"&0)+1) | C25: 1020302 | D25: =IFERROR(IF($C25="","",VLOOKUP($C25,'[1]Paramètres Articles'!$B:$G,2,FALSE)),"Non Trouvé") | E25: =IFERROR(IF($C25="","",_xlfn.XLOOKUP(REGENERANTS!$C25,'[1]New Base PA'!$F:$F,'[1]New Base PA'!$D:$D,"Not Found",0)),"Non Trouvé") | F25: Produit Vente | H25: 1 | J25: =IFERROR(IF($C25="","",VLOOKUP($C25,'[1]New Base PA'!$F:$J,5,FALSE)),"Non Trouvé") | K25: =IFERROR(IF($C25="","",$J25*$H25),"Non Trouvé") | M25: =IFERROR(IF(AND($F25="Produit Vente",H25>0),VLOOKUP($C25,'[1]Paramètres Articles'!$B:$G,6,FALSE),0),"Non Trouvé") | N25: =IFERROR(IF($C25="","",$M25*$H25),"Non Trouvé") | P25: 0.15 | R25: =IFERROR(IF($C25="","",$N25*(1-$P25)),"Non Trouvé") | T25: =IFERROR(IF($C25="","",VLOOKUP($C25,'[1]Paramètres Articles'!$B:$H,7,FALSE)),"Non Trouvé") | V25: =IFERROR(IF($C25="","",IF($P25="","",$T25*(1-$P25))),"Non Trouvé") | X25: =IFERROR(T25-V25,"") | Z25: =IFERROR(IF(OR(T25=0,T25=""),0,T25*H25),"Non Trouvé") | AB25: =AB24 | AC25: =AC24 | AD25: =IFERROR(IF($C25="","",IF($P$15="Cascade",$R25*(1-AC25)*AB25,IF($P$15="Additionnelle",($N25-($N25*($P25+AC25)))*AB25))),"Non Trouvé") | AG25: =AG24 | AH25: =AH24 | AI25: =IFERROR(IF($C25="","",IF($P$15="Cascade",$R25*(1-AH25)*AG25,IF($P$15="Additionnelle",($N25-($N25*($P25+AH25)))*AG25))),"Non Trouvé") | AL25: =AL24 | AM25: =AM24 | AN25: =IFERROR(IF($C25="","",IF($P$15="Cascade",$R25*(1-AM25)*AL25,IF($P$15="Additionnelle",($N25-($N25*($P25+AM25)))*AL25))),"Non Trouvé") | AQ25: =AQ24 | AR25: =AR24 | AS25: =IFERROR(IF($C25="","",IF($P$15="Cascade",$R25*(1-AR25)*AQ25,IF($P$15="Additionnelle",($N25-($N25*($P25+AR25)))*AQ25))),"Non Trouvé") | AV25: =AV24 | AW25: =AW24 | AX25: =IFERROR(IF($C25="","",IF($P$15="Cascade",$R25*(1-AW25)*AV25,IF($P$15="Additionnelle",($N25-($N25*($P25+AW25)))*AV25))),"Non Trouvé") | BA25: =BA24 | BB25: =BB24 | BC25: =IFERROR(IF($C25="","",IF($P$15="Cascade",$R25*(1-BB25)*BA25,IF($P$15="Additionnelle",($N25-($N25*($P25+BB25)))*BA25))),"Non Trouvé") | BF25: =BF24 | BG25: =BG24 | BH25: =IFERROR(IF($C25="","",IF($P$15="Cascade",$R25*(1-BG25)*BF25,IF($P$15="Additionnelle",($N25-($N25*($P25+BG25)))*BF25))),"Non Trouvé") | BK25: =BK24 | BL25: =BL24 | BM25: =IFERROR(IF($C25="","",IF($P$15="Cascade",$R25*(1-BL25)*BK25,IF($P$15="Additionnelle",($N25-($N25*($P25+BL25)))*BK25))),"Non Trouvé") | BP25: =BP24 | BQ25: =BQ24 | BR25: =IFERROR(IF($C25="","",IF($P$15="Cascade",$R25*(1-BQ25)*BP25,IF($P$15="Additionnelle",($N25-($N25*($P25+BQ25)))*BP25))),"Non Trouvé") | BU25: =BU24 | BV25: =BV24 | BW25: =IFERROR(IF($C25="","",IF($P$15="Cascade",$R25*(1-BV25)*BU25,IF($P$15="Additionnelle",($N25-($N25*($P25+BV25)))*BU25))),"Non Trouvé") | BZ25: =BZ24 | CA25: =CA24 | CB25: =IFERROR(IF($C25="","",IF($P$15="Cascade",$R25*(1-CA25)*BZ25,IF($P$15="Additionnelle",($N25-($N25*($P25+CA25)))*BZ25))),"Non Trouvé") | CK25: =IFERROR(IF(F25='[1]Paramètres Généraux'!$K$12,ROUNDUP((REGENERANTS!H25*REGENERANTS!$CF$20)*'[1]Paramètres Généraux'!$M$12,-1),IF(F25='[1]Paramètres Généraux'!$K$15,ROUNDUP((REGENERANTS!H25*REGENERANTS!$CF$20)*'[1]Paramètres Généraux'!$M$15,-1),REGENERANTS!H25*REGENERANTS!$CF$20)),"nd") | DQ25: =SUM(CN25:DP25) | DR25: =SUM(CV25:DP25) | DS25: =IFERROR((IF(AND($F25="Produit Vente",CO25>0),VLOOKUP($C25,'[1]Paramètres Articles'!$B:$H,7,FALSE)*$CO25)*(1-20%)),0) | DT25: =IFERROR((IF(AND($F25="Produit Vente",DR25>0),VLOOKUP($C25,'[1]Paramètres Articles'!$B:$H,6,FALSE)*$DR25)*(1-15%)),0) | DU25: =IFERROR(DQ25*J25,0) | DY25: =VLOOKUP(DX25,C:D,2,FALSE) | DZ25: =SUMIFS('[1]Moteur Produits'!$C:$C,'[1]Moteur Produits'!$B:$B,$DX25)
B26: =IF(C26="",0,COUNTIFS($B$22:B25,">"&0)+1) | C26: 1020721 | D26: =IFERROR(IF($C26="","",VLOOKUP($C26,'[1]Paramètres Articles'!$B:$G,2,FALSE)),"Non Trouvé") | E26: =IFERROR(IF($C26="","",_xlfn.XLOOKUP(REGENERANTS!$C26,'[1]New Base PA'!$F:$F,'[1]New Base PA'!$D:$D,"Not Found",0)),"Non Trouvé") | F26: Produit Vente | H26: 0 | J26: =IFERROR(IF($C26="","",VLOOKUP($C26,'[1]New Base PA'!$F:$J,5,FALSE)),"Non Trouvé") | K26: =IFERROR(IF($C26="","",$J26*$H26),"Non Trouvé") | M26: =IFERROR(IF(AND($F26="Produit Vente",H26>0),VLOOKUP($C26,'[1]Paramètres Articles'!$B:$G,6,FALSE),0),"Non Trouvé") | N26: =IFERROR(IF($C26="","",$M26*$H26),"Non Trouvé") | P26: 0.15 | R26: =IFERROR(IF($C26="","",$N26*(1-$P26)),"Non Trouvé") | T26: =IFERROR(IF($C26="","",VLOOKUP($C26,'[1]Paramètres Articles'!$B:$H,7,FALSE)),"Non Trouvé") | V26: =IFERROR(IF($C26="","",IF($P26="","",$T26*(1-$P26))),"Non Trouvé") | X26: =IFERROR(T26-V26,"") | Z26: =IFERROR(IF(OR(T26=0,T26=""),0,T26*H26),"Non Trouvé") | AB26: =AB25 | AC26: =AC25 | AD26: =IFERROR(IF($C26="","",IF($P$15="Cascade",$R26*(1-AC26)*AB26,IF($P$15="Additionnelle",($N26-($N26*($P26+AC26)))*AB26))),"Non Trouvé") | AG26: =AG25 | AH26: =AH25 | AI26: =IFERROR(IF($C26="","",IF($P$15="Cascade",$R26*(1-AH26)*AG26,IF($P$15="Additionnelle",($N26-($N26*($P26+AH26)))*AG26))),"Non Trouvé") | AL26: =AL25 | AM26: =AM25 | AN26: =IFERROR(IF($C26="","",IF($P$15="Cascade",$R26*(1-AM26)*AL26,IF($P$15="Additionnelle",($N26-($N26*($P26+AM26)))*AL26))),"Non Trouvé") | AQ26: =AQ25 | AR26: =AR25 | AS26: =IFERROR(IF($C26="","",IF($P$15="Cascade",$R26*(1-AR26)*AQ26,IF($P$15="Additionnelle",($N26-($N26*($P26+AR26)))*AQ26))),"Non Trouvé") | AV26: =AV25 | AW26: =AW25 | AX26: =IFERROR(IF($C26="","",IF($P$15="Cascade",$R26*(1-AW26)*AV26,IF($P$15="Additionnelle",($N26-($N26*($P26+AW26)))*AV26))),"Non Trouvé") | BA26: =BA25 | BB26: =BB25 | BC26: =IFERROR(IF($C26="","",IF($P$15="Cascade",$R26*(1-BB26)*BA26,IF($P$15="Additionnelle",($N26-($N26*($P26+BB26)))*BA26))),"Non Trouvé") | BF26: =BF25 | BG26: =BG25 | BH26: =IFERROR(IF($C26="","",IF($P$15="Cascade",$R26*(1-BG26)*BF26,IF($P$15="Additionnelle",($N26-($N26*($P26+BG26)))*BF26))),"Non Trouvé") | BK26: =BK25 | BL26: =BL25 | BM26: =IFERROR(IF($C26="","",IF($P$15="Cascade",$R26*(1-BL26)*BK26,IF($P$15="Additionnelle",($N26-($N26*($P26+BL26)))*BK26))),"Non Trouvé") | BP26: =BP25 | BQ26: =BQ25 | BR26: =IFERROR(IF($C26="","",IF($P$15="Cascade",$R26*(1-BQ26)*BP26,IF($P$15="Additionnelle",($N26-($N26*($P26+BQ26)))*BP26))),"Non Trouvé") | BU26: =BU25 | BV26: =BV25 | BW26: =IFERROR(IF($C26="","",IF($P$15="Cascade",$R26*(1-BV26)*BU26,IF($P$15="Additionnelle",($N26-($N26*($P26+BV26)))*BU26))),"Non Trouvé") | BZ26: =BZ25 | CA26: =CA25 | CB26: =IFERROR(IF($C26="","",IF($P$15="Cascade",$R26*(1-CA26)*BZ26,IF($P$15="Additionnelle",($N26-($N26*($P26+CA26)))*BZ26))),"Non Trouvé") | CG26: UG | CH26: =SUMIFS(K22:K62,F22:F62,CG26)/SUMIFS(K22:K62,F22:F62,"Produit Vente") | CK26: =IFERROR(IF(F26='[1]Paramètres Généraux'!$K$12,ROUNDUP((REGENERANTS!H26*REGENERANTS!$CF$20)*'[1]Paramètres Généraux'!$M$12,-1),IF(F26='[1]Paramètres Généraux'!$K$15,ROUNDUP((REGENERANTS!H26*REGENERANTS!$CF$20)*'[1]Paramètres Généraux'!$M$15,-1),REGENERANTS!H26*REGENERANTS!$CF$20)),"nd") | DQ26: =SUM(CN26:DP26) | DR26: =SUM(CV26:DP26) | DS26: =IFERROR((IF(AND($F26="Produit Vente",CO26>0),VLOOKUP($C26,'[1]Paramètres Articles'!$B:$H,7,FALSE)*$CO26)*(1-20%)),0) | DT26: =IFERROR((IF(AND($F26="Produit Vente",DR26>0),VLOOKUP($C26,'[1]Paramètres Articles'!$B:$H,6,FALSE)*$DR26)*(1-15%)),0) | DU26: =IFERROR(DQ26*J26,0) | DY26: =VLOOKUP(DX26,C:D,2,FALSE) | DZ26: =SUMIFS('[1]Moteur Produits'!$C:$C,'[1]Moteur Produits'!$B:$B,$DX26)
B27: =IF(C27="",0,COUNTIFS($B$22:B26,">"&0)+1) | C27: 1020107 | D27: =IFERROR(IF($C27="","",VLOOKUP($C27,'[1]Paramètres Articles'!$B:$G,2,FALSE)),"Non Trouvé") | E27: =IFERROR(IF($C27="","",_xlfn.XLOOKUP(REGENERANTS!$C27,'[1]New Base PA'!$F:$F,'[1]New Base PA'!$D:$D,"Not Found",0)),"Non Trouvé") | F27: Produit Vente | H27: 3 | J27: =IFERROR(IF($C27="","",VLOOKUP($C27,'[1]New Base PA'!$F:$J,5,FALSE)),"Non Trouvé") | K27: =IFERROR(IF($C27="","",$J27*$H27),"Non Trouvé") | M27: =IFERROR(IF(AND($F27="Produit Vente",H27>0),VLOOKUP($C27,'[1]Paramètres Articles'!$B:$G,6,FALSE),0),"Non Trouvé") | N27: =IFERROR(IF($C27="","",$M27*$H27),"Non Trouvé") | P27: 0.15 | R27: =IFERROR(IF($C27="","",$N27*(1-$P27)),"Non Trouvé") | T27: =IFERROR(IF($C27="","",VLOOKUP($C27,'[1]Paramètres Articles'!$B:$H,7,FALSE)),"Non Trouvé") | V27: =IFERROR(IF($C27="","",IF($P27="","",$T27*(1-$P27))),"Non Trouvé") | X27: =IFERROR(T27-V27,"") | Z27: =IFERROR(IF(OR(T27=0,T27=""),0,T27*H27),"Non Trouvé") | AB27: =AB26 | AC27: =AC26 | AD27: =IFERROR(IF($C27="","",IF($P$15="Cascade",$R27*(1-AC27)*AB27,IF($P$15="Additionnelle",($N27-($N27*($P27+AC27)))*AB27))),"Non Trouvé") | AG27: =AG26 | AH27: =AH26 | AI27: =IFERROR(IF($C27="","",IF($P$15="Cascade",$R27*(1-AH27)*AG27,IF($P$15="Additionnelle",($N27-($N27*($P27+AH27)))*AG27))),"Non Trouvé") | AL27: =AL26 | AM27: =AM26 | AN27: =IFERROR(IF($C27="","",IF($P$15="Cascade",$R27*(1-AM27)*AL27,IF($P$15="Additionnelle",($N27-($N27*($P27+AM27)))*AL27))),"Non Trouvé") | AQ27: =AQ26 | AR27: =AR26 | AS27: =IFERROR(IF($C27="","",IF($P$15="Cascade",$R27*(1-AR27)*AQ27,IF($P$15="Additionnelle",($N27-($N27*($P27+AR27)))*AQ27))),"Non Trouvé") | AV27: =AV26 | AW27: =AW26 | AX27: =IFERROR(IF($C27="","",IF($P$15="Cascade",$R27*(1-AW27)*AV27,IF($P$15="Additionnelle",($N27-($N27*($P27+AW27)))*AV27))),"Non Trouvé") | BA27: =BA26 | BB27: =BB26 | BC27: =IFERROR(IF($C27="","",IF($P$15="Cascade",$R27*(1-BB27)*BA27,IF($P$15="Additionnelle",($N27-($N27*($P27+BB27)))*BA27))),"Non Trouvé") | BF27: =BF26 | BG27: =BG26 | BH27: =IFERROR(IF($C27="","",IF($P$15="Cascade",$R27*(1-BG27)*BF27,IF($P$15="Additionnelle",($N27-($N27*($P27+BG27)))*BF27))),"Non Trouvé") | BK27: =BK26 | BL27: =BL26 | BM27: =IFERROR(IF($C27="","",IF($P$15="Cascade",$R27*(1-BL27)*BK27,IF($P$15="Additionnelle",($N27-($N27*($P27+BL27)))*BK27))),"Non Trouvé") | BP27: =BP26 | BQ27: =BQ26 | BR27: =IFERROR(IF($C27="","",IF($P$15="Cascade",$R27*(1-BQ27)*BP27,IF($P$15="Additionnelle",($N27-($N27*($P27+BQ27)))*BP27))),"Non Trouvé") | BU27: =BU26 | BV27: =BV26 | BW27: =IFERROR(IF($C27="","",IF($P$15="Cascade",$R27*(1-BV27)*BU27,IF($P$15="Additionnelle",($N27-($N27*($P27+BV27)))*BU27))),"Non Trouvé") | BZ27: =BZ26 | CA27: =CA26 | CB27: =IFERROR(IF($C27="","",IF($P$15="Cascade",$R27*(1-CA27)*BZ27,IF($P$15="Additionnelle",($N27-($N27*($P27+CA27)))*BZ27))),"Non Trouvé") | CG27: PLV | CH27: =(SUMIFS(K22:K62,F22:F62,"PLV (PDC ou autre)")+SUMIFS(K22:K62,F22:F62,"PLV (vitrine)"))/K20 | CK27: =IFERROR(IF(F27='[1]Paramètres Généraux'!$K$12,ROUNDUP((REGENERANTS!H27*REGENERANTS!$CF$20)*'[1]Paramètres Généraux'!$M$12,-1),IF(F27='[1]Paramètres Généraux'!$K$15,ROUNDUP((REGENERANTS!H27*REGENERANTS!$CF$20)*'[1]Paramètres Généraux'!$M$15,-1),REGENERANTS!H27*REGENERANTS!$CF$20)),"nd") | DQ27: =SUM(CN27:DP27) | DR27: =SUM(CV27:DP27) | DS27: =IFERROR((IF(AND($F27="Produit Vente",CO27>0),VLOOKUP($C27,'[1]Paramètres Articles'!$B:$H,7,FALSE)*$CO27)*(1-20%)),0) | DT27: =IFERROR((IF(AND($F27="Produit Vente",DR27>0),VLOOKUP($C27,'[1]Paramètres Articles'!$B:$H,6,FALSE)*$DR27)*(1-15%)),0) | DU27: =IFERROR(DQ27*J27,0)
B28: =IF(C28="",0,COUNTIFS($B$22:B27,">"&0)+1) | C28: 1020102 | D28: =IFERROR(IF($C28="","",VLOOKUP($C28,'[1]Paramètres Articles'!$B:$G,2,FALSE)),"Non Trouvé") | E28: =IFERROR(IF($C28="","",_xlfn.XLOOKUP(REGENERANTS!$C28,'[1]New Base PA'!$F:$F,'[1]New Base PA'!$D:$D,"Not Found",0)),"Non Trouvé") | F28: Produit Vente | H28: 3 | J28: =IFERROR(IF($C28="","",VLOOKUP($C28,'[1]New Base PA'!$F:$J,5,FALSE)),"Non Trouvé") | K28: =IFERROR(IF($C28="","",$J28*$H28),"Non Trouvé") | M28: =IFERROR(IF(AND($F28="Produit Vente",H28>0),VLOOKUP($C28,'[1]Paramètres Articles'!$B:$G,6,FALSE),0),"Non Trouvé") | N28: =IFERROR(IF($C28="","",$M28*$H28),"Non Trouvé") | P28: 0.15 | R28: =IFERROR(IF($C28="","",$N28*(1-$P28)),"Non Trouvé") | T28: =IFERROR(IF($C28="","",VLOOKUP($C28,'[1]Paramètres Articles'!$B:$H,7,FALSE)),"Non Trouvé") | V28: =IFERROR(IF($C28="","",IF($P28="","",$T28*(1-$P28))),"Non Trouvé") | X28: =IFERROR(T28-V28,"") | Z28: =IFERROR(IF(OR(T28=0,T28=""),0,T28*H28),"Non Trouvé") | AB28: =AB27 | AC28: =AC27 | AD28: =IFERROR(IF($C28="","",IF($P$15="Cascade",$R28*(1-AC28)*AB28,IF($P$15="Additionnelle",($N28-($N28*($P28+AC28)))*AB28))),"Non Trouvé") | AG28: =AG27 | AH28: =AH27 | AI28: =IFERROR(IF($C28="","",IF($P$15="Cascade",$R28*(1-AH28)*AG28,IF($P$15="Additionnelle",($N28-($N28*($P28+AH28)))*AG28))),"Non Trouvé") | AL28: =AL27 | AM28: =AM27 | AN28: =IFERROR(IF($C28="","",IF($P$15="Cascade",$R28*(1-AM28)*AL28,IF($P$15="Additionnelle",($N28-($N28*($P28+AM28)))*AL28))),"Non Trouvé") | AQ28: =AQ27 | AR28: =AR27 | AS28: =IFERROR(IF($C28="","",IF($P$15="Cascade",$R28*(1-AR28)*AQ28,IF($P$15="Additionnelle",($N28-($N28*($P28+AR28)))*AQ28))),"Non Trouvé") | AV28: =AV27 | AW28: =AW27 | AX28: =IFERROR(IF($C28="","",IF($P$15="Cascade",$R28*(1-AW28)*AV28,IF($P$15="Additionnelle",($N28-($N28*($P28+AW28)))*AV28))),"Non Trouvé") | BA28: =BA27 | BB28: =BB27 | BC28: =IFERROR(IF($C28="","",IF($P$15="Cascade",$R28*(1-BB28)*BA28,IF($P$15="Additionnelle",($N28-($N28*($P28+BB28)))*BA28))),"Non Trouvé") | BF28: =BF27 | BG28: =BG27 | BH28: =IFERROR(IF($C28="","",IF($P$15="Cascade",$R28*(1-BG28)*BF28,IF($P$15="Additionnelle",($N28-($N28*($P28+BG28)))*BF28))),"Non Trouvé") | BK28: =BK27 | BL28: =BL27 | BM28: =IFERROR(IF($C28="","",IF($P$15="Cascade",$R28*(1-BL28)*BK28,IF($P$15="Additionnelle",($N28-($N28*($P28+BL28)))*BK28))),"Non Trouvé") | BP28: =BP27 | BQ28: =BQ27 | BR28: =IFERROR(IF($C28="","",IF($P$15="Cascade",$R28*(1-BQ28)*BP28,IF($P$15="Additionnelle",($N28-($N28*($P28+BQ28)))*BP28))),"Non Trouvé") | BU28: =BU27 | BV28: =BV27 | BW28: =IFERROR(IF($C28="","",IF($P$15="Cascade",$R28*(1-BV28)*BU28,IF($P$15="Additionnelle",($N28-($N28*($P28+BV28)))*BU28))),"Non Trouvé") | BZ28: =BZ27 | CA28: =CA27 | CB28: =IFERROR(IF($C28="","",IF($P$15="Cascade",$R28*(1-CA28)*BZ28,IF($P$15="Additionnelle",($N28-($N28*($P28+CA28)))*BZ28))),"Non Trouvé") | CG28: Echantillon | CH28: =SUMIFS(K22:K62,F22:F62,CG28)/K20 | CK28: =IFERROR(IF(F28='[1]Paramètres Généraux'!$K$12,ROUNDUP((REGENERANTS!H28*REGENERANTS!$CF$20)*'[1]Paramètres Généraux'!$M$12,-1),IF(F28='[1]Paramètres Généraux'!$K$15,ROUNDUP((REGENERANTS!H28*REGENERANTS!$CF$20)*'[1]Paramètres Généraux'!$M$15,-1),REGENERANTS!H28*REGENERANTS!$CF$20)),"nd") | DQ28: =SUM(CN28:DP28) | DR28: =SUM(CV28:DP28) | DS28: =IFERROR((IF(AND($F28="Produit Vente",CO28>0),VLOOKUP($C28,'[1]Paramètres Articles'!$B:$H,7,FALSE)*$CO28)*(1-20%)),0) | DT28: =IFERROR((IF(AND($F28="Produit Vente",DR28>0),VLOOKUP($C28,'[1]Paramètres Articles'!$B:$H,6,FALSE)*$DR28)*(1-15%)),0) | DU28: =IFERROR(DQ28*J28,0)
B29: =IF(C29="",0,COUNTIFS($B$22:B28,">"&0)+1) | C29: 1020722 | D29: =IFERROR(IF($C29="","",VLOOKUP($C29,'[1]Paramètres Articles'!$B:$G,2,FALSE)),"Non Trouvé") | E29: =IFERROR(IF($C29="","",_xlfn.XLOOKUP(REGENERANTS!$C29,'[1]New Base PA'!$F:$F,'[1]New Base PA'!$D:$D,"Not Found",0)),"Non Trouvé") | F29: Produit Vente | H29: 0 | J29: =IFERROR(IF($C29="","",VLOOKUP($C29,'[1]New Base PA'!$F:$J,5,FALSE)),"Non Trouvé") | K29: =IFERROR(IF($C29="","",$J29*$H29),"Non Trouvé") | M29: =IFERROR(IF(AND($F29="Produit Vente",H29>0),VLOOKUP($C29,'[1]Paramètres Articles'!$B:$G,6,FALSE),0),"Non Trouvé") | N29: =IFERROR(IF($C29="","",$M29*$H29),"Non Trouvé") | P29: 0.15 | R29: =IFERROR(IF($C29="","",$N29*(1-$P29)),"Non Trouvé") | T29: =IFERROR(IF($C29="","",VLOOKUP($C29,'[1]Paramètres Articles'!$B:$H,7,FALSE)),"Non Trouvé") | V29: =IFERROR(IF($C29="","",IF($P29="","",$T29*(1-$P29))),"Non Trouvé") | X29: =IFERROR(T29-V29,"") | Z29: =IFERROR(IF(OR(T29=0,T29=""),0,T29*H29),"Non Trouvé") | AB29: =AB28 | AC29: =AC28 | AD29: =IFERROR(IF($C29="","",IF($P$15="Cascade",$R29*(1-AC29)*AB29,IF($P$15="Additionnelle",($N29-($N29*($P29+AC29)))*AB29))),"Non Trouvé") | AG29: =AG28 | AH29: =AH28 | AI29: =IFERROR(IF($C29="","",IF($P$15="Cascade",$R29*(1-AH29)*AG29,IF($P$15="Additionnelle",($N29-($N29*($P29+AH29)))*AG29))),"Non Trouvé") | AL29: =AL28 | AM29: =AM28 | AN29: =IFERROR(IF($C29="","",IF($P$15="Cascade",$R29*(1-AM29)*AL29,IF($P$15="Additionnelle",($N29-($N29*($P29+AM29)))*AL29))),"Non Trouvé") | AQ29: =AQ28 | AR29: =AR28 | AS29: =IFERROR(IF($C29="","",IF($P$15="Cascade",$R29*(1-AR29)*AQ29,IF($P$15="Additionnelle",($N29-($N29*($P29+AR29)))*AQ29))),"Non Trouvé") | AV29: =AV28 | AW29: =AW28 | AX29: =IFERROR(IF($C29="","",IF($P$15="Cascade",$R29*(1-AW29)*AV29,IF($P$15="Additionnelle",($N29-($N29*($P29+AW29)))*AV29))),"Non Trouvé") | BA29: =BA28 | BB29: =BB28 | BC29: =IFERROR(IF($C29="","",IF($P$15="Cascade",$R29*(1-BB29)*BA29,IF($P$15="Additionnelle",($N29-($N29*($P29+BB29)))*BA29))),"Non Trouvé") | BF29: =BF28 | BG29: =BG28 | BH29: =IFERROR(IF($C29="","",IF($P$15="Cascade",$R29*(1-BG29)*BF29,IF($P$15="Additionnelle",($N29-($N29*($P29+BG29)))*BF29))),"Non Trouvé") | BK29: =BK28 | BL29: =BL28 | BM29: =IFERROR(IF($C29="","",IF($P$15="Cascade",$R29*(1-BL29)*BK29,IF($P$15="Additionnelle",($N29-($N29*($P29+BL29)))*BK29))),"Non Trouvé") | BP29: =BP28 | BQ29: =BQ28 | BR29: =IFERROR(IF($C29="","",IF($P$15="Cascade",$R29*(1-BQ29)*BP29,IF($P$15="Additionnelle",($N29-($N29*($P29+BQ29)))*BP29))),"Non Trouvé") | BU29: =BU28 | BV29: =BV28 | BW29: =IFERROR(IF($C29="","",IF($P$15="Cascade",$R29*(1-BV29)*BU29,IF($P$15="Additionnelle",($N29-($N29*($P29+BV29)))*BU29))),"Non Trouvé") | BZ29: =BZ28 | CA29: =CA28 | CB29: =IFERROR(IF($C29="","",IF($P$15="Cascade",$R29*(1-CA29)*BZ29,IF($P$15="Additionnelle",($N29-($N29*($P29+CA29)))*BZ29))),"Non Trouvé") | CG29: Testeur | CH29: =SUMIFS(K22:K62,F22:F62,CG29)/K20 | CK29: =IFERROR(IF(F29='[1]Paramètres Généraux'!$K$12,ROUNDUP((REGENERANTS!H29*REGENERANTS!$CF$20)*'[1]Paramètres Généraux'!$M$12,-1),IF(F29='[1]Paramètres Généraux'!$K$15,ROUNDUP((REGENERANTS!H29*REGENERANTS!$CF$20)*'[1]Paramètres Généraux'!$M$15,-1),REGENERANTS!H29*REGENERANTS!$CF$20)),"nd") | DQ29: =SUM(CN29:DP29) | DR29: =SUM(CV29:DP29) | DS29: =IFERROR((IF(AND($F29="Produit Vente",CO29>0),VLOOKUP($C29,'[1]Paramètres Articles'!$B:$H,7,FALSE)*$CO29)*(1-20%)),0) | DT29: =IFERROR((IF(AND($F29="Produit Vente",DR29>0),VLOOKUP($C29,'[1]Paramètres Articles'!$B:$H,6,FALSE)*$DR29)*(1-15%)),0) | DU29: =IFERROR(DQ29*J29,0)
B30: =IF(C30="",0,COUNTIFS($B$22:B29,">"&0)+1) | C30: 1020719 | D30: =IFERROR(IF($C30="","",VLOOKUP($C30,'[1]Paramètres Articles'!$B:$G,2,FALSE)),"Non Trouvé") | E30: =IFERROR(IF($C30="","",_xlfn.XLOOKUP(REGENERANTS!$C30,'[1]New Base PA'!$F:$F,'[1]New Base PA'!$D:$D,"Not Found",0)),"Non Trouvé") | F30: Produit Vente | H30: 3 | J30: =IFERROR(IF($C30="","",VLOOKUP($C30,'[1]New Base PA'!$F:$J,5,FALSE)),"Non Trouvé") | K30: =IFERROR(IF($C30="","",$J30*$H30),"Non Trouvé") | M30: =IFERROR(IF(AND($F30="Produit Vente",H30>0),VLOOKUP($C30,'[1]Paramètres Articles'!$B:$G,6,FALSE),0),"Non Trouvé") | N30: =IFERROR(IF($C30="","",$M30*$H30),"Non Trouvé") | P30: 0.15 | R30: =IFERROR(IF($C30="","",$N30*(1-$P30)),"Non Trouvé") | T30: =IFERROR(IF($C30="","",VLOOKUP($C30,'[1]Paramètres Articles'!$B:$H,7,FALSE)),"Non Trouvé") | V30: =IFERROR(IF($C30="","",IF($P30="","",$T30*(1-$P30))),"Non Trouvé") | X30: =IFERROR(T30-V30,"") | Z30: =IFERROR(IF(OR(T30=0,T30=""),0,T30*H30),"Non Trouvé") | AB30: =AB29 | AC30: =AC29 | AD30: =IFERROR(IF($C30="","",IF($P$15="Cascade",$R30*(1-AC30)*AB30,IF($P$15="Additionnelle",($N30-($N30*($P30+AC30)))*AB30))),"Non Trouvé") | AG30: =AG29 | AH30: =AH29 | AI30: =IFERROR(IF($C30="","",IF($P$15="Cascade",$R30*(1-AH30)*AG30,IF($P$15="Additionnelle",($N30-($N30*($P30+AH30)))*AG30))),"Non Trouvé") | AL30: =AL29 | AM30: =AM29 | AN30: =IFERROR(IF($C30="","",IF($P$15="Cascade",$R30*(1-AM30)*AL30,IF($P$15="Additionnelle",($N30-($N30*($P30+AM30)))*AL30))),"Non Trouvé") | AQ30: =AQ29 | AR30: =AR29 | AS30: =IFERROR(IF($C30="","",IF($P$15="Cascade",$R30*(1-AR30)*AQ30,IF($P$15="Additionnelle",($N30-($N30*($P30+AR30)))*AQ30))),"Non Trouvé") | AV30: =AV29 | AW30: =AW29 | AX30: =IFERROR(IF($C30="","",IF($P$15="Cascade",$R30*(1-AW30)*AV30,IF($P$15="Additionnelle",($N30-($N30*($P30+AW30)))*AV30))),"Non Trouvé") | BA30: =BA29 | BB30: =BB29 | BC30: =IFERROR(IF($C30="","",IF($P$15="Cascade",$R30*(1-BB30)*BA30,IF($P$15="Additionnelle",($N30-($N30*($P30+BB30)))*BA30))),"Non Trouvé") | BF30: =BF29 | BG30: =BG29 | BH30: =IFERROR(IF($C30="","",IF($P$15="Cascade",$R30*(1-BG30)*BF30,IF($P$15="Additionnelle",($N30-($N30*($P30+BG30)))*BF30))),"Non Trouvé") | BK30: =BK29 | BL30: =BL29 | BM30: =IFERROR(IF($C30="","",IF($P$15="Cascade",$R30*(1-BL30)*BK30,IF($P$15="Additionnelle",($N30-($N30*($P30+BL30)))*BK30))),"Non Trouvé") | BP30: =BP29 | BQ30: =BQ29 | BR30: =IFERROR(IF($C30="","",IF($P$15="Cascade",$R30*(1-BQ30)*BP30,IF($P$15="Additionnelle",($N30-($N30*($P30+BQ30)))*BP30))),"Non Trouvé") | BU30: =BU29 | BV30: =BV29 | BW30: =IFERROR(IF($C30="","",IF($P$15="Cascade",$R30*(1-BV30)*BU30,IF($P$15="Additionnelle",($N30-($N30*($P30+BV30)))*BU30))),"Non Trouvé") | BZ30: =BZ29 | CA30: =CA29 | CB30: =IFERROR(IF($C30="","",IF($P$15="Cascade",$R30*(1-CA30)*BZ30,IF($P$15="Additionnelle",($N30-($N30*($P30+CA30)))*BZ30))),"Non Trouvé") | CK30: =IFERROR(IF(F30='[1]Paramètres Généraux'!$K$12,ROUNDUP((REGENERANTS!H30*REGENERANTS!$CF$20)*'[1]Paramètres Généraux'!$M$12,-1),IF(F30='[1]Paramètres Généraux'!$K$15,ROUNDUP((REGENERANTS!H30*REGENERANTS!$CF$20)*'[1]Paramètres Généraux'!$M$15,-1),REGENERANTS!H30*REGENERANTS!$CF$20)),"nd") | DQ30: =SUM(CN30:DP30) | DR30: =SUM(CV30:DP30) | DS30: =IFERROR((IF(AND($F30="Produit Vente",CO30>0),VLOOKUP($C30,'[1]Paramètres Articles'!$B:$H,7,FALSE)*$CO30)*(1-20%)),0) | DT30: =IFERROR((IF(AND($F30="Produit Vente",DR30>0),VLOOKUP($C30,'[1]Paramètres Articles'!$B:$H,6,FALSE)*$DR30)*(1-15%)),0) | DU30: =IFERROR(DQ30*J30,0)
B31: =IF(C31="",0,COUNTIFS($B$22:B30,">"&0)+1) | C31: 1020717 | D31: =IFERROR(IF($C31="","",VLOOKUP($C31,'[1]Paramètres Articles'!$B:$G,2,FALSE)),"Non Trouvé") | E31: =IFERROR(IF($C31="","",_xlfn.XLOOKUP(REGENERANTS!$C31,'[1]New Base PA'!$F:$F,'[1]New Base PA'!$D:$D,"Not Found",0)),"Non Trouvé") | F31: Produit Vente | H31: 3 | J31: =IFERROR(IF($C31="","",VLOOKUP($C31,'[1]New Base PA'!$F:$J,5,FALSE)),"Non Trouvé") | K31: =IFERROR(IF($C31="","",$J31*$H31),"Non Trouvé") | M31: =IFERROR(IF(AND($F31="Produit Vente",H31>0),VLOOKUP($C31,'[1]Paramètres Articles'!$B:$G,6,FALSE),0),"Non Trouvé") | N31: =IFERROR(IF($C31="","",$M31*$H31),"Non Trouvé") | P31: 0.15 | R31: =IFERROR(IF($C31="","",$N31*(1-$P31)),"Non Trouvé") | T31: =IFERROR(IF($C31="","",VLOOKUP($C31,'[1]Paramètres Articles'!$B:$H,7,FALSE)),"Non Trouvé") | V31: =IFERROR(IF($C31="","",IF($P31="","",$T31*(1-$P31))),"Non Trouvé") | X31: =IFERROR(T31-V31,"") | Z31: =IFERROR(IF(OR(T31=0,T31=""),0,T31*H31),"Non Trouvé") | AB31: =AB30 | AC31: =AC30 | AD31: =IFERROR(IF($C31="","",IF($P$15="Cascade",$R31*(1-AC31)*AB31,IF($P$15="Additionnelle",($N31-($N31*($P31+AC31)))*AB31))),"Non Trouvé") | AG31: =AG30 | AH31: =AH30 | AI31: =IFERROR(IF($C31="","",IF($P$15="Cascade",$R31*(1-AH31)*AG31,IF($P$15="Additionnelle",($N31-($N31*($P31+AH31)))*AG31))),"Non Trouvé") | AL31: =AL30 | AM31: =AM30 | AN31: =IFERROR(IF($C31="","",IF($P$15="Cascade",$R31*(1-AM31)*AL31,IF($P$15="Additionnelle",($N31-($N31*($P31+AM31)))*AL31))),"Non Trouvé") | AQ31: =AQ30 | AR31: =AR30 | AS31: =IFERROR(IF($C31="","",IF($P$15="Cascade",$R31*(1-AR31)*AQ31,IF($P$15="Additionnelle",($N31-($N31*($P31+AR31)))*AQ31))),"Non Trouvé") | AV31: =AV30 | AW31: =AW30 | AX31: =IFERROR(IF($C31="","",IF($P$15="Cascade",$R31*(1-AW31)*AV31,IF($P$15="Additionnelle",($N31-($N31*($P31+AW31)))*AV31))),"Non Trouvé") | BA31: =BA30 | BB31: =BB30 | BC31: =IFERROR(IF($C31="","",IF($P$15="Cascade",$R31*(1-BB31)*BA31,IF($P$15="Additionnelle",($N31-($N31*($P31+BB31)))*BA31))),"Non Trouvé") | BF31: =BF30 | BG31: =BG30 | BH31: =IFERROR(IF($C31="","",IF($P$15="Cascade",$R31*(1-BG31)*BF31,IF($P$15="Additionnelle",($N31-($N31*($P31+BG31)))*BF31))),"Non Trouvé") | BK31: =BK30 | BL31: =BL30 | BM31: =IFERROR(IF($C31="","",IF($P$15="Cascade",$R31*(1-BL31)*BK31,IF($P$15="Additionnelle",($N31-($N31*($P31+BL31)))*BK31))),"Non Trouvé") | BP31: =BP30 | BQ31: =BQ30 | BR31: =IFERROR(IF($C31="","",IF($P$15="Cascade",$R31*(1-BQ31)*BP31,IF($P$15="Additionnelle",($N31-($N31*($P31+BQ31)))*BP31))),"Non Trouvé") | BU31: =BU30 | BV31: =BV30 | BW31: =IFERROR(IF($C31="","",IF($P$15="Cascade",$R31*(1-BV31)*BU31,IF($P$15="Additionnelle",($N31-($N31*($P31+BV31)))*BU31))),"Non Trouvé") | BZ31: =BZ30 | CA31: =CA30 | CB31: =IFERROR(IF($C31="","",IF($P$15="Cascade",$R31*(1-CA31)*BZ31,IF($P$15="Additionnelle",($N31-($N31*($P31+CA31)))*BZ31))),"Non Trouvé") | CK31: =IFERROR(IF(F31='[1]Paramètres Généraux'!$K$12,ROUNDUP((REGENERANTS!H31*REGENERANTS!$CF$20)*'[1]Paramètres Généraux'!$M$12,-1),IF(F31='[1]Paramètres Généraux'!$K$15,ROUNDUP((REGENERANTS!H31*REGENERANTS!$CF$20)*'[1]Paramètres Généraux'!$M$15,-1),REGENERANTS!H31*REGENERANTS!$CF$20)),"nd") | DQ31: =SUM(CN31:DP31) | DR31: =SUM(CV31:DP31) | DS31: =IFERROR((IF(AND($F31="Produit Vente",CO31>0),VLOOKUP($C31,'[1]Paramètres Articles'!$B:$H,7,FALSE)*$CO31)*(1-20%)),0) | DT31: =IFERROR((IF(AND($F31="Produit Vente",DR31>0),VLOOKUP($C31,'[1]Paramètres Articles'!$B:$H,6,FALSE)*$DR31)*(1-15%)),0) | DU31: =IFERROR(DQ31*J31,0)
B32: =IF(C32="",0,COUNTIFS($B$22:B31,">"&0)+1) | C32: 1020718 | D32: =IFERROR(IF($C32="","",VLOOKUP($C32,'[1]Paramètres Articles'!$B:$G,2,FALSE)),"Non Trouvé") | E32: =IFERROR(IF($C32="","",_xlfn.XLOOKUP(REGENERANTS!$C32,'[1]New Base PA'!$F:$F,'[1]New Base PA'!$D:$D,"Not Found",0)),"Non Trouvé") | F32: Produit Vente | H32: 5 | J32: =IFERROR(IF($C32="","",VLOOKUP($C32,'[1]New Base PA'!$F:$J,5,FALSE)),"Non Trouvé") | K32: =IFERROR(IF($C32="","",$J32*$H32),"Non Trouvé") | M32: =IFERROR(IF(AND($F32="Produit Vente",H32>0),VLOOKUP($C32,'[1]Paramètres Articles'!$B:$G,6,FALSE),0),"Non Trouvé") | N32: =IFERROR(IF($C32="","",$M32*$H32),"Non Trouvé") | P32: 0.15 | R32: =IFERROR(IF($C32="","",$N32*(1-$P32)),"Non Trouvé") | T32: =IFERROR(IF($C32="","",VLOOKUP($C32,'[1]Paramètres Articles'!$B:$H,7,FALSE)),"Non Trouvé") | V32: =IFERROR(IF($C32="","",IF($P32="","",$T32*(1-$P32))),"Non Trouvé") | X32: =IFERROR(T32-V32,"") | Z32: =IFERROR(IF(OR(T32=0,T32=""),0,T32*H32),"Non Trouvé") | AB32: =AB31 | AC32: =AC31 | AD32: =IFERROR(IF($C32="","",IF($P$15="Cascade",$R32*(1-AC32)*AB32,IF($P$15="Additionnelle",($N32-($N32*($P32+AC32)))*AB32))),"Non Trouvé") | AG32: =AG31 | AH32: =AH31 | AI32: =IFERROR(IF($C32="","",IF($P$15="Cascade",$R32*(1-AH32)*AG32,IF($P$15="Additionnelle",($N32-($N32*($P32+AH32)))*AG32))),"Non Trouvé") | AL32: =AL31 | AM32: =AM31 | AN32: =IFERROR(IF($C32="","",IF($P$15="Cascade",$R32*(1-AM32)*AL32,IF($P$15="Additionnelle",($N32-($N32*($P32+AM32)))*AL32))),"Non Trouvé") | AQ32: =AQ31 | AR32: =AR31 | AS32: =IFERROR(IF($C32="","",IF($P$15="Cascade",$R32*(1-AR32)*AQ32,IF($P$15="Additionnelle",($N32-($N32*($P32+AR32)))*AQ32))),"Non Trouvé") | AV32: =AV31 | AW32: =AW31 | AX32: =IFERROR(IF($C32="","",IF($P$15="Cascade",$R32*(1-AW32)*AV32,IF($P$15="Additionnelle",($N32-($N32*($P32+AW32)))*AV32))),"Non Trouvé") | BA32: =BA31 | BB32: =BB31 | BC32: =IFERROR(IF($C32="","",IF($P$15="Cascade",$R32*(1-BB32)*BA32,IF($P$15="Additionnelle",($N32-($N32*($P32+BB32)))*BA32))),"Non Trouvé") | BF32: =BF31 | BG32: =BG31 | BH32: =IFERROR(IF($C32="","",IF($P$15="Cascade",$R32*(1-BG32)*BF32,IF($P$15="Additionnelle",($N32-($N32*($P32+BG32)))*BF32))),"Non Trouvé") | BK32: =BK31 | BL32: =BL31 | BM32: =IFERROR(IF($C32="","",IF($P$15="Cascade",$R32*(1-BL32)*BK32,IF($P$15="Additionnelle",($N32-($N32*($P32+BL32)))*BK32))),"Non Trouvé") | BP32: =BP31 | BQ32: =BQ31 | BR32: =IFERROR(IF($C32="","",IF($P$15="Cascade",$R32*(1-BQ32)*BP32,IF($P$15="Additionnelle",($N32-($N32*($P32+BQ32)))*BP32))),"Non Trouvé") | BU32: =BU31 | BV32: =BV31 | BW32: =IFERROR(IF($C32="","",IF($P$15="Cascade",$R32*(1-BV32)*BU32,IF($P$15="Additionnelle",($N32-($N32*($P32+BV32)))*BU32))),"Non Trouvé") | BZ32: =BZ31 | CA32: =CA31 | CB32: =IFERROR(IF($C32="","",IF($P$15="Cascade",$R32*(1-CA32)*BZ32,IF($P$15="Additionnelle",($N32-($N32*($P32+CA32)))*BZ32))),"Non Trouvé") | CK32: =IFERROR(IF(F32='[1]Paramètres Généraux'!$K$12,ROUNDUP((REGENERANTS!H32*REGENERANTS!$CF$20)*'[1]Paramètres Généraux'!$M$12,-1),IF(F32='[1]Paramètres Généraux'!$K$15,ROUNDUP((REGENERANTS!H32*REGENERANTS!$CF$20)*'[1]Paramètres Généraux'!$M$15,-1),REGENERANTS!H32*REGENERANTS!$CF$20)),"nd") | DQ32: =SUM(CN32:DP32) | DR32: =SUM(CV32:DP32) | DS32: =IFERROR((IF(AND($F32="Produit Vente",CO32>0),VLOOKUP($C32,'[1]Paramètres Articles'!$B:$H,7,FALSE)*$CO32)*(1-20%)),0) | DT32: =IFERROR((IF(AND($F32="Produit Vente",DR32>0),VLOOKUP($C32,'[1]Paramètres Articles'!$B:$H,6,FALSE)*$DR32)*(1-15%)),0) | DU32: =IFERROR(DQ32*J32,0)
B33: =IF(C33="",0,COUNTIFS($B$22:B32,">"&0)+1) | C33: 1020301 | D33: =IFERROR(IF($C33="","",VLOOKUP($C33,'[1]Paramètres Articles'!$B:$G,2,FALSE)),"Non Trouvé") | E33: =IFERROR(IF($C33="","",_xlfn.XLOOKUP(REGENERANTS!$C33,'[1]New Base PA'!$F:$F,'[1]New Base PA'!$D:$D,"Not Found",0)),"Non Trouvé") | F33: Produit Vente | H33: 8 | J33: =IFERROR(IF($C33="","",VLOOKUP($C33,'[1]New Base PA'!$F:$J,5,FALSE)),"Non Trouvé") | K33: =IFERROR(IF($C33="","",$J33*$H33),"Non Trouvé") | M33: =IFERROR(IF(AND($F33="Produit Vente",H33>0),VLOOKUP($C33,'[1]Paramètres Articles'!$B:$G,6,FALSE),0),"Non Trouvé") | N33: =IFERROR(IF($C33="","",$M33*$H33),"Non Trouvé") | P33: 0.15 | R33: =IFERROR(IF($C33="","",$N33*(1-$P33)),"Non Trouvé") | T33: =IFERROR(IF($C33="","",VLOOKUP($C33,'[1]Paramètres Articles'!$B:$H,7,FALSE)),"Non Trouvé") | V33: =IFERROR(IF($C33="","",IF($P33="","",$T33*(1-$P33))),"Non Trouvé") | X33: =IFERROR(T33-V33,"") | Z33: =IFERROR(IF(OR(T33=0,T33=""),0,T33*H33),"Non Trouvé") | AB33: =AB32 | AC33: =AC32 | AD33: =IFERROR(IF($C33="","",IF($P$15="Cascade",$R33*(1-AC33)*AB33,IF($P$15="Additionnelle",($N33-($N33*($P33+AC33)))*AB33))),"Non Trouvé") | AG33: =AG32 | AH33: =AH32 | AI33: =IFERROR(IF($C33="","",IF($P$15="Cascade",$R33*(1-AH33)*AG33,IF($P$15="Additionnelle",($N33-($N33*($P33+AH33)))*AG33))),"Non Trouvé") | AL33: =AL32 | AM33: =AM32 | AN33: =IFERROR(IF($C33="","",IF($P$15="Cascade",$R33*(1-AM33)*AL33,IF($P$15="Additionnelle",($N33-($N33*($P33+AM33)))*AL33))),"Non Trouvé") | AQ33: =AQ32 | AR33: =AR32 | AS33: =IFERROR(IF($C33="","",IF($P$15="Cascade",$R33*(1-AR33)*AQ33,IF($P$15="Additionnelle",($N33-($N33*($P33+AR33)))*AQ33))),"Non Trouvé") | AV33: =AV32 | AW33: =AW32 | AX33: =IFERROR(IF($C33="","",IF($P$15="Cascade",$R33*(1-AW33)*AV33,IF($P$15="Additionnelle",($N33-($N33*($P33+AW33)))*AV33))),"Non Trouvé") | BA33: =BA32 | BB33: =BB32 | BC33: =IFERROR(IF($C33="","",IF($P$15="Cascade",$R33*(1-BB33)*BA33,IF($P$15="Additionnelle",($N33-($N33*($P33+BB33)))*BA33))),"Non Trouvé") | BF33: =BF32 | BG33: =BG32 | BH33: =IFERROR(IF($C33="","",IF($P$15="Cascade",$R33*(1-BG33)*BF33,IF($P$15="Additionnelle",($N33-($N33*($P33+BG33)))*BF33))),"Non Trouvé") | BK33: =BK32 | BL33: =BL32 | BM33: =IFERROR(IF($C33="","",IF($P$15="Cascade",$R33*(1-BL33)*BK33,IF($P$15="Additionnelle",($N33-($N33*($P33+BL33)))*BK33))),"Non Trouvé") | BP33: =BP32 | BQ33: =BQ32 | BR33: =IFERROR(IF($C33="","",IF($P$15="Cascade",$R33*(1-BQ33)*BP33,IF($P$15="Additionnelle",($N33-($N33*($P33+BQ33)))*BP33))),"Non Trouvé") | BU33: =BU32 | BV33: =BV32 | BW33: =IFERROR(IF($C33="","",IF($P$15="Cascade",$R33*(1-BV33)*BU33,IF($P$15="Additionnelle",($N33-($N33*($P33+BV33)))*BU33))),"Non Trouvé") | BZ33: =BZ32 | CA33: =CA32 | CB33: =IFERROR(IF($C33="","",IF($P$15="Cascade",$R33*(1-CA33)*BZ33,IF($P$15="Additionnelle",($N33-($N33*($P33+CA33)))*BZ33))),"Non Trouvé") | CK33: =IFERROR(IF(F33='[1]Paramètres Généraux'!$K$12,ROUNDUP((REGENERANTS!H33*REGENERANTS!$CF$20)*'[1]Paramètres Généraux'!$M$12,-1),IF(F33='[1]Paramètres Généraux'!$K$15,ROUNDUP((REGENERANTS!H33*REGENERANTS!$CF$20)*'[1]Paramètres Généraux'!$M$15,-1),REGENERANTS!H33*REGENERANTS!$CF$20)),"nd") | DQ33: =SUM(CN33:DP33) | DR33: =SUM(CV33:DP33) | DS33: =IFERROR((IF(AND($F33="Produit Vente",CO33>0),VLOOKUP($C33,'[1]Paramètres Articles'!$B:$H,7,FALSE)*$CO33)*(1-20%)),0) | DT33: =IFERROR((IF(AND($F33="Produit Vente",DR33>0),VLOOKUP($C33,'[1]Paramètres Articles'!$B:$H,6,FALSE)*$DR33)*(1-15%)),0) | DU33: =IFERROR(DQ33*J33,0)
B34: =IF(C34="",0,COUNTIFS($B$22:B33,">"&0)+1) | C34: 1020720 | D34: =IFERROR(IF($C34="","",VLOOKUP($C34,'[1]Paramètres Articles'!$B:$G,2,FALSE)),"Non Trouvé") | E34: =IFERROR(IF($C34="","",_xlfn.XLOOKUP(REGENERANTS!$C34,'[1]New Base PA'!$F:$F,'[1]New Base PA'!$D:$D,"Not Found",0)),"Non Trouvé") | F34: Produit Vente | H34: 8 | J34: =IFERROR(IF($C34="","",VLOOKUP($C34,'[1]New Base PA'!$F:$J,5,FALSE)),"Non Trouvé") | K34: =IFERROR(IF($C34="","",$J34*$H34),"Non Trouvé") | M34: =IFERROR(IF(AND($F34="Produit Vente",H34>0),VLOOKUP($C34,'[1]Paramètres Articles'!$B:$G,6,FALSE),0),"Non Trouvé") | N34: =IFERROR(IF($C34="","",$M34*$H34),"Non Trouvé") | P34: 0.15 | R34: =IFERROR(IF($C34="","",$N34*(1-$P34)),"Non Trouvé") | T34: =IFERROR(IF($C34="","",VLOOKUP($C34,'[1]Paramètres Articles'!$B:$H,7,FALSE)),"Non Trouvé") | V34: =IFERROR(IF($C34="","",IF($P34="","",$T34*(1-$P34))),"Non Trouvé") | X34: =IFERROR(T34-V34,"") | Z34: =IFERROR(IF(OR(T34=0,T34=""),0,T34*H34),"Non Trouvé") | AB34: =AB33 | AC34: =AC33 | AD34: =IFERROR(IF($C34="","",IF($P$15="Cascade",$R34*(1-AC34)*AB34,IF($P$15="Additionnelle",($N34-($N34*($P34+AC34)))*AB34))),"Non Trouvé") | AG34: =AG33 | AH34: =AH33 | AI34: =IFERROR(IF($C34="","",IF($P$15="Cascade",$R34*(1-AH34)*AG34,IF($P$15="Additionnelle",($N34-($N34*($P34+AH34)))*AG34))),"Non Trouvé") | AL34: =AL33 | AM34: =AM33 | AN34: =IFERROR(IF($C34="","",IF($P$15="Cascade",$R34*(1-AM34)*AL34,IF($P$15="Additionnelle",($N34-($N34*($P34+AM34)))*AL34))),"Non Trouvé") | AQ34: =AQ33 | AR34: =AR33 | AS34: =IFERROR(IF($C34="","",IF($P$15="Cascade",$R34*(1-AR34)*AQ34,IF($P$15="Additionnelle",($N34-($N34*($P34+AR34)))*AQ34))),"Non Trouvé") | AV34: =AV33 | AW34: =AW33 | AX34: =IFERROR(IF($C34="","",IF($P$15="Cascade",$R34*(1-AW34)*AV34,IF($P$15="Additionnelle",($N34-($N34*($P34+AW34)))*AV34))),"Non Trouvé") | BA34: =BA33 | BB34: =BB33 | BC34: =IFERROR(IF($C34="","",IF($P$15="Cascade",$R34*(1-BB34)*BA34,IF($P$15="Additionnelle",($N34-($N34*($P34+BB34)))*BA34))),"Non Trouvé") | BF34: =BF33 | BG34: =BG33 | BH34: =IFERROR(IF($C34="","",IF($P$15="Cascade",$R34*(1-BG34)*BF34,IF($P$15="Additionnelle",($N34-($N34*($P34+BG34)))*BF34))),"Non Trouvé") | BK34: =BK33 | BL34: =BL33 | BM34: =IFERROR(IF($C34="","",IF($P$15="Cascade",$R34*(1-BL34)*BK34,IF($P$15="Additionnelle",($N34-($N34*($P34+BL34)))*BK34))),"Non Trouvé") | BP34: =BP33 | BQ34: =BQ33 | BR34: =IFERROR(IF($C34="","",IF($P$15="Cascade",$R34*(1-BQ34)*BP34,IF($P$15="Additionnelle",($N34-($N34*($P34+BQ34)))*BP34))),"Non Trouvé") | BU34: =BU33 | BV34: =BV33 | BW34: =IFERROR(IF($C34="","",IF($P$15="Cascade",$R34*(1-BV34)*BU34,IF($P$15="Additionnelle",($N34-($N34*($P34+BV34)))*BU34))),"Non Trouvé") | BZ34: =BZ33 | CA34: =CA33 | CB34: =IFERROR(IF($C34="","",IF($P$15="Cascade",$R34*(1-CA34)*BZ34,IF($P$15="Additionnelle",($N34-($N34*($P34+CA34)))*BZ34))),"Non Trouvé") | CG34: Retail | CK34: =IFERROR(IF(F34='[1]Paramètres Généraux'!$K$12,ROUNDUP((REGENERANTS!H34*REGENERANTS!$CF$20)*'[1]Paramètres Généraux'!$M$12,-1),IF(F34='[1]Paramètres Généraux'!$K$15,ROUNDUP((REGENERANTS!H34*REGENERANTS!$CF$20)*'[1]Paramètres Généraux'!$M$15,-1),REGENERANTS!H34*REGENERANTS!$CF$20)),"nd") | DQ34: =SUM(CN34:DP34) | DR34: =SUM(CV34:DP34) | DS34: =IFERROR((IF(AND($F34="Produit Vente",CO34>0),VLOOKUP($C34,'[1]Paramètres Articles'!$B:$H,7,FALSE)*$CO34)*(1-20%)),0) | DT34: =IFERROR((IF(AND($F34="Produit Vente",DR34>0),VLOOKUP($C34,'[1]Paramètres Articles'!$B:$H,6,FALSE)*$DR34)*(1-15%)),0) | DU34: =IFERROR(DQ34*J34,0)
B35: =IF(C35="",0,COUNTIFS($B$22:B34,">"&0)+1) | C35: PANNEAU REGE | D35: =IFERROR(IF($C35="","",VLOOKUP($C35,'[1]Paramètres Articles'!$B:$G,2,FALSE)),"Non Trouvé") | E35: =IFERROR(IF($C35="","",_xlfn.XLOOKUP(REGENERANTS!$C35,'[1]New Base PA'!$F:$F,'[1]New Base PA'!$D:$D,"Not Found",0)),"Non Trouvé") | F35: PLV (vitrine) | H35: 1 | J35: =IFERROR(IF($C35="","",VLOOKUP($C35,'[1]New Base PA'!$F:$J,5,FALSE)),"Non Trouvé") | K35: =IFERROR(IF($C35="","",$J35*$H35),"Non Trouvé") | M35: =IFERROR(IF(AND($F35="Produit Vente",H35>0),VLOOKUP($C35,'[1]Paramètres Articles'!$B:$G,6,FALSE),0),"Non Trouvé") | N35: =IFERROR(IF($C35="","",$M35*$H35),"Non Trouvé") | R35: =IFERROR(IF($C35="","",$N35*(1-$P35)),"Non Trouvé") | T35: =IFERROR(IF($C35="","",VLOOKUP($C35,'[1]Paramètres Articles'!$B:$H,7,FALSE)),"Non Trouvé") | V35: =IFERROR(IF($C35="","",IF($P35="","",$T35*(1-$P35))),"Non Trouvé") | X35: =IFERROR(T35-V35,"") | Z35: =IFERROR(IF(OR(T35=0,T35=""),0,T35*H35),"Non Trouvé") | AB35: =AB34 | AC35: =AC34 | AD35: =IFERROR(IF($C35="","",IF($P$15="Cascade",$R35*(1-AC35)*AB35,IF($P$15="Additionnelle",($N35-($N35*($P35+AC35)))*AB35))),"Non Trouvé") | AG35: =AG34 | AH35: =AH34 | AI35: =IFERROR(IF($C35="","",IF($P$15="Cascade",$R35*(1-AH35)*AG35,IF($P$15="Additionnelle",($N35-($N35*($P35+AH35)))*AG35))),"Non Trouvé") | AL35: =AL34 | AM35: =AM34 | AN35: =IFERROR(IF($C35="","",IF($P$15="Cascade",$R35*(1-AM35)*AL35,IF($P$15="Additionnelle",($N35-($N35*($P35+AM35)))*AL35))),"Non Trouvé") | AQ35: =AQ34 | AR35: =AR34 | AS35: =IFERROR(IF($C35="","",IF($P$15="Cascade",$R35*(1-AR35)*AQ35,IF($P$15="Additionnelle",($N35-($N35*($P35+AR35)))*AQ35))),"Non Trouvé") | AV35: =AV34 | AW35: =AW34 | AX35: =IFERROR(IF($C35="","",IF($P$15="Cascade",$R35*(1-AW35)*AV35,IF($P$15="Additionnelle",($N35-($N35*($P35+AW35)))*AV35))),"Non Trouvé") | BA35: =BA34 | BB35: =BB34 | BC35: =IFERROR(IF($C35="","",IF($P$15="Cascade",$R35*(1-BB35)*BA35,IF($P$15="Additionnelle",($N35-($N35*($P35+BB35)))*BA35))),"Non Trouvé") | BF35: =BF34 | BG35: =BG34 | BH35: =IFERROR(IF($C35="","",IF($P$15="Cascade",$R35*(1-BG35)*BF35,IF($P$15="Additionnelle",($N35-($N35*($P35+BG35)))*BF35))),"Non Trouvé") | BK35: =BK34 | BL35: =BL34 | BM35: =IFERROR(IF($C35="","",IF($P$15="Cascade",$R35*(1-BL35)*BK35,IF($P$15="Additionnelle",($N35-($N35*($P35+BL35)))*BK35))),"Non Trouvé") | BP35: =BP34 | BQ35: =BQ34 | BR35: =IFERROR(IF($C35="","",IF($P$15="Cascade",$R35*(1-BQ35)*BP35,IF($P$15="Additionnelle",($N35-($N35*($P35+BQ35)))*BP35))),"Non Trouvé") | BU35: =BU34 | BV35: =BV34 | BW35: =IFERROR(IF($C35="","",IF($P$15="Cascade",$R35*(1-BV35)*BU35,IF($P$15="Additionnelle",($N35-($N35*($P35+BV35)))*BU35))),"Non Trouvé") | BZ35: =BZ34 | CA35: =CA34 | CB35: =IFERROR(IF($C35="","",IF($P$15="Cascade",$R35*(1-CA35)*BZ35,IF($P$15="Additionnelle",($N35-($N35*($P35+CA35)))*BZ35))),"Non Trouvé") | CG35: Nbrs Offres planifiées | CH35: =SUMIFS($AB20:$AT20,$AB17:$AT17,CG35)+SUMIFS($BZ20:$CC20,$BZ17:$CC17,CG35) | CK35: =IFERROR(IF(F35='[1]Paramètres Généraux'!$K$12,ROUNDUP((REGENERANTS!H35*REGENERANTS!$CF$20)*'[1]Paramètres Généraux'!$M$12,-1),IF(F35='[1]Paramètres Généraux'!$K$15,ROUNDUP((REGENERANTS!H35*REGENERANTS!$CF$20)*'[1]Paramètres Généraux'!$M$15,-1),REGENERANTS!H35*REGENERANTS!$CF$20)),"nd") | CS35: 1 | DQ35: =SUM(CN35:DP35) | DR35: =SUM(CV35:DP35) | DS35: =IFERROR((IF(AND($F35="Produit Vente",CO35>0),VLOOKUP($C35,'[1]Paramètres Articles'!$B:$H,7,FALSE)*$CO35)*(1-20%)),0) | DT35: =IFERROR((IF(AND($F35="Produit Vente",DR35>0),VLOOKUP($C35,'[1]Paramètres Articles'!$B:$H,6,FALSE)*$DR35)*(1-15%)),0) | DU35: =IFERROR(DQ35*J35,0)
B36: =IF(C36="",0,COUNTIFS($B$22:B35,">"&0)+1) | C36: PRESENTOIR REGE | D36: =IFERROR(IF($C36="","",VLOOKUP($C36,'[1]Paramètres Articles'!$B:$G,2,FALSE)),"Non Trouvé") | E36: =IFERROR(IF($C36="","",_xlfn.XLOOKUP(REGENERANTS!$C36,'[1]New Base PA'!$F:$F,'[1]New Base PA'!$D:$D,"Not Found",0)),"Non Trouvé") | F36: PLV (PDC ou autre) | H36: 1 | J36: =IFERROR(IF($C36="","",VLOOKUP($C36,'[1]New Base PA'!$F:$J,5,FALSE)),"Non Trouvé") | K36: =IFERROR(IF($C36="","",$J36*$H36),"Non Trouvé") | M36: =IFERROR(IF(AND($F36="Produit Vente",H36>0),VLOOKUP($C36,'[1]Paramètres Articles'!$B:$G,6,FALSE),0),"Non Trouvé") | N36: =IFERROR(IF($C36="","",$M36*$H36),"Non Trouvé") | R36: =IFERROR(IF($C36="","",$N36*(1-$P36)),"Non Trouvé") | T36: =IFERROR(IF($C36="","",VLOOKUP($C36,'[1]Paramètres Articles'!$B:$H,7,FALSE)),"Non Trouvé") | V36: =IFERROR(IF($C36="","",IF($P36="","",$T36*(1-$P36))),"Non Trouvé") | X36: =IFERROR(T36-V36,"") | Z36: =IFERROR(IF(OR(T36=0,T36=""),0,T36*H36),"Non Trouvé") | AB36: =AB35 | AC36: =AC35 | AD36: =IFERROR(IF($C36="","",IF($P$15="Cascade",$R36*(1-AC36)*AB36,IF($P$15="Additionnelle",($N36-($N36*($P36+AC36)))*AB36))),"Non Trouvé") | AG36: =AG35 | AH36: =AH35 | AI36: =IFERROR(IF($C36="","",IF($P$15="Cascade",$R36*(1-AH36)*AG36,IF($P$15="Additionnelle",($N36-($N36*($P36+AH36)))*AG36))),"Non Trouvé") | AL36: =AL35 | AM36: =AM35 | AN36: =IFERROR(IF($C36="","",IF($P$15="Cascade",$R36*(1-AM36)*AL36,IF($P$15="Additionnelle",($N36-($N36*($P36+AM36)))*AL36))),"Non Trouvé") | AQ36: =AQ35 | AR36: =AR35 | AS36: =IFERROR(IF($C36="","",IF($P$15="Cascade",$R36*(1-AR36)*AQ36,IF($P$15="Additionnelle",($N36-($N36*($P36+AR36)))*AQ36))),"Non Trouvé") | AV36: =AV35 | AW36: =AW35 | AX36: =IFERROR(IF($C36="","",IF($P$15="Cascade",$R36*(1-AW36)*AV36,IF($P$15="Additionnelle",($N36-($N36*($P36+AW36)))*AV36))),"Non Trouvé") | BA36: =BA35 | BB36: =BB35 | BC36: =IFERROR(IF($C36="","",IF($P$15="Cascade",$R36*(1-BB36)*BA36,IF($P$15="Additionnelle",($N36-($N36*($P36+BB36)))*BA36))),"Non Trouvé") | BF36: =BF35 | BG36: =BG35 | BH36: =IFERROR(IF($C36="","",IF($P$15="Cascade",$R36*(1-BG36)*BF36,IF($P$15="Additionnelle",($N36-($N36*($P36+BG36)))*BF36))),"Non Trouvé") | BK36: =BK35 | BL36: =BL35 | BM36: =IFERROR(IF($C36="","",IF($P$15="Cascade",$R36*(1-BL36)*BK36,IF($P$15="Additionnelle",($N36-($N36*($P36+BL36)))*BK36))),"Non Trouvé") | BP36: =BP35 | BQ36: =BQ35 | BR36: =IFERROR(IF($C36="","",IF($P$15="Cascade",$R36*(1-BQ36)*BP36,IF($P$15="Additionnelle",($N36-($N36*($P36+BQ36)))*BP36))),"Non Trouvé") | BU36: =BU35 | BV36: =BV35 | BW36: =IFERROR(IF($C36="","",IF($P$15="Cascade",$R36*(1-BV36)*BU36,IF($P$15="Additionnelle",($N36-($N36*($P36+BV36)))*BU36))),"Non Trouvé") | BZ36: =BZ35 | CA36: =CA35 | CB36: =IFERROR(IF($C36="","",IF($P$15="Cascade",$R36*(1-CA36)*BZ36,IF($P$15="Additionnelle",($N36-($N36*($P36+CA36)))*BZ36))),"Non Trouvé") | CG36: CA | CH36: =SUMIFS($AB20:$AT20,$AB17:$AT17,CG36)+SUMIFS($BZ20:$CC20,$BZ17:$CC17,CG36) | CK36: =IFERROR(IF(F36='[1]Paramètres Généraux'!$K$12,ROUNDUP((REGENERANTS!H36*REGENERANTS!$CF$20)*'[1]Paramètres Généraux'!$M$12,-1),IF(F36='[1]Paramètres Généraux'!$K$15,ROUNDUP((REGENERANTS!H36*REGENERANTS!$CF$20)*'[1]Paramètres Généraux'!$M$15,-1),REGENERANTS!H36*REGENERANTS!$CF$20)),"nd") | CS36: 1 | CX36: 15 | DQ36: =SUM(CN36:DP36) | DR36: =SUM(CV36:DP36) | DS36: =IFERROR((IF(AND($F36="Produit Vente",CO36>0),VLOOKUP($C36,'[1]Paramètres Articles'!$B:$H,7,FALSE)*$CO36)*(1-20%)),0) | DT36: =IFERROR((IF(AND($F36="Produit Vente",DR36>0),VLOOKUP($C36,'[1]Paramètres Articles'!$B:$H,6,FALSE)*$DR36)*(1-15%)),0) | DU36: =IFERROR(DQ36*J36,0) | DX36: BESOIN TOTAL POUR COMMANDE FRANCE | EA36: MAJ le
B37: =IF(C37="",0,COUNTIFS($B$22:B36,">"&0)+1) | C37: 3020202 | D37: =IFERROR(IF($C37="","",VLOOKUP($C37,'[1]Paramètres Articles'!$B:$G,2,FALSE)),"Non Trouvé") | E37: =IFERROR(IF($C37="","",_xlfn.XLOOKUP(REGENERANTS!$C37,'[1]New Base PA'!$F:$F,'[1]New Base PA'!$D:$D,"Not Found",0)),"Non Trouvé") | F37: Testeur | H37: 1 | J37: =IFERROR(IF($C37="","",VLOOKUP($C37,'[1]New Base PA'!$F:$J,5,FALSE)),"Non Trouvé") | K37: =IFERROR(IF($C37="","",$J37*$H37),"Non Trouvé") | M37: =IFERROR(IF(AND($F37="Produit Vente",H37>0),VLOOKUP($C37,'[1]Paramètres Articles'!$B:$G,6,FALSE),0),"Non Trouvé") | N37: =IFERROR(IF($C37="","",$M37*$H37),"Non Trouvé") | R37: =IFERROR(IF($C37="","",$N37*(1-$P37)),"Non Trouvé") | T37: =IFERROR(IF($C37="","",VLOOKUP($C37,'[1]Paramètres Articles'!$B:$H,7,FALSE)),"Non Trouvé") | V37: =IFERROR(IF($C37="","",IF($P37="","",$T37*(1-$P37))),"Non Trouvé") | X37: =IFERROR(T37-V37,"") | Z37: =IFERROR(IF(OR(T37=0,T37=""),0,T37*H37),"Non Trouvé") | AB37: =AB36 | AC37: =AC36 | AD37: =IFERROR(IF($C37="","",IF($P$15="Cascade",$R37*(1-AC37)*AB37,IF($P$15="Additionnelle",($N37-($N37*($P37+AC37)))*AB37))),"Non Trouvé") | AG37: =AG36 | AH37: =AH36 | AI37: =IFERROR(IF($C37="","",IF($P$15="Cascade",$R37*(1-AH37)*AG37,IF($P$15="Additionnelle",($N37-($N37*($P37+AH37)))*AG37))),"Non Trouvé") | AL37: =AL36 | AM37: =AM36 | AN37: =IFERROR(IF($C37="","",IF($P$15="Cascade",$R37*(1-AM37)*AL37,IF($P$15="Additionnelle",($N37-($N37*($P37+AM37)))*AL37))),"Non Trouvé") | AQ37: =AQ36 | AR37: =AR36 | AS37: =IFERROR(IF($C37="","",IF($P$15="Cascade",$R37*(1-AR37)*AQ37,IF($P$15="Additionnelle",($N37-($N37*($P37+AR37)))*AQ37))),"Non Trouvé") | AV37: =AV36 | AW37: =AW36 | AX37: =IFERROR(IF($C37="","",IF($P$15="Cascade",$R37*(1-AW37)*AV37,IF($P$15="Additionnelle",($N37-($N37*($P37+AW37)))*AV37))),"Non Trouvé") | BA37: =BA36 | BB37: =BB36 | BC37: =IFERROR(IF($C37="","",IF($P$15="Cascade",$R37*(1-BB37)*BA37,IF($P$15="Additionnelle",($N37-($N37*($P37+BB37)))*BA37))),"Non Trouvé") | BF37: =BF36 | BG37: =BG36 | BH37: =IFERROR(IF($C37="","",IF($P$15="Cascade",$R37*(1-BG37)*BF37,IF($P$15="Additionnelle",($N37-($N37*($P37+BG37)))*BF37))),"Non Trouvé") | BK37: =BK36 | BL37: =BL36 | BM37: =IFERROR(IF($C37="","",IF($P$15="Cascade",$R37*(1-BL37)*BK37,IF($P$15="Additionnelle",($N37-($N37*($P37+BL37)))*BK37))),"Non Trouvé") | BP37: =BP36 | BQ37: =BQ36 | BR37: =IFERROR(IF($C37="","",IF($P$15="Cascade",$R37*(1-BQ37)*BP37,IF($P$15="Additionnelle",($N37-($N37*($P37+BQ37)))*BP37))),"Non Trouvé") | BU37: =BU36 | BV37: =BV36 | BW37: =IFERROR(IF($C37="","",IF($P$15="Cascade",$R37*(1-BV37)*BU37,IF($P$15="Additionnelle",($N37-($N37*($P37+BV37)))*BU37))),"Non Trouvé") | BZ37: =BZ36 | CA37: =CA36 | CB37: =IFERROR(IF($C37="","",IF($P$15="Cascade",$R37*(1-CA37)*BZ37,IF($P$15="Additionnelle",($N37-($N37*($P37+CA37)))*BZ37))),"Non Trouvé") | CG37: Marges | CH37: =IFERROR((CH36-$K20*CH35)/CH36,"Non Trouvé") | CK37: =IFERROR(IF(F37='[1]Paramètres Généraux'!$K$12,ROUNDUP((REGENERANTS!H37*REGENERANTS!$CF$20)*'[1]Paramètres Généraux'!$M$12,-1),IF(F37='[1]Paramètres Généraux'!$K$15,ROUNDUP((REGENERANTS!H37*REGENERANTS!$CF$20)*'[1]Paramètres Généraux'!$M$15,-1),REGENERANTS!H37*REGENERANTS!$CF$20)),"nd") | DQ37: =SUM(CN37:DP37) | DR37: =SUM(CV37:DP37) | DS37: =IFERROR((IF(AND($F37="Produit Vente",CO37>0),VLOOKUP($C37,'[1]Paramètres Articles'!$B:$H,7,FALSE)*$CO37)*(1-20%)),0) | DT37: =IFERROR((IF(AND($F37="Produit Vente",DR37>0),VLOOKUP($C37,'[1]Paramètres Articles'!$B:$H,6,FALSE)*$DR37)*(1-15%)),0) | DU37: =IFERROR(DQ37*J37,0)
B38: =IF(C38="",0,COUNTIFS($B$22:B37,">"&0)+1) | C38: 3020301 | D38: =IFERROR(IF($C38="","",VLOOKUP($C38,'[1]Paramètres Articles'!$B:$G,2,FALSE)),"Non Trouvé") | E38: =IFERROR(IF($C38="","",_xlfn.XLOOKUP(REGENERANTS!$C38,'[1]New Base PA'!$F:$F,'[1]New Base PA'!$D:$D,"Not Found",0)),"Non Trouvé") | F38: Testeur | H38: 1 | J38: =IFERROR(IF($C38="","",VLOOKUP($C38,'[1]New Base PA'!$F:$J,5,FALSE)),"Non Trouvé") | K38: =IFERROR(IF($C38="","",$J38*$H38),"Non Trouvé") | M38: =IFERROR(IF(AND($F38="Produit Vente",H38>0),VLOOKUP($C38,'[1]Paramètres Articles'!$B:$G,6,FALSE),0),"Non Trouvé") | N38: =IFERROR(IF($C38="","",$M38*$H38),"Non Trouvé") | R38: =IFERROR(IF($C38="","",$N38*(1-$P38)),"Non Trouvé") | T38: =IFERROR(IF($C38="","",VLOOKUP($C38,'[1]Paramètres Articles'!$B:$H,7,FALSE)),"Non Trouvé") | V38: =IFERROR(IF($C38="","",IF($P38="","",$T38*(1-$P38))),"Non Trouvé") | X38: =IFERROR(T38-V38,"") | Z38: =IFERROR(IF(OR(T38=0,T38=""),0,T38*H38),"Non Trouvé") | AB38: =AB37 | AC38: =AC37 | AD38: =IFERROR(IF($C38="","",IF($P$15="Cascade",$R38*(1-AC38)*AB38,IF($P$15="Additionnelle",($N38-($N38*($P38+AC38)))*AB38))),"Non Trouvé") | AG38: =AG37 | AH38: =AH37 | AI38: =IFERROR(IF($C38="","",IF($P$15="Cascade",$R38*(1-AH38)*AG38,IF($P$15="Additionnelle",($N38-($N38*($P38+AH38)))*AG38))),"Non Trouvé") | AL38: =AL37 | AM38: =AM37 | AN38: =IFERROR(IF($C38="","",IF($P$15="Cascade",$R38*(1-AM38)*AL38,IF($P$15="Additionnelle",($N38-($N38*($P38+AM38)))*AL38))),"Non Trouvé") | AQ38: =AQ37 | AR38: =AR37 | AS38: =IFERROR(IF($C38="","",IF($P$15="Cascade",$R38*(1-AR38)*AQ38,IF($P$15="Additionnelle",($N38-($N38*($P38+AR38)))*AQ38))),"Non Trouvé") | AV38: =AV37 | AW38: =AW37 | AX38: =IFERROR(IF($C38="","",IF($P$15="Cascade",$R38*(1-AW38)*AV38,IF($P$15="Additionnelle",($N38-($N38*($P38+AW38)))*AV38))),"Non Trouvé") | BA38: =BA37 | BB38: =BB37 | BC38: =IFERROR(IF($C38="","",IF($P$15="Cascade",$R38*(1-BB38)*BA38,IF($P$15="Additionnelle",($N38-($N38*($P38+BB38)))*BA38))),"Non Trouvé") | BF38: =BF37 | BG38: =BG37 | BH38: =IFERROR(IF($C38="","",IF($P$15="Cascade",$R38*(1-BG38)*BF38,IF($P$15="Additionnelle",($N38-($N38*($P38+BG38)))*BF38))),"Non Trouvé") | BK38: =BK37 | BL38: =BL37 | BM38: =IFERROR(IF($C38="","",IF($P$15="Cascade",$R38*(1-BL38)*BK38,IF($P$15="Additionnelle",($N38-($N38*($P38+BL38)))*BK38))),"Non Trouvé") | BP38: =BP37 | BQ38: =BQ37 | BR38: =IFERROR(IF($C38="","",IF($P$15="Cascade",$R38*(1-BQ38)*BP38,IF($P$15="Additionnelle",($N38-($N38*($P38+BQ38)))*BP38))),"Non Trouvé") | BU38: =BU37 | BV38: =BV37 | BW38: =IFERROR(IF($C38="","",IF($P$15="Cascade",$R38*(1-BV38)*BU38,IF($P$15="Additionnelle",($N38-($N38*($P38+BV38)))*BU38))),"Non Trouvé") | BZ38: =BZ37 | CA38: =CA37 | CB38: =IFERROR(IF($C38="","",IF($P$15="Cascade",$R38*(1-CA38)*BZ38,IF($P$15="Additionnelle",($N38-($N38*($P38+CA38)))*BZ38))),"Non Trouvé") | CG38: Marges € | CH38: =IFERROR(CH36*CH37,0) | CK38: =IFERROR(IF(F38='[1]Paramètres Généraux'!$K$12,ROUNDUP((REGENERANTS!H38*REGENERANTS!$CF$20)*'[1]Paramètres Généraux'!$M$12,-1),IF(F38='[1]Paramètres Généraux'!$K$15,ROUNDUP((REGENERANTS!H38*REGENERANTS!$CF$20)*'[1]Paramètres Généraux'!$M$15,-1),REGENERANTS!H38*REGENERANTS!$CF$20)),"nd") | DQ38: =SUM(CN38:DP38) | DR38: =SUM(CV38:DP38) | DS38: =IFERROR((IF(AND($F38="Produit Vente",CO38>0),VLOOKUP($C38,'[1]Paramètres Articles'!$B:$H,7,FALSE)*$CO38)*(1-20%)),0) | DT38: =IFERROR((IF(AND($F38="Produit Vente",DR38>0),VLOOKUP($C38,'[1]Paramètres Articles'!$B:$H,6,FALSE)*$DR38)*(1-15%)),0) | DU38: =IFERROR(DQ38*J38,0)
B39: =IF(C39="",0,COUNTIFS($B$22:B38,">"&0)+1) | C39: 3020720 | D39: =IFERROR(IF($C39="","",VLOOKUP($C39,'[1]Paramètres Articles'!$B:$G,2,FALSE)),"Non Trouvé") | E39: =IFERROR(IF($C39="","",_xlfn.XLOOKUP(REGENERANTS!$C39,'[1]New Base PA'!$F:$F,'[1]New Base PA'!$D:$D,"Not Found",0)),"Non Trouvé") | F39: Testeur | H39: 1 | J39: =IFERROR(IF($C39="","",VLOOKUP($C39,'[1]New Base PA'!$F:$J,5,FALSE)),"Non Trouvé") | K39: =IFERROR(IF($C39="","",$J39*$H39),"Non Trouvé") | M39: =IFERROR(IF(AND($F39="Produit Vente",H39>0),VLOOKUP($C39,'[1]Paramètres Articles'!$B:$G,6,FALSE),0),"Non Trouvé") | N39: =IFERROR(IF($C39="","",$M39*$H39),"Non Trouvé") | R39: =IFERROR(IF($C39="","",$N39*(1-$P39)),"Non Trouvé") | T39: =IFERROR(IF($C39="","",VLOOKUP($C39,'[1]Paramètres Articles'!$B:$H,7,FALSE)),"Non Trouvé") | V39: =IFERROR(IF($C39="","",IF($P39="","",$T39*(1-$P39))),"Non Trouvé") | X39: =IFERROR(T39-V39,"") | Z39: =IFERROR(IF(OR(T39=0,T39=""),0,T39*H39),"Non Trouvé") | AB39: =AB38 | AC39: =AC38 | AD39: =IFERROR(IF($C39="","",IF($P$15="Cascade",$R39*(1-AC39)*AB39,IF($P$15="Additionnelle",($N39-($N39*($P39+AC39)))*AB39))),"Non Trouvé") | AG39: =AG38 | AH39: =AH38 | AI39: =IFERROR(IF($C39="","",IF($P$15="Cascade",$R39*(1-AH39)*AG39,IF($P$15="Additionnelle",($N39-($N39*($P39+AH39)))*AG39))),"Non Trouvé") | AL39: =AL38 | AM39: =AM38 | AN39: =IFERROR(IF($C39="","",IF($P$15="Cascade",$R39*(1-AM39)*AL39,IF($P$15="Additionnelle",($N39-($N39*($P39+AM39)))*AL39))),"Non Trouvé") | AQ39: =AQ38 | AR39: =AR38 | AS39: =IFERROR(IF($C39="","",IF($P$15="Cascade",$R39*(1-AR39)*AQ39,IF($P$15="Additionnelle",($N39-($N39*($P39+AR39)))*AQ39))),"Non Trouvé") | AV39: =AV38 | AW39: =AW38 | AX39: =IFERROR(IF($C39="","",IF($P$15="Cascade",$R39*(1-AW39)*AV39,IF($P$15="Additionnelle",($N39-($N39*($P39+AW39)))*AV39))),"Non Trouvé") | BA39: =BA38 | BB39: =BB38 | BC39: =IFERROR(IF($C39="","",IF($P$15="Cascade",$R39*(1-BB39)*BA39,IF($P$15="Additionnelle",($N39-($N39*($P39+BB39)))*BA39))),"Non Trouvé") | BF39: =BF38 | BG39: =BG38 | BH39: =IFERROR(IF($C39="","",IF($P$15="Cascade",$R39*(1-BG39)*BF39,IF($P$15="Additionnelle",($N39-($N39*($P39+BG39)))*BF39))),"Non Trouvé") | BK39: =BK38 | BL39: =BL38 | BM39: =IFERROR(IF($C39="","",IF($P$15="Cascade",$R39*(1-BL39)*BK39,IF($P$15="Additionnelle",($N39-($N39*($P39+BL39)))*BK39))),"Non Trouvé") | BP39: =BP38 | BQ39: =BQ38 | BR39: =IFERROR(IF($C39="","",IF($P$15="Cascade",$R39*(1-BQ39)*BP39,IF($P$15="Additionnelle",($N39-($N39*($P39+BQ39)))*BP39))),"Non Trouvé") | BU39: =BU38 | BV39: =BV38 | BW39: =IFERROR(IF($C39="","",IF($P$15="Cascade",$R39*(1-BV39)*BU39,IF($P$15="Additionnelle",($N39-($N39*($P39+BV39)))*BU39))),"Non Trouvé") | BZ39: =BZ38 | CA39: =CA38 | CB39: =IFERROR(IF($C39="","",IF($P$15="Cascade",$R39*(1-CA39)*BZ39,IF($P$15="Additionnelle",($N39-($N39*($P39+CA39)))*BZ39))),"Non Trouvé") | CK39: =IFERROR(IF(F39='[1]Paramètres Généraux'!$K$12,ROUNDUP((REGENERANTS!H39*REGENERANTS!$CF$20)*'[1]Paramètres Généraux'!$M$12,-1),IF(F39='[1]Paramètres Généraux'!$K$15,ROUNDUP((REGENERANTS!H39*REGENERANTS!$CF$20)*'[1]Paramètres Généraux'!$M$15,-1),REGENERANTS!H39*REGENERANTS!$CF$20)),"nd") | DQ39: =SUM(CN39:DP39) | DR39: =SUM(CV39:DP39) | DS39: =IFERROR((IF(AND($F39="Produit Vente",CO39>0),VLOOKUP($C39,'[1]Paramètres Articles'!$B:$H,7,FALSE)*$CO39)*(1-20%)),0) | DT39: =IFERROR((IF(AND($F39="Produit Vente",DR39>0),VLOOKUP($C39,'[1]Paramètres Articles'!$B:$H,6,FALSE)*$DR39)*(1-15%)),0) | DU39: =IFERROR(DQ39*J39,0)
B40: =IF(C40="",0,COUNTIFS($B$22:B39,">"&0)+1) | C40: 3020718 | D40: =IFERROR(IF($C40="","",VLOOKUP($C40,'[1]Paramètres Articles'!$B:$G,2,FALSE)),"Non Trouvé") | E40: =IFERROR(IF($C40="","",_xlfn.XLOOKUP(REGENERANTS!$C40,'[1]New Base PA'!$F:$F,'[1]New Base PA'!$D:$D,"Not Found",0)),"Non Trouvé") | F40: Testeur | H40: 1 | J40: =IFERROR(IF($C40="","",VLOOKUP($C40,'[1]New Base PA'!$F:$J,5,FALSE)),"Non Trouvé") | K40: =IFERROR(IF($C40="","",$J40*$H40),"Non Trouvé") | M40: =IFERROR(IF(AND($F40="Produit Vente",H40>0),VLOOKUP($C40,'[1]Paramètres Articles'!$B:$G,6,FALSE),0),"Non Trouvé") | N40: =IFERROR(IF($C40="","",$M40*$H40),"Non Trouvé") | R40: =IFERROR(IF($C40="","",$N40*(1-$P40)),"Non Trouvé") | T40: =IFERROR(IF($C40="","",VLOOKUP($C40,'[1]Paramètres Articles'!$B:$H,7,FALSE)),"Non Trouvé") | V40: =IFERROR(IF($C40="","",IF($P40="","",$T40*(1-$P40))),"Non Trouvé") | X40: =IFERROR(T40-V40,"") | Z40: =IFERROR(IF(OR(T40=0,T40=""),0,T40*H40),"Non Trouvé") | AB40: =AB39 | AC40: =AC39 | AD40: =IFERROR(IF($C40="","",IF($P$15="Cascade",$R40*(1-AC40)*AB40,IF($P$15="Additionnelle",($N40-($N40*($P40+AC40)))*AB40))),"Non Trouvé") | AG40: =AG39 | AH40: =AH39 | AI40: =IFERROR(IF($C40="","",IF($P$15="Cascade",$R40*(1-AH40)*AG40,IF($P$15="Additionnelle",($N40-($N40*($P40+AH40)))*AG40))),"Non Trouvé") | AL40: =AL39 | AM40: =AM39 | AN40: =IFERROR(IF($C40="","",IF($P$15="Cascade",$R40*(1-AM40)*AL40,IF($P$15="Additionnelle",($N40-($N40*($P40+AM40)))*AL40))),"Non Trouvé") | AQ40: =AQ39 | AR40: =AR39 | AS40: =IFERROR(IF($C40="","",IF($P$15="Cascade",$R40*(1-AR40)*AQ40,IF($P$15="Additionnelle",($N40-($N40*($P40+AR40)))*AQ40))),"Non Trouvé") | AV40: =AV39 | AW40: =AW39 | AX40: =IFERROR(IF($C40="","",IF($P$15="Cascade",$R40*(1-AW40)*AV40,IF($P$15="Additionnelle",($N40-($N40*($P40+AW40)))*AV40))),"Non Trouvé") | BA40: =BA39 | BB40: =BB39 | BC40: =IFERROR(IF($C40="","",IF($P$15="Cascade",$R40*(1-BB40)*BA40,IF($P$15="Additionnelle",($N40-($N40*($P40+BB40)))*BA40))),"Non Trouvé") | BF40: =BF39 | BG40: =BG39 | BH40: =IFERROR(IF($C40="","",IF($P$15="Cascade",$R40*(1-BG40)*BF40,IF($P$15="Additionnelle",($N40-($N40*($P40+BG40)))*BF40))),"Non Trouvé") | BK40: =BK39 | BL40: =BL39 | BM40: =IFERROR(IF($C40="","",IF($P$15="Cascade",$R40*(1-BL40)*BK40,IF($P$15="Additionnelle",($N40-($N40*($P40+BL40)))*BK40))),"Non Trouvé") | BP40: =BP39 | BQ40: =BQ39 | BR40: =IFERROR(IF($C40="","",IF($P$15="Cascade",$R40*(1-BQ40)*BP40,IF($P$15="Additionnelle",($N40-($N40*($P40+BQ40)))*BP40))),"Non Trouvé") | BU40: =BU39 | BV40: =BV39 | BW40: =IFERROR(IF($C40="","",IF($P$15="Cascade",$R40*(1-BV40)*BU40,IF($P$15="Additionnelle",($N40-($N40*($P40+BV40)))*BU40))),"Non Trouvé") | BZ40: =BZ39 | CA40: =CA39 | CB40: =IFERROR(IF($C40="","",IF($P$15="Cascade",$R40*(1-CA40)*BZ40,IF($P$15="Additionnelle",($N40-($N40*($P40+CA40)))*BZ40))),"Non Trouvé") | CG40: Institut | CK40: =IFERROR(IF(F40='[1]Paramètres Généraux'!$K$12,ROUNDUP((REGENERANTS!H40*REGENERANTS!$CF$20)*'[1]Paramètres Généraux'!$M$12,-1),IF(F40='[1]Paramètres Généraux'!$K$15,ROUNDUP((REGENERANTS!H40*REGENERANTS!$CF$20)*'[1]Paramètres Généraux'!$M$15,-1),REGENERANTS!H40*REGENERANTS!$CF$20)),"nd") | DQ40: =SUM(CN40:DP40) | DR40: =SUM(CV40:DP40) | DS40: =IFERROR((IF(AND($F40="Produit Vente",CO40>0),VLOOKUP($C40,'[1]Paramètres Articles'!$B:$H,7,FALSE)*$CO40)*(1-20%)),0) | DT40: =IFERROR((IF(AND($F40="Produit Vente",DR40>0),VLOOKUP($C40,'[1]Paramètres Articles'!$B:$H,6,FALSE)*$DR40)*(1-15%)),0) | DU40: =IFERROR(DQ40*J40,0) | DX40: CODE ARTICLE | DY40: LIBELLE ARTICLE | DZ40: BESOIN | EA40: COMMANDE
B41: =IF(C41="",0,COUNTIFS($B$22:B40,">"&0)+1) | C41: SR REGE RETAIL 1 | D41: =IFERROR(IF($C41="","",VLOOKUP($C41,'[1]Paramètres Articles'!$B:$G,2,FALSE)),"Non Trouvé") | E41: =IFERROR(IF($C41="","",_xlfn.XLOOKUP(REGENERANTS!$C41,'[1]New Base PA'!$F:$F,'[1]New Base PA'!$D:$D,"Not Found",0)),"Non Trouvé") | F41: PLV (PDC ou autre) | H41: 1 | J41: =IFERROR(IF($C41="","",VLOOKUP($C41,'[1]New Base PA'!$F:$J,5,FALSE)),"Non Trouvé") | K41: =IFERROR(IF($C41="","",$J41*$H41),"Non Trouvé") | M41: =IFERROR(IF(AND($F41="Produit Vente",H41>0),VLOOKUP($C41,'[1]Paramètres Articles'!$B:$G,6,FALSE),0),"Non Trouvé") | N41: =IFERROR(IF($C41="","",$M41*$H41),"Non Trouvé") | R41: =IFERROR(IF($C41="","",$N41*(1-$P41)),"Non Trouvé") | T41: =IFERROR(IF($C41="","",VLOOKUP($C41,'[1]Paramètres Articles'!$B:$H,7,FALSE)),"Non Trouvé") | V41: =IFERROR(IF($C41="","",IF($P41="","",$T41*(1-$P41))),"Non Trouvé") | X41: =IFERROR(T41-V41,"") | Z41: =IFERROR(IF(OR(T41=0,T41=""),0,T41*H41),"Non Trouvé") | AB41: =AB40 | AC41: =AC40 | AD41: =IFERROR(IF($C41="","",IF($P$15="Cascade",$R41*(1-AC41)*AB41,IF($P$15="Additionnelle",($N41-($N41*($P41+AC41)))*AB41))),"Non Trouvé") | AG41: =AG40 | AH41: =AH40 | AI41: =IFERROR(IF($C41="","",IF($P$15="Cascade",$R41*(1-AH41)*AG41,IF($P$15="Additionnelle",($N41-($N41*($P41+AH41)))*AG41))),"Non Trouvé") | AL41: =AL40 | AM41: =AM40 | AN41: =IFERROR(IF($C41="","",IF($P$15="Cascade",$R41*(1-AM41)*AL41,IF($P$15="Additionnelle",($N41-($N41*($P41+AM41)))*AL41))),"Non Trouvé") | AQ41: =AQ40 | AR41: =AR40 | AS41: =IFERROR(IF($C41="","",IF($P$15="Cascade",$R41*(1-AR41)*AQ41,IF($P$15="Additionnelle",($N41-($N41*($P41+AR41)))*AQ41))),"Non Trouvé") | AV41: =AV40 | AW41: =AW40 | AX41: =IFERROR(IF($C41="","",IF($P$15="Cascade",$R41*(1-AW41)*AV41,IF($P$15="Additionnelle",($N41-($N41*($P41+AW41)))*AV41))),"Non Trouvé") | BA41: =BA40 | BB41: =BB40 | BC41: =IFERROR(IF($C41="","",IF($P$15="Cascade",$R41*(1-BB41)*BA41,IF($P$15="Additionnelle",($N41-($N41*($P41+BB41)))*BA41))),"Non Trouvé") | BF41: =BF40 | BG41: =BG40 | BH41: =IFERROR(IF($C41="","",IF($P$15="Cascade",$R41*(1-BG41)*BF41,IF($P$15="Additionnelle",($N41-($N41*($P41+BG41)))*BF41))),"Non Trouvé") | BK41: =BK40 | BL41: =BL40 | BM41: =IFERROR(IF($C41="","",IF($P$15="Cascade",$R41*(1-BL41)*BK41,IF($P$15="Additionnelle",($N41-($N41*($P41+BL41)))*BK41))),"Non Trouvé") | BP41: =BP40 | BQ41: =BQ40 | BR41: =IFERROR(IF($C41="","",IF($P$15="Cascade",$R41*(1-BQ41)*BP41,IF($P$15="Additionnelle",($N41-($N41*($P41+BQ41)))*BP41))),"Non Trouvé") | BU41: =BU40 | BV41: =BV40 | BW41: =IFERROR(IF($C41="","",IF($P$15="Cascade",$R41*(1-BV41)*BU41,IF($P$15="Additionnelle",($N41-($N41*($P41+BV41)))*BU41))),"Non Trouvé") | BZ41: =BZ40 | CA41: =CA40 | CB41: =IFERROR(IF($C41="","",IF($P$15="Cascade",$R41*(1-CA41)*BZ41,IF($P$15="Additionnelle",($N41-($N41*($P41+CA41)))*BZ41))),"Non Trouvé") | CG41: Nbrs Offres planifiées | CH41: =SUMIFS($AV20:$BX20,$AV17:$BX17,CG41) | CK41: =IFERROR(IF(F41='[1]Paramètres Généraux'!$K$12,ROUNDUP((REGENERANTS!H41*REGENERANTS!$CF$20)*'[1]Paramètres Généraux'!$M$12,-1),IF(F41='[1]Paramètres Généraux'!$K$15,ROUNDUP((REGENERANTS!H41*REGENERANTS!$CF$20)*'[1]Paramètres Généraux'!$M$15,-1),REGENERANTS!H41*REGENERANTS!$CF$20)),"nd") | CS41: 1 | DQ41: =SUM(CN41:DP41) | DR41: =SUM(CV41:DP41) | DS41: =IFERROR((IF(AND($F41="Produit Vente",CO41>0),VLOOKUP($C41,'[1]Paramètres Articles'!$B:$H,7,FALSE)*$CO41)*(1-20%)),0) | DT41: =IFERROR((IF(AND($F41="Produit Vente",DR41>0),VLOOKUP($C41,'[1]Paramètres Articles'!$B:$H,6,FALSE)*$DR41)*(1-15%)),0) | DU41: =IFERROR(DQ41*J41,0)
B42: =IF(C42="",0,COUNTIFS($B$22:B41,">"&0)+1) | D42: =IFERROR(IF($C42="","",VLOOKUP($C42,'[1]Paramètres Articles'!$B:$G,2,FALSE)),"Non Trouvé") | E42: =IFERROR(IF($C42="","",_xlfn.XLOOKUP(REGENERANTS!$C42,'[1]New Base PA'!$F:$F,'[1]New Base PA'!$D:$D,"Not Found",0)),"Non Trouvé") | J42: =IFERROR(IF($C42="","",VLOOKUP($C42,'[1]New Base PA'!$F:$J,5,FALSE)),"Non Trouvé") | K42: =IFERROR(IF($C42="","",$J42*$H42),"Non Trouvé") | M42: =IFERROR(IF(AND($F42="Produit Vente",H42>0),VLOOKUP($C42,'[1]Paramètres Articles'!$B:$G,6,FALSE),0),"Non Trouvé") | N42: =IFERROR(IF($C42="","",$M42*$H42),"Non Trouvé") | R42: =IFERROR(IF($C42="","",$N42*(1-$P42)),"Non Trouvé") | T42: =IFERROR(IF($C42="","",VLOOKUP($C42,'[1]Paramètres Articles'!$B:$H,7,FALSE)),"Non Trouvé") | V42: =IFERROR(IF($C42="","",IF($P42="","",$T42*(1-$P42))),"Non Trouvé") | X42: =IFERROR(T42-V42,"") | Z42: =IFERROR(IF(OR(T42=0,T42=""),0,T42*H42),"Non Trouvé") | AB42: =AB41 | AC42: =AC41 | AD42: =IFERROR(IF($C42="","",IF($P$15="Cascade",$R42*(1-AC42)*AB42,IF($P$15="Additionnelle",($N42-($N42*($P42+AC42)))*AB42))),"Non Trouvé") | AG42: =AG41 | AH42: =AH41 | AI42: =IFERROR(IF($C42="","",IF($P$15="Cascade",$R42*(1-AH42)*AG42,IF($P$15="Additionnelle",($N42-($N42*($P42+AH42)))*AG42))),"Non Trouvé") | AL42: =AL41 | AM42: =AM41 | AN42: =IFERROR(IF($C42="","",IF($P$15="Cascade",$R42*(1-AM42)*AL42,IF($P$15="Additionnelle",($N42-($N42*($P42+AM42)))*AL42))),"Non Trouvé") | AQ42: =AQ41 | AR42: =AR41 | AS42: =IFERROR(IF($C42="","",IF($P$15="Cascade",$R42*(1-AR42)*AQ42,IF($P$15="Additionnelle",($N42-($N42*($P42+AR42)))*AQ42))),"Non Trouvé") | AV42: =AV41 | AW42: =AW41 | AX42: =IFERROR(IF($C42="","",IF($P$15="Cascade",$R42*(1-AW42)*AV42,IF($P$15="Additionnelle",($N42-($N42*($P42+AW42)))*AV42))),"Non Trouvé") | BA42: =BA41 | BB42: =BB41 | BC42: =IFERROR(IF($C42="","",IF($P$15="Cascade",$R42*(1-BB42)*BA42,IF($P$15="Additionnelle",($N42-($N42*($P42+BB42)))*BA42))),"Non Trouvé") | BF42: =BF41 | BG42: =BG41 | BH42: =IFERROR(IF($C42="","",IF($P$15="Cascade",$R42*(1-BG42)*BF42,IF($P$15="Additionnelle",($N42-($N42*($P42+BG42)))*BF42))),"Non Trouvé") | BK42: =BK41 | BL42: =BL41 | BM42: =IFERROR(IF($C42="","",IF($P$15="Cascade",$R42*(1-BL42)*BK42,IF($P$15="Additionnelle",($N42-($N42*($P42+BL42)))*BK42))),"Non Trouvé") | BP42: =BP41 | BQ42: =BQ41 | BR42: =IFERROR(IF($C42="","",IF($P$15="Cascade",$R42*(1-BQ42)*BP42,IF($P$15="Additionnelle",($N42-($N42*($P42+BQ42)))*BP42))),"Non Trouvé") | BU42: =BU41 | BV42: =BV41 | BW42: =IFERROR(IF($C42="","",IF($P$15="Cascade",$R42*(1-BV42)*BU42,IF($P$15="Additionnelle",($N42-($N42*($P42+BV42)))*BU42))),"Non Trouvé") | BZ42: =BZ41 | CA42: =CA41 | CB42: =IFERROR(IF($C42="","",IF($P$15="Cascade",$R42*(1-CA42)*BZ42,IF($P$15="Additionnelle",($N42-($N42*($P42+CA42)))*BZ42))),"Non Trouvé") | CG42: CA | CH42: =SUMIFS($AV20:$BX20,$AV17:$BX17,CG42) | CK42: =IFERROR(IF(F42='[1]Paramètres Généraux'!$K$12,ROUNDUP((REGENERANTS!H42*REGENERANTS!$CF$20)*'[1]Paramètres Généraux'!$M$12,-1),IF(F42='[1]Paramètres Généraux'!$K$15,ROUNDUP((REGENERANTS!H42*REGENERANTS!$CF$20)*'[1]Paramètres Généraux'!$M$15,-1),REGENERANTS!H42*REGENERANTS!$CF$20)),"nd") | DQ42: =SUM(CN42:DP42) | DR42: =SUM(CV42:DP42) | DS42: =IFERROR((IF(AND($F42="Produit Vente",CO42>0),VLOOKUP($C42,'[1]Paramètres Articles'!$B:$H,7,FALSE)*$CO42)*(1-20%)),0) | DT42: =IFERROR((IF(AND($F42="Produit Vente",DR42>0),VLOOKUP($C42,'[1]Paramètres Articles'!$B:$H,6,FALSE)*$DR42)*(1-15%)),0) | DU42: =IFERROR(DQ42*J42,0) | DX42: =C35 | DY42: =VLOOKUP(DX42,C:D,2,FALSE) | DZ42: =SUMIFS('[1]Moteur Produits'!$C:$C,'[1]Moteur Produits'!$B:$B,$DX42) | EA42: 350
B43: =IF(C43="",0,COUNTIFS($B$22:B42,">"&0)+1) | D43: =IFERROR(IF($C43="","",VLOOKUP($C43,'[1]Paramètres Articles'!$B:$G,2,FALSE)),"Non Trouvé") | E43: =IFERROR(IF($C43="","",_xlfn.XLOOKUP(REGENERANTS!$C43,'[1]New Base PA'!$F:$F,'[1]New Base PA'!$D:$D,"Not Found",0)),"Non Trouvé") | J43: =IFERROR(IF($C43="","",VLOOKUP($C43,'[1]New Base PA'!$F:$J,5,FALSE)),"Non Trouvé") | K43: =IFERROR(IF($C43="","",$J43*$H43),"Non Trouvé") | M43: =IFERROR(IF(AND($F43="Produit Vente",H43>0),VLOOKUP($C43,'[1]Paramètres Articles'!$B:$G,6,FALSE),0),"Non Trouvé") | N43: =IFERROR(IF($C43="","",$M43*$H43),"Non Trouvé") | R43: =IFERROR(IF($C43="","",$N43*(1-$P43)),"Non Trouvé") | T43: =IFERROR(IF($C43="","",VLOOKUP($C43,'[1]Paramètres Articles'!$B:$H,7,FALSE)),"Non Trouvé") | V43: =IFERROR(IF($C43="","",IF($P43="","",$T43*(1-$P43))),"Non Trouvé") | X43: =IFERROR(T43-V43,"") | Z43: =IFERROR(IF(OR(T43=0,T43=""),0,T43*H43),"Non Trouvé") | AB43: =AB42 | AC43: =AC42 | AD43: =IFERROR(IF($C43="","",IF($P$15="Cascade",$R43*(1-AC43)*AB43,IF($P$15="Additionnelle",($N43-($N43*($P43+AC43)))*AB43))),"Non Trouvé") | AG43: =AG42 | AH43: =AH42 | AI43: =IFERROR(IF($C43="","",IF($P$15="Cascade",$R43*(1-AH43)*AG43,IF($P$15="Additionnelle",($N43-($N43*($P43+AH43)))*AG43))),"Non Trouvé") | AL43: =AL42 | AM43: =AM42 | AN43: =IFERROR(IF($C43="","",IF($P$15="Cascade",$R43*(1-AM43)*AL43,IF($P$15="Additionnelle",($N43-($N43*($P43+AM43)))*AL43))),"Non Trouvé") | AQ43: =AQ42 | AR43: =AR42 | AS43: =IFERROR(IF($C43="","",IF($P$15="Cascade",$R43*(1-AR43)*AQ43,IF($P$15="Additionnelle",($N43-($N43*($P43+AR43)))*AQ43))),"Non Trouvé") | AV43: =AV42 | AW43: =AW42 | AX43: =IFERROR(IF($C43="","",IF($P$15="Cascade",$R43*(1-AW43)*AV43,IF($P$15="Additionnelle",($N43-($N43*($P43+AW43)))*AV43))),"Non Trouvé") | BA43: =BA42 | BB43: =BB42 | BC43: =IFERROR(IF($C43="","",IF($P$15="Cascade",$R43*(1-BB43)*BA43,IF($P$15="Additionnelle",($N43-($N43*($P43+BB43)))*BA43))),"Non Trouvé") | BF43: =BF42 | BG43: =BG42 | BH43: =IFERROR(IF($C43="","",IF($P$15="Cascade",$R43*(1-BG43)*BF43,IF($P$15="Additionnelle",($N43-($N43*($P43+BG43)))*BF43))),"Non Trouvé") | BK43: =BK42 | BL43: =BL42 | BM43: =IFERROR(IF($C43="","",IF($P$15="Cascade",$R43*(1-BL43)*BK43,IF($P$15="Additionnelle",($N43-($N43*($P43+BL43)))*BK43))),"Non Trouvé") | BP43: =BP42 | BQ43: =BQ42 | BR43: =IFERROR(IF($C43="","",IF($P$15="Cascade",$R43*(1-BQ43)*BP43,IF($P$15="Additionnelle",($N43-($N43*($P43+BQ43)))*BP43))),"Non Trouvé") | BU43: =BU42 | BV43: =BV42 | BW43: =IFERROR(IF($C43="","",IF($P$15="Cascade",$R43*(1-BV43)*BU43,IF($P$15="Additionnelle",($N43-($N43*($P43+BV43)))*BU43))),"Non Trouvé") | BZ43: =BZ42 | CA43: =CA42 | CB43: =IFERROR(IF($C43="","",IF($P$15="Cascade",$R43*(1-CA43)*BZ43,IF($P$15="Additionnelle",($N43-($N43*($P43+CA43)))*BZ43))),"Non Trouvé") | CG43: Marges | CH43: =IFERROR((CH42-$K20*CH41)/CH42,"Non Trouvé") | CK43: =IFERROR(IF(F43='[1]Paramètres Généraux'!$K$12,ROUNDUP((REGENERANTS!H43*REGENERANTS!$CF$20)*'[1]Paramètres Généraux'!$M$12,-1),IF(F43='[1]Paramètres Généraux'!$K$15,ROUNDUP((REGENERANTS!H43*REGENERANTS!$CF$20)*'[1]Paramètres Généraux'!$M$15,-1),REGENERANTS!H43*REGENERANTS!$CF$20)),"nd") | DQ43: =SUM(CN43:DP43) | DR43: =SUM(CV43:DP43) | DS43: =IFERROR((IF(AND($F43="Produit Vente",CO43>0),VLOOKUP($C43,'[1]Paramètres Articles'!$B:$H,7,FALSE)*$CO43)*(1-20%)),0) | DT43: =IFERROR((IF(AND($F43="Produit Vente",DR43>0),VLOOKUP($C43,'[1]Paramètres Articles'!$B:$H,6,FALSE)*$DR43)*(1-15%)),0) | DU43: =IFERROR(DQ43*J43,0) | DX43: =C36 | DY43: =VLOOKUP(DX43,C:D,2,FALSE) | DZ43: =SUMIFS('[1]Moteur Produits'!$C:$C,'[1]Moteur Produits'!$B:$B,$DX43) | EA43: 400
B44: =IF(C44="",0,COUNTIFS($B$22:B43,">"&0)+1) | D44: =IFERROR(IF($C44="","",VLOOKUP($C44,'[1]Paramètres Articles'!$B:$G,2,FALSE)),"Non Trouvé") | E44: =IFERROR(IF($C44="","",_xlfn.XLOOKUP(REGENERANTS!$C44,'[1]New Base PA'!$F:$F,'[1]New Base PA'!$D:$D,"Not Found",0)),"Non Trouvé") | J44: =IFERROR(IF($C44="","",VLOOKUP($C44,'[1]New Base PA'!$F:$J,5,FALSE)),"Non Trouvé") | K44: =IFERROR(IF($C44="","",$J44*$H44),"Non Trouvé") | M44: =IFERROR(IF(AND($F44="Produit Vente",H44>0),VLOOKUP($C44,'[1]Paramètres Articles'!$B:$G,6,FALSE),0),"Non Trouvé") | N44: =IFERROR(IF($C44="","",$M44*$H44),"Non Trouvé") | R44: =IFERROR(IF($C44="","",$N44*(1-$P44)),"Non Trouvé") | T44: =IFERROR(IF($C44="","",VLOOKUP($C44,'[1]Paramètres Articles'!$B:$H,7,FALSE)),"Non Trouvé") | V44: =IFERROR(IF($C44="","",IF($P44="","",$T44*(1-$P44))),"Non Trouvé") | X44: =IFERROR(T44-V44,"") | Z44: =IFERROR(IF(OR(T44=0,T44=""),0,T44*H44),"Non Trouvé") | AB44: =AB43 | AC44: =AC43 | AD44: =IFERROR(IF($C44="","",IF($P$15="Cascade",$R44*(1-AC44)*AB44,IF($P$15="Additionnelle",($N44-($N44*($P44+AC44)))*AB44))),"Non Trouvé") | AG44: =AG43 | AH44: =AH43 | AI44: =IFERROR(IF($C44="","",IF($P$15="Cascade",$R44*(1-AH44)*AG44,IF($P$15="Additionnelle",($N44-($N44*($P44+AH44)))*AG44))),"Non Trouvé") | AL44: =AL43 | AM44: =AM43 | AN44: =IFERROR(IF($C44="","",IF($P$15="Cascade",$R44*(1-AM44)*AL44,IF($P$15="Additionnelle",($N44-($N44*($P44+AM44)))*AL44))),"Non Trouvé") | AQ44: =AQ43 | AR44: =AR43 | AS44: =IFERROR(IF($C44="","",IF($P$15="Cascade",$R44*(1-AR44)*AQ44,IF($P$15="Additionnelle",($N44-($N44*($P44+AR44)))*AQ44))),"Non Trouvé") | AV44: =AV43 | AW44: =AW43 | AX44: =IFERROR(IF($C44="","",IF($P$15="Cascade",$R44*(1-AW44)*AV44,IF($P$15="Additionnelle",($N44-($N44*($P44+AW44)))*AV44))),"Non Trouvé") | BA44: =BA43 | BB44: =BB43 | BC44: =IFERROR(IF($C44="","",IF($P$15="Cascade",$R44*(1-BB44)*BA44,IF($P$15="Additionnelle",($N44-($N44*($P44+BB44)))*BA44))),"Non Trouvé") | BF44: =BF43 | BG44: =BG43 | BH44: =IFERROR(IF($C44="","",IF($P$15="Cascade",$R44*(1-BG44)*BF44,IF($P$15="Additionnelle",($N44-($N44*($P44+BG44)))*BF44))),"Non Trouvé") | BK44: =BK43 | BL44: =BL43 | BM44: =IFERROR(IF($C44="","",IF($P$15="Cascade",$R44*(1-BL44)*BK44,IF($P$15="Additionnelle",($N44-($N44*($P44+BL44)))*BK44))),"Non Trouvé") | BP44: =BP43 | BQ44: =BQ43 | BR44: =IFERROR(IF($C44="","",IF($P$15="Cascade",$R44*(1-BQ44)*BP44,IF($P$15="Additionnelle",($N44-($N44*($P44+BQ44)))*BP44))),"Non Trouvé") | BU44: =BU43 | BV44: =BV43 | BW44: =IFERROR(IF($C44="","",IF($P$15="Cascade",$R44*(1-BV44)*BU44,IF($P$15="Additionnelle",($N44-($N44*($P44+BV44)))*BU44))),"Non Trouvé") | BZ44: =BZ43 | CA44: =CA43 | CB44: =IFERROR(IF($C44="","",IF($P$15="Cascade",$R44*(1-CA44)*BZ44,IF($P$15="Additionnelle",($N44-($N44*($P44+CA44)))*BZ44))),"Non Trouvé") | CG44: Marges € | CH44: =IFERROR(CH42*CH43,0) | CK44: =IFERROR(IF(F44='[1]Paramètres Généraux'!$K$12,ROUNDUP((REGENERANTS!H44*REGENERANTS!$CF$20)*'[1]Paramètres Généraux'!$M$12,-1),IF(F44='[1]Paramètres Généraux'!$K$15,ROUNDUP((REGENERANTS!H44*REGENERANTS!$CF$20)*'[1]Paramètres Généraux'!$M$15,-1),REGENERANTS!H44*REGENERANTS!$CF$20)),"nd") | DQ44: =SUM(CN44:DP44) | DR44: =SUM(CV44:DP44) | DS44: =IFERROR((IF(AND($F44="Produit Vente",CO44>0),VLOOKUP($C44,'[1]Paramètres Articles'!$B:$H,7,FALSE)*$CO44)*(1-20%)),0) | DT44: =IFERROR((IF(AND($F44="Produit Vente",DR44>0),VLOOKUP($C44,'[1]Paramètres Articles'!$B:$H,6,FALSE)*$DR44)*(1-15%)),0) | DU44: =IFERROR(DQ44*J44,0) | DX44: =C41 | DY44: =VLOOKUP(DX44,C:D,2,FALSE) | DZ44: =SUMIFS('[1]Moteur Produits'!$C:$C,'[1]Moteur Produits'!$B:$B,$DX44)
B45: =IF(C45="",0,COUNTIFS($B$22:B44,">"&0)+1) | D45: =IFERROR(IF($C45="","",VLOOKUP($C45,'[1]Paramètres Articles'!$B:$G,2,FALSE)),"Non Trouvé") | E45: =IFERROR(IF($C45="","",_xlfn.XLOOKUP(REGENERANTS!$C45,'[1]New Base PA'!$F:$F,'[1]New Base PA'!$D:$D,"Not Found",0)),"Non Trouvé") | J45: =IFERROR(IF($C45="","",VLOOKUP($C45,'[1]New Base PA'!$F:$J,5,FALSE)),"Non Trouvé") | K45: =IFERROR(IF($C45="","",$J45*$H45),"Non Trouvé") | M45: =IFERROR(IF(AND($F45="Produit Vente",H45>0),VLOOKUP($C45,'[1]Paramètres Articles'!$B:$G,6,FALSE),0),"Non Trouvé") | N45: =IFERROR(IF($C45="","",$M45*$H45),"Non Trouvé") | R45: =IFERROR(IF($C45="","",$N45*(1-$P45)),"Non Trouvé") | T45: =IFERROR(IF($C45="","",VLOOKUP($C45,'[1]Paramètres Articles'!$B:$H,7,FALSE)),"Non Trouvé") | V45: =IFERROR(IF($C45="","",IF($P45="","",$T45*(1-$P45))),"Non Trouvé") | X45: =IFERROR(T45-V45,"") | Z45: =IFERROR(IF(OR(T45=0,T45=""),0,T45*H45),"Non Trouvé") | AB45: =AB44 | AC45: =AC44 | AD45: =IFERROR(IF($C45="","",IF($P$15="Cascade",$R45*(1-AC45)*AB45,IF($P$15="Additionnelle",($N45-($N45*($P45+AC45)))*AB45))),"Non Trouvé") | AG45: =AG44 | AH45: =AH44 | AI45: =IFERROR(IF($C45="","",IF($P$15="Cascade",$R45*(1-AH45)*AG45,IF($P$15="Additionnelle",($N45-($N45*($P45+AH45)))*AG45))),"Non Trouvé") | AL45: =AL44 | AM45: =AM44 | AN45: =IFERROR(IF($C45="","",IF($P$15="Cascade",$R45*(1-AM45)*AL45,IF($P$15="Additionnelle",($N45-($N45*($P45+AM45)))*AL45))),"Non Trouvé") | AQ45: =AQ44 | AR45: =AR44 | AS45: =IFERROR(IF($C45="","",IF($P$15="Cascade",$R45*(1-AR45)*AQ45,IF($P$15="Additionnelle",($N45-($N45*($P45+AR45)))*AQ45))),"Non Trouvé") | AV45: =AV44 | AW45: =AW44 | AX45: =IFERROR(IF($C45="","",IF($P$15="Cascade",$R45*(1-AW45)*AV45,IF($P$15="Additionnelle",($N45-($N45*($P45+AW45)))*AV45))),"Non Trouvé") | BA45: =BA44 | BB45: =BB44 | BC45: =IFERROR(IF($C45="","",IF($P$15="Cascade",$R45*(1-BB45)*BA45,IF($P$15="Additionnelle",($N45-($N45*($P45+BB45)))*BA45))),"Non Trouvé") | BF45: =BF44 | BG45: =BG44 | BH45: =IFERROR(IF($C45="","",IF($P$15="Cascade",$R45*(1-BG45)*BF45,IF($P$15="Additionnelle",($N45-($N45*($P45+BG45)))*BF45))),"Non Trouvé") | BK45: =BK44 | BL45: =BL44 | BM45: =IFERROR(IF($C45="","",IF($P$15="Cascade",$R45*(1-BL45)*BK45,IF($P$15="Additionnelle",($N45-($N45*($P45+BL45)))*BK45))),"Non Trouvé") | BP45: =BP44 | BQ45: =BQ44 | BR45: =IFERROR(IF($C45="","",IF($P$15="Cascade",$R45*(1-BQ45)*BP45,IF($P$15="Additionnelle",($N45-($N45*($P45+BQ45)))*BP45))),"Non Trouvé") | BU45: =BU44 | BV45: =BV44 | BW45: =IFERROR(IF($C45="","",IF($P$15="Cascade",$R45*(1-BV45)*BU45,IF($P$15="Additionnelle",($N45-($N45*($P45+BV45)))*BU45))),"Non Trouvé") | BZ45: =BZ44 | CA45: =CA44 | CB45: =IFERROR(IF($C45="","",IF($P$15="Cascade",$R45*(1-CA45)*BZ45,IF($P$15="Additionnelle",($N45-($N45*($P45+CA45)))*BZ45))),"Non Trouvé") | CK45: =IFERROR(IF(F45='[1]Paramètres Généraux'!$K$12,ROUNDUP((REGENERANTS!H45*REGENERANTS!$CF$20)*'[1]Paramètres Généraux'!$M$12,-1),IF(F45='[1]Paramètres Généraux'!$K$15,ROUNDUP((REGENERANTS!H45*REGENERANTS!$CF$20)*'[1]Paramètres Généraux'!$M$15,-1),REGENERANTS!H45*REGENERANTS!$CF$20)),"nd") | DQ45: =SUM(CN45:DP45) | DR45: =SUM(CV45:DP45) | DS45: =IFERROR((IF(AND($F45="Produit Vente",CO45>0),VLOOKUP($C45,'[1]Paramètres Articles'!$B:$H,7,FALSE)*$CO45)*(1-20%)),0) | DT45: =IFERROR((IF(AND($F45="Produit Vente",DR45>0),VLOOKUP($C45,'[1]Paramètres Articles'!$B:$H,6,FALSE)*$DR45)*(1-15%)),0) | DU45: =IFERROR(DQ45*J45,0) | DX45: =C133 | DY45: =VLOOKUP(DX45,C:D,2,FALSE) | DZ45: =SUMIFS('[1]Moteur Produits'!$C:$C,'[1]Moteur Produits'!$B:$B,$DX45)
B46: =IF(C46="",0,COUNTIFS($B$22:B45,">"&0)+1) | D46: =IFERROR(IF($C46="","",VLOOKUP($C46,'[1]Paramètres Articles'!$B:$G,2,FALSE)),"Non Trouvé") | E46: =IFERROR(IF($C46="","",_xlfn.XLOOKUP(REGENERANTS!$C46,'[1]New Base PA'!$F:$F,'[1]New Base PA'!$D:$D,"Not Found",0)),"Non Trouvé") | J46: =IFERROR(IF($C46="","",VLOOKUP($C46,'[1]New Base PA'!$F:$J,5,FALSE)),"Non Trouvé") | K46: =IFERROR(IF($C46="","",$J46*$H46),"Non Trouvé") | M46: =IFERROR(IF(AND($F46="Produit Vente",H46>0),VLOOKUP($C46,'[1]Paramètres Articles'!$B:$G,6,FALSE),0),"Non Trouvé") | N46: =IFERROR(IF($C46="","",$M46*$H46),"Non Trouvé") | R46: =IFERROR(IF($C46="","",$N46*(1-$P46)),"Non Trouvé") | T46: =IFERROR(IF($C46="","",VLOOKUP($C46,'[1]Paramètres Articles'!$B:$H,7,FALSE)),"Non Trouvé") | V46: =IFERROR(IF($C46="","",IF($P46="","",$T46*(1-$P46))),"Non Trouvé") | X46: =IFERROR(T46-V46,"") | Z46: =IFERROR(IF(OR(T46=0,T46=""),0,T46*H46),"Non Trouvé") | AB46: =AB45 | AC46: =AC45 | AD46: =IFERROR(IF($C46="","",IF($P$15="Cascade",$R46*(1-AC46)*AB46,IF($P$15="Additionnelle",($N46-($N46*($P46+AC46)))*AB46))),"Non Trouvé") | AG46: =AG45 | AH46: =AH45 | AI46: =IFERROR(IF($C46="","",IF($P$15="Cascade",$R46*(1-AH46)*AG46,IF($P$15="Additionnelle",($N46-($N46*($P46+AH46)))*AG46))),"Non Trouvé") | AL46: =AL45 | AM46: =AM45 | AN46: =IFERROR(IF($C46="","",IF($P$15="Cascade",$R46*(1-AM46)*AL46,IF($P$15="Additionnelle",($N46-($N46*($P46+AM46)))*AL46))),"Non Trouvé") | AQ46: =AQ45 | AR46: =AR45 | AS46: =IFERROR(IF($C46="","",IF($P$15="Cascade",$R46*(1-AR46)*AQ46,IF($P$15="Additionnelle",($N46-($N46*($P46+AR46)))*AQ46))),"Non Trouvé") | AV46: =AV45 | AW46: =AW45 | AX46: =IFERROR(IF($C46="","",IF($P$15="Cascade",$R46*(1-AW46)*AV46,IF($P$15="Additionnelle",($N46-($N46*($P46+AW46)))*AV46))),"Non Trouvé") | BA46: =BA45 | BB46: =BB45 | BC46: =IFERROR(IF($C46="","",IF($P$15="Cascade",$R46*(1-BB46)*BA46,IF($P$15="Additionnelle",($N46-($N46*($P46+BB46)))*BA46))),"Non Trouvé") | BF46: =BF45 | BG46: =BG45 | BH46: =IFERROR(IF($C46="","",IF($P$15="Cascade",$R46*(1-BG46)*BF46,IF($P$15="Additionnelle",($N46-($N46*($P46+BG46)))*BF46))),"Non Trouvé") | BK46: =BK45 | BL46: =BL45 | BM46: =IFERROR(IF($C46="","",IF($P$15="Cascade",$R46*(1-BL46)*BK46,IF($P$15="Additionnelle",($N46-($N46*($P46+BL46)))*BK46))),"Non Trouvé") | BP46: =BP45 | BQ46: =BQ45 | BR46: =IFERROR(IF($C46="","",IF($P$15="Cascade",$R46*(1-BQ46)*BP46,IF($P$15="Additionnelle",($N46-($N46*($P46+BQ46)))*BP46))),"Non Trouvé") | BU46: =BU45 | BV46: =BV45 | BW46: =IFERROR(IF($C46="","",IF($P$15="Cascade",$R46*(1-BV46)*BU46,IF($P$15="Additionnelle",($N46-($N46*($P46+BV46)))*BU46))),"Non Trouvé") | BZ46: =BZ45 | CA46: =CA45 | CB46: =IFERROR(IF($C46="","",IF($P$15="Cascade",$R46*(1-CA46)*BZ46,IF($P$15="Additionnelle",($N46-($N46*($P46+CA46)))*BZ46))),"Non Trouvé") | CK46: =IFERROR(IF(F46='[1]Paramètres Généraux'!$K$12,ROUNDUP((REGENERANTS!H46*REGENERANTS!$CF$20)*'[1]Paramètres Généraux'!$M$12,-1),IF(F46='[1]Paramètres Généraux'!$K$15,ROUNDUP((REGENERANTS!H46*REGENERANTS!$CF$20)*'[1]Paramètres Généraux'!$M$15,-1),REGENERANTS!H46*REGENERANTS!$CF$20)),"nd") | DQ46: =SUM(CN46:DP46) | DR46: =SUM(CV46:DP46) | DS46: =IFERROR((IF(AND($F46="Produit Vente",CO46>0),VLOOKUP($C46,'[1]Paramètres Articles'!$B:$H,7,FALSE)*$CO46)*(1-20%)),0) | DT46: =IFERROR((IF(AND($F46="Produit Vente",DR46>0),VLOOKUP($C46,'[1]Paramètres Articles'!$B:$H,6,FALSE)*$DR46)*(1-15%)),0) | DU46: =IFERROR(DQ46*J46,0) | DZ46: =SUMIFS('[1]Moteur Produits'!$C:$C,'[1]Moteur Produits'!$B:$B,$DX46)
B47: =IF(C47="",0,COUNTIFS($B$22:B46,">"&0)+1) | D47: =IFERROR(IF($C47="","",VLOOKUP($C47,'[1]Paramètres Articles'!$B:$G,2,FALSE)),"Non Trouvé") | E47: =IFERROR(IF($C47="","",_xlfn.XLOOKUP(REGENERANTS!$C47,'[1]New Base PA'!$F:$F,'[1]New Base PA'!$D:$D,"Not Found",0)),"Non Trouvé") | J47: =IFERROR(IF($C47="","",VLOOKUP($C47,'[1]New Base PA'!$F:$J,5,FALSE)),"Non Trouvé") | K47: =IFERROR(IF($C47="","",$J47*$H47),"Non Trouvé") | M47: =IFERROR(IF(AND($F47="Produit Vente",H47>0),VLOOKUP($C47,'[1]Paramètres Articles'!$B:$G,6,FALSE),0),"Non Trouvé") | N47: =IFERROR(IF($C47="","",$M47*$H47),"Non Trouvé") | R47: =IFERROR(IF($C47="","",$N47*(1-$P47)),"Non Trouvé") | T47: =IFERROR(IF($C47="","",VLOOKUP($C47,'[1]Paramètres Articles'!$B:$H,7,FALSE)),"Non Trouvé") | V47: =IFERROR(IF($C47="","",IF($P47="","",$T47*(1-$P47))),"Non Trouvé") | X47: =IFERROR(T47-V47,"") | Z47: =IFERROR(IF(OR(T47=0,T47=""),0,T47*H47),"Non Trouvé") | AB47: =AB46 | AC47: =AC46 | AD47: =IFERROR(IF($C47="","",IF($P$15="Cascade",$R47*(1-AC47)*AB47,IF($P$15="Additionnelle",($N47-($N47*($P47+AC47)))*AB47))),"Non Trouvé") | AG47: =AG46 | AH47: =AH46 | AI47: =IFERROR(IF($C47="","",IF($P$15="Cascade",$R47*(1-AH47)*AG47,IF($P$15="Additionnelle",($N47-($N47*($P47+AH47)))*AG47))),"Non Trouvé") | AL47: =AL46 | AM47: =AM46 | AN47: =IFERROR(IF($C47="","",IF($P$15="Cascade",$R47*(1-AM47)*AL47,IF($P$15="Additionnelle",($N47-($N47*($P47+AM47)))*AL47))),"Non Trouvé") | AQ47: =AQ46 | AR47: =AR46 | AS47: =IFERROR(IF($C47="","",IF($P$15="Cascade",$R47*(1-AR47)*AQ47,IF($P$15="Additionnelle",($N47-($N47*($P47+AR47)))*AQ47))),"Non Trouvé") | AV47: =AV46 | AW47: =AW46 | AX47: =IFERROR(IF($C47="","",IF($P$15="Cascade",$R47*(1-AW47)*AV47,IF($P$15="Additionnelle",($N47-($N47*($P47+AW47)))*AV47))),"Non Trouvé") | BA47: =BA46 | BB47: =BB46 | BC47: =IFERROR(IF($C47="","",IF($P$15="Cascade",$R47*(1-BB47)*BA47,IF($P$15="Additionnelle",($N47-($N47*($P47+BB47)))*BA47))),"Non Trouvé") | BF47: =BF46 | BG47: =BG46 | BH47: =IFERROR(IF($C47="","",IF($P$15="Cascade",$R47*(1-BG47)*BF47,IF($P$15="Additionnelle",($N47-($N47*($P47+BG47)))*BF47))),"Non Trouvé") | BK47: =BK46 | BL47: =BL46 | BM47: =IFERROR(IF($C47="","",IF($P$15="Cascade",$R47*(1-BL47)*BK47,IF($P$15="Additionnelle",($N47-($N47*($P47+BL47)))*BK47))),"Non Trouvé") | BP47: =BP46 | BQ47: =BQ46 | BR47: =IFERROR(IF($C47="","",IF($P$15="Cascade",$R47*(1-BQ47)*BP47,IF($P$15="Additionnelle",($N47-($N47*($P47+BQ47)))*BP47))),"Non Trouvé") | BU47: =BU46 | BV47: =BV46 | BW47: =IFERROR(IF($C47="","",IF($P$15="Cascade",$R47*(1-BV47)*BU47,IF($P$15="Additionnelle",($N47-($N47*($P47+BV47)))*BU47))),"Non Trouvé") | BZ47: =BZ46 | CA47: =CA46 | CB47: =IFERROR(IF($C47="","",IF($P$15="Cascade",$R47*(1-CA47)*BZ47,IF($P$15="Additionnelle",($N47-($N47*($P47+CA47)))*BZ47))),"Non Trouvé") | CK47: =IFERROR(IF(F47='[1]Paramètres Généraux'!$K$12,ROUNDUP((REGENERANTS!H47*REGENERANTS!$CF$20)*'[1]Paramètres Généraux'!$M$12,-1),IF(F47='[1]Paramètres Généraux'!$K$15,ROUNDUP((REGENERANTS!H47*REGENERANTS!$CF$20)*'[1]Paramètres Généraux'!$M$15,-1),REGENERANTS!H47*REGENERANTS!$CF$20)),"nd") | DQ47: =SUM(CN47:DP47) | DR47: =SUM(CV47:DP47) | DS47: =IFERROR((IF(AND($F47="Produit Vente",CO47>0),VLOOKUP($C47,'[1]Paramètres Articles'!$B:$H,7,FALSE)*$CO47)*(1-20%)),0) | DT47: =IFERROR((IF(AND($F47="Produit Vente",DR47>0),VLOOKUP($C47,'[1]Paramètres Articles'!$B:$H,6,FALSE)*$DR47)*(1-15%)),0) | DU47: =IFERROR(DQ47*J47,0)
B48: =IF(C48="",0,COUNTIFS($B$22:B47,">"&0)+1) | D48: =IFERROR(IF($C48="","",VLOOKUP($C48,'[1]Paramètres Articles'!$B:$G,2,FALSE)),"Non Trouvé") | E48: =IFERROR(IF($C48="","",_xlfn.XLOOKUP(REGENERANTS!$C48,'[1]New Base PA'!$F:$F,'[1]New Base PA'!$D:$D,"Not Found",0)),"Non Trouvé") | J48: =IFERROR(IF($C48="","",VLOOKUP($C48,'[1]New Base PA'!$F:$J,5,FALSE)),"Non Trouvé") | K48: =IFERROR(IF($C48="","",$J48*$H48),"Non Trouvé") | M48: =IFERROR(IF(AND($F48="Produit Vente",H48>0),VLOOKUP($C48,'[1]Paramètres Articles'!$B:$G,6,FALSE),0),"Non Trouvé") | N48: =IFERROR(IF($C48="","",$M48*$H48),"Non Trouvé") | R48: =IFERROR(IF($C48="","",$N48*(1-$P48)),"Non Trouvé") | T48: =IFERROR(IF($C48="","",VLOOKUP($C48,'[1]Paramètres Articles'!$B:$H,7,FALSE)),"Non Trouvé") | V48: =IFERROR(IF($C48="","",IF($P48="","",$T48*(1-$P48))),"Non Trouvé") | X48: =IFERROR(T48-V48,"") | Z48: =IFERROR(IF(OR(T48=0,T48=""),0,T48*H48),"Non Trouvé") | AB48: =AB47 | AC48: =AC47 | AD48: =IFERROR(IF($C48="","",IF($P$15="Cascade",$R48*(1-AC48)*AB48,IF($P$15="Additionnelle",($N48-($N48*($P48+AC48)))*AB48))),"Non Trouvé") | AG48: =AG47 | AH48: =AH47 | AI48: =IFERROR(IF($C48="","",IF($P$15="Cascade",$R48*(1-AH48)*AG48,IF($P$15="Additionnelle",($N48-($N48*($P48+AH48)))*AG48))),"Non Trouvé") | AL48: =AL47 | AM48: =AM47 | AN48: =IFERROR(IF($C48="","",IF($P$15="Cascade",$R48*(1-AM48)*AL48,IF($P$15="Additionnelle",($N48-($N48*($P48+AM48)))*AL48))),"Non Trouvé") | AQ48: =AQ47 | AR48: =AR47 | AS48: =IFERROR(IF($C48="","",IF($P$15="Cascade",$R48*(1-AR48)*AQ48,IF($P$15="Additionnelle",($N48-($N48*($P48+AR48)))*AQ48))),"Non Trouvé") | AV48: =AV47 | AW48: =AW47 | AX48: =IFERROR(IF($C48="","",IF($P$15="Cascade",$R48*(1-AW48)*AV48,IF($P$15="Additionnelle",($N48-($N48*($P48+AW48)))*AV48))),"Non Trouvé") | BA48: =BA47 | BB48: =BB47 | BC48: =IFERROR(IF($C48="","",IF($P$15="Cascade",$R48*(1-BB48)*BA48,IF($P$15="Additionnelle",($N48-($N48*($P48+BB48)))*BA48))),"Non Trouvé") | BF48: =BF47 | BG48: =BG47 | BH48: =IFERROR(IF($C48="","",IF($P$15="Cascade",$R48*(1-BG48)*BF48,IF($P$15="Additionnelle",($N48-($N48*($P48+BG48)))*BF48))),"Non Trouvé") | BK48: =BK47 | BL48: =BL47 | BM48: =IFERROR(IF($C48="","",IF($P$15="Cascade",$R48*(1-BL48)*BK48,IF($P$15="Additionnelle",($N48-($N48*($P48+BL48)))*BK48))),"Non Trouvé") | BP48: =BP47 | BQ48: =BQ47 | BR48: =IFERROR(IF($C48="","",IF($P$15="Cascade",$R48*(1-BQ48)*BP48,IF($P$15="Additionnelle",($N48-($N48*($P48+BQ48)))*BP48))),"Non Trouvé") | BU48: =BU47 | BV48: =BV47 | BW48: =IFERROR(IF($C48="","",IF($P$15="Cascade",$R48*(1-BV48)*BU48,IF($P$15="Additionnelle",($N48-($N48*($P48+BV48)))*BU48))),"Non Trouvé") | BZ48: =BZ47 | CA48: =CA47 | CB48: =IFERROR(IF($C48="","",IF($P$15="Cascade",$R48*(1-CA48)*BZ48,IF($P$15="Additionnelle",($N48-($N48*($P48+CA48)))*BZ48))),"Non Trouvé") | CK48: =IFERROR(IF(F48='[1]Paramètres Généraux'!$K$12,ROUNDUP((REGENERANTS!H48*REGENERANTS!$CF$20)*'[1]Paramètres Généraux'!$M$12,-1),IF(F48='[1]Paramètres Généraux'!$K$15,ROUNDUP((REGENERANTS!H48*REGENERANTS!$CF$20)*'[1]Paramètres Généraux'!$M$15,-1),REGENERANTS!H48*REGENERANTS!$CF$20)),"nd") | DQ48: =SUM(CN48:DP48) | DR48: =SUM(CV48:DP48) | DS48: =IFERROR((IF(AND($F48="Produit Vente",CO48>0),VLOOKUP($C48,'[1]Paramètres Articles'!$B:$H,7,FALSE)*$CO48)*(1-20%)),0) | DT48: =IFERROR((IF(AND($F48="Produit Vente",DR48>0),VLOOKUP($C48,'[1]Paramètres Articles'!$B:$H,6,FALSE)*$DR48)*(1-15%)),0) | DU48: =IFERROR(DQ48*J48,0)
B49: =IF(C49="",0,COUNTIFS($B$22:B48,">"&0)+1) | D49: =IFERROR(IF($C49="","",VLOOKUP($C49,'[1]Paramètres Articles'!$B:$G,2,FALSE)),"Non Trouvé") | E49: =IFERROR(IF($C49="","",_xlfn.XLOOKUP(REGENERANTS!$C49,'[1]New Base PA'!$F:$F,'[1]New Base PA'!$D:$D,"Not Found",0)),"Non Trouvé") | J49: =IFERROR(IF($C49="","",VLOOKUP($C49,'[1]New Base PA'!$F:$J,5,FALSE)),"Non Trouvé") | K49: =IFERROR(IF($C49="","",$J49*$H49),"Non Trouvé") | M49: =IFERROR(IF(AND($F49="Produit Vente",H49>0),VLOOKUP($C49,'[1]Paramètres Articles'!$B:$G,6,FALSE),0),"Non Trouvé") | N49: =IFERROR(IF($C49="","",$M49*$H49),"Non Trouvé") | R49: =IFERROR(IF($C49="","",$N49*(1-$P49)),"Non Trouvé") | T49: =IFERROR(IF($C49="","",VLOOKUP($C49,'[1]Paramètres Articles'!$B:$H,7,FALSE)),"Non Trouvé") | V49: =IFERROR(IF($C49="","",IF($P49="","",$T49*(1-$P49))),"Non Trouvé") | X49: =IFERROR(T49-V49,"") | Z49: =IFERROR(IF(OR(T49=0,T49=""),0,T49*H49),"Non Trouvé") | AB49: =AB48 | AC49: =AC48 | AD49: =IFERROR(IF($C49="","",IF($P$15="Cascade",$R49*(1-AC49)*AB49,IF($P$15="Additionnelle",($N49-($N49*($P49+AC49)))*AB49))),"Non Trouvé") | AG49: =AG48 | AH49: =AH48 | AI49: =IFERROR(IF($C49="","",IF($P$15="Cascade",$R49*(1-AH49)*AG49,IF($P$15="Additionnelle",($N49-($N49*($P49+AH49)))*AG49))),"Non Trouvé") | AL49: =AL48 | AM49: =AM48 | AN49: =IFERROR(IF($C49="","",IF($P$15="Cascade",$R49*(1-AM49)*AL49,IF($P$15="Additionnelle",($N49-($N49*($P49+AM49)))*AL49))),"Non Trouvé") | AQ49: =AQ48 | AR49: =AR48 | AS49: =IFERROR(IF($C49="","",IF($P$15="Cascade",$R49*(1-AR49)*AQ49,IF($P$15="Additionnelle",($N49-($N49*($P49+AR49)))*AQ49))),"Non Trouvé") | AV49: =AV48 | AW49: =AW48 | AX49: =IFERROR(IF($C49="","",IF($P$15="Cascade",$R49*(1-AW49)*AV49,IF($P$15="Additionnelle",($N49-($N49*($P49+AW49)))*AV49))),"Non Trouvé") | BA49: =BA48 | BB49: =BB48 | BC49: =IFERROR(IF($C49="","",IF($P$15="Cascade",$R49*(1-BB49)*BA49,IF($P$15="Additionnelle",($N49-($N49*($P49+BB49)))*BA49))),"Non Trouvé") | BF49: =BF48 | BG49: =BG48 | BH49: =IFERROR(IF($C49="","",IF($P$15="Cascade",$R49*(1-BG49)*BF49,IF($P$15="Additionnelle",($N49-($N49*($P49+BG49)))*BF49))),"Non Trouvé") | BK49: =BK48 | BL49: =BL48 | BM49: =IFERROR(IF($C49="","",IF($P$15="Cascade",$R49*(1-BL49)*BK49,IF($P$15="Additionnelle",($N49-($N49*($P49+BL49)))*BK49))),"Non Trouvé") | BP49: =BP48 | BQ49: =BQ48 | BR49: =IFERROR(IF($C49="","",IF($P$15="Cascade",$R49*(1-BQ49)*BP49,IF($P$15="Additionnelle",($N49-($N49*($P49+BQ49)))*BP49))),"Non Trouvé") | BU49: =BU48 | BV49: =BV48 | BW49: =IFERROR(IF($C49="","",IF($P$15="Cascade",$R49*(1-BV49)*BU49,IF($P$15="Additionnelle",($N49-($N49*($P49+BV49)))*BU49))),"Non Trouvé") | BZ49: =BZ48 | CA49: =CA48 | CB49: =IFERROR(IF($C49="","",IF($P$15="Cascade",$R49*(1-CA49)*BZ49,IF($P$15="Additionnelle",($N49-($N49*($P49+CA49)))*BZ49))),"Non Trouvé") | CK49: =IFERROR(IF(F49='[1]Paramètres Généraux'!$K$12,ROUNDUP((REGENERANTS!H49*REGENERANTS!$CF$20)*'[1]Paramètres Généraux'!$M$12,-1),IF(F49='[1]Paramètres Généraux'!$K$15,ROUNDUP((REGENERANTS!H49*REGENERANTS!$CF$20)*'[1]Paramètres Généraux'!$M$15,-1),REGENERANTS!H49*REGENERANTS!$CF$20)),"nd") | DQ49: =SUM(CN49:DP49) | DR49: =SUM(CV49:DP49) | DS49: =IFERROR((IF(AND($F49="Produit Vente",CO49>0),VLOOKUP($C49,'[1]Paramètres Articles'!$B:$H,7,FALSE)*$CO49)*(1-20%)),0) | DT49: =IFERROR((IF(AND($F49="Produit Vente",DR49>0),VLOOKUP($C49,'[1]Paramètres Articles'!$B:$H,6,FALSE)*$DR49)*(1-15%)),0) | DU49: =IFERROR(DQ49*J49,0)
B50: =IF(C50="",0,COUNTIFS($B$22:B49,">"&0)+1) | D50: =IFERROR(IF($C50="","",VLOOKUP($C50,'[1]Paramètres Articles'!$B:$G,2,FALSE)),"Non Trouvé") | E50: =IFERROR(IF($C50="","",_xlfn.XLOOKUP(REGENERANTS!$C50,'[1]New Base PA'!$F:$F,'[1]New Base PA'!$D:$D,"Not Found",0)),"Non Trouvé") | J50: =IFERROR(IF($C50="","",VLOOKUP($C50,'[1]New Base PA'!$F:$J,5,FALSE)),"Non Trouvé") | K50: =IFERROR(IF($C50="","",$J50*$H50),"Non Trouvé") | M50: =IFERROR(IF(AND($F50="Produit Vente",H50>0),VLOOKUP($C50,'[1]Paramètres Articles'!$B:$G,6,FALSE),0),"Non Trouvé") | N50: =IFERROR(IF($C50="","",$M50*$H50),"Non Trouvé") | R50: =IFERROR(IF($C50="","",$N50*(1-$P50)),"Non Trouvé") | T50: =IFERROR(IF($C50="","",VLOOKUP($C50,'[1]Paramètres Articles'!$B:$H,7,FALSE)),"Non Trouvé") | V50: =IFERROR(IF($C50="","",IF($P50="","",$T50*(1-$P50))),"Non Trouvé") | X50: =IFERROR(T50-V50,"") | Z50: =IFERROR(IF(OR(T50=0,T50=""),0,T50*H50),"Non Trouvé") | AB50: =AB49 | AC50: =AC49 | AD50: =IFERROR(IF($C50="","",IF($P$15="Cascade",$R50*(1-AC50)*AB50,IF($P$15="Additionnelle",($N50-($N50*($P50+AC50)))*AB50))),"Non Trouvé") | AG50: =AG49 | AH50: =AH49 | AI50: =IFERROR(IF($C50="","",IF($P$15="Cascade",$R50*(1-AH50)*AG50,IF($P$15="Additionnelle",($N50-($N50*($P50+AH50)))*AG50))),"Non Trouvé") | AL50: =AL49 | AM50: =AM49 | AN50: =IFERROR(IF($C50="","",IF($P$15="Cascade",$R50*(1-AM50)*AL50,IF($P$15="Additionnelle",($N50-($N50*($P50+AM50)))*AL50))),"Non Trouvé") | AQ50: =AQ49 | AR50: =AR49 | AS50: =IFERROR(IF($C50="","",IF($P$15="Cascade",$R50*(1-AR50)*AQ50,IF($P$15="Additionnelle",($N50-($N50*($P50+AR50)))*AQ50))),"Non Trouvé") | AV50: =AV49 | AW50: =AW49 | AX50: =IFERROR(IF($C50="","",IF($P$15="Cascade",$R50*(1-AW50)*AV50,IF($P$15="Additionnelle",($N50-($N50*($P50+AW50)))*AV50))),"Non Trouvé") | BA50: =BA49 | BB50: =BB49 | BC50: =IFERROR(IF($C50="","",IF($P$15="Cascade",$R50*(1-BB50)*BA50,IF($P$15="Additionnelle",($N50-($N50*($P50+BB50)))*BA50))),"Non Trouvé") | BF50: =BF49 | BG50: =BG49 | BH50: =IFERROR(IF($C50="","",IF($P$15="Cascade",$R50*(1-BG50)*BF50,IF($P$15="Additionnelle",($N50-($N50*($P50+BG50)))*BF50))),"Non Trouvé") | BK50: =BK49 | BL50: =BL49 | BM50: =IFERROR(IF($C50="","",IF($P$15="Cascade",$R50*(1-BL50)*BK50,IF($P$15="Additionnelle",($N50-($N50*($P50+BL50)))*BK50))),"Non Trouvé") | BP50: =BP49 | BQ50: =BQ49 | BR50: =IFERROR(IF($C50="","",IF($P$15="Cascade",$R50*(1-BQ50)*BP50,IF($P$15="Additionnelle",($N50-($N50*($P50+BQ50)))*BP50))),"Non Trouvé") | BU50: =BU49 | BV50: =BV49 | BW50: =IFERROR(IF($C50="","",IF($P$15="Cascade",$R50*(1-BV50)*BU50,IF($P$15="Additionnelle",($N50-($N50*($P50+BV50)))*BU50))),"Non Trouvé") | BZ50: =BZ49 | CA50: =CA49 | CB50: =IFERROR(IF($C50="","",IF($P$15="Cascade",$R50*(1-CA50)*BZ50,IF($P$15="Additionnelle",($N50-($N50*($P50+CA50)))*BZ50))),"Non Trouvé") | CK50: =IFERROR(IF(F50='[1]Paramètres Généraux'!$K$12,ROUNDUP((REGENERANTS!H50*REGENERANTS!$CF$20)*'[1]Paramètres Généraux'!$M$12,-1),IF(F50='[1]Paramètres Généraux'!$K$15,ROUNDUP((REGENERANTS!H50*REGENERANTS!$CF$20)*'[1]Paramètres Généraux'!$M$15,-1),REGENERANTS!H50*REGENERANTS!$CF$20)),"nd") | DQ50: =SUM(CN50:DP50) | DR50: =SUM(CV50:DP50) | DS50: =IFERROR((IF(AND($F50="Produit Vente",CO50>0),VLOOKUP($C50,'[1]Paramètres Articles'!$B:$H,7,FALSE)*$CO50)*(1-20%)),0) | DT50: =IFERROR((IF(AND($F50="Produit Vente",DR50>0),VLOOKUP($C50,'[1]Paramètres Articles'!$B:$H,6,FALSE)*$DR50)*(1-15%)),0) | DU50: =IFERROR(DQ50*J50,0)
B51: =IF(C51="",0,COUNTIFS($B$22:B50,">"&0)+1) | D51: =IFERROR(IF($C51="","",VLOOKUP($C51,'[1]Paramètres Articles'!$B:$G,2,FALSE)),"Non Trouvé") | E51: =IFERROR(IF($C51="","",_xlfn.XLOOKUP(REGENERANTS!$C51,'[1]New Base PA'!$F:$F,'[1]New Base PA'!$D:$D,"Not Found",0)),"Non Trouvé") | J51: =IFERROR(IF($C51="","",VLOOKUP($C51,'[1]New Base PA'!$F:$J,5,FALSE)),"Non Trouvé") | K51: =IFERROR(IF($C51="","",$J51*$H51),"Non Trouvé") | M51: =IFERROR(IF(AND($F51="Produit Vente",H51>0),VLOOKUP($C51,'[1]Paramètres Articles'!$B:$G,6,FALSE),0),"Non Trouvé") | N51: =IFERROR(IF($C51="","",$M51*$H51),"Non Trouvé") | R51: =IFERROR(IF($C51="","",$N51*(1-$P51)),"Non Trouvé") | T51: =IFERROR(IF($C51="","",VLOOKUP($C51,'[1]Paramètres Articles'!$B:$H,7,FALSE)),"Non Trouvé") | V51: =IFERROR(IF($C51="","",IF($P51="","",$T51*(1-$P51))),"Non Trouvé") | X51: =IFERROR(T51-V51,"") | Z51: =IFERROR(IF(OR(T51=0,T51=""),0,T51*H51),"Non Trouvé") | AB51: =AB50 | AC51: =AC50 | AD51: =IFERROR(IF($C51="","",IF($P$15="Cascade",$R51*(1-AC51)*AB51,IF($P$15="Additionnelle",($N51-($N51*($P51+AC51)))*AB51))),"Non Trouvé") | AG51: =AG50 | AH51: =AH50 | AI51: =IFERROR(IF($C51="","",IF($P$15="Cascade",$R51*(1-AH51)*AG51,IF($P$15="Additionnelle",($N51-($N51*($P51+AH51)))*AG51))),"Non Trouvé") | AL51: =AL50 | AM51: =AM50 | AN51: =IFERROR(IF($C51="","",IF($P$15="Cascade",$R51*(1-AM51)*AL51,IF($P$15="Additionnelle",($N51-($N51*($P51+AM51)))*AL51))),"Non Trouvé") | AQ51: =AQ50 | AR51: =AR50 | AS51: =IFERROR(IF($C51="","",IF($P$15="Cascade",$R51*(1-AR51)*AQ51,IF($P$15="Additionnelle",($N51-($N51*($P51+AR51)))*AQ51))),"Non Trouvé") | AV51: =AV50 | AW51: =AW50 | AX51: =IFERROR(IF($C51="","",IF($P$15="Cascade",$R51*(1-AW51)*AV51,IF($P$15="Additionnelle",($N51-($N51*($P51+AW51)))*AV51))),"Non Trouvé") | BA51: =BA50 | BB51: =BB50 | BC51: =IFERROR(IF($C51="","",IF($P$15="Cascade",$R51*(1-BB51)*BA51,IF($P$15="Additionnelle",($N51-($N51*($P51+BB51)))*BA51))),"Non Trouvé") | BF51: =BF50 | BG51: =BG50 | BH51: =IFERROR(IF($C51="","",IF($P$15="Cascade",$R51*(1-BG51)*BF51,IF($P$15="Additionnelle",($N51-($N51*($P51+BG51)))*BF51))),"Non Trouvé") | BK51: =BK50 | BL51: =BL50 | BM51: =IFERROR(IF($C51="","",IF($P$15="Cascade",$R51*(1-BL51)*BK51,IF($P$15="Additionnelle",($N51-($N51*($P51+BL51)))*BK51))),"Non Trouvé") | BP51: =BP50 | BQ51: =BQ50 | BR51: =IFERROR(IF($C51="","",IF($P$15="Cascade",$R51*(1-BQ51)*BP51,IF($P$15="Additionnelle",($N51-($N51*($P51+BQ51)))*BP51))),"Non Trouvé") | BU51: =BU50 | BV51: =BV50 | BW51: =IFERROR(IF($C51="","",IF($P$15="Cascade",$R51*(1-BV51)*BU51,IF($P$15="Additionnelle",($N51-($N51*($P51+BV51)))*BU51))),"Non Trouvé") | BZ51: =BZ50 | CA51: =CA50 | CB51: =IFERROR(IF($C51="","",IF($P$15="Cascade",$R51*(1-CA51)*BZ51,IF($P$15="Additionnelle",($N51-($N51*($P51+CA51)))*BZ51))),"Non Trouvé") | CK51: =IFERROR(IF(F51='[1]Paramètres Généraux'!$K$12,ROUNDUP((REGENERANTS!H51*REGENERANTS!$CF$20)*'[1]Paramètres Généraux'!$M$12,-1),IF(F51='[1]Paramètres Généraux'!$K$15,ROUNDUP((REGENERANTS!H51*REGENERANTS!$CF$20)*'[1]Paramètres Généraux'!$M$15,-1),REGENERANTS!H51*REGENERANTS!$CF$20)),"nd") | DQ51: =SUM(CN51:DP51) | DR51: =SUM(CV51:DP51) | DS51: =IFERROR((IF(AND($F51="Produit Vente",CO51>0),VLOOKUP($C51,'[1]Paramètres Articles'!$B:$H,7,FALSE)*$CO51)*(1-20%)),0) | DT51: =IFERROR((IF(AND($F51="Produit Vente",DR51>0),VLOOKUP($C51,'[1]Paramètres Articles'!$B:$H,6,FALSE)*$DR51)*(1-15%)),0) | DU51: =IFERROR(DQ51*J51,0)
B52: =IF(C52="",0,COUNTIFS($B$22:B51,">"&0)+1) | D52: =IFERROR(IF($C52="","",VLOOKUP($C52,'[1]Paramètres Articles'!$B:$G,2,FALSE)),"Non Trouvé") | E52: =IFERROR(IF($C52="","",_xlfn.XLOOKUP(REGENERANTS!$C52,'[1]New Base PA'!$F:$F,'[1]New Base PA'!$D:$D,"Not Found",0)),"Non Trouvé") | J52: =IFERROR(IF($C52="","",VLOOKUP($C52,'[1]New Base PA'!$F:$J,5,FALSE)),"Non Trouvé") | K52: =IFERROR(IF($C52="","",$J52*$H52),"Non Trouvé") | M52: =IFERROR(IF(AND($F52="Produit Vente",H52>0),VLOOKUP($C52,'[1]Paramètres Articles'!$B:$G,6,FALSE),0),"Non Trouvé") | N52: =IFERROR(IF($C52="","",$M52*$H52),"Non Trouvé") | R52: =IFERROR(IF($C52="","",$N52*(1-$P52)),"Non Trouvé") | T52: =IFERROR(IF($C52="","",VLOOKUP($C52,'[1]Paramètres Articles'!$B:$H,7,FALSE)),"Non Trouvé") | V52: =IFERROR(IF($C52="","",IF($P52="","",$T52*(1-$P52))),"Non Trouvé") | X52: =IFERROR(T52-V52,"") | Z52: =IFERROR(IF(OR(T52=0,T52=""),0,T52*H52),"Non Trouvé") | AB52: =AB51 | AC52: =AC51 | AD52: =IFERROR(IF($C52="","",IF($P$15="Cascade",$R52*(1-AC52)*AB52,IF($P$15="Additionnelle",($N52-($N52*($P52+AC52)))*AB52))),"Non Trouvé") | AG52: =AG51 | AH52: =AH51 | AI52: =IFERROR(IF($C52="","",IF($P$15="Cascade",$R52*(1-AH52)*AG52,IF($P$15="Additionnelle",($N52-($N52*($P52+AH52)))*AG52))),"Non Trouvé") | AL52: =AL51 | AM52: =AM51 | AN52: =IFERROR(IF($C52="","",IF($P$15="Cascade",$R52*(1-AM52)*AL52,IF($P$15="Additionnelle",($N52-($N52*($P52+AM52)))*AL52))),"Non Trouvé") | AQ52: =AQ51 | AR52: =AR51 | AS52: =IFERROR(IF($C52="","",IF($P$15="Cascade",$R52*(1-AR52)*AQ52,IF($P$15="Additionnelle",($N52-($N52*($P52+AR52)))*AQ52))),"Non Trouvé") | AV52: =AV51 | AW52: =AW51 | AX52: =IFERROR(IF($C52="","",IF($P$15="Cascade",$R52*(1-AW52)*AV52,IF($P$15="Additionnelle",($N52-($N52*($P52+AW52)))*AV52))),"Non Trouvé") | BA52: =BA51 | BB52: =BB51 | BC52: =IFERROR(IF($C52="","",IF($P$15="Cascade",$R52*(1-BB52)*BA52,IF($P$15="Additionnelle",($N52-($N52*($P52+BB52)))*BA52))),"Non Trouvé") | BF52: =BF51 | BG52: =BG51 | BH52: =IFERROR(IF($C52="","",IF($P$15="Cascade",$R52*(1-BG52)*BF52,IF($P$15="Additionnelle",($N52-($N52*($P52+BG52)))*BF52))),"Non Trouvé") | BK52: =BK51 | BL52: =BL51 | BM52: =IFERROR(IF($C52="","",IF($P$15="Cascade",$R52*(1-BL52)*BK52,IF($P$15="Additionnelle",($N52-($N52*($P52+BL52)))*BK52))),"Non Trouvé") | BP52: =BP51 | BQ52: =BQ51 | BR52: =IFERROR(IF($C52="","",IF($P$15="Cascade",$R52*(1-BQ52)*BP52,IF($P$15="Additionnelle",($N52-($N52*($P52+BQ52)))*BP52))),"Non Trouvé") | BU52: =BU51 | BV52: =BV51 | BW52: =IFERROR(IF($C52="","",IF($P$15="Cascade",$R52*(1-BV52)*BU52,IF($P$15="Additionnelle",($N52-($N52*($P52+BV52)))*BU52))),"Non Trouvé") | BZ52: =BZ51 | CA52: =CA51 | CB52: =IFERROR(IF($C52="","",IF($P$15="Cascade",$R52*(1-CA52)*BZ52,IF($P$15="Additionnelle",($N52-($N52*($P52+CA52)))*BZ52))),"Non Trouvé") | CK52: =IFERROR(IF(F52='[1]Paramètres Généraux'!$K$12,ROUNDUP((REGENERANTS!H52*REGENERANTS!$CF$20)*'[1]Paramètres Généraux'!$M$12,-1),IF(F52='[1]Paramètres Généraux'!$K$15,ROUNDUP((REGENERANTS!H52*REGENERANTS!$CF$20)*'[1]Paramètres Généraux'!$M$15,-1),REGENERANTS!H52*REGENERANTS!$CF$20)),"nd") | DQ52: =SUM(CN52:DP52) | DR52: =SUM(CV52:DP52) | DS52: =IFERROR((IF(AND($F52="Produit Vente",CO52>0),VLOOKUP($C52,'[1]Paramètres Articles'!$B:$H,7,FALSE)*$CO52)*(1-20%)),0) | DT52: =IFERROR((IF(AND($F52="Produit Vente",DR52>0),VLOOKUP($C52,'[1]Paramètres Articles'!$B:$H,6,FALSE)*$DR52)*(1-15%)),0) | DU52: =IFERROR(DQ52*J52,0)
B53: =IF(C53="",0,COUNTIFS($B$22:B52,">"&0)+1) | D53: =IFERROR(IF($C53="","",VLOOKUP($C53,'[1]Paramètres Articles'!$B:$G,2,FALSE)),"Non Trouvé") | E53: =IFERROR(IF($C53="","",_xlfn.XLOOKUP(REGENERANTS!$C53,'[1]New Base PA'!$F:$F,'[1]New Base PA'!$D:$D,"Not Found",0)),"Non Trouvé") | J53: =IFERROR(IF($C53="","",VLOOKUP($C53,'[1]New Base PA'!$F:$J,5,FALSE)),"Non Trouvé") | K53: =IFERROR(IF($C53="","",$J53*$H53),"Non Trouvé") | M53: =IFERROR(IF(AND($F53="Produit Vente",H53>0),VLOOKUP($C53,'[1]Paramètres Articles'!$B:$G,6,FALSE),0),"Non Trouvé") | N53: =IFERROR(IF($C53="","",$M53*$H53),"Non Trouvé") | R53: =IFERROR(IF($C53="","",$N53*(1-$P53)),"Non Trouvé") | T53: =IFERROR(IF($C53="","",VLOOKUP($C53,'[1]Paramètres Articles'!$B:$H,7,FALSE)),"Non Trouvé") | V53: =IFERROR(IF($C53="","",IF($P53="","",$T53*(1-$P53))),"Non Trouvé") | X53: =IFERROR(T53-V53,"") | Z53: =IFERROR(IF(OR(T53=0,T53=""),0,T53*H53),"Non Trouvé") | AB53: =AB52 | AC53: =AC52 | AD53: =IFERROR(IF($C53="","",IF($P$15="Cascade",$R53*(1-AC53)*AB53,IF($P$15="Additionnelle",($N53-($N53*($P53+AC53)))*AB53))),"Non Trouvé") | AG53: =AG52 | AH53: =AH52 | AI53: =IFERROR(IF($C53="","",IF($P$15="Cascade",$R53*(1-AH53)*AG53,IF($P$15="Additionnelle",($N53-($N53*($P53+AH53)))*AG53))),"Non Trouvé") | AL53: =AL52 | AM53: =AM52 | AN53: =IFERROR(IF($C53="","",IF($P$15="Cascade",$R53*(1-AM53)*AL53,IF($P$15="Additionnelle",($N53-($N53*($P53+AM53)))*AL53))),"Non Trouvé") | AQ53: =AQ52 | AR53: =AR52 | AS53: =IFERROR(IF($C53="","",IF($P$15="Cascade",$R53*(1-AR53)*AQ53,IF($P$15="Additionnelle",($N53-($N53*($P53+AR53)))*AQ53))),"Non Trouvé") | AV53: =AV52 | AW53: =AW52 | AX53: =IFERROR(IF($C53="","",IF($P$15="Cascade",$R53*(1-AW53)*AV53,IF($P$15="Additionnelle",($N53-($N53*($P53+AW53)))*AV53))),"Non Trouvé") | BA53: =BA52 | BB53: =BB52 | BC53: =IFERROR(IF($C53="","",IF($P$15="Cascade",$R53*(1-BB53)*BA53,IF($P$15="Additionnelle",($N53-($N53*($P53+BB53)))*BA53))),"Non Trouvé") | BF53: =BF52 | BG53: =BG52 | BH53: =IFERROR(IF($C53="","",IF($P$15="Cascade",$R53*(1-BG53)*BF53,IF($P$15="Additionnelle",($N53-($N53*($P53+BG53)))*BF53))),"Non Trouvé") | BK53: =BK52 | BL53: =BL52 | BM53: =IFERROR(IF($C53="","",IF($P$15="Cascade",$R53*(1-BL53)*BK53,IF($P$15="Additionnelle",($N53-($N53*($P53+BL53)))*BK53))),"Non Trouvé") | BP53: =BP52 | BQ53: =BQ52 | BR53: =IFERROR(IF($C53="","",IF($P$15="Cascade",$R53*(1-BQ53)*BP53,IF($P$15="Additionnelle",($N53-($N53*($P53+BQ53)))*BP53))),"Non Trouvé") | BU53: =BU52 | BV53: =BV52 | BW53: =IFERROR(IF($C53="","",IF($P$15="Cascade",$R53*(1-BV53)*BU53,IF($P$15="Additionnelle",($N53-($N53*($P53+BV53)))*BU53))),"Non Trouvé") | BZ53: =BZ52 | CA53: =CA52 | CB53: =IFERROR(IF($C53="","",IF($P$15="Cascade",$R53*(1-CA53)*BZ53,IF($P$15="Additionnelle",($N53-($N53*($P53+CA53)))*BZ53))),"Non Trouvé") | CK53: =IFERROR(IF(F53='[1]Paramètres Généraux'!$K$12,ROUNDUP((REGENERANTS!H53*REGENERANTS!$CF$20)*'[1]Paramètres Généraux'!$M$12,-1),IF(F53='[1]Paramètres Généraux'!$K$15,ROUNDUP((REGENERANTS!H53*REGENERANTS!$CF$20)*'[1]Paramètres Généraux'!$M$15,-1),REGENERANTS!H53*REGENERANTS!$CF$20)),"nd") | DQ53: =SUM(CN53:DP53) | DR53: =SUM(CV53:DP53) | DS53: =IFERROR((IF(AND($F53="Produit Vente",CO53>0),VLOOKUP($C53,'[1]Paramètres Articles'!$B:$H,7,FALSE)*$CO53)*(1-20%)),0) | DT53: =IFERROR((IF(AND($F53="Produit Vente",DR53>0),VLOOKUP($C53,'[1]Paramètres Articles'!$B:$H,6,FALSE)*$DR53)*(1-15%)),0) | DU53: =IFERROR(DQ53*J53,0)
B54: =IF(C54="",0,COUNTIFS($B$22:B53,">"&0)+1) | D54: =IFERROR(IF($C54="","",VLOOKUP($C54,'[1]Paramètres Articles'!$B:$G,2,FALSE)),"Non Trouvé") | E54: =IFERROR(IF($C54="","",_xlfn.XLOOKUP(REGENERANTS!$C54,'[1]New Base PA'!$F:$F,'[1]New Base PA'!$D:$D,"Not Found",0)),"Non Trouvé") | J54: =IFERROR(IF($C54="","",VLOOKUP($C54,'[1]New Base PA'!$F:$J,5,FALSE)),"Non Trouvé") | K54: =IFERROR(IF($C54="","",$J54*$H54),"Non Trouvé") | M54: =IFERROR(IF(AND($F54="Produit Vente",H54>0),VLOOKUP($C54,'[1]Paramètres Articles'!$B:$G,6,FALSE),0),"Non Trouvé") | N54: =IFERROR(IF($C54="","",$M54*$H54),"Non Trouvé") | R54: =IFERROR(IF($C54="","",$N54*(1-$P54)),"Non Trouvé") | T54: =IFERROR(IF($C54="","",VLOOKUP($C54,'[1]Paramètres Articles'!$B:$H,7,FALSE)),"Non Trouvé") | V54: =IFERROR(IF($C54="","",IF($P54="","",$T54*(1-$P54))),"Non Trouvé") | X54: =IFERROR(T54-V54,"") | Z54: =IFERROR(IF(OR(T54=0,T54=""),0,T54*H54),"Non Trouvé") | AB54: =AB53 | AC54: =AC53 | AD54: =IFERROR(IF($C54="","",IF($P$15="Cascade",$R54*(1-AC54)*AB54,IF($P$15="Additionnelle",($N54-($N54*($P54+AC54)))*AB54))),"Non Trouvé") | AG54: =AG53 | AH54: =AH53 | AI54: =IFERROR(IF($C54="","",IF($P$15="Cascade",$R54*(1-AH54)*AG54,IF($P$15="Additionnelle",($N54-($N54*($P54+AH54)))*AG54))),"Non Trouvé") | AL54: =AL53 | AM54: =AM53 | AN54: =IFERROR(IF($C54="","",IF($P$15="Cascade",$R54*(1-AM54)*AL54,IF($P$15="Additionnelle",($N54-($N54*($P54+AM54)))*AL54))),"Non Trouvé") | AQ54: =AQ53 | AR54: =AR53 | AS54: =IFERROR(IF($C54="","",IF($P$15="Cascade",$R54*(1-AR54)*AQ54,IF($P$15="Additionnelle",($N54-($N54*($P54+AR54)))*AQ54))),"Non Trouvé") | AV54: =AV53 | AW54: =AW53 | AX54: =IFERROR(IF($C54="","",IF($P$15="Cascade",$R54*(1-AW54)*AV54,IF($P$15="Additionnelle",($N54-($N54*($P54+AW54)))*AV54))),"Non Trouvé") | BA54: =BA53 | BB54: =BB53 | BC54: =IFERROR(IF($C54="","",IF($P$15="Cascade",$R54*(1-BB54)*BA54,IF($P$15="Additionnelle",($N54-($N54*($P54+BB54)))*BA54))),"Non Trouvé") | BF54: =BF53 | BG54: =BG53 | BH54: =IFERROR(IF($C54="","",IF($P$15="Cascade",$R54*(1-BG54)*BF54,IF($P$15="Additionnelle",($N54-($N54*($P54+BG54)))*BF54))),"Non Trouvé") | BK54: =BK53 | BL54: =BL53 | BM54: =IFERROR(IF($C54="","",IF($P$15="Cascade",$R54*(1-BL54)*BK54,IF($P$15="Additionnelle",($N54-($N54*($P54+BL54)))*BK54))),"Non Trouvé") | BP54: =BP53 | BQ54: =BQ53 | BR54: =IFERROR(IF($C54="","",IF($P$15="Cascade",$R54*(1-BQ54)*BP54,IF($P$15="Additionnelle",($N54-($N54*($P54+BQ54)))*BP54))),"Non Trouvé") | BU54: =BU53 | BV54: =BV53 | BW54: =IFERROR(IF($C54="","",IF($P$15="Cascade",$R54*(1-BV54)*BU54,IF($P$15="Additionnelle",($N54-($N54*($P54+BV54)))*BU54))),"Non Trouvé") | BZ54: =BZ53 | CA54: =CA53 | CB54: =IFERROR(IF($C54="","",IF($P$15="Cascade",$R54*(1-CA54)*BZ54,IF($P$15="Additionnelle",($N54-($N54*($P54+CA54)))*BZ54))),"Non Trouvé") | CK54: =IFERROR(IF(F54='[1]Paramètres Généraux'!$K$12,ROUNDUP((REGENERANTS!H54*REGENERANTS!$CF$20)*'[1]Paramètres Généraux'!$M$12,-1),IF(F54='[1]Paramètres Généraux'!$K$15,ROUNDUP((REGENERANTS!H54*REGENERANTS!$CF$20)*'[1]Paramètres Généraux'!$M$15,-1),REGENERANTS!H54*REGENERANTS!$CF$20)),"nd") | DQ54: =SUM(CN54:DP54) | DR54: =SUM(CV54:DP54) | DS54: =IFERROR((IF(AND($F54="Produit Vente",CO54>0),VLOOKUP($C54,'[1]Paramètres Articles'!$B:$H,7,FALSE)*$CO54)*(1-20%)),0) | DT54: =IFERROR((IF(AND($F54="Produit Vente",DR54>0),VLOOKUP($C54,'[1]Paramètres Articles'!$B:$H,6,FALSE)*$DR54)*(1-15%)),0) | DU54: =IFERROR(DQ54*J54,0)
B55: =IF(C55="",0,COUNTIFS($B$22:B54,">"&0)+1) | D55: =IFERROR(IF($C55="","",VLOOKUP($C55,'[1]Paramètres Articles'!$B:$G,2,FALSE)),"Non Trouvé") | E55: =IFERROR(IF($C55="","",_xlfn.XLOOKUP(REGENERANTS!$C55,'[1]New Base PA'!$F:$F,'[1]New Base PA'!$D:$D,"Not Found",0)),"Non Trouvé") | J55: =IFERROR(IF($C55="","",VLOOKUP($C55,'[1]New Base PA'!$F:$J,5,FALSE)),"Non Trouvé") | K55: =IFERROR(IF($C55="","",$J55*$H55),"Non Trouvé") | M55: =IFERROR(IF(AND($F55="Produit Vente",H55>0),VLOOKUP($C55,'[1]Paramètres Articles'!$B:$G,6,FALSE),0),"Non Trouvé") | N55: =IFERROR(IF($C55="","",$M55*$H55),"Non Trouvé") | R55: =IFERROR(IF($C55="","",$N55*(1-$P55)),"Non Trouvé") | T55: =IFERROR(IF($C55="","",VLOOKUP($C55,'[1]Paramètres Articles'!$B:$H,7,FALSE)),"Non Trouvé") | V55: =IFERROR(IF($C55="","",IF($P55="","",$T55*(1-$P55))),"Non Trouvé") | X55: =IFERROR(T55-V55,"") | Z55: =IFERROR(IF(OR(T55=0,T55=""),0,T55*H55),"Non Trouvé") | AB55: =AB54 | AC55: =AC54 | AD55: =IFERROR(IF($C55="","",IF($P$15="Cascade",$R55*(1-AC55)*AB55,IF($P$15="Additionnelle",($N55-($N55*($P55+AC55)))*AB55))),"Non Trouvé") | AG55: =AG54 | AH55: =AH54 | AI55: =IFERROR(IF($C55="","",IF($P$15="Cascade",$R55*(1-AH55)*AG55,IF($P$15="Additionnelle",($N55-($N55*($P55+AH55)))*AG55))),"Non Trouvé") | AL55: =AL54 | AM55: =AM54 | AN55: =IFERROR(IF($C55="","",IF($P$15="Cascade",$R55*(1-AM55)*AL55,IF($P$15="Additionnelle",($N55-($N55*($P55+AM55)))*AL55))),"Non Trouvé") | AQ55: =AQ54 | AR55: =AR54 | AS55: =IFERROR(IF($C55="","",IF($P$15="Cascade",$R55*(1-AR55)*AQ55,IF($P$15="Additionnelle",($N55-($N55*($P55+AR55)))*AQ55))),"Non Trouvé") | AV55: =AV54 | AW55: =AW54 | AX55: =IFERROR(IF($C55="","",IF($P$15="Cascade",$R55*(1-AW55)*AV55,IF($P$15="Additionnelle",($N55-($N55*($P55+AW55)))*AV55))),"Non Trouvé") | BA55: =BA54 | BB55: =BB54 | BC55: =IFERROR(IF($C55="","",IF($P$15="Cascade",$R55*(1-BB55)*BA55,IF($P$15="Additionnelle",($N55-($N55*($P55+BB55)))*BA55))),"Non Trouvé") | BF55: =BF54 | BG55: =BG54 | BH55: =IFERROR(IF($C55="","",IF($P$15="Cascade",$R55*(1-BG55)*BF55,IF($P$15="Additionnelle",($N55-($N55*($P55+BG55)))*BF55))),"Non Trouvé") | BK55: =BK54 | BL55: =BL54 | BM55: =IFERROR(IF($C55="","",IF($P$15="Cascade",$R55*(1-BL55)*BK55,IF($P$15="Additionnelle",($N55-($N55*($P55+BL55)))*BK55))),"Non Trouvé") | BP55: =BP54 | BQ55: =BQ54 | BR55: =IFERROR(IF($C55="","",IF($P$15="Cascade",$R55*(1-BQ55)*BP55,IF($P$15="Additionnelle",($N55-($N55*($P55+BQ55)))*BP55))),"Non Trouvé") | BU55: =BU54 | BV55: =BV54 | BW55: =IFERROR(IF($C55="","",IF($P$15="Cascade",$R55*(1-BV55)*BU55,IF($P$15="Additionnelle",($N55-($N55*($P55+BV55)))*BU55))),"Non Trouvé") | BZ55: =BZ54 | CA55: =CA54 | CB55: =IFERROR(IF($C55="","",IF($P$15="Cascade",$R55*(1-CA55)*BZ55,IF($P$15="Additionnelle",($N55-($N55*($P55+CA55)))*BZ55))),"Non Trouvé") | CK55: =IFERROR(IF(F55='[1]Paramètres Généraux'!$K$12,ROUNDUP((REGENERANTS!H55*REGENERANTS!$CF$20)*'[1]Paramètres Généraux'!$M$12,-1),IF(F55='[1]Paramètres Généraux'!$K$15,ROUNDUP((REGENERANTS!H55*REGENERANTS!$CF$20)*'[1]Paramètres Généraux'!$M$15,-1),REGENERANTS!H55*REGENERANTS!$CF$20)),"nd") | DQ55: =SUM(CN55:DP55) | DR55: =SUM(CV55:DP55) | DS55: =IFERROR((IF(AND($F55="Produit Vente",CO55>0),VLOOKUP($C55,'[1]Paramètres Articles'!$B:$H,7,FALSE)*$CO55)*(1-20%)),0) | DT55: =IFERROR((IF(AND($F55="Produit Vente",DR55>0),VLOOKUP($C55,'[1]Paramètres Articles'!$B:$H,6,FALSE)*$DR55)*(1-15%)),0) | DU55: =IFERROR(DQ55*J55,0)
B56: =IF(C56="",0,COUNTIFS($B$22:B55,">"&0)+1) | D56: =IFERROR(IF($C56="","",VLOOKUP($C56,'[1]Paramètres Articles'!$B:$G,2,FALSE)),"Non Trouvé") | E56: =IFERROR(IF($C56="","",_xlfn.XLOOKUP(REGENERANTS!$C56,'[1]New Base PA'!$F:$F,'[1]New Base PA'!$D:$D,"Not Found",0)),"Non Trouvé") | J56: =IFERROR(IF($C56="","",VLOOKUP($C56,'[1]New Base PA'!$F:$J,5,FALSE)),"Non Trouvé") | K56: =IFERROR(IF($C56="","",$J56*$H56),"Non Trouvé") | M56: =IFERROR(IF(AND($F56="Produit Vente",H56>0),VLOOKUP($C56,'[1]Paramètres Articles'!$B:$G,6,FALSE),0),"Non Trouvé") | N56: =IFERROR(IF($C56="","",$M56*$H56),"Non Trouvé") | R56: =IFERROR(IF($C56="","",$N56*(1-$P56)),"Non Trouvé") | T56: =IFERROR(IF($C56="","",VLOOKUP($C56,'[1]Paramètres Articles'!$B:$H,7,FALSE)),"Non Trouvé") | V56: =IFERROR(IF($C56="","",IF($P56="","",$T56*(1-$P56))),"Non Trouvé") | X56: =IFERROR(T56-V56,"") | Z56: =IFERROR(IF(OR(T56=0,T56=""),0,T56*H56),"Non Trouvé") | AB56: =AB55 | AC56: =AC55 | AD56: =IFERROR(IF($C56="","",IF($P$15="Cascade",$R56*(1-AC56)*AB56,IF($P$15="Additionnelle",($N56-($N56*($P56+AC56)))*AB56))),"Non Trouvé") | AG56: =AG55 | AH56: =AH55 | AI56: =IFERROR(IF($C56="","",IF($P$15="Cascade",$R56*(1-AH56)*AG56,IF($P$15="Additionnelle",($N56-($N56*($P56+AH56)))*AG56))),"Non Trouvé") | AL56: =AL55 | AM56: =AM55 | AN56: =IFERROR(IF($C56="","",IF($P$15="Cascade",$R56*(1-AM56)*AL56,IF($P$15="Additionnelle",($N56-($N56*($P56+AM56)))*AL56))),"Non Trouvé") | AQ56: =AQ55 | AR56: =AR55 | AS56: =IFERROR(IF($C56="","",IF($P$15="Cascade",$R56*(1-AR56)*AQ56,IF($P$15="Additionnelle",($N56-($N56*($P56+AR56)))*AQ56))),"Non Trouvé") | AV56: =AV55 | AW56: =AW55 | AX56: =IFERROR(IF($C56="","",IF($P$15="Cascade",$R56*(1-AW56)*AV56,IF($P$15="Additionnelle",($N56-($N56*($P56+AW56)))*AV56))),"Non Trouvé") | BA56: =BA55 | BB56: =BB55 | BC56: =IFERROR(IF($C56="","",IF($P$15="Cascade",$R56*(1-BB56)*BA56,IF($P$15="Additionnelle",($N56-($N56*($P56+BB56)))*BA56))),"Non Trouvé") | BF56: =BF55 | BG56: =BG55 | BH56: =IFERROR(IF($C56="","",IF($P$15="Cascade",$R56*(1-BG56)*BF56,IF($P$15="Additionnelle",($N56-($N56*($P56+BG56)))*BF56))),"Non Trouvé") | BK56: =BK55 | BL56: =BL55 | BM56: =IFERROR(IF($C56="","",IF($P$15="Cascade",$R56*(1-BL56)*BK56,IF($P$15="Additionnelle",($N56-($N56*($P56+BL56)))*BK56))),"Non Trouvé") | BP56: =BP55 | BQ56: =BQ55 | BR56: =IFERROR(IF($C56="","",IF($P$15="Cascade",$R56*(1-BQ56)*BP56,IF($P$15="Additionnelle",($N56-($N56*($P56+BQ56)))*BP56))),"Non Trouvé") | BU56: =BU55 | BV56: =BV55 | BW56: =IFERROR(IF($C56="","",IF($P$15="Cascade",$R56*(1-BV56)*BU56,IF($P$15="Additionnelle",($N56-($N56*($P56+BV56)))*BU56))),"Non Trouvé") | BZ56: =BZ55 | CA56: =CA55 | CB56: =IFERROR(IF($C56="","",IF($P$15="Cascade",$R56*(1-CA56)*BZ56,IF($P$15="Additionnelle",($N56-($N56*($P56+CA56)))*BZ56))),"Non Trouvé") | CK56: =IFERROR(IF(F56='[1]Paramètres Généraux'!$K$12,ROUNDUP((REGENERANTS!H56*REGENERANTS!$CF$20)*'[1]Paramètres Généraux'!$M$12,-1),IF(F56='[1]Paramètres Généraux'!$K$15,ROUNDUP((REGENERANTS!H56*REGENERANTS!$CF$20)*'[1]Paramètres Généraux'!$M$15,-1),REGENERANTS!H56*REGENERANTS!$CF$20)),"nd") | DQ56: =SUM(CN56:DP56) | DR56: =SUM(CV56:DP56) | DS56: =IFERROR((IF(AND($F56="Produit Vente",CO56>0),VLOOKUP($C56,'[1]Paramètres Articles'!$B:$H,7,FALSE)*$CO56)*(1-20%)),0) | DT56: =IFERROR((IF(AND($F56="Produit Vente",DR56>0),VLOOKUP($C56,'[1]Paramètres Articles'!$B:$H,6,FALSE)*$DR56)*(1-15%)),0) | DU56: =IFERROR(DQ56*J56,0)
B57: =IF(C57="",0,COUNTIFS($B$22:B56,">"&0)+1) | D57: =IFERROR(IF($C57="","",VLOOKUP($C57,'[1]Paramètres Articles'!$B:$G,2,FALSE)),"Non Trouvé") | E57: =IFERROR(IF($C57="","",_xlfn.XLOOKUP(REGENERANTS!$C57,'[1]New Base PA'!$F:$F,'[1]New Base PA'!$D:$D,"Not Found",0)),"Non Trouvé") | J57: =IFERROR(IF($C57="","",VLOOKUP($C57,'[1]New Base PA'!$F:$J,5,FALSE)),"Non Trouvé") | K57: =IFERROR(IF($C57="","",$J57*$H57),"Non Trouvé") | M57: =IFERROR(IF(AND($F57="Produit Vente",H57>0),VLOOKUP($C57,'[1]Paramètres Articles'!$B:$G,6,FALSE),0),"Non Trouvé") | N57: =IFERROR(IF($C57="","",$M57*$H57),"Non Trouvé") | R57: =IFERROR(IF($C57="","",$N57*(1-$P57)),"Non Trouvé") | T57: =IFERROR(IF($C57="","",VLOOKUP($C57,'[1]Paramètres Articles'!$B:$H,7,FALSE)),"Non Trouvé") | V57: =IFERROR(IF($C57="","",IF($P57="","",$T57*(1-$P57))),"Non Trouvé") | X57: =IFERROR(T57-V57,"") | Z57: =IFERROR(IF(OR(T57=0,T57=""),0,T57*H57),"Non Trouvé") | AB57: =AB56 | AC57: =AC56 | AD57: =IFERROR(IF($C57="","",IF($P$15="Cascade",$R57*(1-AC57)*AB57,IF($P$15="Additionnelle",($N57-($N57*($P57+AC57)))*AB57))),"Non Trouvé") | AG57: =AG56 | AH57: =AH56 | AI57: =IFERROR(IF($C57="","",IF($P$15="Cascade",$R57*(1-AH57)*AG57,IF($P$15="Additionnelle",($N57-($N57*($P57+AH57)))*AG57))),"Non Trouvé") | AL57: =AL56 | AM57: =AM56 | AN57: =IFERROR(IF($C57="","",IF($P$15="Cascade",$R57*(1-AM57)*AL57,IF($P$15="Additionnelle",($N57-($N57*($P57+AM57)))*AL57))),"Non Trouvé") | AQ57: =AQ56 | AR57: =AR56 | AS57: =IFERROR(IF($C57="","",IF($P$15="Cascade",$R57*(1-AR57)*AQ57,IF($P$15="Additionnelle",($N57-($N57*($P57+AR57)))*AQ57))),"Non Trouvé") | AV57: =AV56 | AW57: =AW56 | AX57: =IFERROR(IF($C57="","",IF($P$15="Cascade",$R57*(1-AW57)*AV57,IF($P$15="Additionnelle",($N57-($N57*($P57+AW57)))*AV57))),"Non Trouvé") | BA57: =BA56 | BB57: =BB56 | BC57: =IFERROR(IF($C57="","",IF($P$15="Cascade",$R57*(1-BB57)*BA57,IF($P$15="Additionnelle",($N57-($N57*($P57+BB57)))*BA57))),"Non Trouvé") | BF57: =BF56 | BG57: =BG56 | BH57: =IFERROR(IF($C57="","",IF($P$15="Cascade",$R57*(1-BG57)*BF57,IF($P$15="Additionnelle",($N57-($N57*($P57+BG57)))*BF57))),"Non Trouvé") | BK57: =BK56 | BL57: =BL56 | BM57: =IFERROR(IF($C57="","",IF($P$15="Cascade",$R57*(1-BL57)*BK57,IF($P$15="Additionnelle",($N57-($N57*($P57+BL57)))*BK57))),"Non Trouvé") | BP57: =BP56 | BQ57: =BQ56 | BR57: =IFERROR(IF($C57="","",IF($P$15="Cascade",$R57*(1-BQ57)*BP57,IF($P$15="Additionnelle",($N57-($N57*($P57+BQ57)))*BP57))),"Non Trouvé") | BU57: =BU56 | BV57: =BV56 | BW57: =IFERROR(IF($C57="","",IF($P$15="Cascade",$R57*(1-BV57)*BU57,IF($P$15="Additionnelle",($N57-($N57*($P57+BV57)))*BU57))),"Non Trouvé") | BZ57: =BZ56 | CA57: =CA56 | CB57: =IFERROR(IF($C57="","",IF($P$15="Cascade",$R57*(1-CA57)*BZ57,IF($P$15="Additionnelle",($N57-($N57*($P57+CA57)))*BZ57))),"Non Trouvé") | CK57: =IFERROR(IF(F57='[1]Paramètres Généraux'!$K$12,ROUNDUP((REGENERANTS!H57*REGENERANTS!$CF$20)*'[1]Paramètres Généraux'!$M$12,-1),IF(F57='[1]Paramètres Généraux'!$K$15,ROUNDUP((REGENERANTS!H57*REGENERANTS!$CF$20)*'[1]Paramètres Généraux'!$M$15,-1),REGENERANTS!H57*REGENERANTS!$CF$20)),"nd") | DQ57: =SUM(CN57:DP57) | DR57: =SUM(CV57:DP57) | DS57: =IFERROR((IF(AND($F57="Produit Vente",CO57>0),VLOOKUP($C57,'[1]Paramètres Articles'!$B:$H,7,FALSE)*$CO57)*(1-20%)),0) | DT57: =IFERROR((IF(AND($F57="Produit Vente",DR57>0),VLOOKUP($C57,'[1]Paramètres Articles'!$B:$H,6,FALSE)*$DR57)*(1-15%)),0) | DU57: =IFERROR(DQ57*J57,0)
B58: =IF(C58="",0,COUNTIFS($B$22:B57,">"&0)+1) | D58: =IFERROR(IF($C58="","",VLOOKUP($C58,'[1]Paramètres Articles'!$B:$G,2,FALSE)),"Non Trouvé") | E58: =IFERROR(IF($C58="","",_xlfn.XLOOKUP(REGENERANTS!$C58,'[1]New Base PA'!$F:$F,'[1]New Base PA'!$D:$D,"Not Found",0)),"Non Trouvé") | J58: =IFERROR(IF($C58="","",VLOOKUP($C58,'[1]New Base PA'!$F:$J,5,FALSE)),"Non Trouvé") | K58: =IFERROR(IF($C58="","",$J58*$H58),"Non Trouvé") | M58: =IFERROR(IF(AND($F58="Produit Vente",H58>0),VLOOKUP($C58,'[1]Paramètres Articles'!$B:$G,6,FALSE),0),"Non Trouvé") | N58: =IFERROR(IF($C58="","",$M58*$H58),"Non Trouvé") | R58: =IFERROR(IF($C58="","",$N58*(1-$P58)),"Non Trouvé") | T58: =IFERROR(IF($C58="","",VLOOKUP($C58,'[1]Paramètres Articles'!$B:$H,7,FALSE)),"Non Trouvé") | V58: =IFERROR(IF($C58="","",IF($P58="","",$T58*(1-$P58))),"Non Trouvé") | X58: =IFERROR(T58-V58,"") | Z58: =IFERROR(IF(OR(T58=0,T58=""),0,T58*H58),"Non Trouvé") | AB58: =AB57 | AC58: =AC57 | AD58: =IFERROR(IF($C58="","",IF($P$15="Cascade",$R58*(1-AC58)*AB58,IF($P$15="Additionnelle",($N58-($N58*($P58+AC58)))*AB58))),"Non Trouvé") | AG58: =AG57 | AH58: =AH57 | AI58: =IFERROR(IF($C58="","",IF($P$15="Cascade",$R58*(1-AH58)*AG58,IF($P$15="Additionnelle",($N58-($N58*($P58+AH58)))*AG58))),"Non Trouvé") | AL58: =AL57 | AM58: =AM57 | AN58: =IFERROR(IF($C58="","",IF($P$15="Cascade",$R58*(1-AM58)*AL58,IF($P$15="Additionnelle",($N58-($N58*($P58+AM58)))*AL58))),"Non Trouvé") | AQ58: =AQ57 | AR58: =AR57 | AS58: =IFERROR(IF($C58="","",IF($P$15="Cascade",$R58*(1-AR58)*AQ58,IF($P$15="Additionnelle",($N58-($N58*($P58+AR58)))*AQ58))),"Non Trouvé") | AV58: =AV57 | AW58: =AW57 | AX58: =IFERROR(IF($C58="","",IF($P$15="Cascade",$R58*(1-AW58)*AV58,IF($P$15="Additionnelle",($N58-($N58*($P58+AW58)))*AV58))),"Non Trouvé") | BA58: =BA57 | BB58: =BB57 | BC58: =IFERROR(IF($C58="","",IF($P$15="Cascade",$R58*(1-BB58)*BA58,IF($P$15="Additionnelle",($N58-($N58*($P58+BB58)))*BA58))),"Non Trouvé") | BF58: =BF57 | BG58: =BG57 | BH58: =IFERROR(IF($C58="","",IF($P$15="Cascade",$R58*(1-BG58)*BF58,IF($P$15="Additionnelle",($N58-($N58*($P58+BG58)))*BF58))),"Non Trouvé") | BK58: =BK57 | BL58: =BL57 | BM58: =IFERROR(IF($C58="","",IF($P$15="Cascade",$R58*(1-BL58)*BK58,IF($P$15="Additionnelle",($N58-($N58*($P58+BL58)))*BK58))),"Non Trouvé") | BP58: =BP57 | BQ58: =BQ57 | BR58: =IFERROR(IF($C58="","",IF($P$15="Cascade",$R58*(1-BQ58)*BP58,IF($P$15="Additionnelle",($N58-($N58*($P58+BQ58)))*BP58))),"Non Trouvé") | BU58: =BU57 | BV58: =BV57 | BW58: =IFERROR(IF($C58="","",IF($P$15="Cascade",$R58*(1-BV58)*BU58,IF($P$15="Additionnelle",($N58-($N58*($P58+BV58)))*BU58))),"Non Trouvé") | BZ58: =BZ57 | CA58: =CA57 | CB58: =IFERROR(IF($C58="","",IF($P$15="Cascade",$R58*(1-CA58)*BZ58,IF($P$15="Additionnelle",($N58-($N58*($P58+CA58)))*BZ58))),"Non Trouvé") | CK58: =IFERROR(IF(F58='[1]Paramètres Généraux'!$K$12,ROUNDUP((REGENERANTS!H58*REGENERANTS!$CF$20)*'[1]Paramètres Généraux'!$M$12,-1),IF(F58='[1]Paramètres Généraux'!$K$15,ROUNDUP((REGENERANTS!H58*REGENERANTS!$CF$20)*'[1]Paramètres Généraux'!$M$15,-1),REGENERANTS!H58*REGENERANTS!$CF$20)),"nd") | DQ58: =SUM(CN58:DP58) | DR58: =SUM(CV58:DP58) | DS58: =IFERROR((IF(AND($F58="Produit Vente",CO58>0),VLOOKUP($C58,'[1]Paramètres Articles'!$B:$H,7,FALSE)*$CO58)*(1-20%)),0) | DT58: =IFERROR((IF(AND($F58="Produit Vente",DR58>0),VLOOKUP($C58,'[1]Paramètres Articles'!$B:$H,6,FALSE)*$DR58)*(1-15%)),0) | DU58: =IFERROR(DQ58*J58,0)
... B62: =IF(C62="",0,COUNTIFS($B$22:B61,">"&0)+1) | D62: =IFERROR(IF($C62="","",VLOOKUP($C62,'[1]Paramètres Articles'!$B:$G,2,FALSE)),"Non Trouvé") | E62: =IFERROR(IF($C62="","",_xlfn.XLOOKUP(REGENERANTS!$C62,'[1]New Base PA'!$F:$F,'[1]New Base PA'!$D:$D,"Not Found",0)),"Non Trouvé") | J62: =IFERROR(IF($C62="","",VLOOKUP($C62,'[1]New Base PA'!$F:$J,5,FALSE)),"Non Trouvé") | K62: =IFERROR(IF($C62="","",$J62*$H62),"Non Trouvé") | M62: =IFERROR(IF(AND($F62="Produit Vente",H62>0),VLOOKUP($C62,'[1]Paramètres Articles'!$B:$G,6,FALSE),0),"Non Trouvé") | N62: =IFERROR(IF($C62="","",$M62*$H62),"Non Trouvé") | R62: =IFERROR(IF($C62="","",$N62*(1-$P62)),"Non Trouvé") | T62: =IFERROR(IF($C62="","",VLOOKUP($C62,'[1]Paramètres Articles'!$B:$H,7,FALSE)),"Non Trouvé") | V62: =IFERROR(IF($C62="","",IF($P62="","",$T62*(1-$P62))),"Non Trouvé") | X62: =IFERROR(T62-V62,"") | Z62: =IFERROR(IF(OR(T62=0,T62=""),0,T62*H62),"Non Trouvé") | AB62: =AB61 | AC62: =AC61 | AD62: =IFERROR(IF($C62="","",IF($P$15="Cascade",$R62*(1-AC62)*AB62,IF($P$15="Additionnelle",($N62-($N62*($P62+AC62)))*AB62))),"Non Trouvé") | AG62: =AG61 | AH62: =AH61 | AI62: =IFERROR(IF($C62="","",IF($P$15="Cascade",$R62*(1-AH62)*AG62,IF($P$15="Additionnelle",($N62-($N62*($P62+AH62)))*AG62))),"Non Trouvé") | AL62: =AL61 | AM62: =AM61 | AN62: =IFERROR(IF($C62="","",IF($P$15="Cascade",$R62*(1-AM62)*AL62,IF($P$15="Additionnelle",($N62-($N62*($P62+AM62)))*AL62))),"Non Trouvé") | AQ62: =AQ61 | AR62: =AR61 | AS62: =IFERROR(IF($C62="","",IF($P$15="Cascade",$R62*(1-AR62)*AQ62,IF($P$15="Additionnelle",($N62-($N62*($P62+AR62)))*AQ62))),"Non Trouvé") | AV62: =AV61 | AW62: =AW61 | AX62: =IFERROR(IF($C62="","",IF($P$15="Cascade",$R62*(1-AW62)*AV62,IF($P$15="Additionnelle",($N62-($N62*($P62+AW62)))*AV62))),"Non Trouvé") | BA62: =BA61 | BB62: =BB61 | BC62: =IFERROR(IF($C62="","",IF($P$15="Cascade",$R62*(1-BB62)*BA62,IF($P$15="Additionnelle",($N62-($N62*($P62+BB62)))*BA62))),"Non Trouvé") | BF62: =BF61 | BG62: =BG61 | BH62: =IFERROR(IF($C62="","",IF($P$15="Cascade",$R62*(1-BG62)*BF62,IF($P$15="Additionnelle",($N62-($N62*($P62+BG62)))*BF62))),"Non Trouvé") | BK62: =BK61 | BL62: =BL61 | BM62: =IFERROR(IF($C62="","",IF($P$15="Cascade",$R62*(1-BL62)*BK62,IF($P$15="Additionnelle",($N62-($N62*($P62+BL62)))*BK62))),"Non Trouvé") | BP62: =BP61 | BQ62: =BQ61 | BR62: =IFERROR(IF($C62="","",IF($P$15="Cascade",$R62*(1-BQ62)*BP62,IF($P$15="Additionnelle",($N62-($N62*($P62+BQ62)))*BP62))),"Non Trouvé") | BU62: =BU61 | BV62: =BV61 | BW62: =IFERROR(IF($C62="","",IF($P$15="Cascade",$R62*(1-BV62)*BU62,IF($P$15="Additionnelle",($N62-($N62*($P62+BV62)))*BU62))),"Non Trouvé") | BZ62: =BZ61 | CA62: =CA61 | CB62: =IFERROR(IF($C62="","",IF($P$15="Cascade",$R62*(1-CA62)*BZ62,IF($P$15="Additionnelle",($N62-($N62*($P62+CA62)))*BZ62))),"Non Trouvé") | CK62: =IFERROR(IF(F62='[1]Paramètres Généraux'!$K$12,ROUNDUP((REGENERANTS!H62*REGENERANTS!$CF$20)*'[1]Paramètres Généraux'!$M$12,-1),IF(F62='[1]Paramètres Généraux'!$K$15,ROUNDUP((REGENERANTS!H62*REGENERANTS!$CF$20)*'[1]Paramètres Généraux'!$M$15,-1),REGENERANTS!H62*REGENERANTS!$CF$20)),"nd") | DQ62: =SUM(CN62:DP62) | DR62: =SUM(CV62:DP62) | DS62: =IFERROR((IF(AND($F62="Produit Vente",CO62>0),VLOOKUP($C62,'[1]Paramètres Articles'!$B:$H,7,FALSE)*$CO62)*(1-20%)),0) | DT62: =IFERROR((IF(AND($F62="Produit Vente",DR62>0),VLOOKUP($C62,'[1]Paramètres Articles'!$B:$H,6,FALSE)*$DR62)*(1-15%)),0) | DU62: =IFERROR(DQ62*J62,0)
AB64: 270
C65: REGENERANTS 1 - Standard | F65: Panachage 24 unités // Remise 10% pour BRI conso 10€ sur 4 produits : Sérum J/N, CDJR, CDJRI, sérum nuit RI (-10€ = prix plancher, à imprimer sur 1 SR sur le présentoir)
AB67: 0.47 | AG67: 0.07 | AV67: 0.15 | BA67: 0.06 | BF67: 0.08 | BK67: 0.09 | BZ67: 0.078
AB68: Tarif Retail | AV68: Tarif Institut | BZ68: Autres | CF68: Tous réseaux
P70: Additionnelle | AB70: Ambassadeur | AG70: Compagnon | AL70: Challenger | AQ70: Partenaire | AV70: Rose | BA70: Prunelier | BF70: Anthylide | BK70: Calendula | BP70: Bourrache | BU70: Herbacée | BZ70: Autres | CF70: Total
H72: Pdt dans offre | J72: PA x Unit. | K72: Coûts Achats | M72: Tarif Rev. x Unit. | N72: Tarif Rev. | P72: Remise Offres x Prod. | R72: Tarif Rev. Remisé | T72: PPC Unitaire Indicatif | V72: PPC Unitaire Remisé | X72: Montant BRI | Z72: PPC global Indicatif | AB72: Nbrs Offres planifiées | AC72: Remise Statut | AD72: CA | AE72: Marges | AG72: Nbrs Offres planifiées | AH72: Remise Statut | AI72: CA | AJ72: Marges | AL72: Nbrs Offres planifiées | AM72: Remise Statut | AN72: CA | AO72: Marges | AQ72: Nbrs Offres planifiées | AR72: Remise Statut | AS72: CA | AT72: Marges | AV72: Nbrs Offres planifiées | AW72: Remise Statut | AX72: CA | AY72: Marges | BA72: Nbrs Offres planifiées | BB72: Remise Statut | BC72: CA | BD72: Marges | BF72: Nbrs Offres planifiées | BG72: Remise Statut | BH72: CA | BI72: Marges | BK72: Nbrs Offres planifiées | BL72: Remise Statut | BM72: CA | BN72: Marges | BP72: Nbrs Offres planifiées | BQ72: Remise Statut | BR72: CA | BS72: Marges | BU72: Nbrs Offres planifiées | BV72: Remise Statut | BW72: CA | BX72: Marges | BZ72: Nbrs Offres planifiées | CA72: Remise Statut | CB72: CA | CC72: Marges | CF72: Nbrs Offres planifiées | CG72: CA | CH72: Marges
C73: Code article | D73: Libellé article | E73: Code à barres (EAN) | F73: Typ. Prod | H73: '# | J73: '€ | K73: '€ | M73: '€ | N73: '€ | P73: '€ | R73: '€ | T73: '€ | V73: '€ | X73: '€ | Z73: '€ | AB73: '# | AC73: '€ | AD73: '€ | AE73: '€ | AG73: '# | AH73: '€ | AI73: '€ | AJ73: '€ | AL73: '# | AM73: '€ | AN73: '€ | AO73: '€ | AQ73: '# | AR73: '€ | AS73: '€ | AT73: '€ | AV73: '# | AW73: '€ | AX73: '€ | AY73: '€ | BA73: '# | BB73: '€ | BC73: '€ | BD73: '€ | BF73: '# | BG73: '€ | BH73: '€ | BI73: '€ | BK73: '# | BL73: '€ | BM73: '€ | BN73: '€ | BP73: '# | BQ73: '€ | BR73: '€ | BS73: '€ | BU73: '# | BV73: '€ | BW73: '€ | BX73: '€ | BZ73: '# | CA73: '€ | CB73: '€ | CC73: '€ | CF73: '# | CG73: '€ | CH73: '€ | CJ73: =ROUNDUP(CF75*40%,-1)
B75: =C65 | C75: Synthèse | H75: =IFERROR(SUMIFS(H77:H98,F77:F98,"Produit Vente"),"Non trouvé") | J75: =IFERROR($K75/$H75,"Non Trouvé") | K75: =IFERROR(SUM(K77:K98),"Non Trouvé") | M75: =IFERROR($N75/$H75,"Non Trouvé") | N75: =IFERROR(SUM(N77:N98),"Non Trouvé") | P75: =IFERROR(-(R75-N75)/N75,"Non Trouvé") | R75: =IFERROR(SUM(R77:R98),"Non Trouvé") | T75: =IFERROR(SUM(T77:T98),"Non Trouvé") | V75: =IFERROR(SUM(V77:V118),"Non Trouvé") | X75: =IFERROR(SUM(X77:X118),"Non Trouvé") | Z75: =IFERROR(SUM(Z77:Z98),"Non Trouvé") | AB75: =ROUND($AB$64*AB67,0) | AC75: =IFERROR(VLOOKUP(AB70,'[1]Paramètres Généraux'!$O:$P,2,FALSE),"Non Trouvé") | AD75: =IFERROR(SUM(AD77:AD98),"Non Trouvé") | AE75: =IFERROR((AD75-$K75*AB75)/AD75,"Non Trouvé") | AG75: =ROUND($AB$64*AG67,0) | AH75: =IFERROR(VLOOKUP(AG70,'[1]Paramètres Généraux'!$O:$P,2,FALSE),"Non Trouvé") | AI75: =IFERROR(SUM(AI77:AI98),"Non Trouvé") | AJ75: =IFERROR((AI75-$K75*AG75)/AI75,"Non Trouvé") | AL75: =ROUND($AB$64*AL67,0) | AM75: =IFERROR(VLOOKUP(AL70,'[1]Paramètres Généraux'!$O:$P,2,FALSE),"Non Trouvé") | AN75: =IFERROR(SUM(AN77:AN98),"Non Trouvé") | AO75: =IFERROR((AN75-$K75*AL75)/AN75,"Non Trouvé") | AQ75: =ROUND($AB$64*AQ67,0) | AR75: =IFERROR(VLOOKUP(AQ70,'[1]Paramètres Généraux'!$O:$P,2,FALSE),"Non Trouvé") | AS75: =IFERROR(SUM(AS77:AS98),"Non Trouvé") | AT75: =IFERROR((AS75-$K75*AQ75)/AS75,"Non Trouvé") | AV75: =ROUND($AB$64*AV67,0) | AW75: =IFERROR(VLOOKUP(AV70,'[1]Paramètres Généraux'!$O:$P,2,FALSE),"Non Trouvé") | AX75: =IFERROR(SUM(AX77:AX98),"Non Trouvé") | AY75: =IFERROR((AX75-$K75*AV75)/AX75,"Non Trouvé") | BA75: =ROUND($AB$64*BA67,0) | BB75: =IFERROR(VLOOKUP(BA70,'[1]Paramètres Généraux'!$O:$P,2,FALSE),"Non Trouvé") | BC75: =IFERROR(SUM(BC77:BC98),"Non Trouvé") | BD75: =IFERROR((BC75-$K75*BA75)/BC75,"Non Trouvé") | BF75: =ROUND($AB$64*BF67,0) | BG75: =IFERROR(VLOOKUP(BF70,'[1]Paramètres Généraux'!$O:$P,2,FALSE),"Non Trouvé") | BH75: =IFERROR(SUM(BH77:BH98),"Non Trouvé") | BI75: =IFERROR((BH75-$K75*BF75)/BH75,"Non Trouvé") | BK75: =ROUND($AB$64*BK67,0) | BL75: =IFERROR(VLOOKUP(BK70,'[1]Paramètres Généraux'!$O:$P,2,FALSE),"Non Trouvé") | BM75: =IFERROR(SUM(BM77:BM98),"Non Trouvé") | BN75: =IFERROR((BM75-$K75*BK75)/BM75,"Non Trouvé") | BP75: =ROUND($AB$64*BP67,0) | BQ75: =IFERROR(VLOOKUP(BP70,'[1]Paramètres Généraux'!$O:$P,2,FALSE),"Non Trouvé") | BR75: =IFERROR(SUM(BR77:BR98),"Non Trouvé") | BS75: =IFERROR((BR75-$K75*BP75)/BR75,"Non Trouvé") | BU75: =ROUND($AB$64*BU67,0) | BV75: =IFERROR(VLOOKUP(BU70,'[1]Paramètres Généraux'!$O:$P,2,FALSE),"Non Trouvé") | BW75: =IFERROR(SUM(BW77:BW98),"Non Trouvé") | BX75: =IFERROR((BW75-$K75*BU75)/BW75,"Non Trouvé") | BZ75: =ROUND($AB$64*BZ67,0) | CA75: =IFERROR(VLOOKUP(BZ70,'[1]Paramètres Généraux'!$O:$P,2,FALSE),"Non Trouvé") | CB75: =IFERROR(SUM(CB77:CB98),"Non Trouvé") | CC75: =IFERROR((CB75-$K75*BZ75)/CB75,"Non Trouvé") | CF75: =SUMIFS($AB75:$CC75,$AB72:$CC72,CF72) | CG75: =SUMIFS($AB75:$CC75,$AB72:$CC72,CG72) | CH75: =IFERROR((CG75-$K75*CF75)/CG75,"Non Trouvé") | CJ75: =ROUNDUP(CF75*70%,-1)
B77: =IF(C77="",0,COUNTIFS($B$22:B76,">"&0)+1) | C77: 1020202 | D77: =IFERROR(IF($C77="","",VLOOKUP($C77,'[1]Paramètres Articles'!$B:$G,2,FALSE)),"Non Trouvé") | E77: =IFERROR(IF($C77="","",_xlfn.XLOOKUP(REGENERANTS!$C77,'[1]New Base PA'!$F:$F,'[1]New Base PA'!$D:$D,"Not Found",0)),"Non Trouvé") | F77: Produit Vente | H77: 3 | J77: =IFERROR(IF($C77="","",VLOOKUP($C77,'[1]New Base PA'!$F:$J,5,FALSE)),"Non Trouvé") | K77: =IFERROR(IF($C77="","",$J77*$H77),"Non Trouvé") | M77: =IFERROR(IF(AND($F77="Produit Vente",H77>0),VLOOKUP($C77,'[1]Paramètres Articles'!$B:$G,6,FALSE),0),"Non Trouvé") | N77: =IFERROR(IF($C77="","",$M77*$H77),"Non Trouvé") | P77: 0.1 | R77: =IFERROR(IF($C77="","",$N77*(1-$P77)),"Non Trouvé") | T77: =IFERROR(IF($C77="","",VLOOKUP($C77,'[1]Paramètres Articles'!$B:$H,7,FALSE)),"Non Trouvé") | V77: =IFERROR(IF($C77="","",IF($P77="","",$T77*(1-$P77))),"Non Trouvé") | X77: =IFERROR(T77-V77,"") | Z77: =IFERROR(IF(OR(T77=0,T77=""),0,T77*H77),"Non Trouvé") | AB77: =AB75 | AC77: =AC75 | AD77: =IFERROR(IF($C77="","",IF($P$15="Cascade",$R77*(1-AC77)*AB77,IF($P$15="Additionnelle",($N77-($N77*($P77+AC77)))*AB77))),"Non Trouvé") | AG77: =AG75 | AH77: =AH75 | AI77: =IFERROR(IF($C77="","",IF($P$15="Cascade",$R77*(1-AH77)*AG77,IF($P$15="Additionnelle",($N77-($N77*($P77+AH77)))*AG77))),"Non Trouvé") | AL77: =AL75 | AM77: =AM75 | AN77: =IFERROR(IF($C77="","",IF($P$15="Cascade",$R77*(1-AM77)*AL77,IF($P$15="Additionnelle",($N77-($N77*($P77+AM77)))*AL77))),"Non Trouvé") | AQ77: =AQ75 | AR77: =AR75 | AS77: =IFERROR(IF($C77="","",IF($P$15="Cascade",$R77*(1-AR77)*AQ77,IF($P$15="Additionnelle",($N77-($N77*($P77+AR77)))*AQ77))),"Non Trouvé") | AV77: =AV75 | AW77: =AW75 | AX77: =IFERROR(IF($C77="","",IF($P$15="Cascade",$R77*(1-AW77)*AV77,IF($P$15="Additionnelle",($N77-($N77*($P77+AW77)))*AV77))),"Non Trouvé") | BA77: =BA75 | BB77: =BB75 | BC77: =IFERROR(IF($C77="","",IF($P$15="Cascade",$R77*(1-BB77)*BA77,IF($P$15="Additionnelle",($N77-($N77*($P77+BB77)))*BA77))),"Non Trouvé") | BF77: =BF75 | BG77: =BG75 | BH77: =IFERROR(IF($C77="","",IF($P$15="Cascade",$R77*(1-BG77)*BF77,IF($P$15="Additionnelle",($N77-($N77*($P77+BG77)))*BF77))),"Non Trouvé") | BK77: =BK75 | BL77: =BL75 | BM77: =IFERROR(IF($C77="","",IF($P$15="Cascade",$R77*(1-BL77)*BK77,IF($P$15="Additionnelle",($N77-($N77*($P77+BL77)))*BK77))),"Non Trouvé") | BP77: =BP75 | BQ77: =BQ75 | BR77: =IFERROR(IF($C77="","",IF($P$15="Cascade",$R77*(1-BQ77)*BP77,IF($P$15="Additionnelle",($N77-($N77*($P77+BQ77)))*BP77))),"Non Trouvé") | BU77: =BU75 | BV77: =BV75 | BW77: =IFERROR(IF($C77="","",IF($P$15="Cascade",$R77*(1-BV77)*BU77,IF($P$15="Additionnelle",($N77-($N77*($P77+BV77)))*BU77))),"Non Trouvé") | BZ77: =BZ75 | CA77: =CA75 | CB77: =IFERROR(IF($C77="","",IF($P$15="Cascade",$R77*(1-CA77)*BZ77,IF($P$15="Additionnelle",($N77-($N77*($P77+CA77)))*BZ77))),"Non Trouvé") | CK77: =IFERROR(IF(F77='[1]Paramètres Généraux'!$K$12,ROUNDUP((REGENERANTS!H77*REGENERANTS!$CF$75)*'[1]Paramètres Généraux'!$M$12,-1),IF(F77='[1]Paramètres Généraux'!$K$15,ROUNDUP((REGENERANTS!H77*REGENERANTS!$CF$75)*'[1]Paramètres Généraux'!$M$15,-1),REGENERANTS!H77*REGENERANTS!$CF$75)),"nd") | DQ77: =SUM(CN77:DP77) | DR77: =SUM(CV77:DP77) | DS77: =IFERROR((IF(AND($F77="Produit Vente",CO77>0),VLOOKUP($C77,'[1]Paramètres Articles'!$B:$H,7,FALSE)*$CO77)*(1-20%)),0) | DT77: =IFERROR((IF(AND($F77="Produit Vente",DR77>0),VLOOKUP($C77,'[1]Paramètres Articles'!$B:$H,6,FALSE)*$DR77)*(1-15%)),0) | DU77: =IFERROR(DQ77*J77,0)
B78: =IF(C78="",0,COUNTIFS($B$22:B77,">"&0)+1) | C78: 1020310 | D78: =IFERROR(IF($C78="","",VLOOKUP($C78,'[1]Paramètres Articles'!$B:$G,2,FALSE)),"Non Trouvé") | E78: =IFERROR(IF($C78="","",_xlfn.XLOOKUP(REGENERANTS!$C78,'[1]New Base PA'!$F:$F,'[1]New Base PA'!$D:$D,"Not Found",0)),"Non Trouvé") | F78: Produit Vente | H78: 2 | J78: =IFERROR(IF($C78="","",VLOOKUP($C78,'[1]New Base PA'!$F:$J,5,FALSE)),"Non Trouvé") | K78: =IFERROR(IF($C78="","",$J78*$H78),"Non Trouvé") | M78: =IFERROR(IF(AND($F78="Produit Vente",H78>0),VLOOKUP($C78,'[1]Paramètres Articles'!$B:$G,6,FALSE),0),"Non Trouvé") | N78: =IFERROR(IF($C78="","",$M78*$H78),"Non Trouvé") | P78: 0.1 | R78: =IFERROR(IF($C78="","",$N78*(1-$P78)),"Non Trouvé") | T78: =IFERROR(IF($C78="","",VLOOKUP($C78,'[1]Paramètres Articles'!$B:$H,7,FALSE)),"Non Trouvé") | V78: =IFERROR(IF($C78="","",IF($P78="","",$T78*(1-$P78))),"Non Trouvé") | X78: =IFERROR(T78-V78,"") | Z78: =IFERROR(IF(OR(T78=0,T78=""),0,T78*H78),"Non Trouvé") | AB78: =AB77 | AC78: =AC77 | AD78: =IFERROR(IF($C78="","",IF($P$15="Cascade",$R78*(1-AC78)*AB78,IF($P$15="Additionnelle",($N78-($N78*($P78+AC78)))*AB78))),"Non Trouvé") | AG78: =AG77 | AH78: =AH77 | AI78: =IFERROR(IF($C78="","",IF($P$15="Cascade",$R78*(1-AH78)*AG78,IF($P$15="Additionnelle",($N78-($N78*($P78+AH78)))*AG78))),"Non Trouvé") | AL78: =AL77 | AM78: =AM77 | AN78: =IFERROR(IF($C78="","",IF($P$15="Cascade",$R78*(1-AM78)*AL78,IF($P$15="Additionnelle",($N78-($N78*($P78+AM78)))*AL78))),"Non Trouvé") | AQ78: =AQ77 | AR78: =AR77 | AS78: =IFERROR(IF($C78="","",IF($P$15="Cascade",$R78*(1-AR78)*AQ78,IF($P$15="Additionnelle",($N78-($N78*($P78+AR78)))*AQ78))),"Non Trouvé") | AV78: =AV77 | AW78: =AW77 | AX78: =IFERROR(IF($C78="","",IF($P$15="Cascade",$R78*(1-AW78)*AV78,IF($P$15="Additionnelle",($N78-($N78*($P78+AW78)))*AV78))),"Non Trouvé") | BA78: =BA77 | BB78: =BB77 | BC78: =IFERROR(IF($C78="","",IF($P$15="Cascade",$R78*(1-BB78)*BA78,IF($P$15="Additionnelle",($N78-($N78*($P78+BB78)))*BA78))),"Non Trouvé") | BF78: =BF77 | BG78: =BG77 | BH78: =IFERROR(IF($C78="","",IF($P$15="Cascade",$R78*(1-BG78)*BF78,IF($P$15="Additionnelle",($N78-($N78*($P78+BG78)))*BF78))),"Non Trouvé") | BK78: =BK77 | BL78: =BL77 | BM78: =IFERROR(IF($C78="","",IF($P$15="Cascade",$R78*(1-BL78)*BK78,IF($P$15="Additionnelle",($N78-($N78*($P78+BL78)))*BK78))),"Non Trouvé") | BP78: =BP77 | BQ78: =BQ77 | BR78: =IFERROR(IF($C78="","",IF($P$15="Cascade",$R78*(1-BQ78)*BP78,IF($P$15="Additionnelle",($N78-($N78*($P78+BQ78)))*BP78))),"Non Trouvé") | BU78: =BU77 | BV78: =BV77 | BW78: =IFERROR(IF($C78="","",IF($P$15="Cascade",$R78*(1-BV78)*BU78,IF($P$15="Additionnelle",($N78-($N78*($P78+BV78)))*BU78))),"Non Trouvé") | BZ78: =BZ77 | CA78: =CA77 | CB78: =IFERROR(IF($C78="","",IF($P$15="Cascade",$R78*(1-CA78)*BZ78,IF($P$15="Additionnelle",($N78-($N78*($P78+CA78)))*BZ78))),"Non Trouvé") | CG78: Prix Offre Moy. Remisé : | CH78: =CG75/CF75 | CK78: =IFERROR(IF(F78='[1]Paramètres Généraux'!$K$12,ROUNDUP((REGENERANTS!H78*REGENERANTS!$CF$75)*'[1]Paramètres Généraux'!$M$12,-1),IF(F78='[1]Paramètres Généraux'!$K$15,ROUNDUP((REGENERANTS!H78*REGENERANTS!$CF$75)*'[1]Paramètres Généraux'!$M$15,-1),REGENERANTS!H78*REGENERANTS!$CF$75)),"nd") | DQ78: =SUM(CN78:DP78) | DR78: =SUM(CV78:DP78) | DS78: =IFERROR((IF(AND($F78="Produit Vente",CO78>0),VLOOKUP($C78,'[1]Paramètres Articles'!$B:$H,7,FALSE)*$CO78)*(1-20%)),0) | DT78: =IFERROR((IF(AND($F78="Produit Vente",DR78>0),VLOOKUP($C78,'[1]Paramètres Articles'!$B:$H,6,FALSE)*$DR78)*(1-15%)),0) | DU78: =IFERROR(DQ78*J78,0)
B79: =IF(C79="",0,COUNTIFS($B$22:B78,">"&0)+1) | C79: 1020401 | D79: =IFERROR(IF($C79="","",VLOOKUP($C79,'[1]Paramètres Articles'!$B:$G,2,FALSE)),"Non Trouvé") | E79: =IFERROR(IF($C79="","",_xlfn.XLOOKUP(REGENERANTS!$C79,'[1]New Base PA'!$F:$F,'[1]New Base PA'!$D:$D,"Not Found",0)),"Non Trouvé") | F79: Produit Vente | H79: 2 | J79: =IFERROR(IF($C79="","",VLOOKUP($C79,'[1]New Base PA'!$F:$J,5,FALSE)),"Non Trouvé") | K79: =IFERROR(IF($C79="","",$J79*$H79),"Non Trouvé") | M79: =IFERROR(IF(AND($F79="Produit Vente",H79>0),VLOOKUP($C79,'[1]Paramètres Articles'!$B:$G,6,FALSE),0),"Non Trouvé") | N79: =IFERROR(IF($C79="","",$M79*$H79),"Non Trouvé") | P79: 0.1 | R79: =IFERROR(IF($C79="","",$N79*(1-$P79)),"Non Trouvé") | T79: =IFERROR(IF($C79="","",VLOOKUP($C79,'[1]Paramètres Articles'!$B:$H,7,FALSE)),"Non Trouvé") | V79: =IFERROR(IF($C79="","",IF($P79="","",$T79*(1-$P79))),"Non Trouvé") | X79: =IFERROR(T79-V79,"") | Z79: =IFERROR(IF(OR(T79=0,T79=""),0,T79*H79),"Non Trouvé") | AB79: =AB77 | AC79: =AC77 | AD79: =IFERROR(IF($C79="","",IF($P$15="Cascade",$R79*(1-AC79)*AB79,IF($P$15="Additionnelle",($N79-($N79*($P79+AC79)))*AB79))),"Non Trouvé") | AG79: =AG77 | AH79: =AH77 | AI79: =IFERROR(IF($C79="","",IF($P$15="Cascade",$R79*(1-AH79)*AG79,IF($P$15="Additionnelle",($N79-($N79*($P79+AH79)))*AG79))),"Non Trouvé") | AL79: =AL77 | AM79: =AM77 | AN79: =IFERROR(IF($C79="","",IF($P$15="Cascade",$R79*(1-AM79)*AL79,IF($P$15="Additionnelle",($N79-($N79*($P79+AM79)))*AL79))),"Non Trouvé") | AQ79: =AQ77 | AR79: =AR77 | AS79: =IFERROR(IF($C79="","",IF($P$15="Cascade",$R79*(1-AR79)*AQ79,IF($P$15="Additionnelle",($N79-($N79*($P79+AR79)))*AQ79))),"Non Trouvé") | AV79: =AV77 | AW79: =AW77 | AX79: =IFERROR(IF($C79="","",IF($P$15="Cascade",$R79*(1-AW79)*AV79,IF($P$15="Additionnelle",($N79-($N79*($P79+AW79)))*AV79))),"Non Trouvé") | BA79: =BA77 | BB79: =BB77 | BC79: =IFERROR(IF($C79="","",IF($P$15="Cascade",$R79*(1-BB79)*BA79,IF($P$15="Additionnelle",($N79-($N79*($P79+BB79)))*BA79))),"Non Trouvé") | BF79: =BF77 | BG79: =BG77 | BH79: =IFERROR(IF($C79="","",IF($P$15="Cascade",$R79*(1-BG79)*BF79,IF($P$15="Additionnelle",($N79-($N79*($P79+BG79)))*BF79))),"Non Trouvé") | BK79: =BK77 | BL79: =BL77 | BM79: =IFERROR(IF($C79="","",IF($P$15="Cascade",$R79*(1-BL79)*BK79,IF($P$15="Additionnelle",($N79-($N79*($P79+BL79)))*BK79))),"Non Trouvé") | BP79: =BP77 | BQ79: =BQ77 | BR79: =IFERROR(IF($C79="","",IF($P$15="Cascade",$R79*(1-BQ79)*BP79,IF($P$15="Additionnelle",($N79-($N79*($P79+BQ79)))*BP79))),"Non Trouvé") | BU79: =BU77 | BV79: =BV77 | BW79: =IFERROR(IF($C79="","",IF($P$15="Cascade",$R79*(1-BV79)*BU79,IF($P$15="Additionnelle",($N79-($N79*($P79+BV79)))*BU79))),"Non Trouvé") | BZ79: =BZ77 | CA79: =CA77 | CB79: =IFERROR(IF($C79="","",IF($P$15="Cascade",$R79*(1-CA79)*BZ79,IF($P$15="Additionnelle",($N79-($N79*($P79+CA79)))*BZ79))),"Non Trouvé") | CG79: Poids Gratuités achats : | CH79: =SUM(CH81:CH84) | CK79: =IFERROR(IF(F79='[1]Paramètres Généraux'!$K$12,ROUNDUP((REGENERANTS!H79*REGENERANTS!$CF$75)*'[1]Paramètres Généraux'!$M$12,-1),IF(F79='[1]Paramètres Généraux'!$K$15,ROUNDUP((REGENERANTS!H79*REGENERANTS!$CF$75)*'[1]Paramètres Généraux'!$M$15,-1),REGENERANTS!H79*REGENERANTS!$CF$75)),"nd") | DQ79: =SUM(CN79:DP79) | DR79: =SUM(CV79:DP79) | DS79: =IFERROR((IF(AND($F79="Produit Vente",CO79>0),VLOOKUP($C79,'[1]Paramètres Articles'!$B:$H,7,FALSE)*$CO79)*(1-20%)),0) | DT79: =IFERROR((IF(AND($F79="Produit Vente",DR79>0),VLOOKUP($C79,'[1]Paramètres Articles'!$B:$H,6,FALSE)*$DR79)*(1-15%)),0) | DU79: =IFERROR(DQ79*J79,0)
B80: =IF(C80="",0,COUNTIFS($B$22:B79,">"&0)+1) | C80: 1020302 | D80: =IFERROR(IF($C80="","",VLOOKUP($C80,'[1]Paramètres Articles'!$B:$G,2,FALSE)),"Non Trouvé") | E80: =IFERROR(IF($C80="","",_xlfn.XLOOKUP(REGENERANTS!$C80,'[1]New Base PA'!$F:$F,'[1]New Base PA'!$D:$D,"Not Found",0)),"Non Trouvé") | F80: Produit Vente | H80: 1 | J80: =IFERROR(IF($C80="","",VLOOKUP($C80,'[1]New Base PA'!$F:$J,5,FALSE)),"Non Trouvé") | K80: =IFERROR(IF($C80="","",$J80*$H80),"Non Trouvé") | M80: =IFERROR(IF(AND($F80="Produit Vente",H80>0),VLOOKUP($C80,'[1]Paramètres Articles'!$B:$G,6,FALSE),0),"Non Trouvé") | N80: =IFERROR(IF($C80="","",$M80*$H80),"Non Trouvé") | P80: 0.1 | R80: =IFERROR(IF($C80="","",$N80*(1-$P80)),"Non Trouvé") | T80: =IFERROR(IF($C80="","",VLOOKUP($C80,'[1]Paramètres Articles'!$B:$H,7,FALSE)),"Non Trouvé") | V80: =IFERROR(IF($C80="","",IF($P80="","",$T80*(1-$P80))),"Non Trouvé") | X80: =IFERROR(T80-V80,"") | Z80: =IFERROR(IF(OR(T80=0,T80=""),0,T80*H80),"Non Trouvé") | AB80: =AB79 | AC80: =AC79 | AD80: =IFERROR(IF($C80="","",IF($P$15="Cascade",$R80*(1-AC80)*AB80,IF($P$15="Additionnelle",($N80-($N80*($P80+AC80)))*AB80))),"Non Trouvé") | AG80: =AG79 | AH80: =AH79 | AI80: =IFERROR(IF($C80="","",IF($P$15="Cascade",$R80*(1-AH80)*AG80,IF($P$15="Additionnelle",($N80-($N80*($P80+AH80)))*AG80))),"Non Trouvé") | AL80: =AL79 | AM80: =AM79 | AN80: =IFERROR(IF($C80="","",IF($P$15="Cascade",$R80*(1-AM80)*AL80,IF($P$15="Additionnelle",($N80-($N80*($P80+AM80)))*AL80))),"Non Trouvé") | AQ80: =AQ79 | AR80: =AR79 | AS80: =IFERROR(IF($C80="","",IF($P$15="Cascade",$R80*(1-AR80)*AQ80,IF($P$15="Additionnelle",($N80-($N80*($P80+AR80)))*AQ80))),"Non Trouvé") | AV80: =AV79 | AW80: =AW79 | AX80: =IFERROR(IF($C80="","",IF($P$15="Cascade",$R80*(1-AW80)*AV80,IF($P$15="Additionnelle",($N80-($N80*($P80+AW80)))*AV80))),"Non Trouvé") | BA80: =BA79 | BB80: =BB79 | BC80: =IFERROR(IF($C80="","",IF($P$15="Cascade",$R80*(1-BB80)*BA80,IF($P$15="Additionnelle",($N80-($N80*($P80+BB80)))*BA80))),"Non Trouvé") | BF80: =BF79 | BG80: =BG79 | BH80: =IFERROR(IF($C80="","",IF($P$15="Cascade",$R80*(1-BG80)*BF80,IF($P$15="Additionnelle",($N80-($N80*($P80+BG80)))*BF80))),"Non Trouvé") | BK80: =BK79 | BL80: =BL79 | BM80: =IFERROR(IF($C80="","",IF($P$15="Cascade",$R80*(1-BL80)*BK80,IF($P$15="Additionnelle",($N80-($N80*($P80+BL80)))*BK80))),"Non Trouvé") | BP80: =BP79 | BQ80: =BQ79 | BR80: =IFERROR(IF($C80="","",IF($P$15="Cascade",$R80*(1-BQ80)*BP80,IF($P$15="Additionnelle",($N80-($N80*($P80+BQ80)))*BP80))),"Non Trouvé") | BU80: =BU79 | BV80: =BV79 | BW80: =IFERROR(IF($C80="","",IF($P$15="Cascade",$R80*(1-BV80)*BU80,IF($P$15="Additionnelle",($N80-($N80*($P80+BV80)))*BU80))),"Non Trouvé") | BZ80: =BZ79 | CA80: =CA79 | CB80: =IFERROR(IF($C80="","",IF($P$15="Cascade",$R80*(1-CA80)*BZ80,IF($P$15="Additionnelle",($N80-($N80*($P80+CA80)))*BZ80))),"Non Trouvé") | CK80: =IFERROR(IF(F80='[1]Paramètres Généraux'!$K$12,ROUNDUP((REGENERANTS!H80*REGENERANTS!$CF$75)*'[1]Paramètres Généraux'!$M$12,-1),IF(F80='[1]Paramètres Généraux'!$K$15,ROUNDUP((REGENERANTS!H80*REGENERANTS!$CF$75)*'[1]Paramètres Généraux'!$M$15,-1),REGENERANTS!H80*REGENERANTS!$CF$75)),"nd") | DQ80: =SUM(CN80:DP80) | DR80: =SUM(CV80:DP80) | DS80: =IFERROR((IF(AND($F80="Produit Vente",CO80>0),VLOOKUP($C80,'[1]Paramètres Articles'!$B:$H,7,FALSE)*$CO80)*(1-20%)),0) | DT80: =IFERROR((IF(AND($F80="Produit Vente",DR80>0),VLOOKUP($C80,'[1]Paramètres Articles'!$B:$H,6,FALSE)*$DR80)*(1-15%)),0) | DU80: =IFERROR(DQ80*J80,0)
B81: =IF(C81="",0,COUNTIFS($B$22:B80,">"&0)+1) | C81: 1020721 | D81: =IFERROR(IF($C81="","",VLOOKUP($C81,'[1]Paramètres Articles'!$B:$G,2,FALSE)),"Non Trouvé") | E81: =IFERROR(IF($C81="","",_xlfn.XLOOKUP(REGENERANTS!$C81,'[1]New Base PA'!$F:$F,'[1]New Base PA'!$D:$D,"Not Found",0)),"Non Trouvé") | F81: Produit Vente | H81: 0 | J81: =IFERROR(IF($C81="","",VLOOKUP($C81,'[1]New Base PA'!$F:$J,5,FALSE)),"Non Trouvé") | K81: =IFERROR(IF($C81="","",$J81*$H81),"Non Trouvé") | M81: =IFERROR(IF(AND($F81="Produit Vente",H81>0),VLOOKUP($C81,'[1]Paramètres Articles'!$B:$G,6,FALSE),0),"Non Trouvé") | N81: =IFERROR(IF($C81="","",$M81*$H81),"Non Trouvé") | P81: 0.1 | R81: =IFERROR(IF($C81="","",$N81*(1-$P81)),"Non Trouvé") | T81: =IFERROR(IF($C81="","",VLOOKUP($C81,'[1]Paramètres Articles'!$B:$H,7,FALSE)),"Non Trouvé") | V81: =IFERROR(IF($C81="","",IF($P81="","",$T81*(1-$P81))),"Non Trouvé") | X81: =IFERROR(T81-V81,"") | Z81: =IFERROR(IF(OR(T81=0,T81=""),0,T81*H81),"Non Trouvé") | AB81: =AB79 | AC81: =AC79 | AD81: =IFERROR(IF($C81="","",IF($P$15="Cascade",$R81*(1-AC81)*AB81,IF($P$15="Additionnelle",($N81-($N81*($P81+AC81)))*AB81))),"Non Trouvé") | AG81: =AG79 | AH81: =AH79 | AI81: =IFERROR(IF($C81="","",IF($P$15="Cascade",$R81*(1-AH81)*AG81,IF($P$15="Additionnelle",($N81-($N81*($P81+AH81)))*AG81))),"Non Trouvé") | AL81: =AL79 | AM81: =AM79 | AN81: =IFERROR(IF($C81="","",IF($P$15="Cascade",$R81*(1-AM81)*AL81,IF($P$15="Additionnelle",($N81-($N81*($P81+AM81)))*AL81))),"Non Trouvé") | AQ81: =AQ79 | AR81: =AR79 | AS81: =IFERROR(IF($C81="","",IF($P$15="Cascade",$R81*(1-AR81)*AQ81,IF($P$15="Additionnelle",($N81-($N81*($P81+AR81)))*AQ81))),"Non Trouvé") | AV81: =AV79 | AW81: =AW79 | AX81: =IFERROR(IF($C81="","",IF($P$15="Cascade",$R81*(1-AW81)*AV81,IF($P$15="Additionnelle",($N81-($N81*($P81+AW81)))*AV81))),"Non Trouvé") | BA81: =BA79 | BB81: =BB79 | BC81: =IFERROR(IF($C81="","",IF($P$15="Cascade",$R81*(1-BB81)*BA81,IF($P$15="Additionnelle",($N81-($N81*($P81+BB81)))*BA81))),"Non Trouvé") | BF81: =BF79 | BG81: =BG79 | BH81: =IFERROR(IF($C81="","",IF($P$15="Cascade",$R81*(1-BG81)*BF81,IF($P$15="Additionnelle",($N81-($N81*($P81+BG81)))*BF81))),"Non Trouvé") | BK81: =BK79 | BL81: =BL79 | BM81: =IFERROR(IF($C81="","",IF($P$15="Cascade",$R81*(1-BL81)*BK81,IF($P$15="Additionnelle",($N81-($N81*($P81+BL81)))*BK81))),"Non Trouvé") | BP81: =BP79 | BQ81: =BQ79 | BR81: =IFERROR(IF($C81="","",IF($P$15="Cascade",$R81*(1-BQ81)*BP81,IF($P$15="Additionnelle",($N81-($N81*($P81+BQ81)))*BP81))),"Non Trouvé") | BU81: =BU79 | BV81: =BV79 | BW81: =IFERROR(IF($C81="","",IF($P$15="Cascade",$R81*(1-BV81)*BU81,IF($P$15="Additionnelle",($N81-($N81*($P81+BV81)))*BU81))),"Non Trouvé") | BZ81: =BZ79 | CA81: =CA79 | CB81: =IFERROR(IF($C81="","",IF($P$15="Cascade",$R81*(1-CA81)*BZ81,IF($P$15="Additionnelle",($N81-($N81*($P81+CA81)))*BZ81))),"Non Trouvé") | CG81: UG | CH81: =SUMIFS(K77:K98,F77:F98,CG81)/SUMIFS(K77:K98,F77:F98,"Produit Vente") | CK81: =IFERROR(IF(F81='[1]Paramètres Généraux'!$K$12,ROUNDUP((REGENERANTS!H81*REGENERANTS!$CF$75)*'[1]Paramètres Généraux'!$M$12,-1),IF(F81='[1]Paramètres Généraux'!$K$15,ROUNDUP((REGENERANTS!H81*REGENERANTS!$CF$75)*'[1]Paramètres Généraux'!$M$15,-1),REGENERANTS!H81*REGENERANTS!$CF$75)),"nd") | DQ81: =SUM(CN81:DP81) | DR81: =SUM(CV81:DP81) | DS81: =IFERROR((IF(AND($F81="Produit Vente",CO81>0),VLOOKUP($C81,'[1]Paramètres Articles'!$B:$H,7,FALSE)*$CO81)*(1-20%)),0) | DT81: =IFERROR((IF(AND($F81="Produit Vente",DR81>0),VLOOKUP($C81,'[1]Paramètres Articles'!$B:$H,6,FALSE)*$DR81)*(1-15%)),0) | DU81: =IFERROR(DQ81*J81,0)
B82: =IF(C82="",0,COUNTIFS($B$22:B81,">"&0)+1) | C82: 1020107 | D82: =IFERROR(IF($C82="","",VLOOKUP($C82,'[1]Paramètres Articles'!$B:$G,2,FALSE)),"Non Trouvé") | E82: =IFERROR(IF($C82="","",_xlfn.XLOOKUP(REGENERANTS!$C82,'[1]New Base PA'!$F:$F,'[1]New Base PA'!$D:$D,"Not Found",0)),"Non Trouvé") | F82: Produit Vente | H82: 1 | J82: =IFERROR(IF($C82="","",VLOOKUP($C82,'[1]New Base PA'!$F:$J,5,FALSE)),"Non Trouvé") | K82: =IFERROR(IF($C82="","",$J82*$H82),"Non Trouvé") | M82: =IFERROR(IF(AND($F82="Produit Vente",H82>0),VLOOKUP($C82,'[1]Paramètres Articles'!$B:$G,6,FALSE),0),"Non Trouvé") | N82: =IFERROR(IF($C82="","",$M82*$H82),"Non Trouvé") | P82: 0.1 | R82: =IFERROR(IF($C82="","",$N82*(1-$P82)),"Non Trouvé") | T82: =IFERROR(IF($C82="","",VLOOKUP($C82,'[1]Paramètres Articles'!$B:$H,7,FALSE)),"Non Trouvé") | V82: =IFERROR(IF($C82="","",IF($P82="","",$T82*(1-$P82))),"Non Trouvé") | X82: =IFERROR(T82-V82,"") | Z82: =IFERROR(IF(OR(T82=0,T82=""),0,T82*H82),"Non Trouvé") | AB82: =AB81 | AC82: =AC81 | AD82: =IFERROR(IF($C82="","",IF($P$15="Cascade",$R82*(1-AC82)*AB82,IF($P$15="Additionnelle",($N82-($N82*($P82+AC82)))*AB82))),"Non Trouvé") | AG82: =AG81 | AH82: =AH81 | AI82: =IFERROR(IF($C82="","",IF($P$15="Cascade",$R82*(1-AH82)*AG82,IF($P$15="Additionnelle",($N82-($N82*($P82+AH82)))*AG82))),"Non Trouvé") | AL82: =AL81 | AM82: =AM81 | AN82: =IFERROR(IF($C82="","",IF($P$15="Cascade",$R82*(1-AM82)*AL82,IF($P$15="Additionnelle",($N82-($N82*($P82+AM82)))*AL82))),"Non Trouvé") | AQ82: =AQ81 | AR82: =AR81 | AS82: =IFERROR(IF($C82="","",IF($P$15="Cascade",$R82*(1-AR82)*AQ82,IF($P$15="Additionnelle",($N82-($N82*($P82+AR82)))*AQ82))),"Non Trouvé") | AV82: =AV81 | AW82: =AW81 | AX82: =IFERROR(IF($C82="","",IF($P$15="Cascade",$R82*(1-AW82)*AV82,IF($P$15="Additionnelle",($N82-($N82*($P82+AW82)))*AV82))),"Non Trouvé") | BA82: =BA81 | BB82: =BB81 | BC82: =IFERROR(IF($C82="","",IF($P$15="Cascade",$R82*(1-BB82)*BA82,IF($P$15="Additionnelle",($N82-($N82*($P82+BB82)))*BA82))),"Non Trouvé") | BF82: =BF81 | BG82: =BG81 | BH82: =IFERROR(IF($C82="","",IF($P$15="Cascade",$R82*(1-BG82)*BF82,IF($P$15="Additionnelle",($N82-($N82*($P82+BG82)))*BF82))),"Non Trouvé") | BK82: =BK81 | BL82: =BL81 | BM82: =IFERROR(IF($C82="","",IF($P$15="Cascade",$R82*(1-BL82)*BK82,IF($P$15="Additionnelle",($N82-($N82*($P82+BL82)))*BK82))),"Non Trouvé") | BP82: =BP81 | BQ82: =BQ81 | BR82: =IFERROR(IF($C82="","",IF($P$15="Cascade",$R82*(1-BQ82)*BP82,IF($P$15="Additionnelle",($N82-($N82*($P82+BQ82)))*BP82))),"Non Trouvé") | BU82: =BU81 | BV82: =BV81 | BW82: =IFERROR(IF($C82="","",IF($P$15="Cascade",$R82*(1-BV82)*BU82,IF($P$15="Additionnelle",($N82-($N82*($P82+BV82)))*BU82))),"Non Trouvé") | BZ82: =BZ81 | CA82: =CA81 | CB82: =IFERROR(IF($C82="","",IF($P$15="Cascade",$R82*(1-CA82)*BZ82,IF($P$15="Additionnelle",($N82-($N82*($P82+CA82)))*BZ82))),"Non Trouvé") | CG82: PLV | CH82: =(SUMIFS(K77:K98,F77:F98,"PLV (PDC ou autre)")+SUMIFS(K77:K98,F77:F98,"PLV (vitrine)"))/K75 | CK82: =IFERROR(IF(F82='[1]Paramètres Généraux'!$K$12,ROUNDUP((REGENERANTS!H82*REGENERANTS!$CF$75)*'[1]Paramètres Généraux'!$M$12,-1),IF(F82='[1]Paramètres Généraux'!$K$15,ROUNDUP((REGENERANTS!H82*REGENERANTS!$CF$75)*'[1]Paramètres Généraux'!$M$15,-1),REGENERANTS!H82*REGENERANTS!$CF$75)),"nd") | DQ82: =SUM(CN82:DP82) | DR82: =SUM(CV82:DP82) | DS82: =IFERROR((IF(AND($F82="Produit Vente",CO82>0),VLOOKUP($C82,'[1]Paramètres Articles'!$B:$H,7,FALSE)*$CO82)*(1-20%)),0) | DT82: =IFERROR((IF(AND($F82="Produit Vente",DR82>0),VLOOKUP($C82,'[1]Paramètres Articles'!$B:$H,6,FALSE)*$DR82)*(1-15%)),0) | DU82: =IFERROR(DQ82*J82,0)
B83: =IF(C83="",0,COUNTIFS($B$22:B82,">"&0)+1) | C83: 1020102 | D83: =IFERROR(IF($C83="","",VLOOKUP($C83,'[1]Paramètres Articles'!$B:$G,2,FALSE)),"Non Trouvé") | E83: =IFERROR(IF($C83="","",_xlfn.XLOOKUP(REGENERANTS!$C83,'[1]New Base PA'!$F:$F,'[1]New Base PA'!$D:$D,"Not Found",0)),"Non Trouvé") | F83: Produit Vente | H83: 1 | J83: =IFERROR(IF($C83="","",VLOOKUP($C83,'[1]New Base PA'!$F:$J,5,FALSE)),"Non Trouvé") | K83: =IFERROR(IF($C83="","",$J83*$H83),"Non Trouvé") | M83: =IFERROR(IF(AND($F83="Produit Vente",H83>0),VLOOKUP($C83,'[1]Paramètres Articles'!$B:$G,6,FALSE),0),"Non Trouvé") | N83: =IFERROR(IF($C83="","",$M83*$H83),"Non Trouvé") | P83: 0.1 | R83: =IFERROR(IF($C83="","",$N83*(1-$P83)),"Non Trouvé") | T83: =IFERROR(IF($C83="","",VLOOKUP($C83,'[1]Paramètres Articles'!$B:$H,7,FALSE)),"Non Trouvé") | V83: =IFERROR(IF($C83="","",IF($P83="","",$T83*(1-$P83))),"Non Trouvé") | X83: =IFERROR(T83-V83,"") | Z83: =IFERROR(IF(OR(T83=0,T83=""),0,T83*H83),"Non Trouvé") | AB83: =AB81 | AC83: =AC81 | AD83: =IFERROR(IF($C83="","",IF($P$15="Cascade",$R83*(1-AC83)*AB83,IF($P$15="Additionnelle",($N83-($N83*($P83+AC83)))*AB83))),"Non Trouvé") | AG83: =AG81 | AH83: =AH81 | AI83: =IFERROR(IF($C83="","",IF($P$15="Cascade",$R83*(1-AH83)*AG83,IF($P$15="Additionnelle",($N83-($N83*($P83+AH83)))*AG83))),"Non Trouvé") | AL83: =AL81 | AM83: =AM81 | AN83: =IFERROR(IF($C83="","",IF($P$15="Cascade",$R83*(1-AM83)*AL83,IF($P$15="Additionnelle",($N83-($N83*($P83+AM83)))*AL83))),"Non Trouvé") | AQ83: =AQ81 | AR83: =AR81 | AS83: =IFERROR(IF($C83="","",IF($P$15="Cascade",$R83*(1-AR83)*AQ83,IF($P$15="Additionnelle",($N83-($N83*($P83+AR83)))*AQ83))),"Non Trouvé") | AV83: =AV81 | AW83: =AW81 | AX83: =IFERROR(IF($C83="","",IF($P$15="Cascade",$R83*(1-AW83)*AV83,IF($P$15="Additionnelle",($N83-($N83*($P83+AW83)))*AV83))),"Non Trouvé") | BA83: =BA81 | BB83: =BB81 | BC83: =IFERROR(IF($C83="","",IF($P$15="Cascade",$R83*(1-BB83)*BA83,IF($P$15="Additionnelle",($N83-($N83*($P83+BB83)))*BA83))),"Non Trouvé") | BF83: =BF81 | BG83: =BG81 | BH83: =IFERROR(IF($C83="","",IF($P$15="Cascade",$R83*(1-BG83)*BF83,IF($P$15="Additionnelle",($N83-($N83*($P83+BG83)))*BF83))),"Non Trouvé") | BK83: =BK81 | BL83: =BL81 | BM83: =IFERROR(IF($C83="","",IF($P$15="Cascade",$R83*(1-BL83)*BK83,IF($P$15="Additionnelle",($N83-($N83*($P83+BL83)))*BK83))),"Non Trouvé") | BP83: =BP81 | BQ83: =BQ81 | BR83: =IFERROR(IF($C83="","",IF($P$15="Cascade",$R83*(1-BQ83)*BP83,IF($P$15="Additionnelle",($N83-($N83*($P83+BQ83)))*BP83))),"Non Trouvé") | BU83: =BU81 | BV83: =BV81 | BW83: =IFERROR(IF($C83="","",IF($P$15="Cascade",$R83*(1-BV83)*BU83,IF($P$15="Additionnelle",($N83-($N83*($P83+BV83)))*BU83))),"Non Trouvé") | BZ83: =BZ81 | CA83: =CA81 | CB83: =IFERROR(IF($C83="","",IF($P$15="Cascade",$R83*(1-CA83)*BZ83,IF($P$15="Additionnelle",($N83-($N83*($P83+CA83)))*BZ83))),"Non Trouvé") | CG83: Echantillon | CH83: =SUMIFS(K77:K99,F77:F99,CG83)/K75 | CK83: =IFERROR(IF(F83='[1]Paramètres Généraux'!$K$12,ROUNDUP((REGENERANTS!H83*REGENERANTS!$CF$75)*'[1]Paramètres Généraux'!$M$12,-1),IF(F83='[1]Paramètres Généraux'!$K$15,ROUNDUP((REGENERANTS!H83*REGENERANTS!$CF$75)*'[1]Paramètres Généraux'!$M$15,-1),REGENERANTS!H83*REGENERANTS!$CF$75)),"nd") | DQ83: =SUM(CN83:DP83) | DR83: =SUM(CV83:DP83) | DS83: =IFERROR((IF(AND($F83="Produit Vente",CO83>0),VLOOKUP($C83,'[1]Paramètres Articles'!$B:$H,7,FALSE)*$CO83)*(1-20%)),0) | DT83: =IFERROR((IF(AND($F83="Produit Vente",DR83>0),VLOOKUP($C83,'[1]Paramètres Articles'!$B:$H,6,FALSE)*$DR83)*(1-15%)),0) | DU83: =IFERROR(DQ83*J83,0)
B84: =IF(C84="",0,COUNTIFS($B$22:B83,">"&0)+1) | C84: 1020722 | D84: =IFERROR(IF($C84="","",VLOOKUP($C84,'[1]Paramètres Articles'!$B:$G,2,FALSE)),"Non Trouvé") | E84: =IFERROR(IF($C84="","",_xlfn.XLOOKUP(REGENERANTS!$C84,'[1]New Base PA'!$F:$F,'[1]New Base PA'!$D:$D,"Not Found",0)),"Non Trouvé") | F84: Produit Vente | H84: 0 | J84: =IFERROR(IF($C84="","",VLOOKUP($C84,'[1]New Base PA'!$F:$J,5,FALSE)),"Non Trouvé") | K84: =IFERROR(IF($C84="","",$J84*$H84),"Non Trouvé") | M84: =IFERROR(IF(AND($F84="Produit Vente",H84>0),VLOOKUP($C84,'[1]Paramètres Articles'!$B:$G,6,FALSE),0),"Non Trouvé") | N84: =IFERROR(IF($C84="","",$M84*$H84),"Non Trouvé") | P84: 0.1 | R84: =IFERROR(IF($C84="","",$N84*(1-$P84)),"Non Trouvé") | T84: =IFERROR(IF($C84="","",VLOOKUP($C84,'[1]Paramètres Articles'!$B:$H,7,FALSE)),"Non Trouvé") | V84: =IFERROR(IF($C84="","",IF($P84="","",$T84*(1-$P84))),"Non Trouvé") | X84: =IFERROR(T84-V84,"") | Z84: =IFERROR(IF(OR(T84=0,T84=""),0,T84*H84),"Non Trouvé") | AB84: =AB82 | AC84: =AC82 | AD84: =IFERROR(IF($C84="","",IF($P$15="Cascade",$R84*(1-AC84)*AB84,IF($P$15="Additionnelle",($N84-($N84*($P84+AC84)))*AB84))),"Non Trouvé") | AG84: =AG82 | AH84: =AH82 | AI84: =IFERROR(IF($C84="","",IF($P$15="Cascade",$R84*(1-AH84)*AG84,IF($P$15="Additionnelle",($N84-($N84*($P84+AH84)))*AG84))),"Non Trouvé") | AL84: =AL82 | AM84: =AM82 | AN84: =IFERROR(IF($C84="","",IF($P$15="Cascade",$R84*(1-AM84)*AL84,IF($P$15="Additionnelle",($N84-($N84*($P84+AM84)))*AL84))),"Non Trouvé") | AQ84: =AQ82 | AR84: =AR82 | AS84: =IFERROR(IF($C84="","",IF($P$15="Cascade",$R84*(1-AR84)*AQ84,IF($P$15="Additionnelle",($N84-($N84*($P84+AR84)))*AQ84))),"Non Trouvé") | AV84: =AV82 | AW84: =AW82 | AX84: =IFERROR(IF($C84="","",IF($P$15="Cascade",$R84*(1-AW84)*AV84,IF($P$15="Additionnelle",($N84-($N84*($P84+AW84)))*AV84))),"Non Trouvé") | BA84: =BA82 | BB84: =BB82 | BC84: =IFERROR(IF($C84="","",IF($P$15="Cascade",$R84*(1-BB84)*BA84,IF($P$15="Additionnelle",($N84-($N84*($P84+BB84)))*BA84))),"Non Trouvé") | BF84: =BF82 | BG84: =BG82 | BH84: =IFERROR(IF($C84="","",IF($P$15="Cascade",$R84*(1-BG84)*BF84,IF($P$15="Additionnelle",($N84-($N84*($P84+BG84)))*BF84))),"Non Trouvé") | BK84: =BK82 | BL84: =BL82 | BM84: =IFERROR(IF($C84="","",IF($P$15="Cascade",$R84*(1-BL84)*BK84,IF($P$15="Additionnelle",($N84-($N84*($P84+BL84)))*BK84))),"Non Trouvé") | BP84: =BP82 | BQ84: =BQ82 | BR84: =IFERROR(IF($C84="","",IF($P$15="Cascade",$R84*(1-BQ84)*BP84,IF($P$15="Additionnelle",($N84-($N84*($P84+BQ84)))*BP84))),"Non Trouvé") | BU84: =BU82 | BV84: =BV82 | BW84: =IFERROR(IF($C84="","",IF($P$15="Cascade",$R84*(1-BV84)*BU84,IF($P$15="Additionnelle",($N84-($N84*($P84+BV84)))*BU84))),"Non Trouvé") | BZ84: =BZ82 | CA84: =CA82 | CB84: =IFERROR(IF($C84="","",IF($P$15="Cascade",$R84*(1-CA84)*BZ84,IF($P$15="Additionnelle",($N84-($N84*($P84+CA84)))*BZ84))),"Non Trouvé") | CG84: Testeur | CH84: =SUMIFS(K77:K99,F77:F99,CG84)/K75 | CK84: =IFERROR(IF(F84='[1]Paramètres Généraux'!$K$12,ROUNDUP((REGENERANTS!H84*REGENERANTS!$CF$75)*'[1]Paramètres Généraux'!$M$12,-1),IF(F84='[1]Paramètres Généraux'!$K$15,ROUNDUP((REGENERANTS!H84*REGENERANTS!$CF$75)*'[1]Paramètres Généraux'!$M$15,-1),REGENERANTS!H84*REGENERANTS!$CF$75)),"nd") | DQ84: =SUM(CN84:DP84) | DR84: =SUM(CV84:DP84) | DS84: =IFERROR((IF(AND($F84="Produit Vente",CO84>0),VLOOKUP($C84,'[1]Paramètres Articles'!$B:$H,7,FALSE)*$CO84)*(1-20%)),0) | DT84: =IFERROR((IF(AND($F84="Produit Vente",DR84>0),VLOOKUP($C84,'[1]Paramètres Articles'!$B:$H,6,FALSE)*$DR84)*(1-15%)),0) | DU84: =IFERROR(DQ84*J84,0)
B85: =IF(C85="",0,COUNTIFS($B$22:B84,">"&0)+1) | C85: 1020719 | D85: =IFERROR(IF($C85="","",VLOOKUP($C85,'[1]Paramètres Articles'!$B:$G,2,FALSE)),"Non Trouvé") | E85: =IFERROR(IF($C85="","",_xlfn.XLOOKUP(REGENERANTS!$C85,'[1]New Base PA'!$F:$F,'[1]New Base PA'!$D:$D,"Not Found",0)),"Non Trouvé") | F85: Produit Vente | H85: 2 | J85: =IFERROR(IF($C85="","",VLOOKUP($C85,'[1]New Base PA'!$F:$J,5,FALSE)),"Non Trouvé") | K85: =IFERROR(IF($C85="","",$J85*$H85),"Non Trouvé") | M85: =IFERROR(IF(AND($F85="Produit Vente",H85>0),VLOOKUP($C85,'[1]Paramètres Articles'!$B:$G,6,FALSE),0),"Non Trouvé") | N85: =IFERROR(IF($C85="","",$M85*$H85),"Non Trouvé") | P85: 0.1 | R85: =IFERROR(IF($C85="","",$N85*(1-$P85)),"Non Trouvé") | T85: =IFERROR(IF($C85="","",VLOOKUP($C85,'[1]Paramètres Articles'!$B:$H,7,FALSE)),"Non Trouvé") | V85: =IFERROR(IF($C85="","",IF($P85="","",$T85*(1-$P85))),"Non Trouvé") | X85: =IFERROR(T85-V85,"") | Z85: =IFERROR(IF(OR(T85=0,T85=""),0,T85*H85),"Non Trouvé") | AB85: =AB84 | AC85: =AC84 | AD85: =IFERROR(IF($C85="","",IF($P$15="Cascade",$R85*(1-AC85)*AB85,IF($P$15="Additionnelle",($N85-($N85*($P85+AC85)))*AB85))),"Non Trouvé") | AG85: =AG84 | AH85: =AH84 | AI85: =IFERROR(IF($C85="","",IF($P$15="Cascade",$R85*(1-AH85)*AG85,IF($P$15="Additionnelle",($N85-($N85*($P85+AH85)))*AG85))),"Non Trouvé") | AL85: =AL84 | AM85: =AM84 | AN85: =IFERROR(IF($C85="","",IF($P$15="Cascade",$R85*(1-AM85)*AL85,IF($P$15="Additionnelle",($N85-($N85*($P85+AM85)))*AL85))),"Non Trouvé") | AQ85: =AQ84 | AR85: =AR84 | AS85: =IFERROR(IF($C85="","",IF($P$15="Cascade",$R85*(1-AR85)*AQ85,IF($P$15="Additionnelle",($N85-($N85*($P85+AR85)))*AQ85))),"Non Trouvé") | AV85: =AV84 | AW85: =AW84 | AX85: =IFERROR(IF($C85="","",IF($P$15="Cascade",$R85*(1-AW85)*AV85,IF($P$15="Additionnelle",($N85-($N85*($P85+AW85)))*AV85))),"Non Trouvé") | BA85: =BA84 | BB85: =BB84 | BC85: =IFERROR(IF($C85="","",IF($P$15="Cascade",$R85*(1-BB85)*BA85,IF($P$15="Additionnelle",($N85-($N85*($P85+BB85)))*BA85))),"Non Trouvé") | BF85: =BF84 | BG85: =BG84 | BH85: =IFERROR(IF($C85="","",IF($P$15="Cascade",$R85*(1-BG85)*BF85,IF($P$15="Additionnelle",($N85-($N85*($P85+BG85)))*BF85))),"Non Trouvé") | BK85: =BK84 | BL85: =BL84 | BM85: =IFERROR(IF($C85="","",IF($P$15="Cascade",$R85*(1-BL85)*BK85,IF($P$15="Additionnelle",($N85-($N85*($P85+BL85)))*BK85))),"Non Trouvé") | BP85: =BP84 | BQ85: =BQ84 | BR85: =IFERROR(IF($C85="","",IF($P$15="Cascade",$R85*(1-BQ85)*BP85,IF($P$15="Additionnelle",($N85-($N85*($P85+BQ85)))*BP85))),"Non Trouvé") | BU85: =BU84 | BV85: =BV84 | BW85: =IFERROR(IF($C85="","",IF($P$15="Cascade",$R85*(1-BV85)*BU85,IF($P$15="Additionnelle",($N85-($N85*($P85+BV85)))*BU85))),"Non Trouvé") | BZ85: =BZ84 | CA85: =CA84 | CB85: =IFERROR(IF($C85="","",IF($P$15="Cascade",$R85*(1-CA85)*BZ85,IF($P$15="Additionnelle",($N85-($N85*($P85+CA85)))*BZ85))),"Non Trouvé") | CK85: =IFERROR(IF(F85='[1]Paramètres Généraux'!$K$12,ROUNDUP((REGENERANTS!H85*REGENERANTS!$CF$75)*'[1]Paramètres Généraux'!$M$12,-1),IF(F85='[1]Paramètres Généraux'!$K$15,ROUNDUP((REGENERANTS!H85*REGENERANTS!$CF$75)*'[1]Paramètres Généraux'!$M$15,-1),REGENERANTS!H85*REGENERANTS!$CF$75)),"nd") | DQ85: =SUM(CN85:DP85) | DR85: =SUM(CV85:DP85) | DS85: =IFERROR((IF(AND($F85="Produit Vente",CO85>0),VLOOKUP($C85,'[1]Paramètres Articles'!$B:$H,7,FALSE)*$CO85)*(1-20%)),0) | DT85: =IFERROR((IF(AND($F85="Produit Vente",DR85>0),VLOOKUP($C85,'[1]Paramètres Articles'!$B:$H,6,FALSE)*$DR85)*(1-15%)),0) | DU85: =IFERROR(DQ85*J85,0)
B86: =IF(C86="",0,COUNTIFS($B$22:B85,">"&0)+1) | C86: 1020717 | D86: =IFERROR(IF($C86="","",VLOOKUP($C86,'[1]Paramètres Articles'!$B:$G,2,FALSE)),"Non Trouvé") | E86: =IFERROR(IF($C86="","",_xlfn.XLOOKUP(REGENERANTS!$C86,'[1]New Base PA'!$F:$F,'[1]New Base PA'!$D:$D,"Not Found",0)),"Non Trouvé") | F86: Produit Vente | H86: 1 | J86: =IFERROR(IF($C86="","",VLOOKUP($C86,'[1]New Base PA'!$F:$J,5,FALSE)),"Non Trouvé") | K86: =IFERROR(IF($C86="","",$J86*$H86),"Non Trouvé") | M86: =IFERROR(IF(AND($F86="Produit Vente",H86>0),VLOOKUP($C86,'[1]Paramètres Articles'!$B:$G,6,FALSE),0),"Non Trouvé") | N86: =IFERROR(IF($C86="","",$M86*$H86),"Non Trouvé") | P86: 0.1 | R86: =IFERROR(IF($C86="","",$N86*(1-$P86)),"Non Trouvé") | T86: =IFERROR(IF($C86="","",VLOOKUP($C86,'[1]Paramètres Articles'!$B:$H,7,FALSE)),"Non Trouvé") | V86: =IFERROR(IF($C86="","",IF($P86="","",$T86*(1-$P86))),"Non Trouvé") | X86: =IFERROR(T86-V86,"") | Z86: =IFERROR(IF(OR(T86=0,T86=""),0,T86*H86),"Non Trouvé") | AB86: =AB84 | AC86: =AC84 | AD86: =IFERROR(IF($C86="","",IF($P$15="Cascade",$R86*(1-AC86)*AB86,IF($P$15="Additionnelle",($N86-($N86*($P86+AC86)))*AB86))),"Non Trouvé") | AG86: =AG84 | AH86: =AH84 | AI86: =IFERROR(IF($C86="","",IF($P$15="Cascade",$R86*(1-AH86)*AG86,IF($P$15="Additionnelle",($N86-($N86*($P86+AH86)))*AG86))),"Non Trouvé") | AL86: =AL84 | AM86: =AM84 | AN86: =IFERROR(IF($C86="","",IF($P$15="Cascade",$R86*(1-AM86)*AL86,IF($P$15="Additionnelle",($N86-($N86*($P86+AM86)))*AL86))),"Non Trouvé") | AQ86: =AQ84 | AR86: =AR84 | AS86: =IFERROR(IF($C86="","",IF($P$15="Cascade",$R86*(1-AR86)*AQ86,IF($P$15="Additionnelle",($N86-($N86*($P86+AR86)))*AQ86))),"Non Trouvé") | AV86: =AV84 | AW86: =AW84 | AX86: =IFERROR(IF($C86="","",IF($P$15="Cascade",$R86*(1-AW86)*AV86,IF($P$15="Additionnelle",($N86-($N86*($P86+AW86)))*AV86))),"Non Trouvé") | BA86: =BA84 | BB86: =BB84 | BC86: =IFERROR(IF($C86="","",IF($P$15="Cascade",$R86*(1-BB86)*BA86,IF($P$15="Additionnelle",($N86-($N86*($P86+BB86)))*BA86))),"Non Trouvé") | BF86: =BF84 | BG86: =BG84 | BH86: =IFERROR(IF($C86="","",IF($P$15="Cascade",$R86*(1-BG86)*BF86,IF($P$15="Additionnelle",($N86-($N86*($P86+BG86)))*BF86))),"Non Trouvé") | BK86: =BK84 | BL86: =BL84 | BM86: =IFERROR(IF($C86="","",IF($P$15="Cascade",$R86*(1-BL86)*BK86,IF($P$15="Additionnelle",($N86-($N86*($P86+BL86)))*BK86))),"Non Trouvé") | BP86: =BP84 | BQ86: =BQ84 | BR86: =IFERROR(IF($C86="","",IF($P$15="Cascade",$R86*(1-BQ86)*BP86,IF($P$15="Additionnelle",($N86-($N86*($P86+BQ86)))*BP86))),"Non Trouvé") | BU86: =BU84 | BV86: =BV84 | BW86: =IFERROR(IF($C86="","",IF($P$15="Cascade",$R86*(1-BV86)*BU86,IF($P$15="Additionnelle",($N86-($N86*($P86+BV86)))*BU86))),"Non Trouvé") | BZ86: =BZ84 | CA86: =CA84 | CB86: =IFERROR(IF($C86="","",IF($P$15="Cascade",$R86*(1-CA86)*BZ86,IF($P$15="Additionnelle",($N86-($N86*($P86+CA86)))*BZ86))),"Non Trouvé") | CK86: =IFERROR(IF(F86='[1]Paramètres Généraux'!$K$12,ROUNDUP((REGENERANTS!H86*REGENERANTS!$CF$75)*'[1]Paramètres Généraux'!$M$12,-1),IF(F86='[1]Paramètres Généraux'!$K$15,ROUNDUP((REGENERANTS!H86*REGENERANTS!$CF$75)*'[1]Paramètres Généraux'!$M$15,-1),REGENERANTS!H86*REGENERANTS!$CF$75)),"nd") | DQ86: =SUM(CN86:DP86) | DR86: =SUM(CV86:DP86) | DS86: =IFERROR((IF(AND($F86="Produit Vente",CO86>0),VLOOKUP($C86,'[1]Paramètres Articles'!$B:$H,7,FALSE)*$CO86)*(1-20%)),0) | DT86: =IFERROR((IF(AND($F86="Produit Vente",DR86>0),VLOOKUP($C86,'[1]Paramètres Articles'!$B:$H,6,FALSE)*$DR86)*(1-15%)),0) | DU86: =IFERROR(DQ86*J86,0)
B87: =IF(C87="",0,COUNTIFS($B$22:B86,">"&0)+1) | C87: 1020718 | D87: =IFERROR(IF($C87="","",VLOOKUP($C87,'[1]Paramètres Articles'!$B:$G,2,FALSE)),"Non Trouvé") | E87: =IFERROR(IF($C87="","",_xlfn.XLOOKUP(REGENERANTS!$C87,'[1]New Base PA'!$F:$F,'[1]New Base PA'!$D:$D,"Not Found",0)),"Non Trouvé") | F87: Produit Vente | H87: 3 | J87: =IFERROR(IF($C87="","",VLOOKUP($C87,'[1]New Base PA'!$F:$J,5,FALSE)),"Non Trouvé") | K87: =IFERROR(IF($C87="","",$J87*$H87),"Non Trouvé") | M87: =IFERROR(IF(AND($F87="Produit Vente",H87>0),VLOOKUP($C87,'[1]Paramètres Articles'!$B:$G,6,FALSE),0),"Non Trouvé") | N87: =IFERROR(IF($C87="","",$M87*$H87),"Non Trouvé") | P87: 0.1 | R87: =IFERROR(IF($C87="","",$N87*(1-$P87)),"Non Trouvé") | T87: =IFERROR(IF($C87="","",VLOOKUP($C87,'[1]Paramètres Articles'!$B:$H,7,FALSE)),"Non Trouvé") | V87: =IFERROR(IF($C87="","",IF($P87="","",$T87*(1-$P87))),"Non Trouvé") | X87: =IFERROR(T87-V87,"") | Z87: =IFERROR(IF(OR(T87=0,T87=""),0,T87*H87),"Non Trouvé") | AB87: =AB86 | AC87: =AC86 | AD87: =IFERROR(IF($C87="","",IF($P$15="Cascade",$R87*(1-AC87)*AB87,IF($P$15="Additionnelle",($N87-($N87*($P87+AC87)))*AB87))),"Non Trouvé") | AG87: =AG86 | AH87: =AH86 | AI87: =IFERROR(IF($C87="","",IF($P$15="Cascade",$R87*(1-AH87)*AG87,IF($P$15="Additionnelle",($N87-($N87*($P87+AH87)))*AG87))),"Non Trouvé") | AL87: =AL86 | AM87: =AM86 | AN87: =IFERROR(IF($C87="","",IF($P$15="Cascade",$R87*(1-AM87)*AL87,IF($P$15="Additionnelle",($N87-($N87*($P87+AM87)))*AL87))),"Non Trouvé") | AQ87: =AQ86 | AR87: =AR86 | AS87: =IFERROR(IF($C87="","",IF($P$15="Cascade",$R87*(1-AR87)*AQ87,IF($P$15="Additionnelle",($N87-($N87*($P87+AR87)))*AQ87))),"Non Trouvé") | AV87: =AV86 | AW87: =AW86 | AX87: =IFERROR(IF($C87="","",IF($P$15="Cascade",$R87*(1-AW87)*AV87,IF($P$15="Additionnelle",($N87-($N87*($P87+AW87)))*AV87))),"Non Trouvé") | BA87: =BA86 | BB87: =BB86 | BC87: =IFERROR(IF($C87="","",IF($P$15="Cascade",$R87*(1-BB87)*BA87,IF($P$15="Additionnelle",($N87-($N87*($P87+BB87)))*BA87))),"Non Trouvé") | BF87: =BF86 | BG87: =BG86 | BH87: =IFERROR(IF($C87="","",IF($P$15="Cascade",$R87*(1-BG87)*BF87,IF($P$15="Additionnelle",($N87-($N87*($P87+BG87)))*BF87))),"Non Trouvé") | BK87: =BK86 | BL87: =BL86 | BM87: =IFERROR(IF($C87="","",IF($P$15="Cascade",$R87*(1-BL87)*BK87,IF($P$15="Additionnelle",($N87-($N87*($P87+BL87)))*BK87))),"Non Trouvé") | BP87: =BP86 | BQ87: =BQ86 | BR87: =IFERROR(IF($C87="","",IF($P$15="Cascade",$R87*(1-BQ87)*BP87,IF($P$15="Additionnelle",($N87-($N87*($P87+BQ87)))*BP87))),"Non Trouvé") | BU87: =BU86 | BV87: =BV86 | BW87: =IFERROR(IF($C87="","",IF($P$15="Cascade",$R87*(1-BV87)*BU87,IF($P$15="Additionnelle",($N87-($N87*($P87+BV87)))*BU87))),"Non Trouvé") | BZ87: =BZ86 | CA87: =CA86 | CB87: =IFERROR(IF($C87="","",IF($P$15="Cascade",$R87*(1-CA87)*BZ87,IF($P$15="Additionnelle",($N87-($N87*($P87+CA87)))*BZ87))),"Non Trouvé") | CK87: =IFERROR(IF(F87='[1]Paramètres Généraux'!$K$12,ROUNDUP((REGENERANTS!H87*REGENERANTS!$CF$75)*'[1]Paramètres Généraux'!$M$12,-1),IF(F87='[1]Paramètres Généraux'!$K$15,ROUNDUP((REGENERANTS!H87*REGENERANTS!$CF$75)*'[1]Paramètres Généraux'!$M$15,-1),REGENERANTS!H87*REGENERANTS!$CF$75)),"nd") | DQ87: =SUM(CN87:DP87) | DR87: =SUM(CV87:DP87) | DS87: =IFERROR((IF(AND($F87="Produit Vente",CO87>0),VLOOKUP($C87,'[1]Paramètres Articles'!$B:$H,7,FALSE)*$CO87)*(1-20%)),0) | DT87: =IFERROR((IF(AND($F87="Produit Vente",DR87>0),VLOOKUP($C87,'[1]Paramètres Articles'!$B:$H,6,FALSE)*$DR87)*(1-15%)),0) | DU87: =IFERROR(DQ87*J87,0)
B88: =IF(C88="",0,COUNTIFS($B$22:B87,">"&0)+1) | C88: 1020301 | D88: =IFERROR(IF($C88="","",VLOOKUP($C88,'[1]Paramètres Articles'!$B:$G,2,FALSE)),"Non Trouvé") | E88: =IFERROR(IF($C88="","",_xlfn.XLOOKUP(REGENERANTS!$C88,'[1]New Base PA'!$F:$F,'[1]New Base PA'!$D:$D,"Not Found",0)),"Non Trouvé") | F88: Produit Vente | H88: 4 | J88: =IFERROR(IF($C88="","",VLOOKUP($C88,'[1]New Base PA'!$F:$J,5,FALSE)),"Non Trouvé") | K88: =IFERROR(IF($C88="","",$J88*$H88),"Non Trouvé") | M88: =IFERROR(IF(AND($F88="Produit Vente",H88>0),VLOOKUP($C88,'[1]Paramètres Articles'!$B:$G,6,FALSE),0),"Non Trouvé") | N88: =IFERROR(IF($C88="","",$M88*$H88),"Non Trouvé") | P88: 0.1 | R88: =IFERROR(IF($C88="","",$N88*(1-$P88)),"Non Trouvé") | T88: =IFERROR(IF($C88="","",VLOOKUP($C88,'[1]Paramètres Articles'!$B:$H,7,FALSE)),"Non Trouvé") | V88: =IFERROR(IF($C88="","",IF($P88="","",$T88*(1-$P88))),"Non Trouvé") | X88: =IFERROR(T88-V88,"") | Z88: =IFERROR(IF(OR(T88=0,T88=""),0,T88*H88),"Non Trouvé") | AB88: =AB86 | AC88: =AC86 | AD88: =IFERROR(IF($C88="","",IF($P$15="Cascade",$R88*(1-AC88)*AB88,IF($P$15="Additionnelle",($N88-($N88*($P88+AC88)))*AB88))),"Non Trouvé") | AG88: =AG86 | AH88: =AH86 | AI88: =IFERROR(IF($C88="","",IF($P$15="Cascade",$R88*(1-AH88)*AG88,IF($P$15="Additionnelle",($N88-($N88*($P88+AH88)))*AG88))),"Non Trouvé") | AL88: =AL86 | AM88: =AM86 | AN88: =IFERROR(IF($C88="","",IF($P$15="Cascade",$R88*(1-AM88)*AL88,IF($P$15="Additionnelle",($N88-($N88*($P88+AM88)))*AL88))),"Non Trouvé") | AQ88: =AQ86 | AR88: =AR86 | AS88: =IFERROR(IF($C88="","",IF($P$15="Cascade",$R88*(1-AR88)*AQ88,IF($P$15="Additionnelle",($N88-($N88*($P88+AR88)))*AQ88))),"Non Trouvé") | AV88: =AV86 | AW88: =AW86 | AX88: =IFERROR(IF($C88="","",IF($P$15="Cascade",$R88*(1-AW88)*AV88,IF($P$15="Additionnelle",($N88-($N88*($P88+AW88)))*AV88))),"Non Trouvé") | BA88: =BA86 | BB88: =BB86 | BC88: =IFERROR(IF($C88="","",IF($P$15="Cascade",$R88*(1-BB88)*BA88,IF($P$15="Additionnelle",($N88-($N88*($P88+BB88)))*BA88))),"Non Trouvé") | BF88: =BF86 | BG88: =BG86 | BH88: =IFERROR(IF($C88="","",IF($P$15="Cascade",$R88*(1-BG88)*BF88,IF($P$15="Additionnelle",($N88-($N88*($P88+BG88)))*BF88))),"Non Trouvé") | BK88: =BK86 | BL88: =BL86 | BM88: =IFERROR(IF($C88="","",IF($P$15="Cascade",$R88*(1-BL88)*BK88,IF($P$15="Additionnelle",($N88-($N88*($P88+BL88)))*BK88))),"Non Trouvé") | BP88: =BP86 | BQ88: =BQ86 | BR88: =IFERROR(IF($C88="","",IF($P$15="Cascade",$R88*(1-BQ88)*BP88,IF($P$15="Additionnelle",($N88-($N88*($P88+BQ88)))*BP88))),"Non Trouvé") | BU88: =BU86 | BV88: =BV86 | BW88: =IFERROR(IF($C88="","",IF($P$15="Cascade",$R88*(1-BV88)*BU88,IF($P$15="Additionnelle",($N88-($N88*($P88+BV88)))*BU88))),"Non Trouvé") | BZ88: =BZ86 | CA88: =CA86 | CB88: =IFERROR(IF($C88="","",IF($P$15="Cascade",$R88*(1-CA88)*BZ88,IF($P$15="Additionnelle",($N88-($N88*($P88+CA88)))*BZ88))),"Non Trouvé") | CK88: =IFERROR(IF(F88='[1]Paramètres Généraux'!$K$12,ROUNDUP((REGENERANTS!H88*REGENERANTS!$CF$75)*'[1]Paramètres Généraux'!$M$12,-1),IF(F88='[1]Paramètres Généraux'!$K$15,ROUNDUP((REGENERANTS!H88*REGENERANTS!$CF$75)*'[1]Paramètres Généraux'!$M$15,-1),REGENERANTS!H88*REGENERANTS!$CF$75)),"nd") | DQ88: =SUM(CN88:DP88) | DR88: =SUM(CV88:DP88) | DS88: =IFERROR((IF(AND($F88="Produit Vente",CO88>0),VLOOKUP($C88,'[1]Paramètres Articles'!$B:$H,7,FALSE)*$CO88)*(1-20%)),0) | DT88: =IFERROR((IF(AND($F88="Produit Vente",DR88>0),VLOOKUP($C88,'[1]Paramètres Articles'!$B:$H,6,FALSE)*$DR88)*(1-15%)),0) | DU88: =IFERROR(DQ88*J88,0)
B89: =IF(C89="",0,COUNTIFS($B$22:B88,">"&0)+1) | C89: 1020720 | D89: =IFERROR(IF($C89="","",VLOOKUP($C89,'[1]Paramètres Articles'!$B:$G,2,FALSE)),"Non Trouvé") | E89: =IFERROR(IF($C89="","",_xlfn.XLOOKUP(REGENERANTS!$C89,'[1]New Base PA'!$F:$F,'[1]New Base PA'!$D:$D,"Not Found",0)),"Non Trouvé") | F89: Produit Vente | H89: 4 | J89: =IFERROR(IF($C89="","",VLOOKUP($C89,'[1]New Base PA'!$F:$J,5,FALSE)),"Non Trouvé") | K89: =IFERROR(IF($C89="","",$J89*$H89),"Non Trouvé") | M89: =IFERROR(IF(AND($F89="Produit Vente",H89>0),VLOOKUP($C89,'[1]Paramètres Articles'!$B:$G,6,FALSE),0),"Non Trouvé") | N89: =IFERROR(IF($C89="","",$M89*$H89),"Non Trouvé") | P89: 0.1 | R89: =IFERROR(IF($C89="","",$N89*(1-$P89)),"Non Trouvé") | T89: =IFERROR(IF($C89="","",VLOOKUP($C89,'[1]Paramètres Articles'!$B:$H,7,FALSE)),"Non Trouvé") | V89: =IFERROR(IF($C89="","",IF($P89="","",$T89*(1-$P89))),"Non Trouvé") | X89: =IFERROR(T89-V89,"") | Z89: =IFERROR(IF(OR(T89=0,T89=""),0,T89*H89),"Non Trouvé") | AB89: =AB88 | AC89: =AC88 | AD89: =IFERROR(IF($C89="","",IF($P$15="Cascade",$R89*(1-AC89)*AB89,IF($P$15="Additionnelle",($N89-($N89*($P89+AC89)))*AB89))),"Non Trouvé") | AG89: =AG88 | AH89: =AH88 | AI89: =IFERROR(IF($C89="","",IF($P$15="Cascade",$R89*(1-AH89)*AG89,IF($P$15="Additionnelle",($N89-($N89*($P89+AH89)))*AG89))),"Non Trouvé") | AL89: =AL88 | AM89: =AM88 | AN89: =IFERROR(IF($C89="","",IF($P$15="Cascade",$R89*(1-AM89)*AL89,IF($P$15="Additionnelle",($N89-($N89*($P89+AM89)))*AL89))),"Non Trouvé") | AQ89: =AQ88 | AR89: =AR88 | AS89: =IFERROR(IF($C89="","",IF($P$15="Cascade",$R89*(1-AR89)*AQ89,IF($P$15="Additionnelle",($N89-($N89*($P89+AR89)))*AQ89))),"Non Trouvé") | AV89: =AV88 | AW89: =AW88 | AX89: =IFERROR(IF($C89="","",IF($P$15="Cascade",$R89*(1-AW89)*AV89,IF($P$15="Additionnelle",($N89-($N89*($P89+AW89)))*AV89))),"Non Trouvé") | BA89: =BA88 | BB89: =BB88 | BC89: =IFERROR(IF($C89="","",IF($P$15="Cascade",$R89*(1-BB89)*BA89,IF($P$15="Additionnelle",($N89-($N89*($P89+BB89)))*BA89))),"Non Trouvé") | BF89: =BF88 | BG89: =BG88 | BH89: =IFERROR(IF($C89="","",IF($P$15="Cascade",$R89*(1-BG89)*BF89,IF($P$15="Additionnelle",($N89-($N89*($P89+BG89)))*BF89))),"Non Trouvé") | BK89: =BK88 | BL89: =BL88 | BM89: =IFERROR(IF($C89="","",IF($P$15="Cascade",$R89*(1-BL89)*BK89,IF($P$15="Additionnelle",($N89-($N89*($P89+BL89)))*BK89))),"Non Trouvé") | BP89: =BP88 | BQ89: =BQ88 | BR89: =IFERROR(IF($C89="","",IF($P$15="Cascade",$R89*(1-BQ89)*BP89,IF($P$15="Additionnelle",($N89-($N89*($P89+BQ89)))*BP89))),"Non Trouvé") | BU89: =BU88 | BV89: =BV88 | BW89: =IFERROR(IF($C89="","",IF($P$15="Cascade",$R89*(1-BV89)*BU89,IF($P$15="Additionnelle",($N89-($N89*($P89+BV89)))*BU89))),"Non Trouvé") | BZ89: =BZ88 | CA89: =CA88 | CB89: =IFERROR(IF($C89="","",IF($P$15="Cascade",$R89*(1-CA89)*BZ89,IF($P$15="Additionnelle",($N89-($N89*($P89+CA89)))*BZ89))),"Non Trouvé") | CG89: Retail | CK89: =IFERROR(IF(F89='[1]Paramètres Généraux'!$K$12,ROUNDUP((REGENERANTS!H89*REGENERANTS!$CF$75)*'[1]Paramètres Généraux'!$M$12,-1),IF(F89='[1]Paramètres Généraux'!$K$15,ROUNDUP((REGENERANTS!H89*REGENERANTS!$CF$75)*'[1]Paramètres Généraux'!$M$15,-1),REGENERANTS!H89*REGENERANTS!$CF$75)),"nd") | DQ89: =SUM(CN89:DP89) | DR89: =SUM(CV89:DP89) | DS89: =IFERROR((IF(AND($F89="Produit Vente",CO89>0),VLOOKUP($C89,'[1]Paramètres Articles'!$B:$H,7,FALSE)*$CO89)*(1-20%)),0) | DT89: =IFERROR((IF(AND($F89="Produit Vente",DR89>0),VLOOKUP($C89,'[1]Paramètres Articles'!$B:$H,6,FALSE)*$DR89)*(1-15%)),0) | DU89: =IFERROR(DQ89*J89,0)
