Workbook

Sheet Proposition template
A3: TG VIP
A4: Nombre d'offres
A5: Nombre de produits | B5: =SUM(E17:E29) -> 0
M6: RETAIL | S6: INSTITUT | AB6: Retail + Institut
M8: Ambassadeur | O8: Compagnon | Q8: Challenger | S8: Rose | U8: Prunelier | W8: Anthylide | Y8: Calendula | AB8: Total
M9: % Offres | O9: % Offres | Q9: % Offres | S9: % Offres | U9: % Offres | W9: % Offres
M10: Remise | N10: 0.17 | O10: Remise | P10: 0.13 | Q10: Remise | R10: 0.08 | S10: Remise | T10: 0.325 | U10: Remise | V10: 0.3 | W10: Remise | X10: 0.28 | Y10: Remise | Z10: 0.25
M11: Nb Offres | N11: =N9*$B$4 -> 0 | O11: Nb Offres | P11: =P9*$B$4 -> 0 | Q11: Nb Offres | R11: =R9*$B$4 -> 0 | S11: Nb Offres | T11: =T9*$B$4 -> 0 | U11: Nb Offres | V11: =V9*$B$4 -> 0 | W11: Nb Offres | X11: =X9*$B$4 -> 0 | Y11: Nb Offres | Z11: =Z9*$B$4 -> 0
E12: Pdt dans offre | F12: Coût achat unitaire | G12: Coûts achats total | H12: Tarif revendeur unitaire | I12: Remise additionnelle | J12: PPC | K12: PPC Remisé | L12: Montant BRI | M12: CA | N12: Marges | O12: CA | P12: Marges | Q12: CA | R12: Marges | S12: CA | T12: Marges | U12: CA | V12: Marges | W12: CA | X12: Marges | Y12: CA | Z12: Marges | AB12: Nbrs Offres planifiées | AC12: CA | AD12: Marges
A13: Code article | B13: Libellé article | C13: Code à barres (EAN) | D13: Typ. Prod | E13: '# | F13: '€ | G13: '€ | H13: '€ | I13: '€ | J13: '€ | K13: '€ | L13: '€ | M13: '€ | N13: '€ | O13: '€ | P13: '€ | Q13: '€ | R13: '€ | S13: '€ | T13: '€ | U13: '€ | V13: '€ | W13: '€ | X13: '€ | Y13: '€ | Z13: '€ | AB13: '# | AC13: '€ | AD13: '€
A15: Synthèse | E15: =IFERROR(SUMIFS(E17:E36,D17:D36,"Produit Vente"),"Non trouvé") -> 0 | G15: =IFERROR(SUM(G17:G36),"Non Trouvé") -> 0 | M15: =SUM(M17:M36) -> 0 | N15: =SUM(N17:N36) -> 0 | O15: =SUM(O17:O36) -> 0 | P15: =SUM(P17:P36) -> 0 | Q15: =SUM(Q17:Q36) -> 0 | R15: =SUM(R17:R36) -> 0 | S15: =SUM(S17:S36) -> 0 | T15: =SUM(T17:T36) -> 0 | ... Z15: =SUM(Z17:Z36) -> 0 | AB15: =B4 -> 0 | AC15: =Y15+W15+U15+S15+O15+M15+Q15 -> 0 | AD15: =Z15+X15+V15+T15+P15+N15+R15 -> 0
B17: =IFERROR(VLOOKUP(A17,Mapping!$A:$F,2,FALSE),"") | C17: =IFERROR(VLOOKUP(A17,Mapping!$A:$F,3,FALSE),"") | F17: =IFERROR(VLOOKUP(A17,Mapping!$A:$F,4,FALSE),0) -> 0 | G17: =E17*F17 -> 0 | H17: =IFERROR(VLOOKUP(A17,Mapping!$A:$F,5,FALSE),0) -> 0 | J17: =IFERROR(VLOOKUP(A17,Mapping!$A:$F,6,FALSE),0) -> 0 | K17: =J17*(1-I17) -> 0 | L17: =IFERROR(J17-K17,"") -> 0 | M17: =E17*H17*(1-I17)*$N$11*(1-$N$10) -> 0 | N17: =M17-E17*F17*$N$11 -> 0 | O17: =E17*H17*(1-I17)*$P$11*(1-$P$10) -> 0 | P17: =O17-E17*F17*$P$11 -> 0 | Q17: =E17*H17*(1-I17)*$R$11*(1-$R$10) -> 0 | R17: =Q17-E17*F17*$R$11 -> 0 | S17: =E17*H17*(1-I17)*$T$11*(1-$T$10) -> 0 | T17: =S17-E17*F17*$T$11 -> 0 | U17: =E17*H17*(1-I17)*$V$11*(1-$V$10) -> 0 | V17: =U17-E17*F17*$V$11 -> 0 | W17: =E17*H17*(1-I17)*$X$11*(1-$X$10) -> 0 | X17: =W17-E17*F17*$X$11 -> 0 | Y17: =E17*H17*(1-I17)*$Z$11*(1-$Z$10) -> 0 | Z17: =Y17-E17*F17*$Z$11 -> 0
B18: =IFERROR(VLOOKUP(A18,Mapping!$A:$F,2,FALSE),"") | C18: =IFERROR(VLOOKUP(A18,Mapping!$A:$F,3,FALSE),"") | F18: =IFERROR(VLOOKUP(A18,Mapping!$A:$F,4,FALSE),0) -> 0 | G18: =E18*F18 -> 0 | H18: =IFERROR(VLOOKUP(A18,Mapping!$A:$F,5,FALSE),0) -> 0 | J18: =IFERROR(VLOOKUP(A18,Mapping!$A:$F,6,FALSE),0) -> 0 | K18: =J18*(1-I18) -> 0 | L18: =IFERROR(J18-K18,"") -> 0 | M18: =E18*H18*(1-I18)*$N$11*(1-$N$10) -> 0 | N18: =M18-E18*F18*$N$11 -> 0 | O18: =E18*H18*(1-I18)*$P$11*(1-$P$10) -> 0 | P18: =O18-E18*F18*$P$11 -> 0 | Q18: =E18*H18*(1-I18)*$R$11*(1-$R$10) -> 0 | R18: =Q18-E18*F18*$R$11 -> 0 | S18: =E18*H18*(1-I18)*$T$11*(1-$T$10) -> 0 | T18: =S18-E18*F18*$T$11 -> 0 | U18: =E18*H18*(1-I18)*$V$11*(1-$V$10) -> 0 | V18: =U18-E18*F18*$V$11 -> 0 | W18: =E18*H18*(1-I18)*$X$11*(1-$X$10) -> 0 | X18: =W18-E18*F18*$X$11 -> 0 | Y18: =E18*H18*(1-I18)*$Z$11*(1-$Z$10) -> 0 | Z18: =Y18-E18*F18*$Z$11 -> 0 | AC18: Prix Offre Moy. Remisé : | AD18: =AC15/AB15 -> #DIV/0!
B19: =IFERROR(VLOOKUP(A19,Mapping!$A:$F,2,FALSE),"") | C19: =IFERROR(VLOOKUP(A19,Mapping!$A:$F,3,FALSE),"") | F19: =IFERROR(VLOOKUP(A19,Mapping!$A:$F,4,FALSE),0) -> 0 | G19: =E19*F19 -> 0 | H19: =IFERROR(VLOOKUP(A19,Mapping!$A:$F,5,FALSE),0) -> 0 | J19: =IFERROR(VLOOKUP(A19,Mapping!$A:$F,6,FALSE),0) -> 0 | K19: =J19*(1-I19) -> 0 | L19: =IFERROR(J19-K19,"") -> 0 | M19: =E19*H19*(1-I19)*$N$11*(1-$N$10) -> 0 | N19: =M19-E19*F19*$N$11 -> 0 | O19: =E19*H19*(1-I19)*$P$11*(1-$P$10) -> 0 | P19: =O19-E19*F19*$P$11 -> 0 | Q19: =E19*H19*(1-I19)*$R$11*(1-$R$10) -> 0 | R19: =Q19-E19*F19*$R$11 -> 0 | S19: =E19*H19*(1-I19)*$T$11*(1-$T$10) -> 0 | T19: =S19-E19*F19*$T$11 -> 0 | U19: =E19*H19*(1-I19)*$V$11*(1-$V$10) -> 0 | V19: =U19-E19*F19*$V$11 -> 0 | W19: =E19*H19*(1-I19)*$X$11*(1-$X$10) -> 0 | X19: =W19-E19*F19*$X$11 -> 0 | Y19: =E19*H19*(1-I19)*$Z$11*(1-$Z$10) -> 0 | Z19: =Y19-E19*F19*$Z$11 -> 0 | AC19: Poids Gratuités achats : | AD19: =SUM(AD21:AD24) -> #DIV/0!
B20: =IFERROR(VLOOKUP(A20,Mapping!$A:$F,2,FALSE),"") | C20: =IFERROR(VLOOKUP(A20,Mapping!$A:$F,3,FALSE),"") | F20: =IFERROR(VLOOKUP(A20,Mapping!$A:$F,4,FALSE),0) -> 0 | G20: =E20*F20 -> 0 | H20: =IFERROR(VLOOKUP(A20,Mapping!$A:$F,5,FALSE),0) -> 0 | J20: =IFERROR(VLOOKUP(A20,Mapping!$A:$F,6,FALSE),0) -> 0 | K20: =J20*(1-I20) -> 0 | L20: =IFERROR(J20-K20,"") -> 0 | M20: =E20*H20*(1-I20)*$N$11*(1-$N$10) -> 0 | N20: =M20-E20*F20*$N$11 -> 0 | O20: =E20*H20*(1-I20)*$P$11*(1-$P$10) -> 0 | P20: =O20-E20*F20*$P$11 -> 0 | Q20: =E20*H20*(1-I20)*$R$11*(1-$R$10) -> 0 | R20: =Q20-E20*F20*$R$11 -> 0 | S20: =E20*H20*(1-I20)*$T$11*(1-$T$10) -> 0 | T20: =S20-E20*F20*$T$11 -> 0 | U20: =E20*H20*(1-I20)*$V$11*(1-$V$10) -> 0 | V20: =U20-E20*F20*$V$11 -> 0 | W20: =E20*H20*(1-I20)*$X$11*(1-$X$10) -> 0 | X20: =W20-E20*F20*$X$11 -> 0 | Y20: =E20*H20*(1-I20)*$Z$11*(1-$Z$10) -> 0 | Z20: =Y20-E20*F20*$Z$11 -> 0
B21: =IFERROR(VLOOKUP(A21,Mapping!$A:$F,2,FALSE),"") | C21: =IFERROR(VLOOKUP(A21,Mapping!$A:$F,3,FALSE),"") | F21: =IFERROR(VLOOKUP(A21,Mapping!$A:$F,4,FALSE),0) -> 0 | G21: =E21*F21 -> 0 | H21: =IFERROR(VLOOKUP(A21,Mapping!$A:$F,5,FALSE),0) -> 0 | J21: =IFERROR(VLOOKUP(A21,Mapping!$A:$F,6,FALSE),0) -> 0 | K21: =J21*(1-I21) -> 0 | L21: =IFERROR(J21-K21,"") -> 0 | M21: =E21*H21*(1-I21)*$N$11*(1-$N$10) -> 0 | N21: =M21-E21*F21*$N$11 -> 0 | O21: =E21*H21*(1-I21)*$P$11*(1-$P$10) -> 0 | P21: =O21-E21*F21*$P$11 -> 0 | Q21: =E21*H21*(1-I21)*$R$11*(1-$R$10) -> 0 | R21: =Q21-E21*F21*$R$11 -> 0 | S21: =E21*H21*(1-I21)*$T$11*(1-$T$10) -> 0 | T21: =S21-E21*F21*$T$11 -> 0 | U21: =E21*H21*(1-I21)*$V$11*(1-$V$10) -> 0 | V21: =U21-E21*F21*$V$11 -> 0 | W21: =E21*H21*(1-I21)*$X$11*(1-$X$10) -> 0 | X21: =W21-E21*F21*$X$11 -> 0 | Y21: =E21*H21*(1-I21)*$Z$11*(1-$Z$10) -> 0 | Z21: =Y21-E21*F21*$Z$11 -> 0 | AC21: UG | AD21: =SUMIF($D$16:$D$36,AC21,$G$16:$G$36)/$AC$15 -> #DIV/0!
B22: =IFERROR(VLOOKUP(A22,Mapping!$A:$F,2,FALSE),"") | C22: =IFERROR(VLOOKUP(A22,Mapping!$A:$F,3,FALSE),"") | F22: =IFERROR(VLOOKUP(A22,Mapping!$A:$F,4,FALSE),0) -> 0 | G22: =E22*F22 -> 0 | H22: =IFERROR(VLOOKUP(A22,Mapping!$A:$F,5,FALSE),0) -> 0 | J22: =IFERROR(VLOOKUP(A22,Mapping!$A:$F,6,FALSE),0) -> 0 | K22: =J22*(1-I22) -> 0 | L22: =IFERROR(J22-K22,"") -> 0 | M22: =E22*H22*(1-I22)*$N$11*(1-$N$10) -> 0 | N22: =M22-E22*F22*$N$11 -> 0 | O22: =E22*H22*(1-I22)*$P$11*(1-$P$10) -> 0 | P22: =O22-E22*F22*$P$11 -> 0 | Q22: =E22*H22*(1-I22)*$R$11*(1-$R$10) -> 0 | R22: =Q22-E22*F22*$R$11 -> 0 | S22: =E22*H22*(1-I22)*$T$11*(1-$T$10) -> 0 | T22: =S22-E22*F22*$T$11 -> 0 | U22: =E22*H22*(1-I22)*$V$11*(1-$V$10) -> 0 | V22: =U22-E22*F22*$V$11 -> 0 | W22: =E22*H22*(1-I22)*$X$11*(1-$X$10) -> 0 | X22: =W22-E22*F22*$X$11 -> 0 | Y22: =E22*H22*(1-I22)*$Z$11*(1-$Z$10) -> 0 | Z22: =Y22-E22*F22*$Z$11 -> 0 | AC22: PLV | AD22: =SUMIF($D$16:$D$36,AC22,$G$16:$G$36)/$AC$15 -> #DIV/0!
B23: =IFERROR(VLOOKUP(A23,Mapping!$A:$F,2,FALSE),"") | C23: =IFERROR(VLOOKUP(A23,Mapping!$A:$F,3,FALSE),"") | F23: =IFERROR(VLOOKUP(A23,Mapping!$A:$F,4,FALSE),0) -> 0 | G23: =E23*F23 -> 0 | H23: =IFERROR(VLOOKUP(A23,Mapping!$A:$F,5,FALSE),0) -> 0 | J23: =IFERROR(VLOOKUP(A23,Mapping!$A:$F,6,FALSE),0) -> 0 | K23: =J23*(1-I23) -> 0 | L23: =IFERROR(J23-K23,"") -> 0 | M23: =E23*H23*(1-I23)*$N$11*(1-$N$10) -> 0 | N23: =M23-E23*F23*$N$11 -> 0 | O23: =E23*H23*(1-I23)*$P$11*(1-$P$10) -> 0 | P23: =O23-E23*F23*$P$11 -> 0 | Q23: =E23*H23*(1-I23)*$R$11*(1-$R$10) -> 0 | R23: =Q23-E23*F23*$R$11 -> 0 | S23: =E23*H23*(1-I23)*$T$11*(1-$T$10) -> 0 | T23: =S23-E23*F23*$T$11 -> 0 | U23: =E23*H23*(1-I23)*$V$11*(1-$V$10) -> 0 | V23: =U23-E23*F23*$V$11 -> 0 | W23: =E23*H23*(1-I23)*$X$11*(1-$X$10) -> 0 | X23: =W23-E23*F23*$X$11 -> 0 | Y23: =E23*H23*(1-I23)*$Z$11*(1-$Z$10) -> 0 | Z23: =Y23-E23*F23*$Z$11 -> 0 | AC23: Echantillon | AD23: =SUMIF($D$16:$D$36,AC23,$G$16:$G$36)/$AC$15 -> #DIV/0!
B24: =IFERROR(VLOOKUP(A24,Mapping!$A:$F,2,FALSE),"") | C24: =IFERROR(VLOOKUP(A24,Mapping!$A:$F,3,FALSE),"") | F24: =IFERROR(VLOOKUP(A24,Mapping!$A:$F,4,FALSE),0) -> 0 | G24: =E24*F24 -> 0 | H24: =IFERROR(VLOOKUP(A24,Mapping!$A:$F,5,FALSE),0) -> 0 | J24: =IFERROR(VLOOKUP(A24,Mapping!$A:$F,6,FALSE),0) -> 0 | K24: =J24*(1-I24) -> 0 | L24: =IFERROR(J24-K24,"") -> 0 | M24: =E24*H24*(1-I24)*$N$11*(1-$N$10) -> 0 | N24: =M24-E24*F24*$N$11 -> 0 | O24: =E24*H24*(1-I24)*$P$11*(1-$P$10) -> 0 | P24: =O24-E24*F24*$P$11 -> 0 | Q24: =E24*H24*(1-I24)*$R$11*(1-$R$10) -> 0 | R24: =Q24-E24*F24*$R$11 -> 0 | S24: =E24*H24*(1-I24)*$T$11*(1-$T$10) -> 0 | T24: =S24-E24*F24*$T$11 -> 0 | U24: =E24*H24*(1-I24)*$V$11*(1-$V$10) -> 0 | V24: =U24-E24*F24*$V$11 -> 0 | W24: =E24*H24*(1-I24)*$X$11*(1-$X$10) -> 0 | X24: =W24-E24*F24*$X$11 -> 0 | Y24: =E24*H24*(1-I24)*$Z$11*(1-$Z$10) -> 0 | Z24: =Y24-E24*F24*$Z$11 -> 0 | AC24: Testeur | AD24: =SUMIF($D$16:$D$36,AC24,$G$16:$G$36)/$AC$15 -> #DIV/0!
B25: =IFERROR(VLOOKUP(A25,Mapping!$A:$F,2,FALSE),"") | C25: =IFERROR(VLOOKUP(A25,Mapping!$A:$F,3,FALSE),"") | F25: =IFERROR(VLOOKUP(A25,Mapping!$A:$F,4,FALSE),0) -> 0 | G25: =E25*F25 -> 0 | H25: =IFERROR(VLOOKUP(A25,Mapping!$A:$F,5,FALSE),0) -> 0 | J25: =IFERROR(VLOOKUP(A25,Mapping!$A:$F,6,FALSE),0) -> 0 | K25: =J25*(1-I25) -> 0 | L25: =IFERROR(J25-K25,"") -> 0 | M25: =E25*H25*(1-I25)*$N$11*(1-$N$10) -> 0 | N25: =M25-E25*F25*$N$11 -> 0 | O25: =E25*H25*(1-I25)*$P$11*(1-$P$10) -> 0 | P25: =O25-E25*F25*$P$11 -> 0 | Q25: =E25*H25*(1-I25)*$R$11*(1-$R$10) -> 0 | R25: =Q25-E25*F25*$R$11 -> 0 | S25: =E25*H25*(1-I25)*$T$11*(1-$T$10) -> 0 | T25: =S25-E25*F25*$T$11 -> 0 | U25: =E25*H25*(1-I25)*$V$11*(1-$V$10) -> 0 | V25: =U25-E25*F25*$V$11 -> 0 | W25: =E25*H25*(1-I25)*$X$11*(1-$X$10) -> 0 | X25: =W25-E25*F25*$X$11 -> 0 | Y25: =E25*H25*(1-I25)*$Z$11*(1-$Z$10) -> 0 | Z25: =Y25-E25*F25*$Z$11 -> 0
B26: =IFERROR(VLOOKUP(A26,Mapping!$A:$F,2,FALSE),"") | C26: =IFERROR(VLOOKUP(A26,Mapping!$A:$F,3,FALSE),"") | F26: =IFERROR(VLOOKUP(A26,Mapping!$A:$F,4,FALSE),0) -> 0 | G26: =E26*F26 -> 0 | H26: =IFERROR(VLOOKUP(A26,Mapping!$A:$F,5,FALSE),0) -> 0 | J26: =IFERROR(VLOOKUP(A26,Mapping!$A:$F,6,FALSE),0) -> 0 | K26: =J26*(1-I26) -> 0 | L26: =IFERROR(J26-K26,"") -> 0 | M26: =E26*H26*(1-I26)*$N$11*(1-$N$10) -> 0 | N26: =M26-E26*F26*$N$11 -> 0 | O26: =E26*H26*(1-I26)*$P$11*(1-$P$10) -> 0 | P26: =O26-E26*F26*$P$11 -> 0 | Q26: =E26*H26*(1-I26)*$R$11*(1-$R$10) -> 0 | R26: =Q26-E26*F26*$R$11 -> 0 | S26: =E26*H26*(1-I26)*$T$11*(1-$T$10) -> 0 | T26: =S26-E26*F26*$T$11 -> 0 | U26: =E26*H26*(1-I26)*$V$11*(1-$V$10) -> 0 | V26: =U26-E26*F26*$V$11 -> 0 | W26: =E26*H26*(1-I26)*$X$11*(1-$X$10) -> 0 | X26: =W26-E26*F26*$X$11 -> 0 | Y26: =E26*H26*(1-I26)*$Z$11*(1-$Z$10) -> 0 | Z26: =Y26-E26*F26*$Z$11 -> 0
B27: =IFERROR(VLOOKUP(A27,Mapping!$A:$F,2,FALSE),"") | C27: =IFERROR(VLOOKUP(A27,Mapping!$A:$F,3,FALSE),"") | F27: =IFERROR(VLOOKUP(A27,Mapping!$A:$F,4,FALSE),0) -> 0 | G27: =E27*F27 -> 0 | H27: =IFERROR(VLOOKUP(A27,Mapping!$A:$F,5,FALSE),0) -> 0 | J27: =IFERROR(VLOOKUP(A27,Mapping!$A:$F,6,FALSE),0) -> 0 | K27: =J27*(1-I27) -> 0 | L27: =IFERROR(J27-K27,"") -> 0 | M27: =E27*H27*(1-I27)*$N$11*(1-$N$10) -> 0 | N27: =M27-E27*F27*$N$11 -> 0 | O27: =E27*H27*(1-I27)*$P$11*(1-$P$10) -> 0 | P27: =O27-E27*F27*$P$11 -> 0 | Q27: =E27*H27*(1-I27)*$R$11*(1-$R$10) -> 0 | R27: =Q27-E27*F27*$R$11 -> 0 | S27: =E27*H27*(1-I27)*$T$11*(1-$T$10) -> 0 | T27: =S27-E27*F27*$T$11 -> 0 | U27: =E27*H27*(1-I27)*$V$11*(1-$V$10) -> 0 | V27: =U27-E27*F27*$V$11 -> 0 | W27: =E27*H27*(1-I27)*$X$11*(1-$X$10) -> 0 | X27: =W27-E27*F27*$X$11 -> 0 | Y27: =E27*H27*(1-I27)*$Z$11*(1-$Z$10) -> 0 | Z27: =Y27-E27*F27*$Z$11 -> 0
B28: =IFERROR(VLOOKUP(A28,Mapping!$A:$F,2,FALSE),"") | C28: =IFERROR(VLOOKUP(A28,Mapping!$A:$F,3,FALSE),"") | F28: =IFERROR(VLOOKUP(A28,Mapping!$A:$F,4,FALSE),0) -> 0 | G28: =E28*F28 -> 0 | H28: =IFERROR(VLOOKUP(A28,Mapping!$A:$F,5,FALSE),0) -> 0 | J28: =IFERROR(VLOOKUP(A28,Mapping!$A:$F,6,FALSE),0) -> 0 | K28: =J28*(1-I28) -> 0 | L28: =IFERROR(J28-K28,"") -> 0 | M28: =E28*H28*(1-I28)*$N$11*(1-$N$10) -> 0 | N28: =M28-E28*F28*$N$11 -> 0 | O28: =E28*H28*(1-I28)*$P$11*(1-$P$10) -> 0 | P28: =O28-E28*F28*$P$11 -> 0 | Q28: =E28*H28*(1-I28)*$R$11*(1-$R$10) -> 0 | R28: =Q28-E28*F28*$R$11 -> 0 | S28: =E28*H28*(1-I28)*$T$11*(1-$T$10) -> 0 | T28: =S28-E28*F28*$T$11 -> 0 | U28: =E28*H28*(1-I28)*$V$11*(1-$V$10) -> 0 | V28: =U28-E28*F28*$V$11 -> 0 | W28: =E28*H28*(1-I28)*$X$11*(1-$X$10) -> 0 | X28: =W28-E28*F28*$X$11 -> 0 | Y28: =E28*H28*(1-I28)*$Z$11*(1-$Z$10) -> 0 | Z28: =Y28-E28*F28*$Z$11 -> 0
B29: =IFERROR(VLOOKUP(A29,Mapping!$A:$F,2,FALSE),"") | C29: =IFERROR(VLOOKUP(A29,Mapping!$A:$F,3,FALSE),"") | F29: =IFERROR(VLOOKUP(A29,Mapping!$A:$F,4,FALSE),0) -> 0 | G29: =E29*F29 -> 0 | H29: =IFERROR(VLOOKUP(A29,Mapping!$A:$F,5,FALSE),0) -> 0 | J29: =IFERROR(VLOOKUP(A29,Mapping!$A:$F,6,FALSE),0) -> 0 | K29: =J29*(1-I29) -> 0 | L29: =IFERROR(J29-K29,"") -> 0 | M29: =E29*H29*(1-I29)*$N$11*(1-$N$10) -> 0 | N29: =M29-E29*F29*$N$11 -> 0 | O29: =E29*H29*(1-I29)*$P$11*(1-$P$10) -> 0 | P29: =O29-E29*F29*$P$11 -> 0 | Q29: =E29*H29*(1-I29)*$R$11*(1-$R$10) -> 0 | R29: =Q29-E29*F29*$R$11 -> 0 | S29: =E29*H29*(1-I29)*$T$11*(1-$T$10) -> 0 | T29: =S29-E29*F29*$T$11 -> 0 | U29: =E29*H29*(1-I29)*$V$11*(1-$V$10) -> 0 | V29: =U29-E29*F29*$V$11 -> 0 | W29: =E29*H29*(1-I29)*$X$11*(1-$X$10) -> 0 | X29: =W29-E29*F29*$X$11 -> 0 | Y29: =E29*H29*(1-I29)*$Z$11*(1-$Z$10) -> 0 | Z29: =Y29-E29*F29*$Z$11 -> 0
B30: =IFERROR(VLOOKUP(A30,Mapping!$A:$F,2,FALSE),"") | C30: =IFERROR(VLOOKUP(A30,Mapping!$A:$F,3,FALSE),"") | F30: =IFERROR(VLOOKUP(A30,Mapping!$A:$F,4,FALSE),0) -> 0 | G30: =E30*F30 -> 0 | H30: =IFERROR(VLOOKUP(A30,Mapping!$A:$F,5,FALSE),0) -> 0 | J30: =IFERROR(VLOOKUP(A30,Mapping!$A:$F,6,FALSE),0) -> 0 | K30: =J30*(1-I30) -> 0 | L30: =IFERROR(J30-K30,"") -> 0 | M30: =E30*H30*(1-I30)*$N$11*(1-$N$10) -> 0 | N30: =M30-E30*F30*$N$11 -> 0 | O30: =E30*H30*(1-I30)*$P$11*(1-$P$10) -> 0 | P30: =O30-E30*F30*$P$11 -> 0 | Q30: =E30*H30*(1-I30)*$R$11*(1-$R$10) -> 0 | R30: =Q30-E30*F30*$R$11 -> 0 | S30: =E30*H30*(1-I30)*$T$11*(1-$T$10) -> 0 | T30: =S30-E30*F30*$T$11 -> 0 | U30: =E30*H30*(1-I30)*$V$11*(1-$V$10) -> 0 | V30: =U30-E30*F30*$V$11 -> 0 | W30: =E30*H30*(1-I30)*$X$11*(1-$X$10) -> 0 | X30: =W30-E30*F30*$X$11 -> 0 | Y30: =E30*H30*(1-I30)*$Z$11*(1-$Z$10) -> 0 | Z30: =Y30-E30*F30*$Z$11 -> 0
B31: =IFERROR(VLOOKUP(A31,Mapping!$A:$F,2,FALSE),"") | C31: =IFERROR(VLOOKUP(A31,Mapping!$A:$F,3,FALSE),"") | F31: =IFERROR(VLOOKUP(A31,Mapping!$A:$F,4,FALSE),0) -> 0 | G31: =E31*F31 -> 0 | H31: =IFERROR(VLOOKUP(A31,Mapping!$A:$F,5,FALSE),0) -> 0 | J31: =IFERROR(VLOOKUP(A31,Mapping!$A:$F,6,FALSE),0) -> 0 | K31: =J31*(1-I31) -> 0 | L31: =IFERROR(J31-K31,"") -> 0 | M31: =E31*H31*(1-I31)*$N$11*(1-$N$10) -> 0 | N31: =M31-E31*F31*$N$11 -> 0 | O31: =E31*H31*(1-I31)*$P$11*(1-$P$10) -> 0 | P31: =O31-E31*F31*$P$11 -> 0 | Q31: =E31*H31*(1-I31)*$R$11*(1-$R$10) -> 0 | R31: =Q31-E31*F31*$R$11 -> 0 | S31: =E31*H31*(1-I31)*$T$11*(1-$T$10) -> 0 | T31: =S31-E31*F31*$T$11 -> 0 | U31: =E31*H31*(1-I31)*$V$11*(1-$V$10) -> 0 | V31: =U31-E31*F31*$V$11 -> 0 | W31: =E31*H31*(1-I31)*$X$11*(1-$X$10) -> 0 | X31: =W31-E31*F31*$X$11 -> 0 | Y31: =E31*H31*(1-I31)*$Z$11*(1-$Z$10) -> 0 | Z31: =Y31-E31*F31*$Z$11 -> 0
B32: =IFERROR(VLOOKUP(A32,Mapping!$A:$F,2,FALSE),"") | C32: =IFERROR(VLOOKUP(A32,Mapping!$A:$F,3,FALSE),"") | F32: =IFERROR(VLOOKUP(A32,Mapping!$A:$F,4,FALSE),0) -> 0 | G32: =E32*F32 -> 0 | H32: =IFERROR(VLOOKUP(A32,Mapping!$A:$F,5,FALSE),0) -> 0 | J32: =IFERROR(VLOOKUP(A32,Mapping!$A:$F,6,FALSE),0) -> 0 | K32: =J32*(1-I32) -> 0 | L32: =IFERROR(J32-K32,"") -> 0 | M32: =E32*H32*(1-I32)*$N$11*(1-$N$10) -> 0 | N32: =M32-E32*F32*$N$11 -> 0 | O32: =E32*H32*(1-I32)*$P$11*(1-$P$10) -> 0 | P32: =O32-E32*F32*$P$11 -> 0 | Q32: =E32*H32*(1-I32)*$R$11*(1-$R$10) -> 0 | R32: =Q32-E32*F32*$R$11 -> 0 | S32: =E32*H32*(1-I32)*$T$11*(1-$T$10) -> 0 | T32: =S32-E32*F32*$T$11 -> 0 | U32: =E32*H32*(1-I32)*$V$11*(1-$V$10) -> 0 | V32: =U32-E32*F32*$V$11 -> 0 | W32: =E32*H32*(1-I32)*$X$11*(1-$X$10) -> 0 | X32: =W32-E32*F32*$X$11 -> 0 | Y32: =E32*H32*(1-I32)*$Z$11*(1-$Z$10) -> 0 | Z32: =Y32-E32*F32*$Z$11 -> 0
B33: =IFERROR(VLOOKUP(A33,Mapping!$A:$F,2,FALSE),"") | C33: =IFERROR(VLOOKUP(A33,Mapping!$A:$F,3,FALSE),"") | F33: =IFERROR(VLOOKUP(A33,Mapping!$A:$F,4,FALSE),0) -> 0 | G33: =E33*F33 -> 0 | H33: =IFERROR(VLOOKUP(A33,Mapping!$A:$F,5,FALSE),0) -> 0 | J33: =IFERROR(VLOOKUP(A33,Mapping!$A:$F,6,FALSE),0) -> 0 | K33: =J33*(1-I33) -> 0 | L33: =IFERROR(J33-K33,"") -> 0 | M33: =E33*H33*(1-I33)*$N$11*(1-$N$10) -> 0 | N33: =M33-E33*F33*$N$11 -> 0 | O33: =E33*H33*(1-I33)*$P$11*(1-$P$10) -> 0 | P33: =O33-E33*F33*$P$11 -> 0 | Q33: =E33*H33*(1-I33)*$R$11*(1-$R$10) -> 0 | R33: =Q33-E33*F33*$R$11 -> 0 | S33: =E33*H33*(1-I33)*$T$11*(1-$T$10) -> 0 | T33: =S33-E33*F33*$T$11 -> 0 | U33: =E33*H33*(1-I33)*$V$11*(1-$V$10) -> 0 | V33: =U33-E33*F33*$V$11 -> 0 | W33: =E33*H33*(1-I33)*$X$11*(1-$X$10) -> 0 | X33: =W33-E33*F33*$X$11 -> 0 | Y33: =E33*H33*(1-I33)*$Z$11*(1-$Z$10) -> 0 | Z33: =Y33-E33*F33*$Z$11 -> 0
B34: =IFERROR(VLOOKUP(A34,Mapping!$A:$F,2,FALSE),"") | C34: =IFERROR(VLOOKUP(A34,Mapping!$A:$F,3,FALSE),"") | F34: =IFERROR(VLOOKUP(A34,Mapping!$A:$F,4,FALSE),0) -> 0 | G34: =E34*F34 -> 0 | H34: =IFERROR(VLOOKUP(A34,Mapping!$A:$F,5,FALSE),0) -> 0 | J34: =IFERROR(VLOOKUP(A34,Mapping!$A:$F,6,FALSE),0) -> 0 | K34: =J34*(1-I34) -> 0 | L34: =IFERROR(J34-K34,"") -> 0 | M34: =E34*H34*(1-I34)*$N$11*(1-$N$10) -> 0 | N34: =M34-E34*F34*$N$11 -> 0 | O34: =E34*H34*(1-I34)*$P$11*(1-$P$10) -> 0 | P34: =O34-E34*F34*$P$11 -> 0 | Q34: =E34*H34*(1-I34)*$R$11*(1-$R$10) -> 0 | R34: =Q34-E34*F34*$R$11 -> 0 | S34: =E34*H34*(1-I34)*$T$11*(1-$T$10) -> 0 | T34: =S34-E34*F34*$T$11 -> 0 | U34: =E34*H34*(1-I34)*$V$11*(1-$V$10) -> 0 | V34: =U34-E34*F34*$V$11 -> 0 | W34: =E34*H34*(1-I34)*$X$11*(1-$X$10) -> 0 | X34: =W34-E34*F34*$X$11 -> 0 | Y34: =E34*H34*(1-I34)*$Z$11*(1-$Z$10) -> 0 | Z34: =Y34-E34*F34*$Z$11 -> 0
B35: =IFERROR(VLOOKUP(A35,Mapping!$A:$F,2,FALSE),"") | C35: =IFERROR(VLOOKUP(A35,Mapping!$A:$F,3,FALSE),"") | F35: =IFERROR(VLOOKUP(A35,Mapping!$A:$F,4,FALSE),0) -> 0 | G35: =E35*F35 -> 0 | H35: =IFERROR(VLOOKUP(A35,Mapping!$A:$F,5,FALSE),0) -> 0 | J35: =IFERROR(VLOOKUP(A35,Mapping!$A:$F,6,FALSE),0) -> 0 | K35: =J35*(1-I35) -> 0 | L35: =IFERROR(J35-K35,"") -> 0 | M35: =E35*H35*(1-I35)*$N$11*(1-$N$10) -> 0 | N35: =M35-E35*F35*$N$11 -> 0 | O35: =E35*H35*(1-I35)*$P$11*(1-$P$10) -> 0 | P35: =O35-E35*F35*$P$11 -> 0 | Q35: =E35*H35*(1-I35)*$R$11*(1-$R$10) -> 0 | R35: =Q35-E35*F35*$R$11 -> 0 | S35: =E35*H35*(1-I35)*$T$11*(1-$T$10) -> 0 | T35: =S35-E35*F35*$T$11 -> 0 | U35: =E35*H35*(1-I35)*$V$11*(1-$V$10) -> 0 | V35: =U35-E35*F35*$V$11 -> 0 | W35: =E35*H35*(1-I35)*$X$11*(1-$X$10) -> 0 | X35: =W35-E35*F35*$X$11 -> 0 | Y35: =E35*H35*(1-I35)*$Z$11*(1-$Z$10) -> 0 | Z35: =Y35-E35*F35*$Z$11 -> 0
B36: =IFERROR(VLOOKUP(A36,Mapping!$A:$F,2,FALSE),"") | C36: =IFERROR(VLOOKUP(A36,Mapping!$A:$F,3,FALSE),"") | F36: =IFERROR(VLOOKUP(A36,Mapping!$A:$F,4,FALSE),0) -> 0 | G36: =E36*F36 -> 0 | H36: =IFERROR(VLOOKUP(A36,Mapping!$A:$F,5,FALSE),0) -> 0 | J36: =IFERROR(VLOOKUP(A36,Mapping!$A:$F,6,FALSE),0) -> 0 | K36: =J36*(1-I36) -> 0 | L36: =IFERROR(J36-K36,"") -> 0 | M36: =E36*H36*(1-I36)*$N$11*(1-$N$10) -> 0 | N36: =M36-E36*F36*$N$11 -> 0 | O36: =E36*H36*(1-I36)*$P$11*(1-$P$10) -> 0 | P36: =O36-E36*F36*$P$11 -> 0 | Q36: =E36*H36*(1-I36)*$R$11*(1-$R$10) -> 0 | R36: =Q36-E36*F36*$R$11 -> 0 | S36: =E36*H36*(1-I36)*$T$11*(1-$T$10) -> 0 | T36: =S36-E36*F36*$T$11 -> 0 | U36: =E36*H36*(1-I36)*$V$11*(1-$V$10) -> 0 | V36: =U36-E36*F36*$V$11 -> 0 | W36: =E36*H36*(1-I36)*$X$11*(1-$X$10) -> 0 | X36: =W36-E36*F36*$X$11 -> 0 | Y36: =E36*H36*(1-I36)*$Z$11*(1-$Z$10) -> 0 | Z36: =Y36-E36*F36*$Z$11 -> 0
A39: PREMIUM
A40: Nombre d'offres
A41: Nombre de produits | B41: =SUM(E53:E65) -> 0
M42: RETAIL | S42: INSTITUT | AB42: Retail + Institut
M44: Ambassadeur | O44: Compagnon | Q44: Challenger | S44: Rose | U44: Prunelier | W44: Anthylide | Y44: Calendula | AB44: Total
M45: % Offres | O45: % Offres | Q45: % Offres | S45: % Offres | U45: % Offres | W45: % Offres
M46: Remise | N46: 0.17 | O46: Remise | P46: 0.13 | Q46: Remise | R46: 0.08 | S46: Remise | T46: 0.325 | U46: Remise | V46: 0.3 | W46: Remise | X46: 0.28 | Y46: Remise | Z46: 0.25
M47: Nb Offres | N47: =N45*$B$4 -> 0 | O47: Nb Offres | P47: =P45*$B$4 -> 0 | Q47: Nb Offres | R47: =R45*$B$4 -> 0 | S47: Nb Offres | T47: =T45*$B$4 -> 0 | U47: Nb Offres | V47: =V45*$B$4 -> 0 | W47: Nb Offres | X47: =X45*$B$4 -> 0 | Y47: Nb Offres | Z47: =Z45*$B$4 -> 0
E48: Pdt dans offre | F48: Coût achat unitaire | G48: Coûts achats total | H48: Tarif revendeur unitaire | I48: Remise additionnelle | J48: PPC | K48: PPC Remisé | L48: Montant BRI | M48: CA | N48: Marges | O48: CA | P48: Marges | Q48: CA | R48: Marges | S48: CA | T48: Marges | U48: CA | V48: Marges | W48: CA | X48: Marges | Y48: CA | Z48: Marges | AB48: Nbrs Offres planifiées | AC48: CA | AD48: Marges
A49: Code article | B49: Libellé article | C49: Code à barres (EAN) | D49: Typ. Prod | E49: '# | F49: '€ | G49: '€ | H49: '€ | I49: '€ | J49: '€ | K49: '€ | L49: '€ | M49: '€ | N49: '€ | O49: '€ | P49: '€ | Q49: '€ | R49: '€ | S49: '€ | T49: '€ | U49: '€ | V49: '€ | W49: '€ | X49: '€ | Y49: '€ | Z49: '€ | AB49: '# | AC49: '€ | AD49: '€
A51: Synthèse | E51: =IFERROR(SUMIFS(E53:E72,D53:D72,"Produit Vente"),"Non trouvé") -> 0 | G51: =IFERROR(SUM(G53:G72),"Non Trouvé") -> 0 | M51: =SUM(M53:M72) -> 0 | N51: =SUM(N53:N72) -> 0 | O51: =SUM(O53:O72) -> 0 | P51: =SUM(P53:P72) -> 0 | Q51: =SUM(Q53:Q72) -> 0 | R51: =SUM(R53:R72) -> 0 | S51: =SUM(S53:S72) -> 0 | T51: =SUM(T53:T72) -> 0 | ... Z51: =SUM(Z53:Z72) -> 0 | AB51: =B40 -> 0 | AC51: =Y51+W51+U51+S51+O51+M51+Q51 -> 0 | AD51: =Z51+X51+V51+T51+P51+N51+R51 -> 0
B53: =IFERROR(VLOOKUP(A53,Mapping!$A:$F,2,FALSE),"") | C53: =IFERROR(VLOOKUP(A53,Mapping!$A:$F,3,FALSE),"") | F53: =IFERROR(VLOOKUP(A53,Mapping!$A:$F,4,FALSE),0) -> 0 | G53: =E53*F53 -> 0 | H53: =IFERROR(VLOOKUP(A53,Mapping!$A:$F,5,FALSE),0) -> 0 | J53: =IFERROR(VLOOKUP(A53,Mapping!$A:$F,6,FALSE),0) -> 0 | K53: =J53*(1-I53) -> 0 | L53: =IFERROR(J53-K53,"") -> 0 | M53: =E53*H53*(1-I53)*$N$11*(1-$N$10) -> 0 | N53: =M53-E53*F53*$N$11 -> 0 | O53: =E53*H53*(1-I53)*$P$11*(1-$P$10) -> 0 | P53: =O53-E53*F53*$P$11 -> 0 | Q53: =E53*H53*(1-I53)*$R$11*(1-$R$10) -> 0 | R53: =Q53-E53*F53*$R$11 -> 0 | S53: =E53*H53*(1-I53)*$T$11*(1-$T$10) -> 0 | T53: =S53-E53*F53*$T$11 -> 0 | U53: =E53*H53*(1-I53)*$V$11*(1-$V$10) -> 0 | V53: =U53-E53*F53*$V$11 -> 0 | W53: =E53*H53*(1-I53)*$X$11*(1-$X$10) -> 0 | X53: =W53-E53*F53*$X$11 -> 0 | Y53: =E53*H53*(1-I53)*$Z$11*(1-$Z$10) -> 0 | Z53: =Y53-E53*F53*$Z$11 -> 0
B54: =IFERROR(VLOOKUP(A54,Mapping!$A:$F,2,FALSE),"") | C54: =IFERROR(VLOOKUP(A54,Mapping!$A:$F,3,FALSE),"") | F54: =IFERROR(VLOOKUP(A54,Mapping!$A:$F,4,FALSE),0) -> 0 | G54: =E54*F54 -> 0 | H54: =IFERROR(VLOOKUP(A54,Mapping!$A:$F,5,FALSE),0) -> 0 | J54: =IFERROR(VLOOKUP(A54,Mapping!$A:$F,6,FALSE),0) -> 0 | K54: =J54*(1-I54) -> 0 | L54: =IFERROR(J54-K54,"") -> 0 | M54: =E54*H54*(1-I54)*$N$11*(1-$N$10) -> 0 | N54: =M54-E54*F54*$N$11 -> 0 | O54: =E54*H54*(1-I54)*$P$11*(1-$P$10) -> 0 | P54: =O54-E54*F54*$P$11 -> 0 | Q54: =E54*H54*(1-I54)*$R$11*(1-$R$10) -> 0 | R54: =Q54-E54*F54*$R$11 -> 0 | S54: =E54*H54*(1-I54)*$T$11*(1-$T$10) -> 0 | T54: =S54-E54*F54*$T$11 -> 0 | U54: =E54*H54*(1-I54)*$V$11*(1-$V$10) -> 0 | V54: =U54-E54*F54*$V$11 -> 0 | W54: =E54*H54*(1-I54)*$X$11*(1-$X$10) -> 0 | X54: =W54-E54*F54*$X$11 -> 0 | Y54: =E54*H54*(1-I54)*$Z$11*(1-$Z$10) -> 0 | Z54: =Y54-E54*F54*$Z$11 -> 0 | AC54: Prix Offre Moy. Remisé : | AD54: =AC51/AB51 -> #DIV/0!
B55: =IFERROR(VLOOKUP(A55,Mapping!$A:$F,2,FALSE),"") | C55: =IFERROR(VLOOKUP(A55,Mapping!$A:$F,3,FALSE),"") | F55: =IFERROR(VLOOKUP(A55,Mapping!$A:$F,4,FALSE),0) -> 0 | G55: =E55*F55 -> 0 | H55: =IFERROR(VLOOKUP(A55,Mapping!$A:$F,5,FALSE),0) -> 0 | J55: =IFERROR(VLOOKUP(A55,Mapping!$A:$F,6,FALSE),0) -> 0 | K55: =J55*(1-I55) -> 0 | L55: =IFERROR(J55-K55,"") -> 0 | M55: =E55*H55*(1-I55)*$N$11*(1-$N$10) -> 0 | N55: =M55-E55*F55*$N$11 -> 0 | O55: =E55*H55*(1-I55)*$P$11*(1-$P$10) -> 0 | P55: =O55-E55*F55*$P$11 -> 0 | Q55: =E55*H55*(1-I55)*$R$11*(1-$R$10) -> 0 | R55: =Q55-E55*F55*$R$11 -> 0 | S55: =E55*H55*(1-I55)*$T$11*(1-$T$10) -> 0 | T55: =S55-E55*F55*$T$11 -> 0 | U55: =E55*H55*(1-I55)*$V$11*(1-$V$10) -> 0 | V55: =U55-E55*F55*$V$11 -> 0 | W55: =E55*H55*(1-I55)*$X$11*(1-$X$10) -> 0 | X55: =W55-E55*F55*$X$11 -> 0 | Y55: =E55*H55*(1-I55)*$Z$11*(1-$Z$10) -> 0 | Z55: =Y55-E55*F55*$Z$11 -> 0 | AC55: Poids Gratuités achats : | AD55: =SUM(AD57:AD60) -> #DIV/0!
B56: =IFERROR(VLOOKUP(A56,Mapping!$A:$F,2,FALSE),"") | C56: =IFERROR(VLOOKUP(A56,Mapping!$A:$F,3,FALSE),"") | F56: =IFERROR(VLOOKUP(A56,Mapping!$A:$F,4,FALSE),0) -> 0 | G56: =E56*F56 -> 0 | H56: =IFERROR(VLOOKUP(A56,Mapping!$A:$F,5,FALSE),0) -> 0 | J56: =IFERROR(VLOOKUP(A56,Mapping!$A:$F,6,FALSE),0) -> 0 | K56: =J56*(1-I56) -> 0 | L56: =IFERROR(J56-K56,"") -> 0 | M56: =E56*H56*(1-I56)*$N$11*(1-$N$10) -> 0 | N56: =M56-E56*F56*$N$11 -> 0 | O56: =E56*H56*(1-I56)*$P$11*(1-$P$10) -> 0 | P56: =O56-E56*F56*$P$11 -> 0 | Q56: =E56*H56*(1-I56)*$R$11*(1-$R$10) -> 0 | R56: =Q56-E56*F56*$R$11 -> 0 | S56: =E56*H56*(1-I56)*$T$11*(1-$T$10) -> 0 | T56: =S56-E56*F56*$T$11 -> 0 | U56: =E56*H56*(1-I56)*$V$11*(1-$V$10) -> 0 | V56: =U56-E56*F56*$V$11 -> 0 | W56: =E56*H56*(1-I56)*$X$11*(1-$X$10) -> 0 | X56: =W56-E56*F56*$X$11 -> 0 | Y56: =E56*H56*(1-I56)*$Z$11*(1-$Z$10) -> 0 | Z56: =Y56-E56*F56*$Z$11 -> 0
B57: =IFERROR(VLOOKUP(A57,Mapping!$A:$F,2,FALSE),"") | C57: =IFERROR(VLOOKUP(A57,Mapping!$A:$F,3,FALSE),"") | F57: =IFERROR(VLOOKUP(A57,Mapping!$A:$F,4,FALSE),0) -> 0 | G57: =E57*F57 -> 0 | H57: =IFERROR(VLOOKUP(A57,Mapping!$A:$F,5,FALSE),0) -> 0 | J57: =IFERROR(VLOOKUP(A57,Mapping!$A:$F,6,FALSE),0) -> 0 | K57: =J57*(1-I57) -> 0 | L57: =IFERROR(J57-K57,"") -> 0 | M57: =E57*H57*(1-I57)*$N$11*(1-$N$10) -> 0 | N57: =M57-E57*F57*$N$11 -> 0 | O57: =E57*H57*(1-I57)*$P$11*(1-$P$10) -> 0 | P57: =O57-E57*F57*$P$11 -> 0 | Q57: =E57*H57*(1-I57)*$R$11*(1-$R$10) -> 0 | R57: =Q57-E57*F57*$R$11 -> 0 | S57: =E57*H57*(1-I57)*$T$11*(1-$T$10) -> 0 | T57: =S57-E57*F57*$T$11 -> 0 | U57: =E57*H57*(1-I57)*$V$11*(1-$V$10) -> 0 | V57: =U57-E57*F57*$V$11 -> 0 | W57: =E57*H57*(1-I57)*$X$11*(1-$X$10) -> 0 | X57: =W57-E57*F57*$X$11 -> 0 | Y57: =E57*H57*(1-I57)*$Z$11*(1-$Z$10) -> 0 | Z57: =Y57-E57*F57*$Z$11 -> 0 | AC57: UG | AD57: =SUMIF($D$16:$D$36,AC57,$G$16:$G$36)/$AC$15 -> #DIV/0!
B58: =IFERROR(VLOOKUP(A58,Mapping!$A:$F,2,FALSE),"") | C58: =IFERROR(VLOOKUP(A58,Mapping!$A:$F,3,FALSE),"") | F58: =IFERROR(VLOOKUP(A58,Mapping!$A:$F,4,FALSE),0) -> 0 | G58: =E58*F58 -> 0 | H58: =IFERROR(VLOOKUP(A58,Mapping!$A:$F,5,FALSE),0) -> 0 | J58: =IFERROR(VLOOKUP(A58,Mapping!$A:$F,6,FALSE),0) -> 0 | K58: =J58*(1-I58) -> 0 | L58: =IFERROR(J58-K58,"") -> 0 | M58: =E58*H58*(1-I58)*$N$11*(1-$N$10) -> 0 | N58: =M58-E58*F58*$N$11 -> 0 | O58: =E58*H58*(1-I58)*$P$11*(1-$P$10) -> 0 | P58: =O58-E58*F58*$P$11 -> 0 | Q58: =E58*H58*(1-I58)*$R$11*(1-$R$10) -> 0 | R58: =Q58-E58*F58*$R$11 -> 0 | S58: =E58*H58*(1-I58)*$T$11*(1-$T$10) -> 0 | T58: =S58-E58*F58*$T$11 -> 0 | U58: =E58*H58*(1-I58)*$V$11*(1-$V$10) -> 0 | V58: =U58-E58*F58*$V$11 -> 0 | W58: =E58*H58*(1-I58)*$X$11*(1-$X$10) -> 0 | X58: =W58-E58*F58*$X$11 -> 0 | Y58: =E58*H58*(1-I58)*$Z$11*(1-$Z$10) -> 0 | Z58: =Y58-E58*F58*$Z$11 -> 0 | AC58: PLV | AD58: =SUMIF($D$16:$D$36,AC58,$G$16:$G$36)/$AC$15 -> #DIV/0!
B59: =IFERROR(VLOOKUP(A59,Mapping!$A:$F,2,FALSE),"") | C59: =IFERROR(VLOOKUP(A59,Mapping!$A:$F,3,FALSE),"") | F59: =IFERROR(VLOOKUP(A59,Mapping!$A:$F,4,FALSE),0) -> 0 | G59: =E59*F59 -> 0 | H59: =IFERROR(VLOOKUP(A59,Mapping!$A:$F,5,FALSE),0) -> 0 | J59: =IFERROR(VLOOKUP(A59,Mapping!$A:$F,6,FALSE),0) -> 0 | K59: =J59*(1-I59) -> 0 | L59: =IFERROR(J59-K59,"") -> 0 | M59: =E59*H59*(1-I59)*$N$11*(1-$N$10) -> 0 | N59: =M59-E59*F59*$N$11 -> 0 | O59: =E59*H59*(1-I59)*$P$11*(1-$P$10) -> 0 | P59: =O59-E59*F59*$P$11 -> 0 | Q59: =E59*H59*(1-I59)*$R$11*(1-$R$10) -> 0 | R59: =Q59-E59*F59*$R$11 -> 0 | S59: =E59*H59*(1-I59)*$T$11*(1-$T$10) -> 0 | T59: =S59-E59*F59*$T$11 -> 0 | U59: =E59*H59*(1-I59)*$V$11*(1-$V$10) -> 0 | V59: =U59-E59*F59*$V$11 -> 0 | W59: =E59*H59*(1-I59)*$X$11*(1-$X$10) -> 0 | X59: =W59-E59*F59*$X$11 -> 0 | Y59: =E59*H59*(1-I59)*$Z$11*(1-$Z$10) -> 0 | Z59: =Y59-E59*F59*$Z$11 -> 0 | AC59: Echantillon | AD59: =SUMIF($D$16:$D$36,AC59,$G$16:$G$36)/$AC$15 -> #DIV/0!
B60: =IFERROR(VLOOKUP(A60,Mapping!$A:$F,2,FALSE),"") | C60: =IFERROR(VLOOKUP(A60,Mapping!$A:$F,3,FALSE),"") | F60: =IFERROR(VLOOKUP(A60,Mapping!$A:$F,4,FALSE),0) -> 0 | G60: =E60*F60 -> 0 | H60: =IFERROR(VLOOKUP(A60,Mapping!$A:$F,5,FALSE),0) -> 0 | J60: =IFERROR(VLOOKUP(A60,Mapping!$A:$F,6,FALSE),0) -> 0 | K60: =J60*(1-I60) -> 0 | L60: =IFERROR(J60-K60,"") -> 0 | M60: =E60*H60*(1-I60)*$N$11*(1-$N$10) -> 0 | N60: =M60-E60*F60*$N$11 -> 0 | O60: =E60*H60*(1-I60)*$P$11*(1-$P$10) -> 0 | P60: =O60-E60*F60*$P$11 -> 0 | Q60: =E60*H60*(1-I60)*$R$11*(1-$R$10) -> 0 | R60: =Q60-E60*F60*$R$11 -> 0 | S60: =E60*H60*(1-I60)*$T$11*(1-$T$10) -> 0 | T60: =S60-E60*F60*$T$11 -> 0 | U60: =E60*H60*(1-I60)*$V$11*(1-$V$10) -> 0 | V60: =U60-E60*F60*$V$11 -> 0 | W60: =E60*H60*(1-I60)*$X$11*(1-$X$10) -> 0 | X60: =W60-E60*F60*$X$11 -> 0 | Y60: =E60*H60*(1-I60)*$Z$11*(1-$Z$10) -> 0 | Z60: =Y60-E60*F60*$Z$11 -> 0 | AC60: Testeur | AD60: =SUMIF($D$16:$D$36,AC60,$G$16:$G$36)/$AC$15 -> #DIV/0!
B61: =IFERROR(VLOOKUP(A61,Mapping!$A:$F,2,FALSE),"") | C61: =IFERROR(VLOOKUP(A61,Mapping!$A:$F,3,FALSE),"") | F61: =IFERROR(VLOOKUP(A61,Mapping!$A:$F,4,FALSE),0) -> 0 | G61: =E61*F61 -> 0 | H61: =IFERROR(VLOOKUP(A61,Mapping!$A:$F,5,FALSE),0) -> 0 | J61: =IFERROR(VLOOKUP(A61,Mapping!$A:$F,6,FALSE),0) -> 0 | K61: =J61*(1-I61) -> 0 | L61: =IFERROR(J61-K61,"") -> 0 | M61: =E61*H61*(1-I61)*$N$11*(1-$N$10) -> 0 | N61: =M61-E61*F61*$N$11 -> 0 | O61: =E61*H61*(1-I61)*$P$11*(1-$P$10) -> 0 | P61: =O61-E61*F61*$P$11 -> 0 | Q61: =E61*H61*(1-I61)*$R$11*(1-$R$10) -> 0 | R61: =Q61-E61*F61*$R$11 -> 0 | S61: =E61*H61*(1-I61)*$T$11*(1-$T$10) -> 0 | T61: =S61-E61*F61*$T$11 -> 0 | U61: =E61*H61*(1-I61)*$V$11*(1-$V$10) -> 0 | V61: =U61-E61*F61*$V$11 -> 0 | W61: =E61*H61*(1-I61)*$X$11*(1-$X$10) -> 0 | X61: =W61-E61*F61*$X$11 -> 0 | Y61: =E61*H61*(1-I61)*$Z$11*(1-$Z$10) -> 0 | Z61: =Y61-E61*F61*$Z$11 -> 0
B62: =IFERROR(VLOOKUP(A62,Mapping!$A:$F,2,FALSE),"") | C62: =IFERROR(VLOOKUP(A62,Mapping!$A:$F,3,FALSE),"") | F62: =IFERROR(VLOOKUP(A62,Mapping!$A:$F,4,FALSE),0) -> 0 | G62: =E62*F62 -> 0 | H62: =IFERROR(VLOOKUP(A62,Mapping!$A:$F,5,FALSE),0) -> 0 | J62: =IFERROR(VLOOKUP(A62,Mapping!$A:$F,6,FALSE),0) -> 0 | K62: =J62*(1-I62) -> 0 | L62: =IFERROR(J62-K62,"") -> 0 | M62: =E62*H62*(1-I62)*$N$11*(1-$N$10) -> 0 | N62: =M62-E62*F62*$N$11 -> 0 | O62: =E62*H62*(1-I62)*$P$11*(1-$P$10) -> 0 | P62: =O62-E62*F62*$P$11 -> 0 | Q62: =E62*H62*(1-I62)*$R$11*(1-$R$10) -> 0 | R62: =Q62-E62*F62*$R$11 -> 0 | S62: =E62*H62*(1-I62)*$T$11*(1-$T$10) -> 0 | T62: =S62-E62*F62*$T$11 -> 0 | U62: =E62*H62*(1-I62)*$V$11*(1-$V$10) -> 0 | V62: =U62-E62*F62*$V$11 -> 0 | W62: =E62*H62*(1-I62)*$X$11*(1-$X$10) -> 0 | X62: =W62-E62*F62*$X$11 -> 0 | Y62: =E62*H62*(1-I62)*$Z$11*(1-$Z$10) -> 0 | Z62: =Y62-E62*F62*$Z$11 -> 0
B63: =IFERROR(VLOOKUP(A63,Mapping!$A:$F,2,FALSE),"") | C63: =IFERROR(VLOOKUP(A63,Mapping!$A:$F,3,FALSE),"") | F63: =IFERROR(VLOOKUP(A63,Mapping!$A:$F,4,FALSE),0) -> 0 | G63: =E63*F63 -> 0 | H63: =IFERROR(VLOOKUP(A63,Mapping!$A:$F,5,FALSE),0) -> 0 | J63: =IFERROR(VLOOKUP(A63,Mapping!$A:$F,6,FALSE),0) -> 0 | K63: =J63*(1-I63) -> 0 | L63: =IFERROR(J63-K63,"") -> 0 | M63: =E63*H63*(1-I63)*$N$11*(1-$N$10) -> 0 | N63: =M63-E63*F63*$N$11 -> 0 | O63: =E63*H63*(1-I63)*$P$11*(1-$P$10) -> 0 | P63: =O63-E63*F63*$P$11 -> 0 | Q63: =E63*H63*(1-I63)*$R$11*(1-$R$10) -> 0 | R63: =Q63-E63*F63*$R$11 -> 0 | S63: =E63*H63*(1-I63)*$T$11*(1-$T$10) -> 0 | T63: =S63-E63*F63*$T$11 -> 0 | U63: =E63*H63*(1-I63)*$V$11*(1-$V$10) -> 0 | V63: =U63-E63*F63*$V$11 -> 0 | W63: =E63*H63*(1-I63)*$X$11*(1-$X$10) -> 0 | X63: =W63-E63*F63*$X$11 -> 0 | Y63: =E63*H63*(1-I63)*$Z$11*(1-$Z$10) -> 0 | Z63: =Y63-E63*F63*$Z$11 -> 0
B64: =IFERROR(VLOOKUP(A64,Mapping!$A:$F,2,FALSE),"") | C64: =IFERROR(VLOOKUP(A64,Mapping!$A:$F,3,FALSE),"") | F64: =IFERROR(VLOOKUP(A64,Mapping!$A:$F,4,FALSE),0) -> 0 | G64: =E64*F64 -> 0 | H64: =IFERROR(VLOOKUP(A64,Mapping!$A:$F,5,FALSE),0) -> 0 | J64: =IFERROR(VLOOKUP(A64,Mapping!$A:$F,6,FALSE),0) -> 0 | K64: =J64*(1-I64) -> 0 | L64: =IFERROR(J64-K64,"") -> 0 | M64: =E64*H64*(1-I64)*$N$11*(1-$N$10) -> 0 | N64: =M64-E64*F64*$N$11 -> 0 | O64: =E64*H64*(1-I64)*$P$11*(1-$P$10) -> 0 | P64: =O64-E64*F64*$P$11 -> 0 | Q64: =E64*H64*(1-I64)*$R$11*(1-$R$10) -> 0 | R64: =Q64-E64*F64*$R$11 -> 0 | S64: =E64*H64*(1-I64)*$T$11*(1-$T$10) -> 0 | T64: =S64-E64*F64*$T$11 -> 0 | U64: =E64*H64*(1-I64)*$V$11*(1-$V$10) -> 0 | V64: =U64-E64*F64*$V$11 -> 0 | W64: =E64*H64*(1-I64)*$X$11*(1-$X$10) -> 0 | X64: =W64-E64*F64*$X$11 -> 0 | Y64: =E64*H64*(1-I64)*$Z$11*(1-$Z$10) -> 0 | Z64: =Y64-E64*F64*$Z$11 -> 0
B65: =IFERROR(VLOOKUP(A65,Mapping!$A:$F,2,FALSE),"") | C65: =IFERROR(VLOOKUP(A65,Mapping!$A:$F,3,FALSE),"") | F65: =IFERROR(VLOOKUP(A65,Mapping!$A:$F,4,FALSE),0) -> 0 | G65: =E65*F65 -> 0 | H65: =IFERROR(VLOOKUP(A65,Mapping!$A:$F,5,FALSE),0) -> 0 | J65: =IFERROR(VLOOKUP(A65,Mapping!$A:$F,6,FALSE),0) -> 0 | K65: =J65*(1-I65) -> 0 | L65: =IFERROR(J65-K65,"") -> 0 | M65: =E65*H65*(1-I65)*$N$11*(1-$N$10) -> 0 | N65: =M65-E65*F65*$N$11 -> 0 | O65: =E65*H65*(1-I65)*$P$11*(1-$P$10) -> 0 | P65: =O65-E65*F65*$P$11 -> 0 | Q65: =E65*H65*(1-I65)*$R$11*(1-$R$10) -> 0 | R65: =Q65-E65*F65*$R$11 -> 0 | S65: =E65*H65*(1-I65)*$T$11*(1-$T$10) -> 0 | T65: =S65-E65*F65*$T$11 -> 0 | U65: =E65*H65*(1-I65)*$V$11*(1-$V$10) -> 0 | V65: =U65-E65*F65*$V$11 -> 0 | W65: =E65*H65*(1-I65)*$X$11*(1-$X$10) -> 0 | X65: =W65-E65*F65*$X$11 -> 0 | Y65: =E65*H65*(1-I65)*$Z$11*(1-$Z$10) -> 0 | Z65: =Y65-E65*F65*$Z$11 -> 0
B66: =IFERROR(VLOOKUP(A66,Mapping!$A:$F,2,FALSE),"") | C66: =IFERROR(VLOOKUP(A66,Mapping!$A:$F,3,FALSE),"") | F66: =IFERROR(VLOOKUP(A66,Mapping!$A:$F,4,FALSE),0) -> 0 | G66: =E66*F66 -> 0 | H66: =IFERROR(VLOOKUP(A66,Mapping!$A:$F,5,FALSE),0) -> 0 | J66: =IFERROR(VLOOKUP(A66,Mapping!$A:$F,6,FALSE),0) -> 0 | K66: =J66*(1-I66) -> 0 | L66: =IFERROR(J66-K66,"") -> 0 | M66: =E66*H66*(1-I66)*$N$11*(1-$N$10) -> 0 | N66: =M66-E66*F66*$N$11 -> 0 | O66: =E66*H66*(1-I66)*$P$11*(1-$P$10) -> 0 | P66: =O66-E66*F66*$P$11 -> 0 | Q66: =E66*H66*(1-I66)*$R$11*(1-$R$10) -> 0 | R66: =Q66-E66*F66*$R$11 -> 0 | S66: =E66*H66*(1-I66)*$T$11*(1-$T$10) -> 0 | T66: =S66-E66*F66*$T$11 -> 0 | U66: =E66*H66*(1-I66)*$V$11*(1-$V$10) -> 0 | V66: =U66-E66*F66*$V$11 -> 0 | W66: =E66*H66*(1-I66)*$X$11*(1-$X$10) -> 0 | X66: =W66-E66*F66*$X$11 -> 0 | Y66: =E66*H66*(1-I66)*$Z$11*(1-$Z$10) -> 0 | Z66: =Y66-E66*F66*$Z$11 -> 0
B67: =IFERROR(VLOOKUP(A67,Mapping!$A:$F,2,FALSE),"") | C67: =IFERROR(VLOOKUP(A67,Mapping!$A:$F,3,FALSE),"") | F67: =IFERROR(VLOOKUP(A67,Mapping!$A:$F,4,FALSE),0) -> 0 | G67: =E67*F67 -> 0 | H67: =IFERROR(VLOOKUP(A67,Mapping!$A:$F,5,FALSE),0) -> 0 | J67: =IFERROR(VLOOKUP(A67,Mapping!$A:$F,6,FALSE),0) -> 0 | K67: =J67*(1-I67) -> 0 | L67: =IFERROR(J67-K67,"") -> 0 | M67: =E67*H67*(1-I67)*$N$11*(1-$N$10) -> 0 | N67: =M67-E67*F67*$N$11 -> 0 | O67: =E67*H67*(1-I67)*$P$11*(1-$P$10) -> 0 | P67: =O67-E67*F67*$P$11 -> 0 | Q67: =E67*H67*(1-I67)*$R$11*(1-$R$10) -> 0 | R67: =Q67-E67*F67*$R$11 -> 0 | S67: =E67*H67*(1-I67)*$T$11*(1-$T$10) -> 0 | T67: =S67-E67*F67*$T$11 -> 0 | U67: =E67*H67*(1-I67)*$V$11*(1-$V$10) -> 0 | V67: =U67-E67*F67*$V$11 -> 0 | W67: =E67*H67*(1-I67)*$X$11*(1-$X$10) -> 0 | X67: =W67-E67*F67*$X$11 -> 0 | Y67: =E67*H67*(1-I67)*$Z$11*(1-$Z$10) -> 0 | Z67: =Y67-E67*F67*$Z$11 -> 0
B68: =IFERROR(VLOOKUP(A68,Mapping!$A:$F,2,FALSE),"") | C68: =IFERROR(VLOOKUP(A68,Mapping!$A:$F,3,FALSE),"") | F68: =IFERROR(VLOOKUP(A68,Mapping!$A:$F,4,FALSE),0) -> 0 | G68: =E68*F68 -> 0 | H68: =IFERROR(VLOOKUP(A68,Mapping!$A:$F,5,FALSE),0) -> 0 | J68: =IFERROR(VLOOKUP(A68,Mapping!$A:$F,6,FALSE),0) -> 0 | K68: =J68*(1-I68) -> 0 | L68: =IFERROR(J68-K68,"") -> 0 | M68: =E68*H68*(1-I68)*$N$11*(1-$N$10) -> 0 | N68: =M68-E68*F68*$N$11 -> 0 | O68: =E68*H68*(1-I68)*$P$11*(1-$P$10) -> 0 | P68: =O68-E68*F68*$P$11 -> 0 | Q68: =E68*H68*(1-I68)*$R$11*(1-$R$10) -> 0 | R68: =Q68-E68*F68*$R$11 -> 0 | S68: =E68*H68*(1-I68)*$T$11*(1-$T$10) -> 0 | T68: =S68-E68*F68*$T$11 -> 0 | U68: =E68*H68*(1-I68)*$V$11*(1-$V$10) -> 0 | V68: =U68-E68*F68*$V$11 -> 0 | W68: =E68*H68*(1-I68)*$X$11*(1-$X$10) -> 0 | X68: =W68-E68*F68*$X$11 -> 0 | Y68: =E68*H68*(1-I68)*$Z$11*(1-$Z$10) -> 0 | Z68: =Y68-E68*F68*$Z$11 -> 0
B69: =IFERROR(VLOOKUP(A69,Mapping!$A:$F,2,FALSE),"") | C69: =IFERROR(VLOOKUP(A69,Mapping!$A:$F,3,FALSE),"") | F69: =IFERROR(VLOOKUP(A69,Mapping!$A:$F,4,FALSE),0) -> 0 | G69: =E69*F69 -> 0 | H69: =IFERROR(VLOOKUP(A69,Mapping!$A:$F,5,FALSE),0) -> 0 | J69: =IFERROR(VLOOKUP(A69,Mapping!$A:$F,6,FALSE),0) -> 0 | K69: =J69*(1-I69) -> 0 | L69: =IFERROR(J69-K69,"") -> 0 | M69: =E69*H69*(1-I69)*$N$11*(1-$N$10) -> 0 | N69: =M69-E69*F69*$N$11 -> 0 | O69: =E69*H69*(1-I69)*$P$11*(1-$P$10) -> 0 | P69: =O69-E69*F69*$P$11 -> 0 | Q69: =E69*H69*(1-I69)*$R$11*(1-$R$10) -> 0 | R69: =Q69-E69*F69*$R$11 -> 0 | S69: =E69*H69*(1-I69)*$T$11*(1-$T$10) -> 0 | T69: =S69-E69*F69*$T$11 -> 0 | U69: =E69*H69*(1-I69)*$V$11*(1-$V$10) -> 0 | V69: =U69-E69*F69*$V$11 -> 0 | W69: =E69*H69*(1-I69)*$X$11*(1-$X$10) -> 0 | X69: =W69-E69*F69*$X$11 -> 0 | Y69: =E69*H69*(1-I69)*$Z$11*(1-$Z$10) -> 0 | Z69: =Y69-E69*F69*$Z$11 -> 0
B70: =IFERROR(VLOOKUP(A70,Mapping!$A:$F,2,FALSE),"") | C70: =IFERROR(VLOOKUP(A70,Mapping!$A:$F,3,FALSE),"") | F70: =IFERROR(VLOOKUP(A70,Mapping!$A:$F,4,FALSE),0) -> 0 | G70: =E70*F70 -> 0 | H70: =IFERROR(VLOOKUP(A70,Mapping!$A:$F,5,FALSE),0) -> 0 | J70: =IFERROR(VLOOKUP(A70,Mapping!$A:$F,6,FALSE),0) -> 0 | K70: =J70*(1-I70) -> 0 | L70: =IFERROR(J70-K70,"") -> 0 | M70: =E70*H70*(1-I70)*$N$11*(1-$N$10) -> 0 | N70: =M70-E70*F70*$N$11 -> 0 | O70: =E70*H70*(1-I70)*$P$11*(1-$P$10) -> 0 | P70: =O70-E70*F70*$P$11 -> 0 | Q70: =E70*H70*(1-I70)*$R$11*(1-$R$10) -> 0 | R70: =Q70-E70*F70*$R$11 -> 0 | S70: =E70*H70*(1-I70)*$T$11*(1-$T$10) -> 0 | T70: =S70-E70*F70*$T$11 -> 0 | U70: =E70*H70*(1-I70)*$V$11*(1-$V$10) -> 0 | V70: =U70-E70*F70*$V$11 -> 0 | W70: =E70*H70*(1-I70)*$X$11*(1-$X$10) -> 0 | X70: =W70-E70*F70*$X$11 -> 0 | Y70: =E70*H70*(1-I70)*$Z$11*(1-$Z$10) -> 0 | Z70: =Y70-E70*F70*$Z$11 -> 0
B71: =IFERROR(VLOOKUP(A71,Mapping!$A:$F,2,FALSE),"") | C71: =IFERROR(VLOOKUP(A71,Mapping!$A:$F,3,FALSE),"") | F71: =IFERROR(VLOOKUP(A71,Mapping!$A:$F,4,FALSE),0) -> 0 | G71: =E71*F71 -> 0 | H71: =IFERROR(VLOOKUP(A71,Mapping!$A:$F,5,FALSE),0) -> 0 | J71: =IFERROR(VLOOKUP(A71,Mapping!$A:$F,6,FALSE),0) -> 0 | K71: =J71*(1-I71) -> 0 | L71: =IFERROR(J71-K71,"") -> 0 | M71: =E71*H71*(1-I71)*$N$11*(1-$N$10) -> 0 | N71: =M71-E71*F71*$N$11 -> 0 | O71: =E71*H71*(1-I71)*$P$11*(1-$P$10) -> 0 | P71: =O71-E71*F71*$P$11 -> 0 | Q71: =E71*H71*(1-I71)*$R$11*(1-$R$10) -> 0 | R71: =Q71-E71*F71*$R$11 -> 0 | S71: =E71*H71*(1-I71)*$T$11*(1-$T$10) -> 0 | T71: =S71-E71*F71*$T$11 -> 0 | U71: =E71*H71*(1-I71)*$V$11*(1-$V$10) -> 0 | V71: =U71-E71*F71*$V$11 -> 0 | W71: =E71*H71*(1-I71)*$X$11*(1-$X$10) -> 0 | X71: =W71-E71*F71*$X$11 -> 0 | Y71: =E71*H71*(1-I71)*$Z$11*(1-$Z$10) -> 0 | Z71: =Y71-E71*F71*$Z$11 -> 0
B72: =IFERROR(VLOOKUP(A72,Mapping!$A:$F,2,FALSE),"") | C72: =IFERROR(VLOOKUP(A72,Mapping!$A:$F,3,FALSE),"") | F72: =IFERROR(VLOOKUP(A72,Mapping!$A:$F,4,FALSE),0) -> 0 | G72: =E72*F72 -> 0 | H72: =IFERROR(VLOOKUP(A72,Mapping!$A:$F,5,FALSE),0) -> 0 | J72: =IFERROR(VLOOKUP(A72,Mapping!$A:$F,6,FALSE),0) -> 0 | K72: =J72*(1-I72) -> 0 | L72: =IFERROR(J72-K72,"") -> 0 | M72: =E72*H72*(1-I72)*$N$11*(1-$N$10) -> 0 | N72: =M72-E72*F72*$N$11 -> 0 | O72: =E72*H72*(1-I72)*$P$11*(1-$P$10) -> 0 | P72: =O72-E72*F72*$P$11 -> 0 | Q72: =E72*H72*(1-I72)*$R$11*(1-$R$10) -> 0 | R72: =Q72-E72*F72*$R$11 -> 0 | S72: =E72*H72*(1-I72)*$T$11*(1-$T$10) -> 0 | T72: =S72-E72*F72*$T$11 -> 0 | U72: =E72*H72*(1-I72)*$V$11*(1-$V$10) -> 0 | V72: =U72-E72*F72*$V$11 -> 0 | W72: =E72*H72*(1-I72)*$X$11*(1-$X$10) -> 0 | X72: =W72-E72*F72*$X$11 -> 0 | Y72: =E72*H72*(1-I72)*$Z$11*(1-$Z$10) -> 0 | Z72: =Y72-E72*F72*$Z$11 -> 0
A75: STANDARD
A77: Nombre d'offres
A78: Nombre de produits | B78: =SUM(E90:E102) -> 0
M79: RETAIL | S79: INSTITUT | AB79: Retail + Institut
M81: Ambassadeur | O81: Compagnon | Q81: Challenger | S81: Rose | U81: Prunelier | W81: Anthylide | Y81: Calendula | AB81: Total
M82: % Offres | O82: % Offres | Q82: % Offres | S82: % Offres | U82: % Offres | W82: % Offres | Y82: % offres
M83: Remise | N83: 0.17 | O83: Remise | P83: 0.13 | Q83: Remise | R83: 0.08 | S83: Remise | T83: 0.325 | U83: Remise | V83: 0.3 | W83: Remise | X83: 0.28 | Y83: Remise | Z83: 0.25
M84: Nb Offres | N84: =N82*$B$77 -> 0 | O84: Nb Offres | P84: =P82*$B$77 -> 0 | Q84: Nb Offres | R84: =R82*$B$77 -> 0 | S84: Nb Offres | T84: =T82*$B$77 -> 0 | U84: Nb Offres | V84: =V82*$B$77 -> 0 | W84: Nb Offres | X84: =X82*$B$77 -> 0 | Y84: Nb Offres | Z84: =Z82*$B$77 -> 0
E85: Pdt dans offre | F85: Coût achat unitaire | G85: Coûts achats total | H85: Tarif revendeur unitaire | I85: Remise additionnelle | J85: PPC | K85: PPC Remisé | L85: Montant BRI | M85: CA | N85: Marges | O85: CA | P85: Marges | Q85: CA | R85: Marges | S85: CA | T85: Marges | U85: CA | V85: Marges | W85: CA | X85: Marges | Y85: CA | Z85: Marges | AB85: Nbrs Offres planifiées | AC85: CA | AD85: Marges
A86: Code article | B86: Libellé article | C86: Code à barres (EAN) | D86: Typ. Prod | E86: '# | F86: '€ | G86: '€ | H86: '€ | I86: '€ | J86: '€ | K86: '€ | L86: '€ | M86: '€ | N86: '€ | O86: '€ | P86: '€ | Q86: '€ | R86: '€ | S86: '€ | T86: '€ | U86: '€ | V86: '€ | W86: '€ | X86: '€ | Y86: '€ | Z86: '€ | AB86: '# | AC86: '€ | AD86: '€
A88: Synthèse | E88: =IFERROR(SUMIFS(E90:E109,D90:D109,"Produit Vente"),"Non trouvé") -> 0 | G88: =IFERROR(SUM(G90:G109),"Non Trouvé") -> 0 | M88: =SUM(M90:M109) -> 0 | N88: =SUM(N90:N109) -> 0 | O88: =SUM(O90:O109) -> 0 | P88: =SUM(P90:P109) -> 0 | Q88: =SUM(Q90:Q109) -> 0 | R88: =SUM(R90:R109) -> 0 | S88: =SUM(S90:S109) -> 0 | T88: =SUM(T90:T109) -> 0 | ... Z88: =SUM(Z90:Z109) -> 0 | AB88: =B77 -> 0 | AC88: =Y88+W88+U88+S88+O88+M88+Q88 -> 0 | AD88: =Z88+X88+V88+T88+P88+N88+R88 -> 0
B90: =IFERROR(VLOOKUP(A90,Mapping!$A:$F,2,FALSE),"") | C90: =IFERROR(VLOOKUP(A90,Mapping!$A:$F,3,FALSE),"") | F90: =IFERROR(VLOOKUP(A90,Mapping!$A:$F,4,FALSE),0) -> 0 | G90: =E90*F90 -> 0 | H90: =IFERROR(VLOOKUP(A90,Mapping!$A:$F,5,FALSE),0) -> 0 | J90: =IFERROR(VLOOKUP(A90,Mapping!$A:$F,6,FALSE),0) -> 0 | K90: =J90*(1-I90) -> 0 | L90: =IFERROR(J90-K90,"") -> 0 | M90: =E90*H90*(1-I90)*$N$84*(1-$N$83) -> 0 | N90: =M90-E90*F90*$N$84 -> 0 | O90: =E90*H90*(1-I90)*$P$84*(1-$P$83) -> 0 | P90: =O90-E90*F90*$P$84 -> 0 | Q90: =E90*H90*(1-I90)*$R$84*(1-$R$83) -> 0 | R90: =Q90-E90*F90*$R$84 -> 0 | S90: =E90*H90*(1-I90)*$T$84*(1-$T$83) -> 0 | T90: =S90-E90*F90*$T$84 -> 0 | U90: =E90*H90*(1-I90)*$V$84*(1-$V$83) -> 0 | V90: =U90-E90*F90*$V$84 -> 0 | W90: =E90*H90*(1-I90)*$X$84*(1-$X$83) -> 0 | X90: =W90-E90*F90*$X$84 -> 0 | Y90: =E90*H90*(1-I90)*$Z$84*(1-$Z$83) -> 0 | Z90: =Y90-E90*F90*$Z$84 -> 0
B91: =IFERROR(VLOOKUP(A91,Mapping!$A:$F,2,FALSE),"") | C91: =IFERROR(VLOOKUP(A91,Mapping!$A:$F,3,FALSE),"") | F91: =IFERROR(VLOOKUP(A91,Mapping!$A:$F,4,FALSE),0) -> 0 | G91: =E91*F91 -> 0 | H91: =IFERROR(VLOOKUP(A91,Mapping!$A:$F,5,FALSE),0) -> 0 | J91: =IFERROR(VLOOKUP(A91,Mapping!$A:$F,6,FALSE),0) -> 0 | K91: =J91*(1-I91) -> 0 | L91: =IFERROR(J91-K91,"") -> 0 | M91: =E91*H91*(1-I91)*$N$84*(1-$N$83) -> 0 | N91: =M91-E91*F91*$N$84 -> 0 | O91: =E91*H91*(1-I91)*$P$84*(1-$P$83) -> 0 | P91: =O91-E91*F91*$P$84 -> 0 | Q91: =E91*H91*(1-I91)*$R$84*(1-$R$83) -> 0 | R91: =Q91-E91*F91*$R$84 -> 0 | S91: =E91*H91*(1-I91)*$T$84*(1-$T$83) -> 0 | T91: =S91-E91*F91*$T$84 -> 0 | U91: =E91*H91*(1-I91)*$V$84*(1-$V$83) -> 0 | V91: =U91-E91*F91*$V$84 -> 0 | W91: =E91*H91*(1-I91)*$X$84*(1-$X$83) -> 0 | X91: =W91-E91*F91*$X$84 -> 0 | Y91: =E91*H91*(1-I91)*$Z$84*(1-$Z$83) -> 0 | Z91: =Y91-E91*F91*$Z$84 -> 0 | AC91: Prix Offre Moy. Remisé : | AD91: =AC88/AB88 -> #DIV/0!
B92: =IFERROR(VLOOKUP(A92,Mapping!$A:$F,2,FALSE),"") | C92: =IFERROR(VLOOKUP(A92,Mapping!$A:$F,3,FALSE),"") | F92: =IFERROR(VLOOKUP(A92,Mapping!$A:$F,4,FALSE),0) -> 0 | G92: =E92*F92 -> 0 | H92: =IFERROR(VLOOKUP(A92,Mapping!$A:$F,5,FALSE),0) -> 0 | J92: =IFERROR(VLOOKUP(A92,Mapping!$A:$F,6,FALSE),0) -> 0 | K92: =J92*(1-I92) -> 0 | L92: =IFERROR(J92-K92,"") -> 0 | M92: =E92*H92*(1-I92)*$N$84*(1-$N$83) -> 0 | N92: =M92-E92*F92*$N$84 -> 0 | O92: =E92*H92*(1-I92)*$P$84*(1-$P$83) -> 0 | P92: =O92-E92*F92*$P$84 -> 0 | Q92: =E92*H92*(1-I92)*$R$84*(1-$R$83) -> 0 | R92: =Q92-E92*F92*$R$84 -> 0 | S92: =E92*H92*(1-I92)*$T$84*(1-$T$83) -> 0 | T92: =S92-E92*F92*$T$84 -> 0 | U92: =E92*H92*(1-I92)*$V$84*(1-$V$83) -> 0 | V92: =U92-E92*F92*$V$84 -> 0 | W92: =E92*H92*(1-I92)*$X$84*(1-$X$83) -> 0 | X92: =W92-E92*F92*$X$84 -> 0 | Y92: =E92*H92*(1-I92)*$Z$84*(1-$Z$83) -> 0 | Z92: =Y92-E92*F92*$Z$84 -> 0 | AC92: Poids Gratuités achats : | AD92: =SUM(AD94:AD97) -> #DIV/0!
B93: =IFERROR(VLOOKUP(A93,Mapping!$A:$F,2,FALSE),"") | C93: =IFERROR(VLOOKUP(A93,Mapping!$A:$F,3,FALSE),"") | F93: =IFERROR(VLOOKUP(A93,Mapping!$A:$F,4,FALSE),0) -> 0 | G93: =E93*F93 -> 0 | H93: =IFERROR(VLOOKUP(A93,Mapping!$A:$F,5,FALSE),0) -> 0 | J93: =IFERROR(VLOOKUP(A93,Mapping!$A:$F,6,FALSE),0) -> 0 | K93: =J93*(1-I93) -> 0 | L93: =IFERROR(J93-K93,"") -> 0 | M93: =E93*H93*(1-I93)*$N$84*(1-$N$83) -> 0 | N93: =M93-E93*F93*$N$84 -> 0 | O93: =E93*H93*(1-I93)*$P$84*(1-$P$83) -> 0 | P93: =O93-E93*F93*$P$84 -> 0 | Q93: =E93*H93*(1-I93)*$R$84*(1-$R$83) -> 0 | R93: =Q93-E93*F93*$R$84 -> 0 | S93: =E93*H93*(1-I93)*$T$84*(1-$T$83) -> 0 | T93: =S93-E93*F93*$T$84 -> 0 | U93: =E93*H93*(1-I93)*$V$84*(1-$V$83) -> 0 | V93: =U93-E93*F93*$V$84 -> 0 | W93: =E93*H93*(1-I93)*$X$84*(1-$X$83) -> 0 | X93: =W93-E93*F93*$X$84 -> 0 | Y93: =E93*H93*(1-I93)*$Z$84*(1-$Z$83) -> 0 | Z93: =Y93-E93*F93*$Z$84 -> 0
B94: =IFERROR(VLOOKUP(A94,Mapping!$A:$F,2,FALSE),"") | C94: =IFERROR(VLOOKUP(A94,Mapping!$A:$F,3,FALSE),"") | F94: =IFERROR(VLOOKUP(A94,Mapping!$A:$F,4,FALSE),0) -> 0 | G94: =E94*F94 -> 0 | H94: =IFERROR(VLOOKUP(A94,Mapping!$A:$F,5,FALSE),0) -> 0 | J94: =IFERROR(VLOOKUP(A94,Mapping!$A:$F,6,FALSE),0) -> 0 | K94: =J94*(1-I94) -> 0 | L94: =IFERROR(J94-K94,"") -> 0 | M94: =E94*H94*(1-I94)*$N$84*(1-$N$83) -> 0 | N94: =M94-E94*F94*$N$84 -> 0 | O94: =E94*H94*(1-I94)*$P$84*(1-$P$83) -> 0 | P94: =O94-E94*F94*$P$84 -> 0 | Q94: =E94*H94*(1-I94)*$R$84*(1-$R$83) -> 0 | R94: =Q94-E94*F94*$R$84 -> 0 | S94: =E94*H94*(1-I94)*$T$84*(1-$T$83) -> 0 | T94: =S94-E94*F94*$T$84 -> 0 | U94: =E94*H94*(1-I94)*$V$84*(1-$V$83) -> 0 | V94: =U94-E94*F94*$V$84 -> 0 | W94: =E94*H94*(1-I94)*$X$84*(1-$X$83) -> 0 | X94: =W94-E94*F94*$X$84 -> 0 | Y94: =E94*H94*(1-I94)*$Z$84*(1-$Z$83) -> 0 | Z94: =Y94-E94*F94*$Z$84 -> 0 | AC94: UG | AD94: =SUMIF($D$90:$D$109,AC94,$G$90:$G$109)/$AC$88 -> #DIV/0!
B95: =IFERROR(VLOOKUP(A95,Mapping!$A:$F,2,FALSE),"") | C95: =IFERROR(VLOOKUP(A95,Mapping!$A:$F,3,FALSE),"") | F95: =IFERROR(VLOOKUP(A95,Mapping!$A:$F,4,FALSE),0) -> 0 | G95: =E95*F95 -> 0 | H95: =IFERROR(VLOOKUP(A95,Mapping!$A:$F,5,FALSE),0) -> 0 | J95: =IFERROR(VLOOKUP(A95,Mapping!$A:$F,6,FALSE),0) -> 0 | K95: =J95*(1-I95) -> 0 | L95: =IFERROR(J95-K95,"") -> 0 | M95: =E95*H95*(1-I95)*$N$84*(1-$N$83) -> 0 | N95: =M95-E95*F95*$N$84 -> 0 | O95: =E95*H95*(1-I95)*$P$84*(1-$P$83) -> 0 | P95: =O95-E95*F95*$P$84 -> 0 | Q95: =E95*H95*(1-I95)*$R$84*(1-$R$83) -> 0 | R95: =Q95-E95*F95*$R$84 -> 0 | S95: =E95*H95*(1-I95)*$T$84*(1-$T$83) -> 0 | T95: =S95-E95*F95*$T$84 -> 0 | U95: =E95*H95*(1-I95)*$V$84*(1-$V$83) -> 0 | V95: =U95-E95*F95*$V$84 -> 0 | W95: =E95*H95*(1-I95)*$X$84*(1-$X$83) -> 0 | X95: =W95-E95*F95*$X$84 -> 0 | Y95: =E95*H95*(1-I95)*$Z$84*(1-$Z$83) -> 0 | Z95: =Y95-E95*F95*$Z$84 -> 0 | AC95: PLV | AD95: =SUMIF($D$90:$D$109,AC95,$G$90:$G$109)/$AC$88 -> #DIV/0!
B96: =IFERROR(VLOOKUP(A96,Mapping!$A:$F,2,FALSE),"") | C96: =IFERROR(VLOOKUP(A96,Mapping!$A:$F,3,FALSE),"") | F96: =IFERROR(VLOOKUP(A96,Mapping!$A:$F,4,FALSE),0) -> 0 | G96: =E96*F96 -> 0 | H96: =IFERROR(VLOOKUP(A96,Mapping!$A:$F,5,FALSE),0) -> 0 | J96: =IFERROR(VLOOKUP(A96,Mapping!$A:$F,6,FALSE),0) -> 0 | K96: =J96*(1-I96) -> 0 | L96: =IFERROR(J96-K96,"") -> 0 | M96: =E96*H96*(1-I96)*$N$84*(1-$N$83) -> 0 | N96: =M96-E96*F96*$N$84 -> 0 | O96: =E96*H96*(1-I96)*$P$84*(1-$P$83) -> 0 | P96: =O96-E96*F96*$P$84 -> 0 | Q96: =E96*H96*(1-I96)*$R$84*(1-$R$83) -> 0 | R96: =Q96-E96*F96*$R$84 -> 0 | S96: =E96*H96*(1-I96)*$T$84*(1-$T$83) -> 0 | T96: =S96-E96*F96*$T$84 -> 0 | U96: =E96*H96*(1-I96)*$V$84*(1-$V$83) -> 0 | V96: =U96-E96*F96*$V$84 -> 0 | W96: =E96*H96*(1-I96)*$X$84*(1-$X$83) -> 0 | X96: =W96-E96*F96*$X$84 -> 0 | Y96: =E96*H96*(1-I96)*$Z$84*(1-$Z$83) -> 0 | Z96: =Y96-E96*F96*$Z$84 -> 0 | AC96: Echantillon | AD96: =SUMIF($D$90:$D$109,AC96,$G$90:$G$109)/$AC$88 -> #DIV/0!
B97: =IFERROR(VLOOKUP(A97,Mapping!$A:$F,2,FALSE),"") | C97: =IFERROR(VLOOKUP(A97,Mapping!$A:$F,3,FALSE),"") | F97: =IFERROR(VLOOKUP(A97,Mapping!$A:$F,4,FALSE),0) -> 0 | G97: =E97*F97 -> 0 | H97: =IFERROR(VLOOKUP(A97,Mapping!$A:$F,5,FALSE),0) -> 0 | J97: =IFERROR(VLOOKUP(A97,Mapping!$A:$F,6,FALSE),0) -> 0 | K97: =J97*(1-I97) -> 0 | L97: =IFERROR(J97-K97,"") -> 0 | M97: =E97*H97*(1-I97)*$N$84*(1-$N$83) -> 0 | N97: =M97-E97*F97*$N$84 -> 0 | O97: =E97*H97*(1-I97)*$P$84*(1-$P$83) -> 0 | P97: =O97-E97*F97*$P$84 -> 0 | Q97: =E97*H97*(1-I97)*$R$84*(1-$R$83) -> 0 | R97: =Q97-E97*F97*$R$84 -> 0 | S97: =E97*H97*(1-I97)*$T$84*(1-$T$83) -> 0 | T97: =S97-E97*F97*$T$84 -> 0 | U97: =E97*H97*(1-I97)*$V$84*(1-$V$83) -> 0 | V97: =U97-E97*F97*$V$84 -> 0 | W97: =E97*H97*(1-I97)*$X$84*(1-$X$83) -> 0 | X97: =W97-E97*F97*$X$84 -> 0 | Y97: =E97*H97*(1-I97)*$Z$84*(1-$Z$83) -> 0 | Z97: =Y97-E97*F97*$Z$84 -> 0 | AC97: Testeur | AD97: =SUMIF($D$90:$D$109,AC97,$G$90:$G$109)/$AC$88 -> #DIV/0!
B98: =IFERROR(VLOOKUP(A98,Mapping!$A:$F,2,FALSE),"") | C98: =IFERROR(VLOOKUP(A98,Mapping!$A:$F,3,FALSE),"") | F98: =IFERROR(VLOOKUP(A98,Mapping!$A:$F,4,FALSE),0) -> 0 | G98: =E98*F98 -> 0 | H98: =IFERROR(VLOOKUP(A98,Mapping!$A:$F,5,FALSE),0) -> 0 | J98: =IFERROR(VLOOKUP(A98,Mapping!$A:$F,6,FALSE),0) -> 0 | K98: =J98*(1-I98) -> 0 | L98: =IFERROR(J98-K98,"") -> 0 | M98: =E98*H98*(1-I98)*$N$84*(1-$N$83) -> 0 | N98: =M98-E98*F98*$N$84 -> 0 | O98: =E98*H98*(1-I98)*$P$84*(1-$P$83) -> 0 | P98: =O98-E98*F98*$P$84 -> 0 | Q98: =E98*H98*(1-I98)*$R$84*(1-$R$83) -> 0 | R98: =Q98-E98*F98*$R$84 -> 0 | S98: =E98*H98*(1-I98)*$T$84*(1-$T$83) -> 0 | T98: =S98-E98*F98*$T$84 -> 0 | U98: =E98*H98*(1-I98)*$V$84*(1-$V$83) -> 0 | V98: =U98-E98*F98*$V$84 -> 0 | W98: =E98*H98*(1-I98)*$X$84*(1-$X$83) -> 0 | X98: =W98-E98*F98*$X$84 -> 0 | Y98: =E98*H98*(1-I98)*$Z$84*(1-$Z$83) -> 0 | Z98: =Y98-E98*F98*$Z$84 -> 0
B99: =IFERROR(VLOOKUP(A99,Mapping!$A:$F,2,FALSE),"") | C99: =IFERROR(VLOOKUP(A99,Mapping!$A:$F,3,FALSE),"") | F99: =IFERROR(VLOOKUP(A99,Mapping!$A:$F,4,FALSE),0) -> 0 | G99: =E99*F99 -> 0 | H99: =IFERROR(VLOOKUP(A99,Mapping!$A:$F,5,FALSE),0) -> 0 | J99: =IFERROR(VLOOKUP(A99,Mapping!$A:$F,6,FALSE),0) -> 0 | K99: =J99*(1-I99) -> 0 | L99: =IFERROR(J99-K99,"") -> 0 | M99: =E99*H99*(1-I99)*$N$84*(1-$N$83) -> 0 | N99: =M99-E99*F99*$N$84 -> 0 | O99: =E99*H99*(1-I99)*$P$84*(1-$P$83) -> 0 | P99: =O99-E99*F99*$P$84 -> 0 | Q99: =E99*H99*(1-I99)*$R$84*(1-$R$83) -> 0 | R99: =Q99-E99*F99*$R$84 -> 0 | S99: =E99*H99*(1-I99)*$T$84*(1-$T$83) -> 0 | T99: =S99-E99*F99*$T$84 -> 0 | U99: =E99*H99*(1-I99)*$V$84*(1-$V$83) -> 0 | V99: =U99-E99*F99*$V$84 -> 0 | W99: =E99*H99*(1-I99)*$X$84*(1-$X$83) -> 0 | X99: =W99-E99*F99*$X$84 -> 0 | Y99: =E99*H99*(1-I99)*$Z$84*(1-$Z$83) -> 0 | Z99: =Y99-E99*F99*$Z$84 -> 0
B100: =IFERROR(VLOOKUP(A100,Mapping!$A:$F,2,FALSE),"") | C100: =IFERROR(VLOOKUP(A100,Mapping!$A:$F,3,FALSE),"") | F100: =IFERROR(VLOOKUP(A100,Mapping!$A:$F,4,FALSE),0) -> 0 | G100: =E100*F100 -> 0 | H100: =IFERROR(VLOOKUP(A100,Mapping!$A:$F,5,FALSE),0) -> 0 | J100: =IFERROR(VLOOKUP(A100,Mapping!$A:$F,6,FALSE),0) -> 0 | K100: =J100*(1-I100) -> 0 | L100: =IFERROR(J100-K100,"") -> 0 | M100: =E100*H100*(1-I100)*$N$84*(1-$N$83) -> 0 | N100: =M100-E100*F100*$N$84 -> 0 | O100: =E100*H100*(1-I100)*$P$84*(1-$P$83) -> 0 | P100: =O100-E100*F100*$P$84 -> 0 | Q100: =E100*H100*(1-I100)*$R$84*(1-$R$83) -> 0 | R100: =Q100-E100*F100*$R$84 -> 0 | S100: =E100*H100*(1-I100)*$T$84*(1-$T$83) -> 0 | T100: =S100-E100*F100*$T$84 -> 0 | U100: =E100*H100*(1-I100)*$V$84*(1-$V$83) -> 0 | V100: =U100-E100*F100*$V$84 -> 0 | W100: =E100*H100*(1-I100)*$X$84*(1-$X$83) -> 0 | X100: =W100-E100*F100*$X$84 -> 0 | Y100: =E100*H100*(1-I100)*$Z$84*(1-$Z$83) -> 0 | Z100: =Y100-E100*F100*$Z$84 -> 0
B101: =IFERROR(VLOOKUP(A101,Mapping!$A:$F,2,FALSE),"") | C101: =IFERROR(VLOOKUP(A101,Mapping!$A:$F,3,FALSE),"") | F101: =IFERROR(VLOOKUP(A101,Mapping!$A:$F,4,FALSE),0) -> 0 | G101: =E101*F101 -> 0 | H101: =IFERROR(VLOOKUP(A101,Mapping!$A:$F,5,FALSE),0) -> 0 | J101: =IFERROR(VLOOKUP(A101,Mapping!$A:$F,6,FALSE),0) -> 0 | K101: =J101*(1-I101) -> 0 | L101: =IFERROR(J101-K101,"") -> 0 | M101: =E101*H101*(1-I101)*$N$84*(1-$N$83) -> 0 | N101: =M101-E101*F101*$N$84 -> 0 | O101: =E101*H101*(1-I101)*$P$84*(1-$P$83) -> 0 | P101: =O101-E101*F101*$P$84 -> 0 | Q101: =E101*H101*(1-I101)*$R$84*(1-$R$83) -> 0 | R101: =Q101-E101*F101*$R$84 -> 0 | S101: =E101*H101*(1-I101)*$T$84*(1-$T$83) -> 0 | T101: =S101-E101*F101*$T$84 -> 0 | U101: =E101*H101*(1-I101)*$V$84*(1-$V$83) -> 0 | V101: =U101-E101*F101*$V$84 -> 0 | W101: =E101*H101*(1-I101)*$X$84*(1-$X$83) -> 0 | X101: =W101-E101*F101*$X$84 -> 0 | Y101: =E101*H101*(1-I101)*$Z$84*(1-$Z$83) -> 0 | Z101: =Y101-E101*F101*$Z$84 -> 0
B102: =IFERROR(VLOOKUP(A102,Mapping!$A:$F,2,FALSE),"") | C102: =IFERROR(VLOOKUP(A102,Mapping!$A:$F,3,FALSE),"") | F102: =IFERROR(VLOOKUP(A102,Mapping!$A:$F,4,FALSE),0) -> 0 | G102: =E102*F102 -> 0 | H102: =IFERROR(VLOOKUP(A102,Mapping!$A:$F,5,FALSE),0) -> 0 | J102: =IFERROR(VLOOKUP(A102,Mapping!$A:$F,6,FALSE),0) -> 0 | K102: =J102*(1-I102) -> 0 | L102: =IFERROR(J102-K102,"") -> 0 | M102: =E102*H102*(1-I102)*$N$84*(1-$N$83) -> 0 | N102: =M102-E102*F102*$N$84 -> 0 | O102: =E102*H102*(1-I102)*$P$84*(1-$P$83) -> 0 | P102: =O102-E102*F102*$P$84 -> 0 | Q102: =E102*H102*(1-I102)*$R$84*(1-$R$83) -> 0 | R102: =Q102-E102*F102*$R$84 -> 0 | S102: =E102*H102*(1-I102)*$T$84*(1-$T$83) -> 0 | T102: =S102-E102*F102*$T$84 -> 0 | U102: =E102*H102*(1-I102)*$V$84*(1-$V$83) -> 0 | V102: =U102-E102*F102*$V$84 -> 0 | W102: =E102*H102*(1-I102)*$X$84*(1-$X$83) -> 0 | X102: =W102-E102*F102*$X$84 -> 0 | Y102: =E102*H102*(1-I102)*$Z$84*(1-$Z$83) -> 0 | Z102: =Y102-E102*F102*$Z$84 -> 0
B103: =IFERROR(VLOOKUP(A103,Mapping!$A:$F,2,FALSE),"") | C103: =IFERROR(VLOOKUP(A103,Mapping!$A:$F,3,FALSE),"") | F103: =IFERROR(VLOOKUP(A103,Mapping!$A:$F,4,FALSE),0) -> 0 | G103: =E103*F103 -> 0 | H103: =IFERROR(VLOOKUP(A103,Mapping!$A:$F,5,FALSE),0) -> 0 | J103: =IFERROR(VLOOKUP(A103,Mapping!$A:$F,6,FALSE),0) -> 0 | K103: =J103*(1-I103) -> 0 | L103: =IFERROR(J103-K103,"") -> 0 | M103: =E103*H103*(1-I103)*$N$84*(1-$N$83) -> 0 | N103: =M103-E103*F103*$N$84 -> 0 | O103: =E103*H103*(1-I103)*$P$84*(1-$P$83) -> 0 | P103: =O103-E103*F103*$P$84 -> 0 | Q103: =E103*H103*(1-I103)*$R$84*(1-$R$83) -> 0 | R103: =Q103-E103*F103*$R$84 -> 0 | S103: =E103*H103*(1-I103)*$T$84*(1-$T$83) -> 0 | T103: =S103-E103*F103*$T$84 -> 0 | U103: =E103*H103*(1-I103)*$V$84*(1-$V$83) -> 0 | V103: =U103-E103*F103*$V$84 -> 0 | W103: =E103*H103*(1-I103)*$X$84*(1-$X$83) -> 0 | X103: =W103-E103*F103*$X$84 -> 0 | Y103: =E103*H103*(1-I103)*$Z$84*(1-$Z$83) -> 0 | Z103: =Y103-E103*F103*$Z$84 -> 0
B104: =IFERROR(VLOOKUP(A104,Mapping!$A:$F,2,FALSE),"") | C104: =IFERROR(VLOOKUP(A104,Mapping!$A:$F,3,FALSE),"") | F104: =IFERROR(VLOOKUP(A104,Mapping!$A:$F,4,FALSE),0) -> 0 | G104: =E104*F104 -> 0 | H104: =IFERROR(VLOOKUP(A104,Mapping!$A:$F,5,FALSE),0) -> 0 | J104: =IFERROR(VLOOKUP(A104,Mapping!$A:$F,6,FALSE),0) -> 0 | K104: =J104*(1-I104) -> 0 | L104: =IFERROR(J104-K104,"") -> 0 | M104: =E104*H104*(1-I104)*$N$84*(1-$N$83) -> 0 | N104: =M104-E104*F104*$N$84 -> 0 | O104: =E104*H104*(1-I104)*$P$84*(1-$P$83) -> 0 | P104: =O104-E104*F104*$P$84 -> 0 | Q104: =E104*H104*(1-I104)*$R$84*(1-$R$83) -> 0 | R104: =Q104-E104*F104*$R$84 -> 0 | S104: =E104*H104*(1-I104)*$T$84*(1-$T$83) -> 0 | T104: =S104-E104*F104*$T$84 -> 0 | U104: =E104*H104*(1-I104)*$V$84*(1-$V$83) -> 0 | V104: =U104-E104*F104*$V$84 -> 0 | W104: =E104*H104*(1-I104)*$X$84*(1-$X$83) -> 0 | X104: =W104-E104*F104*$X$84 -> 0 | Y104: =E104*H104*(1-I104)*$Z$84*(1-$Z$83) -> 0 | Z104: =Y104-E104*F104*$Z$84 -> 0
B105: =IFERROR(VLOOKUP(A105,Mapping!$A:$F,2,FALSE),"") | C105: =IFERROR(VLOOKUP(A105,Mapping!$A:$F,3,FALSE),"") | F105: =IFERROR(VLOOKUP(A105,Mapping!$A:$F,4,FALSE),0) -> 0 | G105: =E105*F105 -> 0 | H105: =IFERROR(VLOOKUP(A105,Mapping!$A:$F,5,FALSE),0) -> 0 | J105: =IFERROR(VLOOKUP(A105,Mapping!$A:$F,6,FALSE),0) -> 0 | K105: =J105*(1-I105) -> 0 | L105: =IFERROR(J105-K105,"") -> 0 | M105: =E105*H105*(1-I105)*$N$84*(1-$N$83) -> 0 | N105: =M105-E105*F105*$N$84 -> 0 | O105: =E105*H105*(1-I105)*$P$84*(1-$P$83) -> 0 | P105: =O105-E105*F105*$P$84 -> 0 | Q105: =E105*H105*(1-I105)*$R$84*(1-$R$83) -> 0 | R105: =Q105-E105*F105*$R$84 -> 0 | S105: =E105*H105*(1-I105)*$T$84*(1-$T$83) -> 0 | T105: =S105-E105*F105*$T$84 -> 0 | U105: =E105*H105*(1-I105)*$V$84*(1-$V$83) -> 0 | V105: =U105-E105*F105*$V$84 -> 0 | W105: =E105*H105*(1-I105)*$X$84*(1-$X$83) -> 0 | X105: =W105-E105*F105*$X$84 -> 0 | Y105: =E105*H105*(1-I105)*$Z$84*(1-$Z$83) -> 0 | Z105: =Y105-E105*F105*$Z$84 -> 0
B106: =IFERROR(VLOOKUP(A106,Mapping!$A:$F,2,FALSE),"") | C106: =IFERROR(VLOOKUP(A106,Mapping!$A:$F,3,FALSE),"") | F106: =IFERROR(VLOOKUP(A106,Mapping!$A:$F,4,FALSE),0) -> 0 | G106: =E106*F106 -> 0 | H106: =IFERROR(VLOOKUP(A106,Mapping!$A:$F,5,FALSE),0) -> 0 | J106: =IFERROR(VLOOKUP(A106,Mapping!$A:$F,6,FALSE),0) -> 0 | K106: =J106*(1-I106) -> 0 | L106: =IFERROR(J106-K106,"") -> 0 | M106: =E106*H106*(1-I106)*$N$84*(1-$N$83) -> 0 | N106: =M106-E106*F106*$N$84 -> 0 | O106: =E106*H106*(1-I106)*$P$84*(1-$P$83) -> 0 | P106: =O106-E106*F106*$P$84 -> 0 | Q106: =E106*H106*(1-I106)*$R$84*(1-$R$83) -> 0 | R106: =Q106-E106*F106*$R$84 -> 0 | S106: =E106*H106*(1-I106)*$T$84*(1-$T$83) -> 0 | T106: =S106-E106*F106*$T$84 -> 0 | U106: =E106*H106*(1-I106)*$V$84*(1-$V$83) -> 0 | V106: =U106-E106*F106*$V$84 -> 0 | W106: =E106*H106*(1-I106)*$X$84*(1-$X$83) -> 0 | X106: =W106-E106*F106*$X$84 -> 0 | Y106: =E106*H106*(1-I106)*$Z$84*(1-$Z$83) -> 0 | Z106: =Y106-E106*F106*$Z$84 -> 0
B107: =IFERROR(VLOOKUP(A107,Mapping!$A:$F,2,FALSE),"") | C107: =IFERROR(VLOOKUP(A107,Mapping!$A:$F,3,FALSE),"") | F107: =IFERROR(VLOOKUP(A107,Mapping!$A:$F,4,FALSE),0) -> 0 | G107: =E107*F107 -> 0 | H107: =IFERROR(VLOOKUP(A107,Mapping!$A:$F,5,FALSE),0) -> 0 | J107: =IFERROR(VLOOKUP(A107,Mapping!$A:$F,6,FALSE),0) -> 0 | K107: =J107*(1-I107) -> 0 | L107: =IFERROR(J107-K107,"") -> 0 | M107: =E107*H107*(1-I107)*$N$84*(1-$N$83) -> 0 | N107: =M107-E107*F107*$N$84 -> 0 | O107: =E107*H107*(1-I107)*$P$84*(1-$P$83) -> 0 | P107: =O107-E107*F107*$P$84 -> 0 | Q107: =E107*H107*(1-I107)*$R$84*(1-$R$83) -> 0 | R107: =Q107-E107*F107*$R$84 -> 0 | S107: =E107*H107*(1-I107)*$T$84*(1-$T$83) -> 0 | T107: =S107-E107*F107*$T$84 -> 0 | U107: =E107*H107*(1-I107)*$V$84*(1-$V$83) -> 0 | V107: =U107-E107*F107*$V$84 -> 0 | W107: =E107*H107*(1-I107)*$X$84*(1-$X$83) -> 0 | X107: =W107-E107*F107*$X$84 -> 0 | Y107: =E107*H107*(1-I107)*$Z$84*(1-$Z$83) -> 0 | Z107: =Y107-E107*F107*$Z$84 -> 0
B108: =IFERROR(VLOOKUP(A108,Mapping!$A:$F,2,FALSE),"") | C108: =IFERROR(VLOOKUP(A108,Mapping!$A:$F,3,FALSE),"") | F108: =IFERROR(VLOOKUP(A108,Mapping!$A:$F,4,FALSE),0) -> 0 | G108: =E108*F108 -> 0 | H108: =IFERROR(VLOOKUP(A108,Mapping!$A:$F,5,FALSE),0) -> 0 | J108: =IFERROR(VLOOKUP(A108,Mapping!$A:$F,6,FALSE),0) -> 0 | K108: =J108*(1-I108) -> 0 | L108: =IFERROR(J108-K108,"") -> 0 | M108: =E108*H108*(1-I108)*$N$84*(1-$N$83) -> 0 | N108: =M108-E108*F108*$N$84 -> 0 | O108: =E108*H108*(1-I108)*$P$84*(1-$P$83) -> 0 | P108: =O108-E108*F108*$P$84 -> 0 | Q108: =E108*H108*(1-I108)*$R$84*(1-$R$83) -> 0 | R108: =Q108-E108*F108*$R$84 -> 0 | S108: =E108*H108*(1-I108)*$T$84*(1-$T$83) -> 0 | T108: =S108-E108*F108*$T$84 -> 0 | U108: =E108*H108*(1-I108)*$V$84*(1-$V$83) -> 0 | V108: =U108-E108*F108*$V$84 -> 0 | W108: =E108*H108*(1-I108)*$X$84*(1-$X$83) -> 0 | X108: =W108-E108*F108*$X$84 -> 0 | Y108: =E108*H108*(1-I108)*$Z$84*(1-$Z$83) -> 0 | Z108: =Y108-E108*F108*$Z$84 -> 0
B109: =IFERROR(VLOOKUP(A109,Mapping!$A:$F,2,FALSE),"") | C109: =IFERROR(VLOOKUP(A109,Mapping!$A:$F,3,FALSE),"") | F109: =IFERROR(VLOOKUP(A109,Mapping!$A:$F,4,FALSE),0) -> 0 | G109: =E109*F109 -> 0 | H109: =IFERROR(VLOOKUP(A109,Mapping!$A:$F,5,FALSE),0) -> 0 | J109: =IFERROR(VLOOKUP(A109,Mapping!$A:$F,6,FALSE),0) -> 0 | K109: =J109*(1-I109) -> 0 | L109: =IFERROR(J109-K109,"") -> 0 | M109: =E109*H109*(1-I109)*$N$84*(1-$N$83) -> 0 | N109: =M109-E109*F109*$N$84 -> 0 | O109: =E109*H109*(1-I109)*$P$84*(1-$P$83) -> 0 | P109: =O109-E109*F109*$P$84 -> 0 | Q109: =E109*H109*(1-I109)*$R$84*(1-$R$83) -> 0 | R109: =Q109-E109*F109*$R$84 -> 0 | S109: =E109*H109*(1-I109)*$T$84*(1-$T$83) -> 0 | T109: =S109-E109*F109*$T$84 -> 0 | U109: =E109*H109*(1-I109)*$V$84*(1-$V$83) -> 0 | V109: =U109-E109*F109*$V$84 -> 0 | W109: =E109*H109*(1-I109)*$X$84*(1-$X$83) -> 0 | X109: =W109-E109*F109*$X$84 -> 0 | Y109: =E109*H109*(1-I109)*$Z$84*(1-$Z$83) -> 0 | Z109: =Y109-E109*F109*$Z$84 -> 0
A112: ESSENTIEL
A114: Nombre d'offres
A115: Nombre de produits | B115: =SUM(E127:E139) -> 0
M116: RETAIL | S116: INSTITUT | AB116: Retail + Institut
M118: Ambassadeur | O118: Compagnon | Q118: Challenger | S118: Rose | U118: Prunelier | W118: Anthylide | Y118: Calendula | AB118: Total
M119: % Offres | O119: % Offres | Q119: % Offres | S119: % Offres | U119: % Offres | W119: % Offres | Y119: % offres
M120: Remise | N120: 0.17 | O120: Remise | P120: 0.13 | Q120: Remise | R120: 0.08 | S120: Remise | T120: 0.325 | U120: Remise | V120: 0.3 | W120: Remise | X120: 0.28 | Y120: Remise | Z120: 0.25
...

Sheet Mapping
A1: Code article | B1: Libellé article | C1: Code à barres (EAN) | D1: Coût achat unitaire | E1: Tarif revendeur unitaire | F1: PPC
A2: 1010101 | B2: Crème Purifiante pour le Visage - 50 ml | C2: 4020829005181 | D2: 3.92 | E2: 10.58 | F2: 18
A3: 1010102 | B3: Lait Démaquillant et Nettoyant - 145 ml | C3: 4020829006041 | D3: 6.55 | E3: 17.06 | F3: 29
A4: 1010110 | B4: Démaquillant pour les Yeux - 75 ml | C4: 4020829063143 | D4: 6.08 | E4: 16.47 | F4: 28
A5: 1010115 | B5: Lait Démaquillant et Nettoyant - 30 ml | C5: 4020829066441 | D5: 2.47 | E5: 0 | F5: 0
A6: 1010116 | B6: Baume Lacté Nettoyant - 75 ml | C6: 4020829094048 | D6: 4.84 | E6: 12.94 | F6: 22
A7: 1010120 | B7: Baume Lacté Nettoyant - 20 ml | C7: 4020829101838 | D7: 1.61 | E7: 0 | F7: 0
A8: 1010121 | B8: Crème Purifiante pour le Visage - 20 ml | C8: 4020829101821 | D8: 1.63 | E8: 0 | F8: 0
A9: 1010122 | B9: Baume Lacté Nettoyant 20ml Édition spéciale 2025 | C9: 4020829111776 | D9: 0 | E9: 0 | F9: 0
A10: 1010201 | B10: Lotion Tonifiante - 100 ml | C10: 4020829005235 | D10: 6.72 | E10: 18.24 | F10: 31
A11: 1010202 | B11: Lotion Clarifiante - 100 ml | C11: 4020829005297 | D11: 7.06 | E11: 18.24 | F11: 31
A12: 1010205 | B12: Lotion Tonifiante - 30 ml | C12: 4020829066465 | D12: 2.44 | E12: 0 | F12: 9.2
A13: 1010206 | B13: Lotion Clarifiante - 30 ml | C13: 4020829114241 | D13: 2.64 | E13: 0 | F13: 0
... A63: 1011050 | B63: Coffret Rituel de Rose* DLV 01/2026* (copie) | C63: 1011050999999 | D63: 11.86 | E63: 15.8 | F63: 39.5
A64: 1011054 | B64: Coffret de noël rituel soin 2025 (copie) | D64: 11.95 | E64: 15.8 | F64: 39.5
A65: 1011055 | B65: Mon rituel Apaisant 2026 | C65: 3770026497562 | D65: 5.34 | E65: 10.53 | F65: 17.9
A66: 1011056 | B66: Mon rituel Éclat 2026 | C66: 3770026497579 | D66: 5.38 | E66: 10.53 | F66: 17.9
A67: 1011057 | B67: Coffret Les Essentiels Éclat 2026 | C67: 3770026497586 | D67: 6.35 | E67: 10.58 | F67: 18
A68: 1011058 | B68: Duo Baume Lacté Nettoyant 2026 | C68: 3770026497593 | D68: 9.58 | E68: 19.41 | F68: 33
A69: 1011059 | B69: Coffret Noël 2026 Rituel de Roses | C69: 3770026497623 | D69: 12.45 | E69: 27.59 | F69: 46.9
A70: 1011060 | B70: Coffret Noël 2026 Rituel Éclat | C70: 3770026497630 | D70: 10.72 | E70: 17.59 | F70: 29.9
A71: 1011061 | B71: Coffret Noël 2026 Duo Mains & Lèvres | C71: 3770026497654 | D71: 4.31 | E71: 8.76 | F71: 14.9
A72: 1011062 | B72: Calendrier de l’Avent 2026 | D72: 43.36 | E72: 0 | F72: 0
A73: 1011063 | B73: Duo Stick Éclat des Lèvres 2026 | C73: 3770026497609 | D73: 6.22 | E73: 10.23 | F73: 17.9
A74: 1020101 | B74: Lait pour le Corps Régénérant - 150 ml | C74: 4020829008410 | D74: 10.23 | E74: 26.12 | F74: 44.4
A75: 1020102 | B75: Crème pour les Mains - Régénérant - 50 ml | C75: 4020829049666 | D75: 6.55 | E75: 17.35 | F75: 29.5
A76: 1020107 | B76: Lait pour le Corps - Régénérant - 150 ml | C76: 4020829103160 | D76: 10.34 | E76: 26.12 | F76: 44.4
A77: 1020202 | B77: Sérum Jour/Nuit - Régénérant - 30 ml | C77: 4020829103115 | D77: 15.84 | E77: 41.12 | F77: 69.9
A78: 1020301 | B78: Crème de Jour - Régénérant - 40 ml | C78: 4020829007383 | D78: 14.8 | E78: 38.53 | F78: 65.5
A79: 1020302 | B79: Crème Cou et Décolleté - Régénérant - 40 ml | C79: 4020829008366 | D79: 13.77 | E79: 35.88 | F79: 61
A80: 1020310 | B80: Crème de Jour Eclat du Teint - Régénérant - 40 ml | C80: 4020829060999 | D80: 16.22 | E80: 41.12 | F80: 69.9
A81: 1020401 | B81: Crème Contour des Yeux - Régénérant - 15 ml | C81: 4020829013919 | D81: 15.34 | E81: 39.71 | F81: 67.5
A82: 1020704 | B82: Sérum Huile Régénérant Intensif - 20 ml | C82: 4020829074101 | D82: 0 | E82: 46.18 | F82: 78.5
A83: 1020717 | B83: Sérum Contour des Yeux - Régénérant Intensif -15 ml | C83: 4020829101067 | D83: 17.64 | E83: 44.12 | F83: 75
A84: 1020718 | B84: Sérum de Nuit - Régénérant Intensif - 30 ml | C84: 4020829101111 | D84: 18.28 | E84: 46.76 | F84: 79.5
... A116: 1030504 | B116: Après-Soleil 30ml | C116: 4020829087446 | D116: 2.16 | E116: 0 | F116: 28.92
A117: 1030601 | B117: Poudre de Soie - 50 g | D117: 6.99 | E117: 17.94 | F117: 30.5
A118: 1030602 | B118: Poudre de Soie - 50 g - DLV -20% | C118: 4020829005631 | D118: 0 | E118: 14.35 | F118: 0
A119: 1030703 | B119: Déodorant Rose - 50 ml | C119: 4020829025332 | D119: 4.13 | E119: 10.41 | F119: 17.7
A120: 1030704 | B120: Déodorant Sauge Menthe - 50 ml | C120: 4020829025370 | D120: 3.78 | E120: 9.47 | F120: 16.1
A121: 1040115 | B121: Crème Douche - 150 ml | C121: 4020829066540 | D121: 2.53 | E121: 6.7 | F121: 11.4
A122: 1040201 | B122: Bain Rose - 100 ml | C122: 4020829005914 | D122: 5.16 | E122: 13.24 | F122: 22.5
A123: 1040202 | B123: Bain Moor Lavande - 100 ml | C123: 4020829005877 | D123: 5.16 | E123: 13.24 | F123: 22.5
A124: 1040205 | B124: Bain Sauge - 100 ml | C124: 4020829011403 | D124: 4.47 | E124: 11.76 | F124: 20
A125: 1040221 | B125: Bain Caprices des saisons - 100 ml | C125: 4020829088436 | D125: 4.26 | E125: 11.17 | F125: 19
A126: 1040224 | B126: Bain Moor Lavande 100ml Edition Limitée Noël 2023 | C126: 4020829100114 | D126: 5.03 | E126: 12.76 | F126: 21.7
A127: 1040305 | B127: Après-Shampooing - 150 ml | C127: 4020829077478 | D127: 5.13 | E127: 13.47 | F127: 22.9
A128: 1040306 | B128: Lotion pour les Cheveux - 100 ml | C128: 4020829077515 | D128: 4.38 | E128: 11.65 | F128: 19.8
A129: 1040307 | B129: Huile pour les Cheveux - 75 ml | C129: 4020829077553 | D129: 4.7 | E129: 12.65 | F129: 21.5
... A235: 1820105 | B235: Crème pour les Mains Régénérante - 50 ml*DLV 09/24* - 25 %* | C235: 18201059999 | D235: 6.39 | E235: 12.16 | F235: 27.2
A236: 1820310 | B236: Crème de Jour Régénérante Eclat du Teint - 40 ml | D236: 15.43 | E236: 0 | F236: 56.08
A237: 1820704 | B237: Sérum Huile Régénérant Intensif - 20 ml*DLV 05/25*-20%* | D237: 17.97 | E237: 38.54 | F237: 78.5
A238: 1820717 | B238: Sérum Contour des Yeux - Régénérant Intensif -15 ml*DLV 07/25*-10%* | D238: 17.64 | E238: 30.88 | F238: 75
A239: 1820718 | B239: Sérum de Nuit - Régénérant Intensif - 30 ml*DLV 06/2025*-20%* | C239: 182071899999 | D239: 18.1 | E239: 36.43 | F239: 78.2
A240: 1820719 | B240: Huile Fortifiante - Régénérant Intensif - 20ml -20% DLV 03/2027 | D240: 18.24 | E240: 37.41 | F240: 63.6
A241: 1830102 | B241: Lait Crème pour le Corps Lavande Bois de Santal - 145 ml*DLV 11/24* - 15 %* | C241: 18301029999 | D241: 5.72 | E241: 12.6 | F241: 24.3
A242: 1830123 | B242: Lait Crème pour le Corps Lavande Bois de Santal - 50 ml*DLV 01/25* | C242: 4020829095793 | D242: 2.8 | E242: 0 | F242: 0
A243: 1830125 | B243: Lait Crème pour le Corps Rose - 50 ml | C243: 4020829100367 | D243: 2.54 | E243: 0 | F243: 0
A244: 1830126 | B244: Lait Crème pour le Corps Lavande Bois de Santal - 30 ml | C244: 4020829100381 | D244: 2.54 | E244: 0 | F244: 0
A245: 1830127 | B245: Lait Crème pour le Corps Amande - 50 ml | C245: 4020829100374 | D245: 2.54 | E245: 0 | F245: 0
A246: 1830308 | B246: Huile au Neem pour les Ongles - 18 ml*DLV 08/25* - 15 %* | D246: 4.71 | E246: 9.41 | F246: 16.67
A247: 1830502 | B247: Lait Après-Soleil 150 ml*DLV 06/2025*- 30%* | C247: 183050299999 | D247: 6 | E247: 10.7 | F247: 26
A248: 1830601 | B248: Poudre de Soie - 50 g | C248: 9999991830601 | D248: 6.4 | E248: 0 | F248: 0
A249: 1840202 | B249: Bain Moor Lavande - 100 ml*DLV 11/25* - 10 %* | C249: 184020299999 | D249: 5.03 | E249: 11.75 | F249: 22.2
A250: 1840205 | B250: Bain Sauge - 100 ml (copie) | C250: 1840205999999 | D250: 4.36 | E250: 9.75 | F250: 19.5
A251: 1840221 | B251: Bain Caprices des saisons - 100 ml*DLV 01/2026*- 10%* | C251: 1840221999999 | D251: 4.22 | E251: 9.79 | F251: 18.5
A252: 1840225 | B252: Bain Rose - 100 ml * DLV 01/2026* - 10%* | C252: 184022599999 | D252: 5.03 | E252: 9.93 | F252: 22.2
A253: 1850502 | B253: Shampooing à la Ficoïde à Cristaux - 150 ml*DLV 11/24*-15 %* | C253: 105050299999 | D253: 5.2 | E253: 11.44 | F253: 22.5
A254: 1850506 | B254: Masque pour le Cuir Chevelu aux Graines de Courge - 25 ml*DLV 09/24* - 25%* | C254: 185050699999 | D254: 5.43 | E254: 10.72 | F254: 23.8
A255: 1860124 | B255: Mascara Longue Tenue 02 brun -20% DLV 03/2027 | D255: 5.76 | E255: 12.46 | F255: 21.2
A256: 1860531 | B256: Crayon à Sourcils 01 brun clair *DLV 11/26* | D256: 3.75 | E256: 9.47 | F256: 17.9
A257: 1860733 | B257: Baume Stick Lèvres et Joues 04 doré *DLV 11/26* -10% | D257: 6.66 | E257: 16.14 | F257: 30.5
A258: 1861026 | B258: Fond de Teint 06 noix*DLV 11/25*- 20%* | C258: 1861026999999 | D258: 6.84 | E258: 15.05 | F258: 32
A259: 1861027 | B259: Fond de teint - 001 cajou*DLV 01/26*- 20% | C259: 1861027999999 | D259: 6.64 | E259: 15.05 | F259: 32
A260: 2010101 | B260: Cabine - Crème Purifiante - 100 ml | C260: 4020829005143 | D260: 3.95 | E260: 10.53 | F260: 0
A261: 2010352 | B261: Cabine - Huile Equilibrante pour le visage -18 ml | C261: 9999992010352 | D261: 6.02 | E261: 13.91 | F261: 0
A262: 2010501 | B262: Cabine - Baume Contour des Yeux - 10 ml | C262: 9999992010501 | D262: 7.75 | E262: 17.49 | F262: 0
A263: 2010505 | B263: Cabine - Lotion Fraîcheur pour les Yeux - 50 x 5 ml | C263: 4020829077072 | D263: 18.04 | E263: 44.59 | F263: 0
A264: 2010602 | B264: Cabine - Baume pour les Lèvres - 4,5 ml | C264: 9999992010602 | D264: 2.9 | E264: 6.71 | F264: 0
A265: 2010701 | B265: Cabine - Cure Intensive pour la Nuit 50 amp. | C265: 9999992010701 | D265: 18.94 | E265: 33.47 | F265: 0
A266: 2010703 | B266: Cabine - Cure Intensive Jour/Nuit pour Peaux Sensibles 50 amp. | C266: 9999992010703 | D266: 19.97 | E266: 33.47 | F266: 0
A267: 2010705 | B267: Cabine - Bain de Vapeur pour le Visage - 100 ml | C267: 9999992010705 | D267: 6.72 | E267: 14.16 | F267: 0
A268: 2010706 | B268: Cabine - Masque Purifiant - 5 x 90 g | C268: 4020829004955 | D268: 19.34 | E268: 43.66 | F268: 0
A269: 2010707 | B269: Cabine - Masque Revitalisant - 100 ml | C269: 4020829004726 | D269: 14.65 | E269: 36.2 | F269: 0
... A272: 2010717 | B272: Cabine - Masque Crème Nourrissant - 100 ml | C272: 4020829041325 | D272: 18.94 | E272: 46.82 | F272: 0
A273: 2010727 | B273: Cabine - Cure Revitalisante & Stimulante 28 ampoules x 2ml | D273: 19.13 | E273: 33.47 | F273: 0
A274: 2010728 | B274: Cabine - Cure Apaisante & Équilibrante 28 ampoules x 2 ml | D274: 20.16 | E274: 33.47 | F274: 0
A275: 2030201 | B275: Cabine - Huile de Soin Rose - 75 ml | C275: 9999992030201 | D275: 5.51 | E275: 11.36 | F275: 0
A276: 2030202 | B276: Cabine - Huile de Soin Prunelle - 75 ml | C276: 9999992030202 | D276: 4.99 | E276: 10.28 | F276: 0
A277: 2030203 | B277: Cabine - Huile de Soin Citron Citronnelle - 75 ml | C277: 9999992030203 | D277: 4.99 | E277: 10.28 | F277: 0
A278: 2030204 | B278: Cabine - Huile de Soin Bouleau Arnica - 75 ml | C278: 9999992030204 | D278: 4.66 | E278: 9.58 | F278: 0
A279: 2030206 | B279: Cabine - Huile de Soin Moor Lavande - 75 ml | C279: 9999992030206 | D279: 5.51 | E279: 11.36 | F279: 0
A280: 2030301 | B280: Cabine - Crème pour les Mains - 100 ml | C280: 4020829005693 | D280: 3.75 | E280: 10.19 | F280: 0
A281: 2030308 | B281: Cabine - Huile au Neem pour les Ongles - 18 ml | C281: 9999992030308 | D281: 4.9 | E281: 11.1 | F281: 0
A282: 2030408 | B282: Cabine - Crème Déodorante pour les Pieds - 30 ml - nouvelle | D282: 3.74 | E282: 6.55 | F282: 0
A283: 2040201 | B283: Cabine - Bain Rose - 100 ml | C283: 9999992040201 | D283: 5.16 | E283: 10.94 | F283: 0
A284: 2040202 | B284: Cabine - Bain Moor Lavande - 100 ml | C284: 9999992040202 | D284: 5.16 | E284: 10.94 | F284: 0
A285: 2040205 | B285: Cabine - Bain à la Sauge - 100 ml | C285: 9999992040205 | D285: 4.47 | E285: 11.38 | F285: 0
A286: 2040221 | B286: Cabine - Bain Caprice des saisons - 100 ml | C286: 9999992040221 | D286: 4.24 | E286: 9.79 | F286: 0
A287: 2050103 | B287: Cabine - Crème pour les Mains à la Ficoïde à Cristaux - 50 ml | C287: 9999992050103 | D287: 4.56 | E287: 10.4 | F287: 0
...

Sheet Synthèse logistique
